Workbook

Sheet ANALISE
A3: Rótulos de Linha | B3: Soma de DIFERENÇA VALOR
A4: Insumo Terc. | B4: 0
A5: AÇUCAR | B5: 0
A6: LACRE | B6: 0
A7: AROMA | B7: 0
A8: LATA | B8: 0
A9: CARVAO | B9: 0
A10: LUPULO | B10: 0
A11: CONCENTRADO | B11: 0
A12: MALTE | B12: 0
A13: CORANTE | B13: 0
A14: PREFORMA | B14: 0
A15: ELABORAÇÃO | B15: 0
... A35: Total Geral | B35: 0

Sheet KPI
B2: VALOR ESTOQUE FÍSICO (MP) | M2: CUSTO (R$) DIVERGÊNCIA (MP)
B3: MÊS | C3: VALOR (R$) | M3: MÊS | N3: VALOR (R$)
B4: JANEIRO | C4: 14484679 | M4: JANEIRO | N4: 118144.18
B5: FEVEREIRO | C5: 13521013 | M5: FEVEREIRO | N5: 267353.14
B6: MARÇO | C6: 14243064 | M6: MARÇO | N6: 281640.56
B7: ABRIL | C7: 12258289 | M7: ABRIL | N7: 206892.35
B8: MAIO | C8: 9350849.2 | M8: MAIO | N8: 85994.001
B9: JUNHO | C9: 8710025.7 | M9: JUNHO | N9: 100512.52
B10: JULHO | M10: JULHO
B11: AGOSTO | M11: AGOSTO
B12: SETEMBRO | M12: SETEMBRO
B13: OUTUBRO | C13: 9786201.2 | M13: OUTUBRO | N13: =C13-C29 -> -823245.49
B14: NOVEMBRO | C14: 11626525 | M14: NOVEMBRO | N14: =C14-C30 -> 47666.517
B15: DEZEMBRO | C15: 11050986 | M15: DEZEMBRO | N15: 55057.669
B16: MÉDIA | C16: =AVERAGE(C4:C15) -> 11670181 | M16: MÉDIA | N16: =AVERAGE(N4:N15) -> 37779.494
B18: VALOR ESTOQUE SISTEMA (MP) | M18: % DIVERGÊNCIA (MP)
B19: MÊS | C19: VALOR (R$) | M19: MÊS | N19: VALOR (R$)
B20: JANEIRO | C20: 14366535 | M20: JANEIRO | N20: 0.0082235682
B21: FEVEREIRO | C21: 13253660 | M21: FEVEREIRO | N21: 0.020172023
B22: MARÇO | C22: 13961423 | M22: MARÇO | N22: 0.020172769
B23: ABRIL | C23: 12051397 | M23: ABRIL | N23: 0.017167499
B24: MAIO | C24: 9264855.2 | M24: MAIO | N24: 0.0092817426
B25: JUNHO | C25: 8609513.2 | M25: JUNHO | N25: 0.011674588
B26: JULHO | M26: JULHO
B27: AGOSTO | M27: AGOSTO
B28: SETEMBRO | M28: SETEMBRO
B29: OUTUBRO | C29: 10609447 | M29: OUTUBRO | N29: =IFERROR(N13/C29,"") -> -0.077595516
B30: NOVEMBRO | C30: 11578858 | M30: NOVEMBRO | N30: =IFERROR(N14/C30,"") -> 0.0041166855
B31: DEZEMBRO | C31: 10995928 | M31: DEZEMBRO | N31: 0.0050070962
B32: MÉDIA | C32: =AVERAGE(C20:C31) -> 11632402 | M32: MÉDIA | N32: =AVERAGE(N20:N31) -> 0.0020244951
B34: VALOR ESTOQUE FÍSICO (PA) | M34: ACURACIDADE QUALITATIVA (MP)
B35: MÊS | C35: VALOR (R$) | M35: MÊS | N35: %
B36: JANEIRO | C36: 2390297.8 | M36: JANEIRO | N36: 0.64661654
B37: FEVEREIRO | C37: 3642342.8 | M37: FEVEREIRO | N37: 0.62737643
B38: MARÇO | C38: 1858028.3 | M38: MARÇO | N38: 0.6627907
B39: ABRIL | C39: 1454970.4 | M39: ABRIL | N39: 0.70342205
B40: MAIO | C40: 1203577.7 | M40: MAIO | N40: 0.73705179
B41: JUNHO | C41: 2240566.9 | M41: JUNHO | N41: 0.74501992
B42: JULHO | M42: JULHO
B43: AGOSTO | M43: AGOSTO
B44: SETEMBRO | M44: SETEMBRO
B45: OUTUBRO | C45: 3036154.1 | M45: OUTUBRO | N45: 0.338
B46: NOVEMBRO | C46: 1835764.6 | M46: NOVEMBRO | N46: 0.60661765
B47: DEZEMBRO | C47: 1838676.7 | M47: DEZEMBRO | N47: 0.61832061
B48: MÉDIA | C48: =AVERAGE(C36:C47) -> 2166708.8 | M48: MÉDIA | N48: =AVERAGE(N36:N47) -> 0.63169063
B50: VALOR ESTOQUE SISTEMA (PA) | M50: CUSTO (R$) DIVERGÊNCIA (PA)
B51: MÊS | C51: VALOR (R$) | M51: MÊS | N51: VALOR (R$)
B52: JANEIRO | C52: 2415675.3 | M52: JANEIRO | N52: -12823.707
B53: FEVEREIRO | C53: 3657759.1 | M53: FEVEREIRO | N53: -15416.318
B54: MARÇO | C54: 1875975.5 | M54: MARÇO | N54: -17947.256
B55: ABRIL | C55: 1472804.5 | M55: ABRIL | N55: -17834.113
B56: MAIO | C56: 1221473.1 | M56: MAIO | N56: -17895.359
B57: JUNHO | C57: 2240114.6 | M57: JUNHO | N57: 452.33174
B58: JULHO | M58: JULHO
B59: AGOSTO | M59: AGOSTO
B60: SETEMBRO | M60: SETEMBRO
B61: OUTUBRO | C61: 3089099.7 | M61: OUTUBRO | N61: -52945.61
B62: NOVEMBRO | C62: 1889315.3 | M62: NOVEMBRO | N62: -53550.63
B63: DEZEMBRO | C63: 1879873.3 | M63: DEZEMBRO | N63: -41196.64
B64: MÉDIA | C64: =AVERAGE(C52:C63) -> 2193565.6 | M64: MÉDIA | N64: =AVERAGE(N52:N63) -> -25461.922
B66: ACURACIDADE QUALITATIVA (PA) | M66: % DIVERGÊNCIA (PA)
B67: MÊS | C67: % | M67: MÊS | N67: VALOR (R$)
B68: JANEIRO | C68: 0.66666667 | M68: JANEIRO | N68: 0.07046603
B69: FEVEREIRO | C69: 0.87058824 | M69: FEVEREIRO | N69: 0.06068542
B70: MARÇO | C70: 0.84810127 | M70: MARÇO | N70: 0.012294521
B71: ABRIL | C71: 0.46099291 | M71: ABRIL | N71: 0.16666667
B72: MAIO | C72: 0.94029851 | M72: MAIO | N72: -0.014650638
B73: JUNHO | C73: 0.91954023 | M73: JUNHO | N73: 0.00020192348
B74: JULHO | M74: JULHO
B75: AGOSTO | M75: AGOSTO
B76: SETEMBRO | M76: SETEMBRO
B77: OUTUBRO | M77: OUTUBRO | N77: -0.0171
B78: NOVEMBRO | M78: NOVEMBRO | N78: 0.7531
B79: DEZEMBRO | M79: DEZEMBRO | N79: 0.1257
B80: MÉDIA | C80: =AVERAGE(C68:C79) -> 0.78436464 | M80: MÉDIA | N80: =AVERAGE(N68:N79) -> 0.12859599

Sheet BASE PRODUTOS
A1: BASE DE CADASTRO TOTVS
A2: Codigo | B2: Descricao | C2: Tipo | D2: Unidade | E2: Fator Conv.
A3: 2000010001 | B3: AT MALDIVES 12X250ML | C3: PA | D3: FD | E3: 12
A4: 2000010002 | B4: REFRIKO COLA 12X200ML | C4: PA | D4: FD | E4: 12
A5: 2000010003 | B5: REFRIKO COLA 12X500ML | C5: PA | D5: FD | E5: 12
A6: 2000010004 | B6: REFRIKO COLA 4X3LT | C6: PA | D6: FD | E6: 4
A7: 2000010005 | B7: REFRIKO COLA 6X2LT | C7: PA | D7: FD | E7: 6
A8: 2000010006 | B8: REFRIKO COLA 6X350ML | C8: PA | D8: FD | E8: 6
A9: 2000010007 | B9: REFRIKO FRAMBOESA 6X2LT | C9: PA | D9: FD | E9: 6
A10: 2000010008 | B10: REFRIKO GUARANA 12X200ML | C10: PA | D10: FD | E10: 12
A11: 2000010009 | B11: REFRIKO GUARANA 12X500ML | C11: PA | D11: FD | E11: 12
A12: 2000010010 | B12: REFRIKO GUARANA 24X600ML - RET | C12: PA | D12: CX | E12: 24
A13: 2000010011 | B13: REFRIKO GUARANA 4X3LT | C13: PA | D13: FD | E13: 4
A14: 2000010012 | B14: REFRIKO GUARANA 6X2LT | C14: PA | D14: FD | E14: 6
... A13198: 9999990006 | B13198: REEMBOLSO DE VIAGEM | C13198: OU | D13198: UN | E13198: 0
A13199: FL03040001 | B13199: FILTRO DE PAPEL MELITTA | C13199: MC | D13199: UN | E13199: 0
A13200: 2701010044 | B13200: ROTULO SLEEVE FURIOSO TANGERINA E LIMAO ZERO 473ML | E13200: 0.0020921

Sheet CONCILIÇÃO_COM_CERVEJA
J1: Valor Estoque Físico | M1: Valor Estoque Sistema | R1: Acuracidade Qualitativa | S1: Custo Diferença | T1: Percentual Diferença
J2: =SUBTOTAL(9,#REF!) -> #REF! | M2: =SUBTOTAL(9,CONCILIÇÃO_COM_CERVEJA!$N$5:$N$378) -> 9260128.5 | R2: =(COUNTIF(CONCILIÇÃO_COM_CERVEJA!$J$5:$J$378,">0")-COUNTIF(CONCILIÇÃO_COM_CERVEJA!$T$5:$T$378,">1,05")-COUNTIF(CONCILIÇÃO_COM_CERVEJA!$T$5:$T$378,"<0,95"))/COUNTIF(CONCILIÇÃO_COM_CERVEJA!$J$5:$J$378,">0") -> 1 | S2: =SUBTOTAL(9,CONCILIÇÃO_COM_CERVEJA!$S$5:$S$378) -> -500976.35 | T2: =S2/M2 -> -0.054100367
A4: CÓD. SAIB | B4: CÓD. PRODUTO | C4: CODIGO NOVO | D4: DESCRIÇÃO | E4: Consumo total mês 7 | F4: CLASSE | G4: Fator Conv. | H4: 30/jun | I4: ? | J4: Contagem | K4: SIST COD KG | L4: SIST COD UND | M4: SALDO SISTEMA TOTAL | N4: CUSTO SISTEMA | O4: DIFERENÇA ANTERIOR | P4: Diferença atual | Q4: Diveregencia mês anterior | R4: CUSTO MP (UN) | S4: CUSTO DIVERGÊNCIA | T4: ACURACIDADE | U4: DIFERENÇA VALOR | V4: OBS
A5: 55 | B5: 2701080001 | C5: - | D5: ACUCAR CRISTAL | E5: =IFERROR(VLOOKUP(B5,[1]AGLUTINADO!$A:$C,3,0),0)/G5 -> 133961.33 | F5: AÇUCAR | G5: 1 | H5: =VLOOKUP(CONCILIÇÃO_COM_CERVEJA!$B5,CONT_ANTE!A:D,4,0) -> 42000 | I5: =IF(AND(E5=0,H5<>J5),"!@##@!","ok") -> ok | J5: 55200 | K5: =SUMIF(SISTEMA!B:B,CONCILIÇÃO_COM_CERVEJA!$B5,SISTEMA!I:I)/G5 -> 63047.67 | L5: =SUMIF(SISTEMA!B:B,CONCILIÇÃO_COM_CERVEJA!$C5,SISTEMA!I:I) -> 0 | M5: =K5+L5 -> 63047.67 | N5: =IFERROR(SUM(CONCILIÇÃO_COM_CERVEJA!$M5*CONCILIÇÃO_COM_CERVEJA!$R5),0) -> 148650.93 | O5: =IFERROR(VLOOKUP(CONCILIÇÃO_COM_CERVEJA!$B5,DIF_ANTE!A:D,4,0),"0")/CONCILIÇÃO_COM_CERVEJA!$G5 -> 991 | P5: =J5-M5 -> -7847.67 | Q5: =CONCILIÇÃO_COM_CERVEJA!$P5-CONCILIÇÃO_COM_CERVEJA!$O5 -> -8838.67 | R5: =IFERROR(VLOOKUP(CONCILIÇÃO_COM_CERVEJA!$B5,CUSTO!E:H,4,0),(VLOOKUP(CONCILIÇÃO_COM_CERVEJA!$A5,CUSTO!A:H,8,0))) -> 2.3577545 | S5: =IFERROR(SUM(CONCILIÇÃO_COM_CERVEJA!$P5*CONCILIÇÃO_COM_CERVEJA!$R5),0) -> -18502.879 | T5: =IFERROR(#REF!/CONCILIÇÃO_COM_CERVEJA!$M5,"") | U5: =IFERROR(#REF!*CONCILIÇÃO_COM_CERVEJA!$R5,"-") -> - | V5: VERIFICAR
A6: 31395 | B6: 2701170002 | C6: - | D6: ETANOL NEUTRO ALCOOL ETILICO POTAVEL 96° | E6: =IFERROR(VLOOKUP(B6,[1]AGLUTINADO!$A:$C,3,0),0)/G6 -> 67132.062 | F6: ALCOOL | G6: 1 | H6: =VLOOKUP(CONCILIÇÃO_COM_CERVEJA!$B6,CONT_ANTE!A:D,4,0) -> 41958 | I6: =IF(AND(E6=0,H6<>J6),"!@##@!","ok") -> ok | J6: 52674 | K6: =SUMIF(SISTEMA!B:B,CONCILIÇÃO_COM_CERVEJA!$B6,SISTEMA!I:I)/G6 -> 65761 | L6: =SUMIF(SISTEMA!B:B,CONCILIÇÃO_COM_CERVEJA!$C6,SISTEMA!I:I) -> 0 | M6: =K6+L6 -> 65761 | N6: =IFERROR(SUM(CONCILIÇÃO_COM_CERVEJA!$M6*CONCILIÇÃO_COM_CERVEJA!$R6),0) -> 252294.82 | O6: =IFERROR(VLOOKUP(CONCILIÇÃO_COM_CERVEJA!$B6,DIF_ANTE!A:D,4,0),"0")/CONCILIÇÃO_COM_CERVEJA!$G6 -> 428.93839 | P6: =J6-M6 -> -13087 | Q6: =CONCILIÇÃO_COM_CERVEJA!$P6-CONCILIÇÃO_COM_CERVEJA!$O6 -> -13515.938 | R6: =IFERROR(VLOOKUP(CONCILIÇÃO_COM_CERVEJA!$B6,CUSTO!E:H,4,0),(VLOOKUP(CONCILIÇÃO_COM_CERVEJA!$A6,CUSTO!A:H,8,0))) -> 3.8365417 | S6: =IFERROR(SUM(CONCILIÇÃO_COM_CERVEJA!$P6*CONCILIÇÃO_COM_CERVEJA!$R6),0) -> -50208.822 | T6: =IFERROR(#REF!/CONCILIÇÃO_COM_CERVEJA!$M6,"") | U6: =IFERROR(#REF!*CONCILIÇÃO_COM_CERVEJA!$R6,"-") -> - | V6: ok
A7: 31352 | B7: 2701050004 | C7: - | D7: AROMA ARTIFICIAL ENERGY SYMRISE | E7: =IFERROR(VLOOKUP(B7,[1]AGLUTINADO!$A:$C,3,0),0)/G7 -> 0 | F7: AROMA | G7: 1 | H7: =VLOOKUP(CONCILIÇÃO_COM_CERVEJA!$B7,CONT_ANTE!A:D,4,0) -> 0 | I7: =IF(AND(E7=0,H7<>J7),"!@##@!","ok") -> ok | J7: =VLOOKUP(CONCILIÇÃO_COM_CERVEJA!$B7,CONTAGEM!B:G,6,0) -> 0 | K7: =SUMIF(SISTEMA!B:B,CONCILIÇÃO_COM_CERVEJA!$B7,SISTEMA!I:I)/G7 -> 0 | L7: =SUMIF(SISTEMA!B:B,CONCILIÇÃO_COM_CERVEJA!$C7,SISTEMA!I:I) -> 0 | M7: =K7+L7 -> 0 | N7: =IFERROR(SUM(CONCILIÇÃO_COM_CERVEJA!$M7*CONCILIÇÃO_COM_CERVEJA!$R7),0) -> 0 | O7: =IFERROR(VLOOKUP(CONCILIÇÃO_COM_CERVEJA!$B7,DIF_ANTE!A:D,4,0),"0")/CONCILIÇÃO_COM_CERVEJA!$G7 -> 0 | P7: =J7-M7 -> 0 | Q7: =CONCILIÇÃO_COM_CERVEJA!$P7-CONCILIÇÃO_COM_CERVEJA!$O7 -> 0 | R7: =IFERROR(VLOOKUP(CONCILIÇÃO_COM_CERVEJA!$B7,CUSTO!E:H,4,0),(VLOOKUP(CONCILIÇÃO_COM_CERVEJA!$A7,CUSTO!A:H,8,0))) -> 103.63169 | S7: =IFERROR(SUM(CONCILIÇÃO_COM_CERVEJA!$P7*CONCILIÇÃO_COM_CERVEJA!$R7),0) -> 0 | T7: =IFERROR(#REF!/CONCILIÇÃO_COM_CERVEJA!$M7,"") | U7: =IFERROR(#REF!*CONCILIÇÃO_COM_CERVEJA!$R7,"-") -> - | V7: OK
A8: 31335 | B8: 2701050008 | C8: - | D8: AROMA ARTIFICIAL FRUTAS TROPICAIS MONARCH | E8: =IFERROR(VLOOKUP(B8,[1]AGLUTINADO!$A:$C,3,0),0)/G8 -> 92.35 | F8: AROMA | G8: 1 | H8: =VLOOKUP(CONCILIÇÃO_COM_CERVEJA!$B8,CONT_ANTE!A:D,4,0) -> 331 | I8: =IF(AND(E8=0,H8<>J8),"!@##@!","ok") -> ok | J8: =VLOOKUP(CONCILIÇÃO_COM_CERVEJA!$B8,CONTAGEM!B:G,6,0) -> 240 | K8: =SUMIF(SISTEMA!B:B,CONCILIÇÃO_COM_CERVEJA!$B8,SISTEMA!I:I)/G8 -> 241.65 | L8: =SUMIF(SISTEMA!B:B,CONCILIÇÃO_COM_CERVEJA!$C8,SISTEMA!I:I) -> 0 | M8: =K8+L8 -> 241.65 | N8: =IFERROR(SUM(CONCILIÇÃO_COM_CERVEJA!$M8*CONCILIÇÃO_COM_CERVEJA!$R8),0) -> 30803.162 | O8: =IFERROR(VLOOKUP(CONCILIÇÃO_COM_CERVEJA!$B8,DIF_ANTE!A:D,4,0),"0")/CONCILIÇÃO_COM_CERVEJA!$G8 -> -3 | P8: =J8-M8 -> -1.65 | Q8: =CONCILIÇÃO_COM_CERVEJA!$P8-CONCILIÇÃO_COM_CERVEJA!$O8 -> 1.35 | R8: =IFERROR(VLOOKUP(CONCILIÇÃO_COM_CERVEJA!$B8,CUSTO!E:H,4,0),(VLOOKUP(CONCILIÇÃO_COM_CERVEJA!$A8,CUSTO!A:H,8,0))) -> 127.47015 | S8: =IFERROR(SUM(CONCILIÇÃO_COM_CERVEJA!$P8*CONCILIÇÃO_COM_CERVEJA!$R8),0) -> -210.32575 | T8: =IFERROR(#REF!/CONCILIÇÃO_COM_CERVEJA!$M8,"") | U8: =IFERROR(#REF!*CONCILIÇÃO_COM_CERVEJA!$R8,"-") -> - | V8: ok
A9: 31351 | B9: 2701050009 | C9: - | D9: AROMA ARTIFICIAL GUARANA DUAS RODAS | E9: =IFERROR(VLOOKUP(B9,[1]AGLUTINADO!$A:$C,3,0),0)/G9 -> 0 | F9: AROMA | G9: 1 | H9: =VLOOKUP(CONCILIÇÃO_COM_CERVEJA!$B9,CONT_ANTE!A:D,4,0) -> 0 | I9: =IF(AND(E9=0,H9<>J9),"!@##@!","ok") -> ok | J9: =VLOOKUP(CONCILIÇÃO_COM_CERVEJA!$B9,CONTAGEM!B:G,6,0) -> 0 | K9: =SUMIF(SISTEMA!B:B,CONCILIÇÃO_COM_CERVEJA!$B9,SISTEMA!I:I)/G9 -> 0 | L9: =SUMIF(SISTEMA!B:B,CONCILIÇÃO_COM_CERVEJA!$C9,SISTEMA!I:I) -> 0 | M9: =K9+L9 -> 0 | N9: =IFERROR(SUM(CONCILIÇÃO_COM_CERVEJA!$M9*CONCILIÇÃO_COM_CERVEJA!$R9),0) -> 0 | O9: =IFERROR(VLOOKUP(CONCILIÇÃO_COM_CERVEJA!$B9,DIF_ANTE!A:D,4,0),"0")/CONCILIÇÃO_COM_CERVEJA!$G9 -> 0 | P9: =J9-M9 -> 0 | Q9: =CONCILIÇÃO_COM_CERVEJA!$P9-CONCILIÇÃO_COM_CERVEJA!$O9 -> 0 | R9: =IFERROR(VLOOKUP(CONCILIÇÃO_COM_CERVEJA!$B9,CUSTO!E:H,4,0),(VLOOKUP(CONCILIÇÃO_COM_CERVEJA!$A9,CUSTO!A:H,8,0))) -> 49.614813 | S9: =IFERROR(SUM(CONCILIÇÃO_COM_CERVEJA!$P9*CONCILIÇÃO_COM_CERVEJA!$R9),0) -> 0 | T9: =IFERROR(#REF!/CONCILIÇÃO_COM_CERVEJA!$M9,"") | U9: =IFERROR(#REF!*CONCILIÇÃO_COM_CERVEJA!$R9,"-") -> - | V9: OK
B10: 2701050035 | C10: - | D10: AROMA ARTIFICIAL GUARANA IFB | E10: =IFERROR(VLOOKUP(B10,[1]AGLUTINADO!$A:$C,3,0),0)/G10 -> 151.03 | F10: AROMA | G10: 1 | H10: =VLOOKUP(CONCILIÇÃO_COM_CERVEJA!$B10,CONT_ANTE!A:D,4,0) -> 952 | I10: =IF(AND(E10=0,H10<>J10),"!@##@!","ok") -> ok | J10: =VLOOKUP(CONCILIÇÃO_COM_CERVEJA!$B10,CONTAGEM!B:G,6,0) -> 797 | K10: =SUMIF(SISTEMA!B:B,CONCILIÇÃO_COM_CERVEJA!$B10,SISTEMA!I:I)/G10 -> 812.43 | L10: =SUMIF(SISTEMA!B:B,CONCILIÇÃO_COM_CERVEJA!$C10,SISTEMA!I:I) -> 0 | M10: =K10+L10 -> 812.43 | N10: =IFERROR(SUM(CONCILIÇÃO_COM_CERVEJA!$M10*CONCILIÇÃO_COM_CERVEJA!$R10),0) -> 30612.362 | O10: =IFERROR(VLOOKUP(CONCILIÇÃO_COM_CERVEJA!$B10,DIF_ANTE!A:D,4,0),"0")/CONCILIÇÃO_COM_CERVEJA!$G10 -> -11.46 | P10: =J10-M10 -> -15.43 | Q10: =CONCILIÇÃO_COM_CERVEJA!$P10-CONCILIÇÃO_COM_CERVEJA!$O10 -> -3.97 | R10: =IFERROR(VLOOKUP(CONCILIÇÃO_COM_CERVEJA!$B10,CUSTO!E:H,4,0),(VLOOKUP(CONCILIÇÃO_COM_CERVEJA!$A10,CUSTO!A:H,8,0))) -> 37.68 | S10: =IFERROR(SUM(CONCILIÇÃO_COM_CERVEJA!$P10*CONCILIÇÃO_COM_CERVEJA!$R10),0) -> -581.4024 | T10: =IFERROR(#REF!/CONCILIÇÃO_COM_CERVEJA!$M10,"") | U10: =IFERROR(#REF!*CONCILIÇÃO_COM_CERVEJA!$R10,"-") -> -
A11: 31349 | B11: 2701050017 | C11: - | D11: AROMA ARTIFICIAL MELANCIA DUAS RODAS | E11: =IFERROR(VLOOKUP(B11,[1]AGLUTINADO!$A:$C,3,0),0)/G11 -> 69.71 | F11: AROMA | G11: 1 | H11: =VLOOKUP(CONCILIÇÃO_COM_CERVEJA!$B11,CONT_ANTE!A:D,4,0) -> 159 | I11: =IF(AND(E11=0,H11<>J11),"!@##@!","ok") -> ok | J11: =VLOOKUP(CONCILIÇÃO_COM_CERVEJA!$B11,CONTAGEM!B:G,6,0) -> 184 | K11: =SUMIF(SISTEMA!B:B,CONCILIÇÃO_COM_CERVEJA!$B11,SISTEMA!I:I)/G11 -> 204.1 | L11: =SUMIF(SISTEMA!B:B,CONCILIÇÃO_COM_CERVEJA!$C11,SISTEMA!I:I) -> 0 | M11: =K11+L11 -> 204.1 | N11: =IFERROR(SUM(CONCILIÇÃO_COM_CERVEJA!$M11*CONCILIÇÃO_COM_CERVEJA!$R11),0) -> 6403.0742 | O11: =IFERROR(VLOOKUP(CONCILIÇÃO_COM_CERVEJA!$B11,DIF_ANTE!A:D,4,0),"0")/CONCILIÇÃO_COM_CERVEJA!$G11 -> -14.81 | P11: =J11-M11 -> -20.1 | Q11: =CONCILIÇÃO_COM_CERVEJA!$P11-CONCILIÇÃO_COM_CERVEJA!$O11 -> -5.29 | R11: =IFERROR(VLOOKUP(CONCILIÇÃO_COM_CERVEJA!$B11,CUSTO!E:H,4,0),(VLOOKUP(CONCILIÇÃO_COM_CERVEJA!$A11,CUSTO!A:H,8,0))) -> 31.37224 | S11: =IFERROR(SUM(CONCILIÇÃO_COM_CERVEJA!$P11*CONCILIÇÃO_COM_CERVEJA!$R11),0) -> -630.58202 | T11: =IFERROR(#REF!/CONCILIÇÃO_COM_CERVEJA!$M11,"") | U11: =IFERROR(#REF!*CONCILIÇÃO_COM_CERVEJA!$R11,"-") -> -
A12: 31354 | B12: 2701050006 | C12: - | D12: AROMA IDENTICO AO NATURAL BLUEBERRY KALABROS | E12: =IFERROR(VLOOKUP(B12,[1]AGLUTINADO!$A:$C,3,0),0)/G12 -> 0 | F12: AROMA | G12: 1 | H12: =VLOOKUP(CONCILIÇÃO_COM_CERVEJA!$B12,CONT_ANTE!A:D,4,0) -> 0 | I12: =IF(AND(E12=0,H12<>J12),"!@##@!","ok") -> ok | J12: =VLOOKUP(CONCILIÇÃO_COM_CERVEJA!$B12,CONTAGEM!B:G,6,0) -> 0 | K12: =SUMIF(SISTEMA!B:B,CONCILIÇÃO_COM_CERVEJA!$B12,SISTEMA!I:I)/G12 -> 0 | L12: =SUMIF(SISTEMA!B:B,CONCILIÇÃO_COM_CERVEJA!$C12,SISTEMA!I:I) -> 0 | M12: =K12+L12 -> 0 | N12: =IFERROR(SUM(CONCILIÇÃO_COM_CERVEJA!$M12*CONCILIÇÃO_COM_CERVEJA!$R12),0) -> 0 | O12: =IFERROR(VLOOKUP(CONCILIÇÃO_COM_CERVEJA!$B12,DIF_ANTE!A:D,4,0),"0")/CONCILIÇÃO_COM_CERVEJA!$G12 -> 0 | P12: =J12-M12 -> 0 | Q12: =CONCILIÇÃO_COM_CERVEJA!$P12-CONCILIÇÃO_COM_CERVEJA!$O12 -> 0 | R12: =IFERROR(VLOOKUP(CONCILIÇÃO_COM_CERVEJA!$B12,CUSTO!E:H,4,0),(VLOOKUP(CONCILIÇÃO_COM_CERVEJA!$A12,CUSTO!A:H,8,0))) -> 45.981938 | S12: =IFERROR(SUM(CONCILIÇÃO_COM_CERVEJA!$P12*CONCILIÇÃO_COM_CERVEJA!$R12),0) -> 0 | T12: =IFERROR(#REF!/CONCILIÇÃO_COM_CERVEJA!$M12,"") | U12: =IFERROR(#REF!*CONCILIÇÃO_COM_CERVEJA!$R12,"-") -> - | V12: OK
B13: 2701050029 | C13: - | D13: AROMA IDENTICO AO NATURAL CLOUDING LEMON | E13: =IFERROR(VLOOKUP(B13,[1]AGLUTINADO!$A:$C,3,0),0)/G13 -> 0 | F13: AROMA | G13: 1 | H13: =VLOOKUP(CONCILIÇÃO_COM_CERVEJA!$B13,CONT_ANTE!A:D,4,0) -> 0 | I13: =IF(AND(E13=0,H13<>J13),"!@##@!","ok") -> ok | J13: =VLOOKUP(CONCILIÇÃO_COM_CERVEJA!$B13,CONTAGEM!B:G,6,0) -> 0 | K13: =SUMIF(SISTEMA!B:B,CONCILIÇÃO_COM_CERVEJA!$B13,SISTEMA!I:I)/G13 -> 0 | L13: =SUMIF(SISTEMA!B:B,CONCILIÇÃO_COM_CERVEJA!$C13,SISTEMA!I:I) -> 0 | M13: =K13+L13 -> 0 | N13: =IFERROR(SUM(CONCILIÇÃO_COM_CERVEJA!$M13*CONCILIÇÃO_COM_CERVEJA!$R13),0) -> 0 | O13: =IFERROR(VLOOKUP(CONCILIÇÃO_COM_CERVEJA!$B13,DIF_ANTE!A:D,4,0),"0")/CONCILIÇÃO_COM_CERVEJA!$G13 -> 0 | P13: =J13-M13 -> 0 | Q13: =CONCILIÇÃO_COM_CERVEJA!$P13-CONCILIÇÃO_COM_CERVEJA!$O13 -> 0 | R13: =IFERROR(VLOOKUP(CONCILIÇÃO_COM_CERVEJA!$B13,CUSTO!E:H,4,0),(VLOOKUP(CONCILIÇÃO_COM_CERVEJA!$A13,CUSTO!A:H,8,0))) -> 0.11037425 | S13: =IFERROR(SUM(CONCILIÇÃO_COM_CERVEJA!$P13*CONCILIÇÃO_COM_CERVEJA!$R13),0) -> 0 | T13: =IFERROR(#REF!/CONCILIÇÃO_COM_CERVEJA!$M13,"") | U13: =IFERROR(#REF!*CONCILIÇÃO_COM_CERVEJA!$R13,"-") -> - | V13: ok
A14: 1820 | B14: 2701050010 | C14: - | D14: AROMA IDENTICO AO NATURAL DE LARANJA | E14: =IFERROR(VLOOKUP(B14,[1]AGLUTINADO!$A:$C,3,0),0)/G14 -> 1.08 | F14: AROMA | G14: 1 | H14: =VLOOKUP(CONCILIÇÃO_COM_CERVEJA!$B14,CONT_ANTE!A:D,4,0) -> 15.5 | I14: =IF(AND(E14=0,H14<>J14),"!@##@!","ok") -> ok | J14: =VLOOKUP(CONCILIÇÃO_COM_CERVEJA!$B14,CONTAGEM!B:G,6,0) -> 14.5 | K14: =SUMIF(SISTEMA!B:B,CONCILIÇÃO_COM_CERVEJA!$B14,SISTEMA!I:I)/G14 -> 15.31 | L14: =SUMIF(SISTEMA!B:B,CONCILIÇÃO_COM_CERVEJA!$C14,SISTEMA!I:I) -> 0 | M14: =K14+L14 -> 15.31 | N14: =IFERROR(SUM(CONCILIÇÃO_COM_CERVEJA!$M14*CONCILIÇÃO_COM_CERVEJA!$R14),0) -> 919.68871 | O14: =IFERROR(VLOOKUP(CONCILIÇÃO_COM_CERVEJA!$B14,DIF_ANTE!A:D,4,0),"0")/CONCILIÇÃO_COM_CERVEJA!$G14 -> -0.89 | P14: =J14-M14 -> -0.81 | Q14: =CONCILIÇÃO_COM_CERVEJA!$P14-CONCILIÇÃO_COM_CERVEJA!$O14 -> 0.08 | R14: =IFERROR(VLOOKUP(CONCILIÇÃO_COM_CERVEJA!$B14,CUSTO!E:H,4,0),(VLOOKUP(CONCILIÇÃO_COM_CERVEJA!$A14,CUSTO!A:H,8,0))) -> 60.071111 | S14: =IFERROR(SUM(CONCILIÇÃO_COM_CERVEJA!$P14*CONCILIÇÃO_COM_CERVEJA!$R14),0) -> -48.6576 | T14: =IFERROR(#REF!/CONCILIÇÃO_COM_CERVEJA!$M14,"") | U14: =IFERROR(#REF!*CONCILIÇÃO_COM_CERVEJA!$R14,"-") -> -
A15: 43 | B15: 2701050011 | C15: - | D15: AROMA IDENTICO AO NATURAL DE LIMAO 41 SAPORITI | E15: =IFERROR(VLOOKUP(B15,[1]AGLUTINADO!$A:$C,3,0),0)/G15 -> 14.36 | F15: AROMA | G15: 1 | H15: =VLOOKUP(CONCILIÇÃO_COM_CERVEJA!$B15,CONT_ANTE!A:D,4,0) -> 6 | I15: =IF(AND(E15=0,H15<>J15),"!@##@!","ok") -> ok | J15: =VLOOKUP(CONCILIÇÃO_COM_CERVEJA!$B15,CONTAGEM!B:G,6,0) -> 61.5 | K15: =SUMIF(SISTEMA!B:B,CONCILIÇÃO_COM_CERVEJA!$B15,SISTEMA!I:I)/G15 -> 77.91 | L15: =SUMIF(SISTEMA!B:B,CONCILIÇÃO_COM_CERVEJA!$C15,SISTEMA!I:I) -> 0 | M15: =K15+L15 -> 77.91 | N15: =IFERROR(SUM(CONCILIÇÃO_COM_CERVEJA!$M15*CONCILIÇÃO_COM_CERVEJA!$R15),0) -> 3156.199 | O15: =IFERROR(VLOOKUP(CONCILIÇÃO_COM_CERVEJA!$B15,DIF_ANTE!A:D,4,0),"0")/CONCILIÇÃO_COM_CERVEJA!$G15 -> -14.27 | P15: =J15-M15 -> -16.41 | Q15: =CONCILIÇÃO_COM_CERVEJA!$P15-CONCILIÇÃO_COM_CERVEJA!$O15 -> -2.14 | R15: =IFERROR(VLOOKUP(CONCILIÇÃO_COM_CERVEJA!$B15,CUSTO!E:H,4,0),(VLOOKUP(CONCILIÇÃO_COM_CERVEJA!$A15,CUSTO!A:H,8,0))) -> 40.510833 | S15: =IFERROR(SUM(CONCILIÇÃO_COM_CERVEJA!$P15*CONCILIÇÃO_COM_CERVEJA!$R15),0) -> -664.78277 | T15: =IFERROR(#REF!/CONCILIÇÃO_COM_CERVEJA!$M15,"") | U15: =IFERROR(#REF!*CONCILIÇÃO_COM_CERVEJA!$R15,"-") -> -
A16: 41 | B16: 2701050027 | C16: - | D16: AROMA IDENTICO AO NATURAL DE UVA SAPORITI | E16: =IFERROR(VLOOKUP(B16,[1]AGLUTINADO!$A:$C,3,0),0)/G16 -> 119.35 | F16: AROMA | G16: 1 | H16: =VLOOKUP(CONCILIÇÃO_COM_CERVEJA!$B16,CONT_ANTE!A:D,4,0) -> 129.5 | I16: =IF(AND(E16=0,H16<>J16),"!@##@!","ok") -> ok | J16: =VLOOKUP(CONCILIÇÃO_COM_CERVEJA!$B16,CONTAGEM!B:G,6,0) -> 113 | K16: =SUMIF(SISTEMA!B:B,CONCILIÇÃO_COM_CERVEJA!$B16,SISTEMA!I:I)/G16 -> 123.51 | L16: =SUMIF(SISTEMA!B:B,CONCILIÇÃO_COM_CERVEJA!$C16,SISTEMA!I:I) -> 0 | M16: =K16+L16 -> 123.51 | N16: =IFERROR(SUM(CONCILIÇÃO_COM_CERVEJA!$M16*CONCILIÇÃO_COM_CERVEJA!$R16),0) -> 3048.1562 | O16: =IFERROR(VLOOKUP(CONCILIÇÃO_COM_CERVEJA!$B16,DIF_ANTE!A:D,4,0),"0")/CONCILIÇÃO_COM_CERVEJA!$G16 -> -8.36 | P16: =J16-M16 -> -10.51 | Q16: =CONCILIÇÃO_COM_CERVEJA!$P16-CONCILIÇÃO_COM_CERVEJA!$O16 -> -2.15 | R16: =IFERROR(VLOOKUP(CONCILIÇÃO_COM_CERVEJA!$B16,CUSTO!E:H,4,0),(VLOOKUP(CONCILIÇÃO_COM_CERVEJA!$A16,CUSTO!A:H,8,0))) -> 24.679429 | S16: =IFERROR(SUM(CONCILIÇÃO_COM_CERVEJA!$P16*CONCILIÇÃO_COM_CERVEJA!$R16),0) -> -259.38079 | T16: =IFERROR(#REF!/CONCILIÇÃO_COM_CERVEJA!$M16,"") | U16: =IFERROR(#REF!*CONCILIÇÃO_COM_CERVEJA!$R16,"-") -> -
B17: 2701050033 | C17: - | D17: AROMA IDENTICO AO NATURAL DE UVA VERDE SAPORITI | E17: =IFERROR(VLOOKUP(B17,[1]AGLUTINADO!$A:$C,3,0),0)/G17 -> 16.36 | F17: AROMA | G17: 1 | H17: =VLOOKUP(CONCILIÇÃO_COM_CERVEJA!$B17,CONT_ANTE!A:D,4,0) -> 147 | I17: =IF(AND(E17=0,H17<>J17),"!@##@!","ok") -> ok | J17: =VLOOKUP(CONCILIÇÃO_COM_CERVEJA!$B17,CONTAGEM!B:G,6,0) -> 129.5 | K17: =SUMIF(SISTEMA!B:B,CONCILIÇÃO_COM_CERVEJA!$B17,SISTEMA!I:I)/G17 -> 135.28 | L17: =SUMIF(SISTEMA!B:B,CONCILIÇÃO_COM_CERVEJA!$C17,SISTEMA!I:I) -> 0 | M17: =K17+L17 -> 135.28 | N17: =IFERROR(SUM(CONCILIÇÃO_COM_CERVEJA!$M17*CONCILIÇÃO_COM_CERVEJA!$R17),0) -> 12674.195 | O17: =IFERROR(VLOOKUP(CONCILIÇÃO_COM_CERVEJA!$B17,DIF_ANTE!A:D,4,0),"0")/CONCILIÇÃO_COM_CERVEJA!$G17 -> -4.64 | P17: =J17-M17 -> -5.78 | Q17: =CONCILIÇÃO_COM_CERVEJA!$P17-CONCILIÇÃO_COM_CERVEJA!$O17 -> -1.14 | R17: =IFERROR(VLOOKUP(CONCILIÇÃO_COM_CERVEJA!$B17,CUSTO!E:H,4,0),(VLOOKUP(CONCILIÇÃO_COM_CERVEJA!$A17,CUSTO!A:H,8,0))) -> 93.688611 | S17: =IFERROR(SUM(CONCILIÇÃO_COM_CERVEJA!$P17*CONCILIÇÃO_COM_CERVEJA!$R17),0) -> -541.52017 | T17: =IFERROR(#REF!/CONCILIÇÃO_COM_CERVEJA!$M17,"") | U17: =IFERROR(#REF!*CONCILIÇÃO_COM_CERVEJA!$R17,"-") -> -
A18: 31337 | B18: 2701050013 | C18: - | D18: AROMA IDENTICO AO NATURAL MACA VERDE DUAS RODAS | E18: =IFERROR(VLOOKUP(B18,[1]AGLUTINADO!$A:$C,3,0),0)/G18 -> 51.848 | F18: AROMA | G18: 1 | H18: =VLOOKUP(CONCILIÇÃO_COM_CERVEJA!$B18,CONT_ANTE!A:D,4,0) -> 68 | I18: =IF(AND(E18=0,H18<>J18),"!@##@!","ok") -> ok | J18: =VLOOKUP(CONCILIÇÃO_COM_CERVEJA!$B18,CONTAGEM!B:G,6,0) -> 98 | K18: =SUMIF(SISTEMA!B:B,CONCILIÇÃO_COM_CERVEJA!$B18,SISTEMA!I:I)/G18 -> 104.392 | L18: =SUMIF(SISTEMA!B:B,CONCILIÇÃO_COM_CERVEJA!$C18,SISTEMA!I:I) -> 0 | M18: =K18+L18 -> 104.392 | N18: =IFERROR(SUM(CONCILIÇÃO_COM_CERVEJA!$M18*CONCILIÇÃO_COM_CERVEJA!$R18),0) -> 4092.1323 | O18: =IFERROR(VLOOKUP(CONCILIÇÃO_COM_CERVEJA!$B18,DIF_ANTE!A:D,4,0),"0")/CONCILIÇÃO_COM_CERVEJA!$G18 -> -3.24 | P18: =J18-M18 -> -6.392 | Q18: =CONCILIÇÃO_COM_CERVEJA!$P18-CONCILIÇÃO_COM_CERVEJA!$O18 -> -3.152 | R18: =IFERROR(VLOOKUP(CONCILIÇÃO_COM_CERVEJA!$B18,CUSTO!E:H,4,0),(VLOOKUP(CONCILIÇÃO_COM_CERVEJA!$A18,CUSTO!A:H,8,0))) -> 39.199673 | S18: =IFERROR(SUM(CONCILIÇÃO_COM_CERVEJA!$P18*CONCILIÇÃO_COM_CERVEJA!$R18),0) -> -250.56431 | T18: =IFERROR(#REF!/CONCILIÇÃO_COM_CERVEJA!$M18,"") | U18: =IFERROR(#REF!*CONCILIÇÃO_COM_CERVEJA!$R18,"-") -> -
A19: 31786 | B19: 2701050014 | C19: - | D19: AROMA IDENTICO AO NATURAL MANGA HS 25409 SAPORITI | E19: =IFERROR(VLOOKUP(B19,[1]AGLUTINADO!$A:$C,3,0),0)/G19 -> 0 | F19: AROMA | G19: 1 | H19: =VLOOKUP(CONCILIÇÃO_COM_CERVEJA!$B19,CONT_ANTE!A:D,4,0) -> 0 | I19: =IF(AND(E19=0,H19<>J19),"!@##@!","ok") -> ok | J19: =VLOOKUP(CONCILIÇÃO_COM_CERVEJA!$B19,CONTAGEM!B:G,6,0) -> 0 | K19: =SUMIF(SISTEMA!B:B,CONCILIÇÃO_COM_CERVEJA!$B19,SISTEMA!I:I)/G19 -> 0 | L19: =SUMIF(SISTEMA!B:B,CONCILIÇÃO_COM_CERVEJA!$C19,SISTEMA!I:I) -> 0 | M19: =K19+L19 -> 0 | N19: =IFERROR(SUM(CONCILIÇÃO_COM_CERVEJA!$M19*CONCILIÇÃO_COM_CERVEJA!$R19),0) -> 0 | O19: =IFERROR(VLOOKUP(CONCILIÇÃO_COM_CERVEJA!$B19,DIF_ANTE!A:D,4,0),"0")/CONCILIÇÃO_COM_CERVEJA!$G19 -> 0 | P19: =J19-M19 -> 0 | Q19: =CONCILIÇÃO_COM_CERVEJA!$P19-CONCILIÇÃO_COM_CERVEJA!$O19 -> 0 | R19: =IFERROR(VLOOKUP(CONCILIÇÃO_COM_CERVEJA!$B19,CUSTO!E:H,4,0),(VLOOKUP(CONCILIÇÃO_COM_CERVEJA!$A19,CUSTO!A:H,8,0))) -> 44.0552 | S19: =IFERROR(SUM(CONCILIÇÃO_COM_CERVEJA!$P19*CONCILIÇÃO_COM_CERVEJA!$R19),0) -> 0 | T19: =IFERROR(#REF!/CONCILIÇÃO_COM_CERVEJA!$M19,"") | U19: =IFERROR(#REF!*CONCILIÇÃO_COM_CERVEJA!$R19,"-") -> - | V19: OK
A20: 31348 | B20: 2701050015 | C20: - | D20: AROMA IDENTICO AO NATURAL MARACUJA DUAS RODAS | E20: =IFERROR(VLOOKUP(B20,[1]AGLUTINADO!$A:$C,3,0),0)/G20 -> 0 | F20: AROMA | G20: 1 | H20: =VLOOKUP(CONCILIÇÃO_COM_CERVEJA!$B20,CONT_ANTE!A:D,4,0) -> 0 | I20: =IF(AND(E20=0,H20<>J20),"!@##@!","ok") -> ok | J20: =VLOOKUP(CONCILIÇÃO_COM_CERVEJA!$B20,CONTAGEM!B:G,6,0) -> 0 | K20: =SUMIF(SISTEMA!B:B,CONCILIÇÃO_COM_CERVEJA!$B20,SISTEMA!I:I)/G20 -> 0.535 | L20: =SUMIF(SISTEMA!B:B,CONCILIÇÃO_COM_CERVEJA!$C20,SISTEMA!I:I) -> 0 | M20: =K20+L20 -> 0.535 | N20: =IFERROR(SUM(CONCILIÇÃO_COM_CERVEJA!$M20*CONCILIÇÃO_COM_CERVEJA!$R20),0) -> 24.475448 | O20: =IFERROR(VLOOKUP(CONCILIÇÃO_COM_CERVEJA!$B20,DIF_ANTE!A:D,4,0),"0")/CONCILIÇÃO_COM_CERVEJA!$G20 -> -0.535 | P20: =J20-M20 -> -0.535 | Q20: =CONCILIÇÃO_COM_CERVEJA!$P20-CONCILIÇÃO_COM_CERVEJA!$O20 -> 0 | R20: =IFERROR(VLOOKUP(CONCILIÇÃO_COM_CERVEJA!$B20,CUSTO!E:H,4,0),(VLOOKUP(CONCILIÇÃO_COM_CERVEJA!$A20,CUSTO!A:H,8,0))) -> 45.7485 | S20: =IFERROR(SUM(CONCILIÇÃO_COM_CERVEJA!$P20*CONCILIÇÃO_COM_CERVEJA!$R20),0) -> -24.475448 | T20: =IFERROR(#REF!/CONCILIÇÃO_COM_CERVEJA!$M20,"") | U20: =IFERROR(#REF!*CONCILIÇÃO_COM_CERVEJA!$R20,"-") -> - | V20: OK
A21: 31336 | B21: 2701050019 | C21: - | D21: AROMA IDENTICO AO NATURAL MELAO DUAS RODAS | E21: =IFERROR(VLOOKUP(B21,[1]AGLUTINADO!$A:$C,3,0),0)/G21 -> 116.3 | F21: AROMA | G21: 1 | H21: =VLOOKUP(CONCILIÇÃO_COM_CERVEJA!$B21,CONT_ANTE!A:D,4,0) -> 188.5 | I21: =IF(AND(E21=0,H21<>J21),"!@##@!","ok") -> ok | J21: =VLOOKUP(CONCILIÇÃO_COM_CERVEJA!$B21,CONTAGEM!B:G,6,0) -> 325 | K21: =SUMIF(SISTEMA!B:B,CONCILIÇÃO_COM_CERVEJA!$B21,SISTEMA!I:I)/G21 -> 353.7704 | L21: =SUMIF(SISTEMA!B:B,CONCILIÇÃO_COM_CERVEJA!$C21,SISTEMA!I:I) -> 0 | M21: =K21+L21 -> 353.7704 | N21: =IFERROR(SUM(CONCILIÇÃO_COM_CERVEJA!$M21*CONCILIÇÃO_COM_CERVEJA!$R21),0) -> 17607.93 | O21: =IFERROR(VLOOKUP(CONCILIÇÃO_COM_CERVEJA!$B21,DIF_ANTE!A:D,4,0),"0")/CONCILIÇÃO_COM_CERVEJA!$G21 -> -26.5704 | P21: =J21-M21 -> -28.7704 | Q21: =CONCILIÇÃO_COM_CERVEJA!$P21-CONCILIÇÃO_COM_CERVEJA!$O21 -> -2.2 | R21: =IFERROR(VLOOKUP(CONCILIÇÃO_COM_CERVEJA!$B21,CUSTO!E:H,4,0),(VLOOKUP(CONCILIÇÃO_COM_CERVEJA!$A21,CUSTO!A:H,8,0))) -> 49.772196 | S21: =IFERROR(SUM(CONCILIÇÃO_COM_CERVEJA!$P21*CONCILIÇÃO_COM_CERVEJA!$R21),0) -> -1431.966 | T21: =IFERROR(#REF!/CONCILIÇÃO_COM_CERVEJA!$M21,"") | U21: =IFERROR(#REF!*CONCILIÇÃO_COM_CERVEJA!$R21,"-") -> -
A22: 31350 | B22: 2701050021 | C22: - | D22: AROMA IDENTICO AO NATURAL MORANGO DUAS RODAS | E22: =IFERROR(VLOOKUP(B22,[1]AGLUTINADO!$A:$C,3,0),0)/G22 -> 39.05 | F22: AROMA | G22: 1 | H22: =VLOOKUP(CONCILIÇÃO_COM_CERVEJA!$B22,CONT_ANTE!A:D,4,0) -> 110 | I22: =IF(AND(E22=0,H22<>J22),"!@##@!","ok") -> ok | J22: =VLOOKUP(CONCILIÇÃO_COM_CERVEJA!$B22,CONTAGEM!B:G,6,0) -> 121 | K22: =SUMIF(SISTEMA!B:B,CONCILIÇÃO_COM_CERVEJA!$B22,SISTEMA!I:I)/G22 -> 117.23 | L22: =SUMIF(SISTEMA!B:B,CONCILIÇÃO_COM_CERVEJA!$C22,SISTEMA!I:I) -> 0 | M22: =K22+L22 -> 117.23 | N22: =IFERROR(SUM(CONCILIÇÃO_COM_CERVEJA!$M22*CONCILIÇÃO_COM_CERVEJA!$R22),0) -> 7507.8957 | O22: =IFERROR(VLOOKUP(CONCILIÇÃO_COM_CERVEJA!$B22,DIF_ANTE!A:D,4,0),"0")/CONCILIÇÃO_COM_CERVEJA!$G22 -> 3.72 | P22: =J22-M22 -> 3.77 | Q22: =CONCILIÇÃO_COM_CERVEJA!$P22-CONCILIÇÃO_COM_CERVEJA!$O22 -> 0.05 | R22: =IFERROR(VLOOKUP(CONCILIÇÃO_COM_CERVEJA!$B22,CUSTO!E:H,4,0),(VLOOKUP(CONCILIÇÃO_COM_CERVEJA!$A22,CUSTO!A:H,8,0))) -> 64.04415 | S22: =IFERROR(SUM(CONCILIÇÃO_COM_CERVEJA!$P22*CONCILIÇÃO_COM_CERVEJA!$R22),0) -> 241.44645 | T22: =IFERROR(#REF!/CONCILIÇÃO_COM_CERVEJA!$M22,"") | U22: =IFERROR(#REF!*CONCILIÇÃO_COM_CERVEJA!$R22,"-") -> -
A23: 31346 | B23: 2701050026 | C23: - | D23: AROMA IDENTICO AO NATURAL PESSEGO RB 25049 SAPORITI | E23: =IFERROR(VLOOKUP(B23,[1]AGLUTINADO!$A:$C,3,0),0)/G23 -> 12.31 | F23: AROMA | G23: 1 | H23: =VLOOKUP(CONCILIÇÃO_COM_CERVEJA!$B23,CONT_ANTE!A:D,4,0) -> 55 | I23: =IF(AND(E23=0,H23<>J23),"!@##@!","ok") -> ok | J23: =VLOOKUP(CONCILIÇÃO_COM_CERVEJA!$B23,CONTAGEM!B:G,6,0) -> 41 | K23: =SUMIF(SISTEMA!B:B,CONCILIÇÃO_COM_CERVEJA!$B23,SISTEMA!I:I)/G23 -> 44.59 | L23: =SUMIF(SISTEMA!B:B,CONCILIÇÃO_COM_CERVEJA!$C23,SISTEMA!I:I) -> 0 | M23: =K23+L23 -> 44.59 | N23: =IFERROR(SUM(CONCILIÇÃO_COM_CERVEJA!$M23*CONCILIÇÃO_COM_CERVEJA!$R23),0) -> 2194.3185 | O23: =IFERROR(VLOOKUP(CONCILIÇÃO_COM_CERVEJA!$B23,DIF_ANTE!A:D,4,0),"0")/CONCILIÇÃO_COM_CERVEJA!$G23 -> -1.9 | P23: =J23-M23 -> -3.59 | Q23: =CONCILIÇÃO_COM_CERVEJA!$P23-CONCILIÇÃO_COM_CERVEJA!$O23 -> -1.69 | R23: =IFERROR(VLOOKUP(CONCILIÇÃO_COM_CERVEJA!$B23,CUSTO!E:H,4,0),(VLOOKUP(CONCILIÇÃO_COM_CERVEJA!$A23,CUSTO!A:H,8,0))) -> 49.211 | S23: =IFERROR(SUM(CONCILIÇÃO_COM_CERVEJA!$P23*CONCILIÇÃO_COM_CERVEJA!$R23),0) -> -176.66749 | T23: =IFERROR(#REF!/CONCILIÇÃO_COM_CERVEJA!$M23,"") | U23: =IFERROR(#REF!*CONCILIÇÃO_COM_CERVEJA!$R23,"-") -> -
A24: 31355 | B24: 2701050005 | C24: - | D24: AROMA NATURAL BAUNILHA KALABROS | E24: =IFERROR(VLOOKUP(B24,[1]AGLUTINADO!$A:$C,3,0),0)/G24 -> 0 | F24: AROMA | G24: 1 | H24: =VLOOKUP(CONCILIÇÃO_COM_CERVEJA!$B24,CONT_ANTE!A:D,4,0) -> 0 | I24: =IF(AND(E24=0,H24<>J24),"!@##@!","ok") -> ok | J24: =VLOOKUP(CONCILIÇÃO_COM_CERVEJA!$B24,CONTAGEM!B:G,6,0) -> 0 | K24: =SUMIF(SISTEMA!B:B,CONCILIÇÃO_COM_CERVEJA!$B24,SISTEMA!I:I)/G24 -> 0 | L24: =SUMIF(SISTEMA!B:B,CONCILIÇÃO_COM_CERVEJA!$C24,SISTEMA!I:I) -> 0 | M24: =K24+L24 -> 0 | N24: =IFERROR(SUM(CONCILIÇÃO_COM_CERVEJA!$M24*CONCILIÇÃO_COM_CERVEJA!$R24),0) -> 0 | O24: =IFERROR(VLOOKUP(CONCILIÇÃO_COM_CERVEJA!$B24,DIF_ANTE!A:D,4,0),"0")/CONCILIÇÃO_COM_CERVEJA!$G24 -> 0 | P24: =J24-M24 -> 0 | Q24: =CONCILIÇÃO_COM_CERVEJA!$P24-CONCILIÇÃO_COM_CERVEJA!$O24 -> 0 | R24: =IFERROR(VLOOKUP(CONCILIÇÃO_COM_CERVEJA!$B24,CUSTO!E:H,4,0),(VLOOKUP(CONCILIÇÃO_COM_CERVEJA!$A24,CUSTO!A:H,8,0))) -> 45.476671 | S24: =IFERROR(SUM(CONCILIÇÃO_COM_CERVEJA!$P24*CONCILIÇÃO_COM_CERVEJA!$R24),0) -> 0 | T24: =IFERROR(#REF!/CONCILIÇÃO_COM_CERVEJA!$M24,"") | U24: =IFERROR(#REF!*CONCILIÇÃO_COM_CERVEJA!$R24,"-") -> - | V24: OK
B25: 2701050007 | C25: - | D25: AROMA NATURAL DE CITRUS RB 25395 SAPORITI | E25: =IFERROR(VLOOKUP(B25,[1]AGLUTINADO!$A:$C,3,0),0)/G25 -> 0 | F25: AROMA | G25: 1 | H25: =VLOOKUP(CONCILIÇÃO_COM_CERVEJA!$B25,CONT_ANTE!A:D,4,0) -> 0 | I25: =IF(AND(E25=0,H25<>J25),"!@##@!","ok") -> ok | J25: =VLOOKUP(CONCILIÇÃO_COM_CERVEJA!$B25,CONTAGEM!B:G,6,0) -> 0 | K25: =SUMIF(SISTEMA!B:B,CONCILIÇÃO_COM_CERVEJA!$B25,SISTEMA!I:I)/G25 -> 0 | L25: =SUMIF(SISTEMA!B:B,CONCILIÇÃO_COM_CERVEJA!$C25,SISTEMA!I:I) -> 0 | M25: =K25+L25 -> 0 | N25: =IFERROR(SUM(CONCILIÇÃO_COM_CERVEJA!$M25*CONCILIÇÃO_COM_CERVEJA!$R25),0) -> 0 | O25: =IFERROR(VLOOKUP(CONCILIÇÃO_COM_CERVEJA!$B25,DIF_ANTE!A:D,4,0),"0")/CONCILIÇÃO_COM_CERVEJA!$G25 -> 0 | P25: =J25-M25 -> 0 | Q25: =CONCILIÇÃO_COM_CERVEJA!$P25-CONCILIÇÃO_COM_CERVEJA!$O25 -> 0 | R25: =IFERROR(VLOOKUP(CONCILIÇÃO_COM_CERVEJA!$B25,CUSTO!E:H,4,0),(VLOOKUP(CONCILIÇÃO_COM_CERVEJA!$A25,CUSTO!A:H,8,0))) -> 88.617222 | S25: =IFERROR(SUM(CONCILIÇÃO_COM_CERVEJA!$P25*CONCILIÇÃO_COM_CERVEJA!$R25),0) -> 0 | T25: =IFERROR(#REF!/CONCILIÇÃO_COM_CERVEJA!$M25,"") | U25: =IFERROR(#REF!*CONCILIÇÃO_COM_CERVEJA!$R25,"-") -> - | V25: OK
B26: 2701050036 | C26: - | D26: AROMA NATURAL DE TANGERINA DOHLER | E26: =IFERROR(VLOOKUP(B26,[1]AGLUTINADO!$A:$C,3,0),0)/G26 -> 0 | F26: AROMA | G26: 1 | H26: =VLOOKUP(CONCILIÇÃO_COM_CERVEJA!$B26,CONT_ANTE!A:D,4,0) -> 110 | I26: =IF(AND(E26=0,H26<>J26),"!@##@!","ok") -> ok | J26: =VLOOKUP(CONCILIÇÃO_COM_CERVEJA!$B26,CONTAGEM!B:G,6,0) -> 110 | K26: =SUMIF(SISTEMA!B:B,CONCILIÇÃO_COM_CERVEJA!$B26,SISTEMA!I:I)/G26 -> 119.11 | L26: =SUMIF(SISTEMA!B:B,CONCILIÇÃO_COM_CERVEJA!$C26,SISTEMA!I:I) -> 0 | M26: =K26+L26 -> 119.11 | N26: =IFERROR(SUM(CONCILIÇÃO_COM_CERVEJA!$M26*CONCILIÇÃO_COM_CERVEJA!$R26),0) -> 17253.905 | O26: =IFERROR(VLOOKUP(CONCILIÇÃO_COM_CERVEJA!$B26,DIF_ANTE!A:D,4,0),"0")/CONCILIÇÃO_COM_CERVEJA!$G26 -> -9.11 | P26: =J26-M26 -> -9.11 | Q26: =CONCILIÇÃO_COM_CERVEJA!$P26-CONCILIÇÃO_COM_CERVEJA!$O26 -> 0 | R26: =IFERROR(VLOOKUP(CONCILIÇÃO_COM_CERVEJA!$B26,CUSTO!E:H,4,0),(VLOOKUP(CONCILIÇÃO_COM_CERVEJA!$A26,CUSTO!A:H,8,0))) -> 144.8569 | S26: =IFERROR(SUM(CONCILIÇÃO_COM_CERVEJA!$P26*CONCILIÇÃO_COM_CERVEJA!$R26),0) -> -1319.6464 | T26: =IFERROR(#REF!/CONCILIÇÃO_COM_CERVEJA!$M26,"") | U26: =IFERROR(#REF!*CONCILIÇÃO_COM_CERVEJA!$R26,"-") -> - | V26: OK
A27: 31312 | B27: 2701050012 | C27: - | D27: AROMA NATURAL LIMAO VERDE MAJUFRAN | E27: =IFERROR(VLOOKUP(B27,[1]AGLUTINADO!$A:$C,3,0),0)/G27 -> 0 | F27: AROMA | G27: 1 | H27: =VLOOKUP(CONCILIÇÃO_COM_CERVEJA!$B27,CONT_ANTE!A:D,4,0) -> 25 | I27: =IF(AND(E27=0,H27<>J27),"!@##@!","ok") -> !@##@! | J27: =VLOOKUP(CONCILIÇÃO_COM_CERVEJA!$B27,CONTAGEM!B:G,6,0) -> 0 | K27: =SUMIF(SISTEMA!B:B,CONCILIÇÃO_COM_CERVEJA!$B27,SISTEMA!I:I)/G27 -> 0 | L27: =SUMIF(SISTEMA!B:B,CONCILIÇÃO_COM_CERVEJA!$C27,SISTEMA!I:I) -> 0 | M27: =K27+L27 -> 0 | N27: =IFERROR(SUM(CONCILIÇÃO_COM_CERVEJA!$M27*CONCILIÇÃO_COM_CERVEJA!$R27),0) -> 0 | O27: =IFERROR(VLOOKUP(CONCILIÇÃO_COM_CERVEJA!$B27,DIF_ANTE!A:D,4,0),"0")/CONCILIÇÃO_COM_CERVEJA!$G27 -> -0.90412 | P27: =J27-M27 -> 0 | Q27: =CONCILIÇÃO_COM_CERVEJA!$P27-CONCILIÇÃO_COM_CERVEJA!$O27 -> 0.90412 | R27: =IFERROR(VLOOKUP(CONCILIÇÃO_COM_CERVEJA!$B27,CUSTO!E:H,4,0),(VLOOKUP(CONCILIÇÃO_COM_CERVEJA!$A27,CUSTO!A:H,8,0))) -> 30.3832 | S27: =IFERROR(SUM(CONCILIÇÃO_COM_CERVEJA!$P27*CONCILIÇÃO_COM_CERVEJA!$R27),0) -> 0 | T27: =IFERROR(#REF!/CONCILIÇÃO_COM_CERVEJA!$M27,"") | U27: =IFERROR(#REF!*CONCILIÇÃO_COM_CERVEJA!$R27,"-") -> - | V27: OK
A28: 2477 | B28: 2701050001 | C28: - | D28: AROMA NATURAL MOUTHFEEL ADM | E28: =IFERROR(VLOOKUP(B28,[1]AGLUTINADO!$A:$C,3,0),0)/G28 -> 33.64 | F28: AROMA | G28: 1 | H28: =VLOOKUP(CONCILIÇÃO_COM_CERVEJA!$B28,CONT_ANTE!A:D,4,0) -> 114.84 | I28: =IF(AND(E28=0,H28<>J28),"!@##@!","ok") -> ok | J28: =VLOOKUP(CONCILIÇÃO_COM_CERVEJA!$B28,CONTAGEM!B:G,6,0) -> 70 | K28: =SUMIF(SISTEMA!B:B,CONCILIÇÃO_COM_CERVEJA!$B28,SISTEMA!I:I)/G28 -> 60.36 | L28: =SUMIF(SISTEMA!B:B,CONCILIÇÃO_COM_CERVEJA!$C28,SISTEMA!I:I) -> 0 | M28: =K28+L28 -> 60.36 | N28: =IFERROR(SUM(CONCILIÇÃO_COM_CERVEJA!$M28*CONCILIÇÃO_COM_CERVEJA!$R28),0) -> 8697.8849 | O28: =IFERROR(VLOOKUP(CONCILIÇÃO_COM_CERVEJA!$B28,DIF_ANTE!A:D,4,0),"0")/CONCILIÇÃO_COM_CERVEJA!$G28 -> -15.44 | P28: =J28-M28 -> 9.64 | Q28: =CONCILIÇÃO_COM_CERVEJA!$P28-CONCILIÇÃO_COM_CERVEJA!$O28 -> 25.08 | R28: =IFERROR(VLOOKUP(CONCILIÇÃO_COM_CERVEJA!$B28,CUSTO!E:H,4,0),(VLOOKUP(CONCILIÇÃO_COM_CERVEJA!$A28,CUSTO!A:H,8,0))) -> 144.10015 | S28: =IFERROR(SUM(CONCILIÇÃO_COM_CERVEJA!$P28*CONCILIÇÃO_COM_CERVEJA!$R28),0) -> 1389.1254 | T28: =IFERROR(#REF!/CONCILIÇÃO_COM_CERVEJA!$M28,"") | U28: =IFERROR(#REF!*CONCILIÇÃO_COM_CERVEJA!$R28,"-") -> -
A29: 353 | B29: 2701050028 | C29: - | D29: AROMA NATURAL VODKA DUAS RODAS | E29: =IFERROR(VLOOKUP(B29,[1]AGLUTINADO!$A:$C,3,0),0)/G29 -> 152.17 | F29: AROMA | G29: 1 | H29: =VLOOKUP(CONCILIÇÃO_COM_CERVEJA!$B29,CONT_ANTE!A:D,4,0) -> 0 | I29: =IF(AND(E29=0,H29<>J29),"!@##@!","ok") -> ok | J29: =VLOOKUP(CONCILIÇÃO_COM_CERVEJA!$B29,CONTAGEM!B:G,6,0) -> 270.5 | K29: =SUMIF(SISTEMA!B:B,CONCILIÇÃO_COM_CERVEJA!$B29,SISTEMA!I:I)/G29 -> 302.33 | L29: =SUMIF(SISTEMA!B:B,CONCILIÇÃO_COM_CERVEJA!$C29,SISTEMA!I:I) -> 0 | M29: =K29+L29 -> 302.33 | N29: =IFERROR(SUM(CONCILIÇÃO_COM_CERVEJA!$M29*CONCILIÇÃO_COM_CERVEJA!$R29),0) -> 6603.5292 | O29: =IFERROR(VLOOKUP(CONCILIÇÃO_COM_CERVEJA!$B29,DIF_ANTE!A:D,4,0),"0")/CONCILIÇÃO_COM_CERVEJA!$G29 -> 0 | P29: =J29-M29 -> -31.83 | Q29: =CONCILIÇÃO_COM_CERVEJA!$P29-CONCILIÇÃO_COM_CERVEJA!$O29 -> -31.83 | R29: =IFERROR(VLOOKUP(CONCILIÇÃO_COM_CERVEJA!$B29,CUSTO!E:H,4,0),(VLOOKUP(CONCILIÇÃO_COM_CERVEJA!$A29,CUSTO!A:H,8,0))) -> 21.842123 | S29: =IFERROR(SUM(CONCILIÇÃO_COM_CERVEJA!$P29*CONCILIÇÃO_COM_CERVEJA!$R29),0) -> -695.23479 | T29: =IFERROR(#REF!/CONCILIÇÃO_COM_CERVEJA!$M29,"") | U29: =IFERROR(#REF!*CONCILIÇÃO_COM_CERVEJA!$R29,"-") -> - | V29: ok
A30: 31518 | B30: 2701050023 | C30: - | D30: PREPARADO ACIDO COLA | E30: =IFERROR(VLOOKUP(B30,[1]AGLUTINADO!$A:$C,3,0),0)/G30 -> 61.52 | F30: AROMA | G30: 1 | H30: =VLOOKUP(CONCILIÇÃO_COM_CERVEJA!$B30,CONT_ANTE!A:D,4,0) -> 115 | I30: =IF(AND(E30=0,H30<>J30),"!@##@!","ok") -> ok | J30: =VLOOKUP(CONCILIÇÃO_COM_CERVEJA!$B30,CONTAGEM!B:G,6,0) -> 395 | K30: =SUMIF(SISTEMA!B:B,CONCILIÇÃO_COM_CERVEJA!$B30,SISTEMA!I:I)/G30 -> 372.21 | L30: =SUMIF(SISTEMA!B:B,CONCILIÇÃO_COM_CERVEJA!$C30,SISTEMA!I:I) -> 0 | M30: =K30+L30 -> 372.21 | N30: =IFERROR(SUM(CONCILIÇÃO_COM_CERVEJA!$M30*CONCILIÇÃO_COM_CERVEJA!$R30),0) -> 7508.034 | O30: =IFERROR(VLOOKUP(CONCILIÇÃO_COM_CERVEJA!$B30,DIF_ANTE!A:D,4,0),"0")/CONCILIÇÃO_COM_CERVEJA!$G30 -> 1.27 | P30: =J30-M30 -> 22.79 | Q30: =CONCILIÇÃO_COM_CERVEJA!$P30-CONCILIÇÃO_COM_CERVEJA!$O30 -> 21.52 | R30: =IFERROR(VLOOKUP(CONCILIÇÃO_COM_CERVEJA!$B30,CUSTO!E:H,4,0),(VLOOKUP(CONCILIÇÃO_COM_CERVEJA!$A30,CUSTO!A:H,8,0))) -> 20.1715 | S30: =IFERROR(SUM(CONCILIÇÃO_COM_CERVEJA!$P30*CONCILIÇÃO_COM_CERVEJA!$R30),0) -> 459.70849 | T30: =IFERROR(#REF!/CONCILIÇÃO_COM_CERVEJA!$M30,"") | U30: =IFERROR(#REF!*CONCILIÇÃO_COM_CERVEJA!$R30,"-") -> -
A31: 30758 | B31: 2701160011 | C31: - | D31: CAIXA CER BAMBOA LAGER 12X330ML | E31: =IFERROR(VLOOKUP(B31,[1]AGLUTINADO!$A:$C,3,0),0)/G31 -> 6688 | F31: CAIXA | G31: 1 | H31: =VLOOKUP(CONCILIÇÃO_COM_CERVEJA!$B31,CONT_ANTE!A:D,4,0) -> 39805 | I31: =IF(AND(E31=0,H31<>J31),"!@##@!","ok") -> ok | J31: =VLOOKUP(CONCILIÇÃO_COM_CERVEJA!$B31,CONTAGEM!B:G,6,0) -> 32600 | K31: =SUMIF(SISTEMA!B:B,CONCILIÇÃO_COM_CERVEJA!$B31,SISTEMA!I:I)/G31 -> 34779 | L31: =SUMIF(SISTEMA!B:B,CONCILIÇÃO_COM_CERVEJA!$C31,SISTEMA!I:I) -> 0 | M31: =K31+L31 -> 34779 | N31: =IFERROR(SUM(CONCILIÇÃO_COM_CERVEJA!$M31*CONCILIÇÃO_COM_CERVEJA!$R31),0) -> 54008.524 | O31: =IFERROR(VLOOKUP(CONCILIÇÃO_COM_CERVEJA!$B31,DIF_ANTE!A:D,4,0),"0")/CONCILIÇÃO_COM_CERVEJA!$G31 -> -1662 | P31: =J31-M31 -> -2179 | Q31: =CONCILIÇÃO_COM_CERVEJA!$P31-CONCILIÇÃO_COM_CERVEJA!$O31 -> -517 | R31: =IFERROR(VLOOKUP(CONCILIÇÃO_COM_CERVEJA!$B31,CUSTO!E:H,4,0),(VLOOKUP(CONCILIÇÃO_COM_CERVEJA!$A31,CUSTO!A:H,8,0))) -> 1.5529062 | S31: =IFERROR(SUM(CONCILIÇÃO_COM_CERVEJA!$P31*CONCILIÇÃO_COM_CERVEJA!$R31),0) -> -3383.7826 | T31: =IFERROR(#REF!/CONCILIÇÃO_COM_CERVEJA!$M31,"") | U31: =IFERROR(#REF!*CONCILIÇÃO_COM_CERVEJA!$R31,"-") -> -
A32: 30756 | B32: 2701160008 | C32: - | D32: CAIXA CER BAMBOA PILSEN 12X300ML | E32: =IFERROR(VLOOKUP(B32,[1]AGLUTINADO!$A:$C,3,0),0)/G32 -> 0 | F32: CAIXA | G32: 1 | H32: =VLOOKUP(CONCILIÇÃO_COM_CERVEJA!$B32,CONT_ANTE!A:D,4,0) -> 0 | I32: =IF(AND(E32=0,H32<>J32),"!@##@!","ok") -> ok | J32: =VLOOKUP(CONCILIÇÃO_COM_CERVEJA!$B32,CONTAGEM!B:G,6,0) -> 0 | K32: =SUMIF(SISTEMA!B:B,CONCILIÇÃO_COM_CERVEJA!$B32,SISTEMA!I:I)/G32 -> 0 | L32: =SUMIF(SISTEMA!B:B,CONCILIÇÃO_COM_CERVEJA!$C32,SISTEMA!I:I) -> 0 | M32: =K32+L32 -> 0 | N32: =IFERROR(SUM(CONCILIÇÃO_COM_CERVEJA!$M32*CONCILIÇÃO_COM_CERVEJA!$R32),0) -> 0 | O32: =IFERROR(VLOOKUP(CONCILIÇÃO_COM_CERVEJA!$B32,DIF_ANTE!A:D,4,0),"0")/CONCILIÇÃO_COM_CERVEJA!$G32 -> 0 | P32: =J32-M32 -> 0 | Q32: =CONCILIÇÃO_COM_CERVEJA!$P32-CONCILIÇÃO_COM_CERVEJA!$O32 -> 0 | R32: =IFERROR(VLOOKUP(CONCILIÇÃO_COM_CERVEJA!$B32,CUSTO!E:H,4,0),(VLOOKUP(CONCILIÇÃO_COM_CERVEJA!$A32,CUSTO!A:H,8,0))) -> 1.3587996 | S32: =IFERROR(SUM(CONCILIÇÃO_COM_CERVEJA!$P32*CONCILIÇÃO_COM_CERVEJA!$R32),0) -> 0 | T32: =IFERROR(#REF!/CONCILIÇÃO_COM_CERVEJA!$M32,"") | U32: =IFERROR(#REF!*CONCILIÇÃO_COM_CERVEJA!$R32,"-") -> - | V32: OK
A33: 1444 | B33: 2701160007 | C33: - | D33: CAIXA CER BAMBOA PILSEN 6X600ML | E33: =IFERROR(VLOOKUP(B33,[1]AGLUTINADO!$A:$C,3,0),0)/G33 -> 0 | F33: CAIXA | G33: 1 | H33: =VLOOKUP(CONCILIÇÃO_COM_CERVEJA!$B33,CONT_ANTE!A:D,4,0) -> 0 | I33: =IF(AND(E33=0,H33<>J33),"!@##@!","ok") -> ok | J33: =VLOOKUP(CONCILIÇÃO_COM_CERVEJA!$B33,CONTAGEM!B:G,6,0) -> 0 | K33: =SUMIF(SISTEMA!B:B,CONCILIÇÃO_COM_CERVEJA!$B33,SISTEMA!I:I)/G33 -> 0 | L33: =SUMIF(SISTEMA!B:B,CONCILIÇÃO_COM_CERVEJA!$C33,SISTEMA!I:I) -> 0 | M33: =K33+L33 -> 0 | N33: =IFERROR(SUM(CONCILIÇÃO_COM_CERVEJA!$M33*CONCILIÇÃO_COM_CERVEJA!$R33),0) -> 0 | O33: =IFERROR(VLOOKUP(CONCILIÇÃO_COM_CERVEJA!$B33,DIF_ANTE!A:D,4,0),"0")/CONCILIÇÃO_COM_CERVEJA!$G33 -> 0 | P33: =J33-M33 -> 0 | Q33: =CONCILIÇÃO_COM_CERVEJA!$P33-CONCILIÇÃO_COM_CERVEJA!$O33 -> 0 | R33: =IFERROR(VLOOKUP(CONCILIÇÃO_COM_CERVEJA!$B33,CUSTO!E:H,4,0),(VLOOKUP(CONCILIÇÃO_COM_CERVEJA!$A33,CUSTO!A:H,8,0))) -> 2.1716379 | S33: =IFERROR(SUM(CONCILIÇÃO_COM_CERVEJA!$P33*CONCILIÇÃO_COM_CERVEJA!$R33),0) -> 0 | T33: =IFERROR(#REF!/CONCILIÇÃO_COM_CERVEJA!$M33,"") | U33: =IFERROR(#REF!*CONCILIÇÃO_COM_CERVEJA!$R33,"-") -> - | V33: OK
A34: 30739 | B34: 2701160006 | C34: - | D34: CAIXA CER MOEMA 12X300ML | E34: =IFERROR(VLOOKUP(B34,[1]AGLUTINADO!$A:$C,3,0),0)/G34 -> 0 | F34: CAIXA | G34: 1 | H34: =VLOOKUP(CONCILIÇÃO_COM_CERVEJA!$B34,CONT_ANTE!A:D,4,0) -> 4400 | I34: =IF(AND(E34=0,H34<>J34),"!@##@!","ok") -> ok | J34: =VLOOKUP(CONCILIÇÃO_COM_CERVEJA!$B34,CONTAGEM!B:G,6,0) -> 4400 | K34: =SUMIF(SISTEMA!B:B,CONCILIÇÃO_COM_CERVEJA!$B34,SISTEMA!I:I)/G34 -> 4400 | L34: =SUMIF(SISTEMA!B:B,CONCILIÇÃO_COM_CERVEJA!$C34,SISTEMA!I:I) -> 0 | M34: =K34+L34 -> 4400 | N34: =IFERROR(SUM(CONCILIÇÃO_COM_CERVEJA!$M34*CONCILIÇÃO_COM_CERVEJA!$R34),0) -> 8173.3211 | O34: =IFERROR(VLOOKUP(CONCILIÇÃO_COM_CERVEJA!$B34,DIF_ANTE!A:D,4,0),"0")/CONCILIÇÃO_COM_CERVEJA!$G34 -> 0 | P34: =J34-M34 -> 0 | Q34: =CONCILIÇÃO_COM_CERVEJA!$P34-CONCILIÇÃO_COM_CERVEJA!$O34 -> 0 | R34: =IFERROR(VLOOKUP(CONCILIÇÃO_COM_CERVEJA!$B34,CUSTO!E:H,4,0),(VLOOKUP(CONCILIÇÃO_COM_CERVEJA!$A34,CUSTO!A:H,8,0))) -> 1.857573 | S34: =IFERROR(SUM(CONCILIÇÃO_COM_CERVEJA!$P34*CONCILIÇÃO_COM_CERVEJA!$R34),0) -> 0 | T34: =IFERROR(#REF!/CONCILIÇÃO_COM_CERVEJA!$M34,"") | U34: =IFERROR(#REF!*CONCILIÇÃO_COM_CERVEJA!$R34,"-") -> - | V34: OK
A35: 30738 | B35: 2701160005 | C35: - | D35: CAIXA CER MOEMA 6X600ML | E35: =IFERROR(VLOOKUP(B35,[1]AGLUTINADO!$A:$C,3,0),0)/G35 -> 0 | F35: CAIXA | G35: 1 | H35: =VLOOKUP(CONCILIÇÃO_COM_CERVEJA!$B35,CONT_ANTE!A:D,4,0) -> 10597 | I35: =IF(AND(E35=0,H35<>J35),"!@##@!","ok") -> !@##@! | J35: =VLOOKUP(CONCILIÇÃO_COM_CERVEJA!$B35,CONTAGEM!B:G,6,0) -> 10537 | K35: =SUMIF(SISTEMA!B:B,CONCILIÇÃO_COM_CERVEJA!$B35,SISTEMA!I:I)/G35 -> 11537 | L35: =SUMIF(SISTEMA!B:B,CONCILIÇÃO_COM_CERVEJA!$C35,SISTEMA!I:I) -> 0 | M35: =K35+L35 -> 11537 | N35: =IFERROR(SUM(CONCILIÇÃO_COM_CERVEJA!$M35*CONCILIÇÃO_COM_CERVEJA!$R35),0) -> 15676.471 | O35: =IFERROR(VLOOKUP(CONCILIÇÃO_COM_CERVEJA!$B35,DIF_ANTE!A:D,4,0),"0")/CONCILIÇÃO_COM_CERVEJA!$G35 -> -1000 | P35: =J35-M35 -> -1000 | Q35: =CONCILIÇÃO_COM_CERVEJA!$P35-CONCILIÇÃO_COM_CERVEJA!$O35 -> 0 | R35: =IFERROR(VLOOKUP(CONCILIÇÃO_COM_CERVEJA!$B35,CUSTO!E:H,4,0),(VLOOKUP(CONCILIÇÃO_COM_CERVEJA!$A35,CUSTO!A:H,8,0))) -> 1.3587996 | S35: =IFERROR(SUM(CONCILIÇÃO_COM_CERVEJA!$P35*CONCILIÇÃO_COM_CERVEJA!$R35),0) -> -1358.7996 | T35: =IFERROR(#REF!/CONCILIÇÃO_COM_CERVEJA!$M35,"") | U35: =IFERROR(#REF!*CONCILIÇÃO_COM_CERVEJA!$R35,"-") -> - | V35: OK
A36: 32711 | B36: 2701160001 | C36: - | D36: CAIXA GIN JAMES COOK 6X900ML | E36: =IFERROR(VLOOKUP(B36,[1]AGLUTINADO!$A:$C,3,0),0)/G36 -> 795 | F36: CAIXA | G36: 1 | H36: =VLOOKUP(CONCILIÇÃO_COM_CERVEJA!$B36,CONT_ANTE!A:D,4,0) -> 800 | I36: =IF(AND(E36=0,H36<>J36),"!@##@!","ok") -> ok | J36: =VLOOKUP(CONCILIÇÃO_COM_CERVEJA!$B36,CONTAGEM!B:G,6,0) -> 0 | K36: =SUMIF(SISTEMA!B:B,CONCILIÇÃO_COM_CERVEJA!$B36,SISTEMA!I:I)/G36 -> 20 | L36: =SUMIF(SISTEMA!B:B,CONCILIÇÃO_COM_CERVEJA!$C36,SISTEMA!I:I) -> 0 | M36: =K36+L36 -> 20 | N36: =IFERROR(SUM(CONCILIÇÃO_COM_CERVEJA!$M36*CONCILIÇÃO_COM_CERVEJA!$R36),0) -> 49.96335 | O36: =IFERROR(VLOOKUP(CONCILIÇÃO_COM_CERVEJA!$B36,DIF_ANTE!A:D,4,0),"0")/CONCILIÇÃO_COM_CERVEJA!$G36 -> -15 | P36: =J36-M36 -> -20 | Q36: =CONCILIÇÃO_COM_CERVEJA!$P36-CONCILIÇÃO_COM_CERVEJA!$O36 -> -5 | R36: =IFERROR(VLOOKUP(CONCILIÇÃO_COM_CERVEJA!$B36,CUSTO!E:H,4,0),(VLOOKUP(CONCILIÇÃO_COM_CERVEJA!$A36,CUSTO!A:H,8,0))) -> 2.4981675 | S36: =IFERROR(SUM(CONCILIÇÃO_COM_CERVEJA!$P36*CONCILIÇÃO_COM_CERVEJA!$R36),0) -> -49.96335 | T36: =IFERROR(#REF!/CONCILIÇÃO_COM_CERVEJA!$M36,"") | U36: =IFERROR(#REF!*CONCILIÇÃO_COM_CERVEJA!$R36,"-") -> -
A37: 31584 | B37: 2701160012 | C37: - | D37: CAIXA REFRIGERANTE REFRIKO TUBAINA 12X300ML | E37: =IFERROR(VLOOKUP(B37,[1]AGLUTINADO!$A:$C,3,0),0)/G37 -> 10177 | F37: CAIXA | G37: 1 | H37: =VLOOKUP(CONCILIÇÃO_COM_CERVEJA!$B37,CONT_ANTE!A:D,4,0) -> 17200 | I37: =IF(AND(E37=0,H37<>J37),"!@##@!","ok") -> ok | J37: =VLOOKUP(CONCILIÇÃO_COM_CERVEJA!$B37,CONTAGEM!B:G,6,0) -> 25425 | K37: =SUMIF(SISTEMA!B:B,CONCILIÇÃO_COM_CERVEJA!$B37,SISTEMA!I:I)/G37 -> 28252 | L37: =SUMIF(SISTEMA!B:B,CONCILIÇÃO_COM_CERVEJA!$C37,SISTEMA!I:I) -> 0 | M37: =K37+L37 -> 28252 | N37: =IFERROR(SUM(CONCILIÇÃO_COM_CERVEJA!$M37*CONCILIÇÃO_COM_CERVEJA!$R37),0) -> 44532.761 | O37: =IFERROR(VLOOKUP(CONCILIÇÃO_COM_CERVEJA!$B37,DIF_ANTE!A:D,4,0),"0")/CONCILIÇÃO_COM_CERVEJA!$G37 -> -454 | P37: =J37-M37 -> -2827 | Q37: =CONCILIÇÃO_COM_CERVEJA!$P37-CONCILIÇÃO_COM_CERVEJA!$O37 -> -2373 | R37: =IFERROR(VLOOKUP(CONCILIÇÃO_COM_CERVEJA!$B37,CUSTO!E:H,4,0),(VLOOKUP(CONCILIÇÃO_COM_CERVEJA!$A37,CUSTO!A:H,8,0))) -> 1.5762693 | S37: =IFERROR(SUM(CONCILIÇÃO_COM_CERVEJA!$P37*CONCILIÇÃO_COM_CERVEJA!$R37),0) -> -4456.1133 | T37: =IFERROR(#REF!/CONCILIÇÃO_COM_CERVEJA!$M37,"") | U37: =IFERROR(#REF!*CONCILIÇÃO_COM_CERVEJA!$R37,"-") -> -
B38: 2701160013 | C38: - | D38: CAIXA REFRIGERANTE REFRIKO TUBAINA 12X355ML | E38: =IFERROR(VLOOKUP(B38,[1]AGLUTINADO!$A:$C,3,0),0)/G38 -> 0 | F38: CAIXA | G38: 1 | H38: =VLOOKUP(CONCILIÇÃO_COM_CERVEJA!$B38,CONT_ANTE!A:D,4,0) -> 21167 | I38: =IF(AND(E38=0,H38<>J38),"!@##@!","ok") -> !@##@! | J38: =VLOOKUP(CONCILIÇÃO_COM_CERVEJA!$B38,CONTAGEM!B:G,6,0) -> 18812 | K38: =SUMIF(SISTEMA!B:B,CONCILIÇÃO_COM_CERVEJA!$B38,SISTEMA!I:I)/G38 -> 18877 | L38: =SUMIF(SISTEMA!B:B,CONCILIÇÃO_COM_CERVEJA!$C38,SISTEMA!I:I) -> 0 | M38: =K38+L38 -> 18877 | N38: =IFERROR(SUM(CONCILIÇÃO_COM_CERVEJA!$M38*CONCILIÇÃO_COM_CERVEJA!$R38),0) -> 35614.631 | O38: =IFERROR(VLOOKUP(CONCILIÇÃO_COM_CERVEJA!$B38,DIF_ANTE!A:D,4,0),"0")/CONCILIÇÃO_COM_CERVEJA!$G38 -> 0 | P38: =J38-M38 -> -65 | Q38: =CONCILIÇÃO_COM_CERVEJA!$P38-CONCILIÇÃO_COM_CERVEJA!$O38 -> -65 | R38: =IFERROR(VLOOKUP(CONCILIÇÃO_COM_CERVEJA!$B38,CUSTO!E:H,4,0),(VLOOKUP(CONCILIÇÃO_COM_CERVEJA!$A38,CUSTO!A:H,8,0))) -> 1.886668 | S38: =IFERROR(SUM(CONCILIÇÃO_COM_CERVEJA!$P38*CONCILIÇÃO_COM_CERVEJA!$R38),0) -> -122.63342 | T38: =IFERROR(#REF!/CONCILIÇÃO_COM_CERVEJA!$M38,"") | U38: =IFERROR(#REF!*CONCILIÇÃO_COM_CERVEJA!$R38,"-") -> -
B39: 2701160009 | C39: - | D39: CAIXA REFRIGERANTE REFRIKO TUBAINA S/ ACUCARES 12X300ML | E39: =IFERROR(VLOOKUP(B39,[1]AGLUTINADO!$A:$C,3,0),0)/G39 -> 2693 | F39: CAIXA | G39: 1 | H39: =VLOOKUP(CONCILIÇÃO_COM_CERVEJA!$B39,CONT_ANTE!A:D,4,0) -> 26875 | I39: =IF(AND(E39=0,H39<>J39),"!@##@!","ok") -> ok | J39: =VLOOKUP(CONCILIÇÃO_COM_CERVEJA!$B39,CONTAGEM!B:G,6,0) -> 23945 | K39: =SUMIF(SISTEMA!B:B,CONCILIÇÃO_COM_CERVEJA!$B39,SISTEMA!I:I)/G39 -> 24182 | L39: =SUMIF(SISTEMA!B:B,CONCILIÇÃO_COM_CERVEJA!$C39,SISTEMA!I:I) -> 0 | M39: =K39+L39 -> 24182 | N39: =IFERROR(SUM(CONCILIÇÃO_COM_CERVEJA!$M39*CONCILIÇÃO_COM_CERVEJA!$R39),0) -> 37122.88 | O39: =IFERROR(VLOOKUP(CONCILIÇÃO_COM_CERVEJA!$B39,DIF_ANTE!A:D,4,0),"0")/CONCILIÇÃO_COM_CERVEJA!$G39 -> 0 | P39: =J39-M39 -> -237 | Q39: =CONCILIÇÃO_COM_CERVEJA!$P39-CONCILIÇÃO_COM_CERVEJA!$O39 -> -237 | R39: =IFERROR(VLOOKUP(CONCILIÇÃO_COM_CERVEJA!$B39,CUSTO!E:H,4,0),(VLOOKUP(CONCILIÇÃO_COM_CERVEJA!$A39,CUSTO!A:H,8,0))) -> 1.5351451 | S39: =IFERROR(SUM(CONCILIÇÃO_COM_CERVEJA!$P39*CONCILIÇÃO_COM_CERVEJA!$R39),0) -> -363.8294 | T39: =IFERROR(#REF!/CONCILIÇÃO_COM_CERVEJA!$M39,"") | U39: =IFERROR(#REF!*CONCILIÇÃO_COM_CERVEJA!$R39,"-") -> -
A40: 32714 | B40: 2701160002 | C40: - | D40: CAIXA VODKA JAMES COOK 6X900ML | E40: =IFERROR(VLOOKUP(B40,[1]AGLUTINADO!$A:$C,3,0),0)/G40 -> 1736 | F40: CAIXA | G40: 1 | H40: =VLOOKUP(CONCILIÇÃO_COM_CERVEJA!$B40,CONT_ANTE!A:D,4,0) -> 4804 | I40: =IF(AND(E40=0,H40<>J40),"!@##@!","ok") -> ok | J40: =VLOOKUP(CONCILIÇÃO_COM_CERVEJA!$B40,CONTAGEM!B:G,6,0) -> 3284 | K40: =SUMIF(SISTEMA!B:B,CONCILIÇÃO_COM_CERVEJA!$B40,SISTEMA!I:I)/G40 -> 3112 | L40: =SUMIF(SISTEMA!B:B,CONCILIÇÃO_COM_CERVEJA!$C40,SISTEMA!I:I) -> 0 | M40: =K40+L40 -> 3112 | N40: =IFERROR(SUM(CONCILIÇÃO_COM_CERVEJA!$M40*CONCILIÇÃO_COM_CERVEJA!$R40),0) -> 7774.2854 | O40: =IFERROR(VLOOKUP(CONCILIÇÃO_COM_CERVEJA!$B40,DIF_ANTE!A:D,4,0),"0")/CONCILIÇÃO_COM_CERVEJA!$G40 -> -44 | P40: =J40-M40 -> 172 | Q40: =CONCILIÇÃO_COM_CERVEJA!$P40-CONCILIÇÃO_COM_CERVEJA!$O40 -> 216 | R40: =IFERROR(VLOOKUP(CONCILIÇÃO_COM_CERVEJA!$B40,CUSTO!E:H,4,0),(VLOOKUP(CONCILIÇÃO_COM_CERVEJA!$A40,CUSTO!A:H,8,0))) -> 2.4981637 | S40: =IFERROR(SUM(CONCILIÇÃO_COM_CERVEJA!$P40*CONCILIÇÃO_COM_CERVEJA!$R40),0) -> 429.68415 | T40: =IFERROR(#REF!/CONCILIÇÃO_COM_CERVEJA!$M40,"") | U40: =IFERROR(#REF!*CONCILIÇÃO_COM_CERVEJA!$R40,"-") -> -
A41: 30574 | B41: 2701240002 | C41: - | D41: CANTONEIRA SIMPLES 100X100X1580MM | E41: =IFERROR(VLOOKUP(B41,[1]AGLUTINADO!$A:$C,3,0),0)/G41 -> 556.46477 | F41: CAIXA | G41: 1 | H41: =VLOOKUP(CONCILIÇÃO_COM_CERVEJA!$B41,CONT_ANTE!A:D,4,0) -> 6360 | I41: =IF(AND(E41=0,H41<>J41),"!@##@!","ok") -> ok | J41: =VLOOKUP(CONCILIÇÃO_COM_CERVEJA!$B41,CONTAGEM!B:G,6,0) -> 6200 | K41: =SUMIF(SISTEMA!B:B,CONCILIÇÃO_COM_CERVEJA!$B41,SISTEMA!I:I)/G41 -> 4126.6767 | L41: =SUMIF(SISTEMA!B:B,CONCILIÇÃO_COM_CERVEJA!$C41,SISTEMA!I:I) -> 0 | M41: =K41+L41 -> 4126.6767 | N41: =IFERROR(SUM(CONCILIÇÃO_COM_CERVEJA!$M41*CONCILIÇÃO_COM_CERVEJA!$R41),0) -> 5035.4694 | O41: =IFERROR(VLOOKUP(CONCILIÇÃO_COM_CERVEJA!$B41,DIF_ANTE!A:D,4,0),"0")/CONCILIÇÃO_COM_CERVEJA!$G41 -> 120.8601 | P41: =J41-M41 -> 2073.3233 | Q41: =CONCILIÇÃO_COM_CERVEJA!$P41-CONCILIÇÃO_COM_CERVEJA!$O41 -> 1952.4632 | R41: =IFERROR(VLOOKUP(CONCILIÇÃO_COM_CERVEJA!$B41,CUSTO!E:H,4,0),(VLOOKUP(CONCILIÇÃO_COM_CERVEJA!$A41,CUSTO!A:H,8,0))) -> 1.2202239 | S41: =IFERROR(SUM(CONCILIÇÃO_COM_CERVEJA!$P41*CONCILIÇÃO_COM_CERVEJA!$R41),0) -> 2529.9186 | T41: =IFERROR(#REF!/CONCILIÇÃO_COM_CERVEJA!$M41,"") | U41: =IFERROR(#REF!*CONCILIÇÃO_COM_CERVEJA!$R41,"-") -> -
B42: 2701240004 | C42: - | D42: CHAPA SEM IMPRESSAO 1000X1200MM | E42: =IFERROR(VLOOKUP(B42,[1]AGLUTINADO!$A:$C,3,0),0)/G42 -> 14735.345 | F42: CAIXA | G42: 1 | H42: =VLOOKUP(CONCILIÇÃO_COM_CERVEJA!$B42,CONT_ANTE!A:D,4,0) -> 15828.571 | I42: =IF(AND(E42=0,H42<>J42),"!@##@!","ok") -> ok | J42: =VLOOKUP(CONCILIÇÃO_COM_CERVEJA!$B42,CONTAGEM!B:G,6,0) -> 40650 | K42: =SUMIF(SISTEMA!B:B,CONCILIÇÃO_COM_CERVEJA!$B42,SISTEMA!I:I)/G42 -> 49041.124 | L42: =SUMIF(SISTEMA!B:B,CONCILIÇÃO_COM_CERVEJA!$C42,SISTEMA!I:I) -> 0 | M42: =K42+L42 -> 49041.124 | N42: =IFERROR(SUM(CONCILIÇÃO_COM_CERVEJA!$M42*CONCILIÇÃO_COM_CERVEJA!$R42),0) -> 51921.141 | O42: =IFERROR(VLOOKUP(CONCILIÇÃO_COM_CERVEJA!$B42,DIF_ANTE!A:D,4,0),"0")/CONCILIÇÃO_COM_CERVEJA!$G42 -> -5643.8971 | P42: =J42-M42 -> -8391.1239 | Q42: =CONCILIÇÃO_COM_CERVEJA!$P42-CONCILIÇÃO_COM_CERVEJA!$O42 -> -2747.2268 | R42: =IFERROR(VLOOKUP(CONCILIÇÃO_COM_CERVEJA!$B42,CUSTO!E:H,4,0),(VLOOKUP(CONCILIÇÃO_COM_CERVEJA!$A42,CUSTO!A:H,8,0))) -> 1.0587266 | S42: =IFERROR(SUM(CONCILIÇÃO_COM_CERVEJA!$P42*CONCILIÇÃO_COM_CERVEJA!$R42),0) -> -8883.9058 | T42: =IFERROR(#REF!/CONCILIÇÃO_COM_CERVEJA!$M42,"") | U42: =IFERROR(#REF!*CONCILIÇÃO_COM_CERVEJA!$R42,"-") -> -
B43: 2701240005 | C43: - | D43: CHAPA SEM IMPRESSAO CORRUGADA 1000X1200MM | E43: =IFERROR(VLOOKUP(B43,[1]AGLUTINADO!$A:$C,3,0),0)/G43 -> 423.35962 | F43: CAIXA | G43: 1 | H43: =VLOOKUP(CONCILIÇÃO_COM_CERVEJA!$B43,CONT_ANTE!A:D,4,0) -> 8300 | I43: =IF(AND(E43=0,H43<>J43),"!@##@!","ok") -> ok | J43: =VLOOKUP(CONCILIÇÃO_COM_CERVEJA!$B43,CONTAGEM!B:G,6,0) -> 7600 | K43: =SUMIF(SISTEMA!B:B,CONCILIÇÃO_COM_CERVEJA!$B43,SISTEMA!I:I)/G43 -> 7715.0033 | L43: =SUMIF(SISTEMA!B:B,CONCILIÇÃO_COM_CERVEJA!$C43,SISTEMA!I:I) -> 0 | M43: =K43+L43 -> 7715.0033 | N43: =IFERROR(SUM(CONCILIÇÃO_COM_CERVEJA!$M43*CONCILIÇÃO_COM_CERVEJA!$R43),0) -> 26420.679 | O43: =IFERROR(VLOOKUP(CONCILIÇÃO_COM_CERVEJA!$B43,DIF_ANTE!A:D,4,0),"0")/CONCILIÇÃO_COM_CERVEJA!$G43 -> 161.63712 | P43: =J43-M43 -> -115.00326 | Q43: =CONCILIÇÃO_COM_CERVEJA!$P43-CONCILIÇÃO_COM_CERVEJA!$O43 -> -276.64038 | R43: =IFERROR(VLOOKUP(CONCILIÇÃO_COM_CERVEJA!$B43,CUSTO!E:H,4,0),(VLOOKUP(CONCILIÇÃO_COM_CERVEJA!$A43,CUSTO!A:H,8,0))) -> 3.4245843 | S43: =IFERROR(SUM(CONCILIÇÃO_COM_CERVEJA!$P43*CONCILIÇÃO_COM_CERVEJA!$R43),0) -> -393.83836 | T43: =IFERROR(#REF!/CONCILIÇÃO_COM_CERVEJA!$M43,"") | U43: =IFERROR(#REF!*CONCILIÇÃO_COM_CERVEJA!$R43,"-") -> -
A44: 60 | B44: 3002020007 | C44: - | D44: CARVAO ATIVADO | E44: =IFERROR(VLOOKUP(B44,[1]AGLUTINADO!$A:$C,3,0),0)/G44 -> 0 | F44: CARVAO | G44: 1 | H44: =VLOOKUP(CONCILIÇÃO_COM_CERVEJA!$B44,CONT_ANTE!A:D,4,0) -> 355 | I44: =IF(AND(E44=0,H44<>J44),"!@##@!","ok") -> !@##@! | J44: =VLOOKUP(CONCILIÇÃO_COM_CERVEJA!$B44,CONTAGEM!B:G,6,0) -> 800 | K44: =SUMIF(SISTEMA!B:B,CONCILIÇÃO_COM_CERVEJA!$B44,SISTEMA!I:I)/G44 -> 860 | L44: =SUMIF(SISTEMA!B:B,CONCILIÇÃO_COM_CERVEJA!$C44,SISTEMA!I:I) -> 0 | M44: =K44+L44 -> 860 | N44: =IFERROR(SUM(CONCILIÇÃO_COM_CERVEJA!$M44*CONCILIÇÃO_COM_CERVEJA!$R44),0) -> 9072.742 | O44: =IFERROR(VLOOKUP(CONCILIÇÃO_COM_CERVEJA!$B44,DIF_ANTE!A:D,4,0),"0")/CONCILIÇÃO_COM_CERVEJA!$G44 -> -5 | P44: =J44-M44 -> -60 | Q44: =CONCILIÇÃO_COM_CERVEJA!$P44-CONCILIÇÃO_COM_CERVEJA!$O44 -> -55 | R44: =IFERROR(VLOOKUP(CONCILIÇÃO_COM_CERVEJA!$B44,CUSTO!E:H,4,0),(VLOOKUP(CONCILIÇÃO_COM_CERVEJA!$A44,CUSTO!A:H,8,0))) -> 10.5497 | S44: =IFERROR(SUM(CONCILIÇÃO_COM_CERVEJA!$P44*CONCILIÇÃO_COM_CERVEJA!$R44),0) -> -632.982 | T44: =IFERROR(#REF!/CONCILIÇÃO_COM_CERVEJA!$M44,"") | U44: =IFERROR(#REF!*CONCILIÇÃO_COM_CERVEJA!$R44,"-") -> -
A45: 30257 | B45: 2701090003 | C45: - | D45: ACIDO LACTICO | E45: =IFERROR(VLOOKUP(B45,[1]AGLUTINADO!$A:$C,3,0),0)/G45 -> 350.59991 | F45: CERVEJARIA | G45: 1 | H45: =VLOOKUP(CONCILIÇÃO_COM_CERVEJA!$B45,CONT_ANTE!A:D,4,0) -> 325 | I45: =IF(AND(E45=0,H45<>J45),"!@##@!","ok") -> ok | J45: =VLOOKUP(CONCILIÇÃO_COM_CERVEJA!$B45,CONTAGEM!B:G,6,0) -> 900 | K45: =SUMIF(SISTEMA!B:B,CONCILIÇÃO_COM_CERVEJA!$B45,SISTEMA!I:I)/G45 -> 974.40009 | L45: =SUMIF(SISTEMA!B:B,CONCILIÇÃO_COM_CERVEJA!$C45,SISTEMA!I:I) -> 0 | M45: =K45+L45 -> 974.40009 | N45: =IFERROR(SUM(CONCILIÇÃO_COM_CERVEJA!$M45*CONCILIÇÃO_COM_CERVEJA!$R45),0) -> 8954.2357 | O45: =IFERROR(VLOOKUP(CONCILIÇÃO_COM_CERVEJA!$B45,DIF_ANTE!A:D,4,0),"0")/CONCILIÇÃO_COM_CERVEJA!$G45 -> 0 | P45: =J45-M45 -> -74.40009 | Q45: =CONCILIÇÃO_COM_CERVEJA!$P45-CONCILIÇÃO_COM_CERVEJA!$O45 -> -74.40009 | R45: =IFERROR(VLOOKUP(CONCILIÇÃO_COM_CERVEJA!$B45,CUSTO!E:H,4,0),(VLOOKUP(CONCILIÇÃO_COM_CERVEJA!$A45,CUSTO!A:H,8,0))) -> 9.1894857 | S45: =IFERROR(SUM(CONCILIÇÃO_COM_CERVEJA!$P45*CONCILIÇÃO_COM_CERVEJA!$R45),0) -> -683.69856 | T45: =IFERROR(#REF!/CONCILIÇÃO_COM_CERVEJA!$M45,"") | U45: =IFERROR(#REF!*CONCILIÇÃO_COM_CERVEJA!$R45,"-") -> -
A46: 31198 | B46: 3103110072 | C46: - | D46: ACIDO TANICO | E46: =IFERROR(VLOOKUP(B46,[1]AGLUTINADO!$A:$C,3,0),0)/G46 -> 0 | F46: CERVEJARIA | G46: 1 | H46: =VLOOKUP(CONCILIÇÃO_COM_CERVEJA!$B46,CONT_ANTE!A:D,4,0) -> 13 | I46: =IF(AND(E46=0,H46<>J46),"!@##@!","ok") -> ok | J46: =VLOOKUP(CONCILIÇÃO_COM_CERVEJA!$B46,CONTAGEM!B:G,6,0) -> 13 | K46: =SUMIF(SISTEMA!B:B,CONCILIÇÃO_COM_CERVEJA!$B46,SISTEMA!I:I)/G46 -> 13 | L46: =SUMIF(SISTEMA!B:B,CONCILIÇÃO_COM_CERVEJA!$C46,SISTEMA!I:I) -> 0 | M46: =K46+L46 -> 13 | N46: =IFERROR(SUM(CONCILIÇÃO_COM_CERVEJA!$M46*CONCILIÇÃO_COM_CERVEJA!$R46),0) -> 4745.1599 | O46: =IFERROR(VLOOKUP(CONCILIÇÃO_COM_CERVEJA!$B46,DIF_ANTE!A:D,4,0),"0")/CONCILIÇÃO_COM_CERVEJA!$G46 -> 0 | P46: =J46-M46 -> 0 | Q46: =CONCILIÇÃO_COM_CERVEJA!$P46-CONCILIÇÃO_COM_CERVEJA!$O46 -> 0 | R46: =IFERROR(VLOOKUP(CONCILIÇÃO_COM_CERVEJA!$B46,CUSTO!E:H,4,0),(VLOOKUP(CONCILIÇÃO_COM_CERVEJA!$A46,CUSTO!A:H,8,0))) -> 365.0123 | S46: =IFERROR(SUM(CONCILIÇÃO_COM_CERVEJA!$P46*CONCILIÇÃO_COM_CERVEJA!$R46),0) -> 0 | T46: =IFERROR(#REF!/CONCILIÇÃO_COM_CERVEJA!$M46,"") | U46: =IFERROR(#REF!*CONCILIÇÃO_COM_CERVEJA!$R46,"-") -> - | V46: OK
A47: 30247 | B47: 2701210005 | C47: - | D47: ALGINATO PROPILENO GLICOL | E47: =IFERROR(VLOOKUP(B47,[1]AGLUTINADO!$A:$C,3,0),0)/G47 -> 109.1 | F47: CERVEJARIA | G47: 1 | H47: =VLOOKUP(CONCILIÇÃO_COM_CERVEJA!$B47,CONT_ANTE!A:D,4,0) -> 960 | I47: =IF(AND(E47=0,H47<>J47),"!@##@!","ok") -> ok | J47: =VLOOKUP(CONCILIÇÃO_COM_CERVEJA!$B47,CONTAGEM!B:G,6,0) -> 950 | K47: =SUMIF(SISTEMA!B:B,CONCILIÇÃO_COM_CERVEJA!$B47,SISTEMA!I:I)/G47 -> 838.1 | L47: =SUMIF(SISTEMA!B:B,CONCILIÇÃO_COM_CERVEJA!$C47,SISTEMA!I:I) -> 0 | M47: =K47+L47 -> 838.1 | N47: =IFERROR(SUM(CONCILIÇÃO_COM_CERVEJA!$M47*CONCILIÇÃO_COM_CERVEJA!$R47),0) -> 176007.7 | O47: =IFERROR(VLOOKUP(CONCILIÇÃO_COM_CERVEJA!$B47,DIF_ANTE!A:D,4,0),"0")/CONCILIÇÃO_COM_CERVEJA!$G47 -> 12.8 | P47: =J47-M47 -> 111.9 | Q47: =CONCILIÇÃO_COM_CERVEJA!$P47-CONCILIÇÃO_COM_CERVEJA!$O47 -> 99.1 | R47: =IFERROR(VLOOKUP(CONCILIÇÃO_COM_CERVEJA!$B47,CUSTO!E:H,4,0),(VLOOKUP(CONCILIÇÃO_COM_CERVEJA!$A47,CUSTO!A:H,8,0))) -> 210.008 | S47: =IFERROR(SUM(CONCILIÇÃO_COM_CERVEJA!$P47*CONCILIÇÃO_COM_CERVEJA!$R47),0) -> 23499.895 | T47: =IFERROR(#REF!/CONCILIÇÃO_COM_CERVEJA!$M47,"") | U47: =IFERROR(#REF!*CONCILIÇÃO_COM_CERVEJA!$R47,"-") -> -
A48: 31998 | B48: 2701090005 | C48: - | D48: ANTIOXIDANTE INNODOX BEER | E48: =IFERROR(VLOOKUP(B48,[1]AGLUTINADO!$A:$C,3,0),0)/G48 -> 42.4 | F48: CERVEJARIA | G48: 1 | H48: =VLOOKUP(CONCILIÇÃO_COM_CERVEJA!$B48,CONT_ANTE!A:D,4,0) -> 125 | I48: =IF(AND(E48=0,H48<>J48),"!@##@!","ok") -> ok | J48: =VLOOKUP(CONCILIÇÃO_COM_CERVEJA!$B48,CONTAGEM!B:G,6,0) -> 100 | K48: =SUMIF(SISTEMA!B:B,CONCILIÇÃO_COM_CERVEJA!$B48,SISTEMA!I:I)/G48 -> 65.08006 | L48: =SUMIF(SISTEMA!B:B,CONCILIÇÃO_COM_CERVEJA!$C48,SISTEMA!I:I) -> 0 | M48: =K48+L48 -> 65.08006 | N48: =IFERROR(SUM(CONCILIÇÃO_COM_CERVEJA!$M48*CONCILIÇÃO_COM_CERVEJA!$R48),0) -> 1782.0613 | O48: =IFERROR(VLOOKUP(CONCILIÇÃO_COM_CERVEJA!$B48,DIF_ANTE!A:D,4,0),"0")/CONCILIÇÃO_COM_CERVEJA!$G48 -> 17.51994 | P48: =J48-M48 -> 34.91994 | Q48: =CONCILIÇÃO_COM_CERVEJA!$P48-CONCILIÇÃO_COM_CERVEJA!$O48 -> 17.4 | R48: =IFERROR(VLOOKUP(CONCILIÇÃO_COM_CERVEJA!$B48,CUSTO!E:H,4,0),(VLOOKUP(CONCILIÇÃO_COM_CERVEJA!$A48,CUSTO!A:H,8,0))) -> 27.3826 | S48: =IFERROR(SUM(CONCILIÇÃO_COM_CERVEJA!$P48*CONCILIÇÃO_COM_CERVEJA!$R48),0) -> 956.19875 | T48: =IFERROR(#REF!/CONCILIÇÃO_COM_CERVEJA!$M48,"") | U48: =IFERROR(#REF!*CONCILIÇÃO_COM_CERVEJA!$R48,"-") -> -
B49: 2701210008 | C49: - | D49: BREWERS CLAREX | E49: =IFERROR(VLOOKUP(B49,[1]AGLUTINADO!$A:$C,3,0),0)/G49 -> 0 | F49: CERVEJARIA | G49: 1 | H49: =VLOOKUP(CONCILIÇÃO_COM_CERVEJA!$B49,CONT_ANTE!A:D,4,0) -> 50 | I49: =IF(AND(E49=0,H49<>J49),"!@##@!","ok") -> ok | J49: =VLOOKUP(CONCILIÇÃO_COM_CERVEJA!$B49,CONTAGEM!B:G,6,0) -> 50 | K49: =SUMIF(SISTEMA!B:B,CONCILIÇÃO_COM_CERVEJA!$B49,SISTEMA!I:I)/G49 -> 40 | L49: =SUMIF(SISTEMA!B:B,CONCILIÇÃO_COM_CERVEJA!$C49,SISTEMA!I:I) -> 0 | M49: =K49+L49 -> 40 | N49: =IFERROR(SUM(CONCILIÇÃO_COM_CERVEJA!$M49*CONCILIÇÃO_COM_CERVEJA!$R49),0) -> 12273.02 | O49: =IFERROR(VLOOKUP(CONCILIÇÃO_COM_CERVEJA!$B49,DIF_ANTE!A:D,4,0),"0")/CONCILIÇÃO_COM_CERVEJA!$G49 -> 10 | P49: =J49-M49 -> 10 | Q49: =CONCILIÇÃO_COM_CERVEJA!$P49-CONCILIÇÃO_COM_CERVEJA!$O49 -> 0 | R49: =IFERROR(VLOOKUP(CONCILIÇÃO_COM_CERVEJA!$B49,CUSTO!E:H,4,0),(VLOOKUP(CONCILIÇÃO_COM_CERVEJA!$A49,CUSTO!A:H,8,0))) -> 306.8255 | S49: =IFERROR(SUM(CONCILIÇÃO_COM_CERVEJA!$P49*CONCILIÇÃO_COM_CERVEJA!$R49),0) -> 3068.255 | T49: =IFERROR(#REF!/CONCILIÇÃO_COM_CERVEJA!$M49,"") | U49: =IFERROR(#REF!*CONCILIÇÃO_COM_CERVEJA!$R49,"-") -> - | V49: OK
A50: 30256 | B50: 2701250001 | C50: - | D50: CLORETO CALCIO | E50: =IFERROR(VLOOKUP(B50,[1]AGLUTINADO!$A:$C,3,0),0)/G50 -> 211.17 | F50: CERVEJARIA | G50: 1 | H50: =VLOOKUP(CONCILIÇÃO_COM_CERVEJA!$B50,CONT_ANTE!A:D,4,0) -> 825 | I50: =IF(AND(E50=0,H50<>J50),"!@##@!","ok") -> ok | J50: =VLOOKUP(CONCILIÇÃO_COM_CERVEJA!$B50,CONTAGEM!B:G,6,0) -> 1050 | K50: =SUMIF(SISTEMA!B:B,CONCILIÇÃO_COM_CERVEJA!$B50,SISTEMA!I:I)/G50 -> 1113.83 | L50: =SUMIF(SISTEMA!B:B,CONCILIÇÃO_COM_CERVEJA!$C50,SISTEMA!I:I) -> 0 | M50: =K50+L50 -> 1113.83 | N50: =IFERROR(SUM(CONCILIÇÃO_COM_CERVEJA!$M50*CONCILIÇÃO_COM_CERVEJA!$R50),0) -> 4986.0823 | O50: =IFERROR(VLOOKUP(CONCILIÇÃO_COM_CERVEJA!$B50,DIF_ANTE!A:D,4,0),"0")/CONCILIÇÃO_COM_CERVEJA!$G50 -> 0 | P50: =J50-M50 -> -63.83 | Q50: =CONCILIÇÃO_COM_CERVEJA!$P50-CONCILIÇÃO_COM_CERVEJA!$O50 -> -63.83 | R50: =IFERROR(VLOOKUP(CONCILIÇÃO_COM_CERVEJA!$B50,CUSTO!E:H,4,0),(VLOOKUP(CONCILIÇÃO_COM_CERVEJA!$A50,CUSTO!A:H,8,0))) -> 4.47652 | S50: =IFERROR(SUM(CONCILIÇÃO_COM_CERVEJA!$P50*CONCILIÇÃO_COM_CERVEJA!$R50),0) -> -285.73627 | T50: =IFERROR(#REF!/CONCILIÇÃO_COM_CERVEJA!$M50,"") | U50: =IFERROR(#REF!*CONCILIÇÃO_COM_CERVEJA!$R50,"-") -> -
A51: 30356 | B51: 2701060006 | C51: - | D51: CORANTE CARAMELO CERVEJA | E51: =IFERROR(VLOOKUP(B51,[1]AGLUTINADO!$A:$C,3,0),0)/G51 -> 205.44183 | F51: CERVEJARIA | G51: 1 | H51: =VLOOKUP(CONCILIÇÃO_COM_CERVEJA!$B51,CONT_ANTE!A:D,4,0) -> 700 | I51: =IF(AND(E51=0,H51<>J51),"!@##@!","ok") -> ok | J51: =VLOOKUP(CONCILIÇÃO_COM_CERVEJA!$B51,CONTAGEM!B:G,6,0) -> 560 | K51: =SUMIF(SISTEMA!B:B,CONCILIÇÃO_COM_CERVEJA!$B51,SISTEMA!I:I)/G51 -> 363.25817 | L51: =SUMIF(SISTEMA!B:B,CONCILIÇÃO_COM_CERVEJA!$C51,SISTEMA!I:I) -> 0 | M51: =K51+L51 -> 363.25817 | N51: =IFERROR(SUM(CONCILIÇÃO_COM_CERVEJA!$M51*CONCILIÇÃO_COM_CERVEJA!$R51),0) -> 2645.0817 | O51: =IFERROR(VLOOKUP(CONCILIÇÃO_COM_CERVEJA!$B51,DIF_ANTE!A:D,4,0),"0")/CONCILIÇÃO_COM_CERVEJA!$G51 -> 131.3 | P51: =J51-M51 -> 196.74183 | Q51: =CONCILIÇÃO_COM_CERVEJA!$P51-CONCILIÇÃO_COM_CERVEJA!$O51 -> 65.44183 | R51: =IFERROR(VLOOKUP(CONCILIÇÃO_COM_CERVEJA!$B51,CUSTO!E:H,4,0),(VLOOKUP(CONCILIÇÃO_COM_CERVEJA!$A51,CUSTO!A:H,8,0))) -> 7.2815476 | S51: =IFERROR(SUM(CONCILIÇÃO_COM_CERVEJA!$P51*CONCILIÇÃO_COM_CERVEJA!$R51),0) -> 1432.585 | T51: =IFERROR(#REF!/CONCILIÇÃO_COM_CERVEJA!$M51,"") | U51: =IFERROR(#REF!*CONCILIÇÃO_COM_CERVEJA!$R51,"-") -> -
B52: 2701210007 | C52: - | D52: ENZIMAS LISOBEER | E52: =IFERROR(VLOOKUP(B52,[1]AGLUTINADO!$A:$C,3,0),0)/G52 -> 0 | F52: CERVEJARIA | G52: 1 | H52: =VLOOKUP(CONCILIÇÃO_COM_CERVEJA!$B52,CONT_ANTE!A:D,4,0) -> 5.5 | I52: =IF(AND(E52=0,H52<>J52),"!@##@!","ok") -> ok | J52: =VLOOKUP(CONCILIÇÃO_COM_CERVEJA!$B52,CONTAGEM!B:G,6,0) -> 5.5 | K52: =SUMIF(SISTEMA!B:B,CONCILIÇÃO_COM_CERVEJA!$B52,SISTEMA!I:I)/G52 -> 5.5 | L52: =SUMIF(SISTEMA!B:B,CONCILIÇÃO_COM_CERVEJA!$C52,SISTEMA!I:I) -> 0 | M52: =K52+L52 -> 5.5 | N52: =IFERROR(SUM(CONCILIÇÃO_COM_CERVEJA!$M52*CONCILIÇÃO_COM_CERVEJA!$R52),0) -> 3617.933 | O52: =IFERROR(VLOOKUP(CONCILIÇÃO_COM_CERVEJA!$B52,DIF_ANTE!A:D,4,0),"0")/CONCILIÇÃO_COM_CERVEJA!$G52 -> 0 | P52: =J52-M52 -> 0 | Q52: =CONCILIÇÃO_COM_CERVEJA!$P52-CONCILIÇÃO_COM_CERVEJA!$O52 -> 0 | R52: =IFERROR(VLOOKUP(CONCILIÇÃO_COM_CERVEJA!$B52,CUSTO!E:H,4,0),(VLOOKUP(CONCILIÇÃO_COM_CERVEJA!$A52,CUSTO!A:H,8,0))) -> 657.806 | S52: =IFERROR(SUM(CONCILIÇÃO_COM_CERVEJA!$P52*CONCILIÇÃO_COM_CERVEJA!$R52),0) -> 0 | T52: =IFERROR(#REF!/CONCILIÇÃO_COM_CERVEJA!$M52,"") | U52: =IFERROR(#REF!*CONCILIÇÃO_COM_CERVEJA!$R52,"-") -> - | V52: OK
A53: 31828 | B53: 2701210004 | C53: - | D53: ENZIMAS ULTRAFLO | E53: =IFERROR(VLOOKUP(B53,[1]AGLUTINADO!$A:$C,3,0),0)/G53 -> 37.7 | F53: CERVEJARIA | G53: 1 | H53: =VLOOKUP(CONCILIÇÃO_COM_CERVEJA!$B53,CONT_ANTE!A:D,4,0) -> 120 | I53: =IF(AND(E53=0,H53<>J53),"!@##@!","ok") -> ok | J53: =VLOOKUP(CONCILIÇÃO_COM_CERVEJA!$B53,CONTAGEM!B:G,6,0) -> 75 | K53: =SUMIF(SISTEMA!B:B,CONCILIÇÃO_COM_CERVEJA!$B53,SISTEMA!I:I)/G53 -> 82.3 | L53: =SUMIF(SISTEMA!B:B,CONCILIÇÃO_COM_CERVEJA!$C53,SISTEMA!I:I) -> 0 | M53: =K53+L53 -> 82.3 | N53: =IFERROR(SUM(CONCILIÇÃO_COM_CERVEJA!$M53*CONCILIÇÃO_COM_CERVEJA!$R53),0) -> 5444.6319 | O53: =IFERROR(VLOOKUP(CONCILIÇÃO_COM_CERVEJA!$B53,DIF_ANTE!A:D,4,0),"0")/CONCILIÇÃO_COM_CERVEJA!$G53 -> 0 | P53: =J53-M53 -> -7.3 | Q53: =CONCILIÇÃO_COM_CERVEJA!$P53-CONCILIÇÃO_COM_CERVEJA!$O53 -> -7.3 | R53: =IFERROR(VLOOKUP(CONCILIÇÃO_COM_CERVEJA!$B53,CUSTO!E:H,4,0),(VLOOKUP(CONCILIÇÃO_COM_CERVEJA!$A53,CUSTO!A:H,8,0))) -> 66.155917 | S53: =IFERROR(SUM(CONCILIÇÃO_COM_CERVEJA!$P53*CONCILIÇÃO_COM_CERVEJA!$R53),0) -> -482.93819 | T53: =IFERROR(#REF!/CONCILIÇÃO_COM_CERVEJA!$M53,"") | U53: =IFERROR(#REF!*CONCILIÇÃO_COM_CERVEJA!$R53,"-") -> -
A54: 30254 | B54: 2701210003 | C54: - | D54: ESTABILIZANTE PVPP CLEAR MAX | E54: =IFERROR(VLOOKUP(B54,[1]AGLUTINADO!$A:$C,3,0),0)/G54 -> 41.148 | F54: CERVEJARIA | G54: 1 | H54: =VLOOKUP(CONCILIÇÃO_COM_CERVEJA!$B54,CONT_ANTE!A:D,4,0) -> 160 | I54: =IF(AND(E54=0,H54<>J54),"!@##@!","ok") -> ok | J54: =VLOOKUP(CONCILIÇÃO_COM_CERVEJA!$B54,CONTAGEM!B:G,6,0) -> 100 | K54: =SUMIF(SISTEMA!B:B,CONCILIÇÃO_COM_CERVEJA!$B54,SISTEMA!I:I)/G54 -> 98.1632 | L54: =SUMIF(SISTEMA!B:B,CONCILIÇÃO_COM_CERVEJA!$C54,SISTEMA!I:I) -> 0 | M54: =K54+L54 -> 98.1632 | N54: =IFERROR(SUM(CONCILIÇÃO_COM_CERVEJA!$M54*CONCILIÇÃO_COM_CERVEJA!$R54),0) -> 12071.502 | O54: =IFERROR(VLOOKUP(CONCILIÇÃO_COM_CERVEJA!$B54,DIF_ANTE!A:D,4,0),"0")/CONCILIÇÃO_COM_CERVEJA!$G54 -> 0.6888 | P54: =J54-M54 -> 1.8368 | Q54: =CONCILIÇÃO_COM_CERVEJA!$P54-CONCILIÇÃO_COM_CERVEJA!$O54 -> 1.148 | R54: =IFERROR(VLOOKUP(CONCILIÇÃO_COM_CERVEJA!$B54,CUSTO!E:H,4,0),(VLOOKUP(CONCILIÇÃO_COM_CERVEJA!$A54,CUSTO!A:H,8,0))) -> 122.9738 | S54: =IFERROR(SUM(CONCILIÇÃO_COM_CERVEJA!$P54*CONCILIÇÃO_COM_CERVEJA!$R54),0) -> 225.87828 | T54: =IFERROR(#REF!/CONCILIÇÃO_COM_CERVEJA!$M54,"") | U54: =IFERROR(#REF!*CONCILIÇÃO_COM_CERVEJA!$R54,"-") -> -
A55: 2041 | B55: 2701220001 | C55: - | D55: FERMENTO CERVEJEIRO FERMENTIS W-34/70 | E55: =IFERROR(VLOOKUP(B55,[1]AGLUTINADO!$A:$C,3,0),0)/G55 -> 0 | F55: CERVEJARIA | G55: 1 | H55: =VLOOKUP(CONCILIÇÃO_COM_CERVEJA!$B55,CONT_ANTE!A:D,4,0) -> 12 | I55: =IF(AND(E55=0,H55<>J55),"!@##@!","ok") -> ok | J55: =VLOOKUP(CONCILIÇÃO_COM_CERVEJA!$B55,CONTAGEM!B:G,6,0) -> 12 | K55: =SUMIF(SISTEMA!B:B,CONCILIÇÃO_COM_CERVEJA!$B55,SISTEMA!I:I)/G55 -> 10.5 | L55: =SUMIF(SISTEMA!B:B,CONCILIÇÃO_COM_CERVEJA!$C55,SISTEMA!I:I) -> 0 | M55: =K55+L55 -> 10.5 | N55: =IFERROR(SUM(CONCILIÇÃO_COM_CERVEJA!$M55*CONCILIÇÃO_COM_CERVEJA!$R55),0) -> 9153.816 | O55: =IFERROR(VLOOKUP(CONCILIÇÃO_COM_CERVEJA!$B55,DIF_ANTE!A:D,4,0),"0")/CONCILIÇÃO_COM_CERVEJA!$G55 -> 1.5 | P55: =J55-M55 -> 1.5 | Q55: =CONCILIÇÃO_COM_CERVEJA!$P55-CONCILIÇÃO_COM_CERVEJA!$O55 -> 0 | R55: =IFERROR(VLOOKUP(CONCILIÇÃO_COM_CERVEJA!$B55,CUSTO!E:H,4,0),(VLOOKUP(CONCILIÇÃO_COM_CERVEJA!$A55,CUSTO!A:H,8,0))) -> 871.792 | S55: =IFERROR(SUM(CONCILIÇÃO_COM_CERVEJA!$P55*CONCILIÇÃO_COM_CERVEJA!$R55),0) -> 1307.688 | T55: =IFERROR(#REF!/CONCILIÇÃO_COM_CERVEJA!$M55,"") | U55: =IFERROR(#REF!*CONCILIÇÃO_COM_CERVEJA!$R55,"-") -> - | V55: OK
B56: 2701210009 | C56: - | D56: MATUFAST DIMETILPOLISILOXANO | E56: =IFERROR(VLOOKUP(B56,[1]AGLUTINADO!$A:$C,3,0),0)/G56 -> 0 | F56: CERVEJARIA | G56: 1 | H56: =VLOOKUP(CONCILIÇÃO_COM_CERVEJA!$B56,CONT_ANTE!A:D,4,0) -> 21 | I56: =IF(AND(E56=0,H56<>J56),"!@##@!","ok") -> ok | J56: =VLOOKUP(CONCILIÇÃO_COM_CERVEJA!$B56,CONTAGEM!B:G,6,0) -> 21 | K56: =SUMIF(SISTEMA!B:B,CONCILIÇÃO_COM_CERVEJA!$B56,SISTEMA!I:I)/G56 -> 21 | L56: =SUMIF(SISTEMA!B:B,CONCILIÇÃO_COM_CERVEJA!$C56,SISTEMA!I:I) -> 0 | M56: =K56+L56 -> 21 | N56: =IFERROR(SUM(CONCILIÇÃO_COM_CERVEJA!$M56*CONCILIÇÃO_COM_CERVEJA!$R56),0) -> 16306.97 | O56: =IFERROR(VLOOKUP(CONCILIÇÃO_COM_CERVEJA!$B56,DIF_ANTE!A:D,4,0),"0")/CONCILIÇÃO_COM_CERVEJA!$G56 -> 0 | P56: =J56-M56 -> 0 | Q56: =CONCILIÇÃO_COM_CERVEJA!$P56-CONCILIÇÃO_COM_CERVEJA!$O56 -> 0 | R56: =IFERROR(VLOOKUP(CONCILIÇÃO_COM_CERVEJA!$B56,CUSTO!E:H,4,0),(VLOOKUP(CONCILIÇÃO_COM_CERVEJA!$A56,CUSTO!A:H,8,0))) -> 776.5224 | S56: =IFERROR(SUM(CONCILIÇÃO_COM_CERVEJA!$P56*CONCILIÇÃO_COM_CERVEJA!$R56),0) -> 0 | T56: =IFERROR(#REF!/CONCILIÇÃO_COM_CERVEJA!$M56,"") | U56: =IFERROR(#REF!*CONCILIÇÃO_COM_CERVEJA!$R56,"-") -> - | V56: OK
A57: 30606 | B57: 2701210002 | C57: - | D57: SILICA HP 9000 DERACLAR | E57: =IFERROR(VLOOKUP(B57,[1]AGLUTINADO!$A:$C,3,0),0)/G57 -> 255 | F57: CERVEJARIA | G57: 1 | H57: =VLOOKUP(CONCILIÇÃO_COM_CERVEJA!$B57,CONT_ANTE!A:D,4,0) -> 6780 | I57: =IF(AND(E57=0,H57<>J57),"!@##@!","ok") -> ok | J57: =VLOOKUP(CONCILIÇÃO_COM_CERVEJA!$B57,CONTAGEM!B:G,6,0) -> 3510 | K57: =SUMIF(SISTEMA!B:B,CONCILIÇÃO_COM_CERVEJA!$B57,SISTEMA!I:I)/G57 -> 1247.0499 | L57: =SUMIF(SISTEMA!B:B,CONCILIÇÃO_COM_CERVEJA!$C57,SISTEMA!I:I) -> 0 | M57: =K57+L57 -> 1247.0499 | N57: =IFERROR(SUM(CONCILIÇÃO_COM_CERVEJA!$M57*CONCILIÇÃO_COM_CERVEJA!$R57),0) -> 37127.396 | O57: =IFERROR(VLOOKUP(CONCILIÇÃO_COM_CERVEJA!$B57,DIF_ANTE!A:D,4,0),"0")/CONCILIÇÃO_COM_CERVEJA!$G57 -> 2127.9501 | P57: =J57-M57 -> 2262.9501 | Q57: =CONCILIÇÃO_COM_CERVEJA!$P57-CONCILIÇÃO_COM_CERVEJA!$O57 -> 135 | R57: =IFERROR(VLOOKUP(CONCILIÇÃO_COM_CERVEJA!$B57,CUSTO!E:H,4,0),(VLOOKUP(CONCILIÇÃO_COM_CERVEJA!$A57,CUSTO!A:H,8,0))) -> 29.772182 | S57: =IFERROR(SUM(CONCILIÇÃO_COM_CERVEJA!$P57*CONCILIÇÃO_COM_CERVEJA!$R57),0) -> 67372.963 | T57: =IFERROR(#REF!/CONCILIÇÃO_COM_CERVEJA!$M57,"") | U57: =IFERROR(#REF!*CONCILIÇÃO_COM_CERVEJA!$R57,"-") -> -
B58: 2701210006 | C58: - | D58: TANINO SETABREW | E58: =IFERROR(VLOOKUP(B58,[1]AGLUTINADO!$A:$C,3,0),0)/G58 -> 0 | F58: CERVEJARIA | G58: =IFERROR(VLOOKUP(CONCILIÇÃO_COM_CERVEJA!$B58,'BASE PRODUTOS'!A:E,5,0),"") -> 1 | H58: =VLOOKUP(CONCILIÇÃO_COM_CERVEJA!$B58,CONT_ANTE!A:D,4,0) -> 12 | I58: =IF(AND(E58=0,H58<>J58),"!@##@!","ok") -> !@##@! | J58: =VLOOKUP(CONCILIÇÃO_COM_CERVEJA!$B58,CONTAGEM!B:G,6,0) -> 14 | K58: =SUMIF(SISTEMA!B:B,CONCILIÇÃO_COM_CERVEJA!$B58,SISTEMA!I:I)/G58 -> 12 | L58: =SUMIF(SISTEMA!B:B,CONCILIÇÃO_COM_CERVEJA!$C58,SISTEMA!I:I) -> 0 | M58: =K58+L58 -> 12 | N58: =IFERROR(SUM(CONCILIÇÃO_COM_CERVEJA!$M58*CONCILIÇÃO_COM_CERVEJA!$R58),0) -> 4578.56 | O58: =IFERROR(VLOOKUP(CONCILIÇÃO_COM_CERVEJA!$B58,DIF_ANTE!A:D,4,0),"0")/CONCILIÇÃO_COM_CERVEJA!$G58 -> 0 | P58: =J58-M58 -> 2 | Q58: =CONCILIÇÃO_COM_CERVEJA!$P58-CONCILIÇÃO_COM_CERVEJA!$O58 -> 2 | R58: =IFERROR(VLOOKUP(CONCILIÇÃO_COM_CERVEJA!$B58,CUSTO!E:H,4,0),(VLOOKUP(CONCILIÇÃO_COM_CERVEJA!$A58,CUSTO!A:H,8,0))) -> 381.54667 | S58: =IFERROR(SUM(CONCILIÇÃO_COM_CERVEJA!$P58*CONCILIÇÃO_COM_CERVEJA!$R58),0) -> 763.09333 | T58: =IFERROR(#REF!/CONCILIÇÃO_COM_CERVEJA!$M58,"") | U58: =IFERROR(#REF!*CONCILIÇÃO_COM_CERVEJA!$R58,"-") -> -
A59: 2032 | B59: 2701190004 | C59: - | D59: XAROPE HIGH MALTOSE | E59: =IFERROR(VLOOKUP(B59,[1]AGLUTINADO!$A:$C,3,0),0)/G59 -> 100657.01 | F59: CERVEJARIA | G59: 1 | H59: =VLOOKUP(CONCILIÇÃO_COM_CERVEJA!$B59,CONT_ANTE!A:D,4,0) -> 54430 | I59: =IF(AND(E59=0,H59<>J59),"!@##@!","ok") -> ok | J59: =VLOOKUP(CONCILIÇÃO_COM_CERVEJA!$B59,CONTAGEM!B:G,6,0) -> 16464 | K59: =SUMIF(SISTEMA!B:B,CONCILIÇÃO_COM_CERVEJA!$B59,SISTEMA!I:I)/G59 -> 15106.295 | L59: =SUMIF(SISTEMA!B:B,CONCILIÇÃO_COM_CERVEJA!$C59,SISTEMA!I:I) -> 0 | M59: =K59+L59 -> 15106.295 | N59: =IFERROR(SUM(CONCILIÇÃO_COM_CERVEJA!$M59*CONCILIÇÃO_COM_CERVEJA!$R59),0) -> 35172.44 | O59: =IFERROR(VLOOKUP(CONCILIÇÃO_COM_CERVEJA!$B59,DIF_ANTE!A:D,4,0),"0")/CONCILIÇÃO_COM_CERVEJA!$G59 -> -643.3 | P59: =J59-M59 -> 1357.705 | Q59: =CONCILIÇÃO_COM_CERVEJA!$P59-CONCILIÇÃO_COM_CERVEJA!$O59 -> 2001.005 | R59: =IFERROR(VLOOKUP(CONCILIÇÃO_COM_CERVEJA!$B59,CUSTO!E:H,4,0),(VLOOKUP(CONCILIÇÃO_COM_CERVEJA!$A59,CUSTO!A:H,8,0))) -> 2.32833 | S59: =IFERROR(SUM(CONCILIÇÃO_COM_CERVEJA!$P59*CONCILIÇÃO_COM_CERVEJA!$R59),0) -> 3161.1853 | T59: =IFERROR(#REF!/CONCILIÇÃO_COM_CERVEJA!$M59,"") | U59: =IFERROR(#REF!*CONCILIÇÃO_COM_CERVEJA!$R59,"-") -> -
A60: 31334 | B60: 2701050024 | C60: - | D60: CONCENTRADO BEBIDA ENERGETICA AF883 ACAI ADM | E60: =IFERROR(VLOOKUP(B60,[1]AGLUTINADO!$A:$C,3,0),0)/G60 -> 0 | F60: CONCENTRADO | G60: =IFERROR(VLOOKUP(CONCILIÇÃO_COM_CERVEJA!$B60,'BASE PRODUTOS'!A:E,5,0),"") -> 58.54 | H60: =VLOOKUP(CONCILIÇÃO_COM_CERVEJA!$B60,CONT_ANTE!A:D,4,0) -> 0 | I60: =IF(AND(E60=0,H60<>J60),"!@##@!","ok") -> ok | J60: =VLOOKUP(CONCILIÇÃO_COM_CERVEJA!$B60,CONTAGEM!B:G,6,0) -> 0 | K60: =SUMIF(SISTEMA!B:B,CONCILIÇÃO_COM_CERVEJA!$B60,SISTEMA!I:I)/G60 -> 0.010249402 | L60: =SUMIF(SISTEMA!B:B,CONCILIÇÃO_COM_CERVEJA!$C60,SISTEMA!I:I) -> 0 | M60: =K60+L60 -> 0.010249402 | N60: =IFERROR(SUM(CONCILIÇÃO_COM_CERVEJA!$M60*CONCILIÇÃO_COM_CERVEJA!$R60),0) -> 0.31226475 | O60: =IFERROR(VLOOKUP(CONCILIÇÃO_COM_CERVEJA!$B60,DIF_ANTE!A:D,4,0),"0")/CONCILIÇÃO_COM_CERVEJA!$G60 -> -0.010249402 | P60: =J60-M60 -> -0.010249402 | Q60: =CONCILIÇÃO_COM_CERVEJA!$P60-CONCILIÇÃO_COM_CERVEJA!$O60 -> 0 | R60: =IFERROR(VLOOKUP(CONCILIÇÃO_COM_CERVEJA!$B60,CUSTO!E:H,4,0),(VLOOKUP(CONCILIÇÃO_COM_CERVEJA!$A60,CUSTO!A:H,8,0))) -> 30.466631 | S60: =IFERROR(SUM(CONCILIÇÃO_COM_CERVEJA!$P60*CONCILIÇÃO_COM_CERVEJA!$R60),0) -> -0.31226475 | T60: =IFERROR(#REF!/CONCILIÇÃO_COM_CERVEJA!$M60,"") | U60: =IFERROR(#REF!*CONCILIÇÃO_COM_CERVEJA!$R60,"-") -> - | V60: OK
A61: 48 | B61: 2701050025 | C61: 2701050040 | D61: CONCENTRADO BEBIDA ENERGETICA TRADICIONAL ADM | E61: =IFERROR(VLOOKUP(B61,[1]AGLUTINADO!$A:$C,3,0),0)/G61 -> 32.447075 | F61: CONCENTRADO | G61: =IFERROR(VLOOKUP(CONCILIÇÃO_COM_CERVEJA!$B61,'BASE PRODUTOS'!A:E,5,0),"") -> 57.44 | H61: =VLOOKUP(CONCILIÇÃO_COM_CERVEJA!$B61,CONT_ANTE!A:D,4,0) -> 83 | I61: =IF(AND(E61=0,H61<>J61),"!@##@!","ok") -> ok | J61: =VLOOKUP(CONCILIÇÃO_COM_CERVEJA!$B61,CONTAGEM!B:G,6,0) -> 12981.44 | K61: =SUMIF(SISTEMA!B:B,CONCILIÇÃO_COM_CERVEJA!$B61,SISTEMA!I:I)/G61 -> 278.80101 | L61: =SUMIF(SISTEMA!B:B,CONCILIÇÃO_COM_CERVEJA!$C61,SISTEMA!I:I) -> 0 | M61: =K61+L61 -> 278.80101 | N61: =IFERROR(SUM(CONCILIÇÃO_COM_CERVEJA!$M61*CONCILIÇÃO_COM_CERVEJA!$R61),0) -> 8560.0518 | O61: =IFERROR(VLOOKUP(CONCILIÇÃO_COM_CERVEJA!$B61,DIF_ANTE!A:D,4,0),"0")/CONCILIÇÃO_COM_CERVEJA!$G61 -> -1.6579039 | P61: =J61-M61 -> 12702.639 | Q61: =CONCILIÇÃO_COM_CERVEJA!$P61-CONCILIÇÃO_COM_CERVEJA!$O61 -> 12704.297 | R61: =IFERROR(VLOOKUP(CONCILIÇÃO_COM_CERVEJA!$B61,CUSTO!E:H,4,0),(VLOOKUP(CONCILIÇÃO_COM_CERVEJA!$A61,CUSTO!A:H,8,0))) -> 30.703088 | S61: =IFERROR(SUM(CONCILIÇÃO_COM_CERVEJA!$P61*CONCILIÇÃO_COM_CERVEJA!$R61),0) -> 390010.24 | T61: =IFERROR(#REF!/CONCILIÇÃO_COM_CERVEJA!$M61,"") | U61: =IFERROR(#REF!*CONCILIÇÃO_COM_CERVEJA!$R61,"-") -> -
A62: 1764 | B62: 2701050022 | C62: - | D62: CONCENTRADO TUBAINA 7205 INTERAMERICAS | E62: =IFERROR(VLOOKUP(B62,[1]AGLUTINADO!$A:$C,3,0),0)/G62 -> 336.5 | F62: CONCENTRADO | G62: 1 | H62: =VLOOKUP(CONCILIÇÃO_COM_CERVEJA!$B62,CONT_ANTE!A:D,4,0) -> 484 | I62: =IF(AND(E62=0,H62<>J62),"!@##@!","ok") -> ok | J62: =VLOOKUP(CONCILIÇÃO_COM_CERVEJA!$B62,CONTAGEM!B:G,6,0) -> 2158 | K62: =SUMIF(SISTEMA!B:B,CONCILIÇÃO_COM_CERVEJA!$B62,SISTEMA!I:I)/G62 -> 2227.09 | L62: =SUMIF(SISTEMA!B:B,CONCILIÇÃO_COM_CERVEJA!$C62,SISTEMA!I:I) -> 0 | M62: =K62+L62 -> 2227.09 | N62: =IFERROR(SUM(CONCILIÇÃO_COM_CERVEJA!$M62*CONCILIÇÃO_COM_CERVEJA!$R62),0) -> 51386.381 | O62: =IFERROR(VLOOKUP(CONCILIÇÃO_COM_CERVEJA!$B62,DIF_ANTE!A:D,4,0),"0")/CONCILIÇÃO_COM_CERVEJA!$G62 -> -9.59 | P62: =J62-M62 -> -69.09 | Q62: =CONCILIÇÃO_COM_CERVEJA!$P62-CONCILIÇÃO_COM_CERVEJA!$O62 -> -59.5 | R62: =IFERROR(VLOOKUP(CONCILIÇÃO_COM_CERVEJA!$B62,CUSTO!E:H,4,0),(VLOOKUP(CONCILIÇÃO_COM_CERVEJA!$A62,CUSTO!A:H,8,0))) -> 23.073329 | S62: =IFERROR(SUM(CONCILIÇÃO_COM_CERVEJA!$P62*CONCILIÇÃO_COM_CERVEJA!$R62),0) -> -1594.1363 | T62: =IFERROR(#REF!/CONCILIÇÃO_COM_CERVEJA!$M62,"") | U62: =IFERROR(#REF!*CONCILIÇÃO_COM_CERVEJA!$R62,"-") -> -
A63: 30058 | B63: 2901050016 | C63: - | D63: CONCENTRADO TUBAINA FUNADA | E63: =IFERROR(VLOOKUP(B63,[1]AGLUTINADO!$A:$C,3,0),0)/G63 -> 10.325098 | F63: CONCENTRADO | G63: =IFERROR(VLOOKUP(CONCILIÇÃO_COM_CERVEJA!$B63,'BASE PRODUTOS'!A:E,5,0),"") -> 15.38 | H63: =VLOOKUP(CONCILIÇÃO_COM_CERVEJA!$B63,CONT_ANTE!A:D,4,0) -> 9 | I63: =IF(AND(E63=0,H63<>J63),"!@##@!","ok") -> ok | J63: =VLOOKUP(CONCILIÇÃO_COM_CERVEJA!$B63,CONTAGEM!B:G,6,0) -> 0 | K63: =SUMIF(SISTEMA!B:B,CONCILIÇÃO_COM_CERVEJA!$B63,SISTEMA!I:I)/G63 -> 22.674902 | L63: =SUMIF(SISTEMA!B:B,CONCILIÇÃO_COM_CERVEJA!$C63,SISTEMA!I:I) -> 0 | M63: =K63+L63 -> 22.674902 | N63: =IFERROR(SUM(CONCILIÇÃO_COM_CERVEJA!$M63*CONCILIÇÃO_COM_CERVEJA!$R63),0) -> 705.91053 | O63: =IFERROR(VLOOKUP(CONCILIÇÃO_COM_CERVEJA!$B63,DIF_ANTE!A:D,4,0),"0")/CONCILIÇÃO_COM_CERVEJA!$G63 -> 0 | P63: =J63-M63 -> -22.674902 | Q63: =CONCILIÇÃO_COM_CERVEJA!$P63-CONCILIÇÃO_COM_CERVEJA!$O63 -> -22.674902 | R63: =IFERROR(VLOOKUP(CONCILIÇÃO_COM_CERVEJA!$B63,CUSTO!E:H,4,0),(VLOOKUP(CONCILIÇÃO_COM_CERVEJA!$A63,CUSTO!A:H,8,0))) -> 31.1318 | S63: =IFERROR(SUM(CONCILIÇÃO_COM_CERVEJA!$P63*CONCILIÇÃO_COM_CERVEJA!$R63),0) -> -705.91053 | T63: =IFERROR(#REF!/CONCILIÇÃO_COM_CERVEJA!$M63,"") | U63: =IFERROR(#REF!*CONCILIÇÃO_COM_CERVEJA!$R63,"-") -> -
A64: 31341 | B64: 2701130008 | C64: - | D64: POLPA ACAI DESIDRATADA SOLUVEL | E64: =IFERROR(VLOOKUP(B64,[1]AGLUTINADO!$A:$C,3,0),0)/G64 -> 0 | F64: CONCENTRADO | G64: 1 | H64: =VLOOKUP(CONCILIÇÃO_COM_CERVEJA!$B64,CONT_ANTE!A:D,4,0) -> 0 | I64: =IF(AND(E64=0,H64<>J64),"!@##@!","ok") -> ok | J64: =VLOOKUP(CONCILIÇÃO_COM_CERVEJA!$B64,CONTAGEM!B:G,6,0) -> 0 | K64: =SUMIF(SISTEMA!B:B,CONCILIÇÃO_COM_CERVEJA!$B64,SISTEMA!I:I)/G64 -> 0 | L64: =SUMIF(SISTEMA!B:B,CONCILIÇÃO_COM_CERVEJA!$C64,SISTEMA!I:I) -> 0 | M64: =K64+L64 -> 0 | N64: =IFERROR(SUM(CONCILIÇÃO_COM_CERVEJA!$M64*CONCILIÇÃO_COM_CERVEJA!$R64),0) -> 0 | O64: =IFERROR(VLOOKUP(CONCILIÇÃO_COM_CERVEJA!$B64,DIF_ANTE!A:D,4,0),"0")/CONCILIÇÃO_COM_CERVEJA!$G64 -> 0 | P64: =J64-M64 -> 0 | Q64: =CONCILIÇÃO_COM_CERVEJA!$P64-CONCILIÇÃO_COM_CERVEJA!$O64 -> 0 | R64: =IFERROR(VLOOKUP(CONCILIÇÃO_COM_CERVEJA!$B64,CUSTO!E:H,4,0),(VLOOKUP(CONCILIÇÃO_COM_CERVEJA!$A64,CUSTO!A:H,8,0))) -> 44.2232 | S64: =IFERROR(SUM(CONCILIÇÃO_COM_CERVEJA!$P64*CONCILIÇÃO_COM_CERVEJA!$R64),0) -> 0 | T64: =IFERROR(#REF!/CONCILIÇÃO_COM_CERVEJA!$M64,"") | U64: =IFERROR(#REF!*CONCILIÇÃO_COM_CERVEJA!$R64,"-") -> - | V64: OK
A65: 33 | B65: 2701090001 | C65: - | D65: ACIDO ASCORBICO | E65: =IFERROR(VLOOKUP(B65,[1]AGLUTINADO!$A:$C,3,0),0)/G65 -> 0 | F65: CONSERVANTE | G65: 1 | H65: =VLOOKUP(CONCILIÇÃO_COM_CERVEJA!$B65,CONT_ANTE!A:D,4,0) -> 0 | I65: =IF(AND(E65=0,H65<>J65),"!@##@!","ok") -> ok | J65: =VLOOKUP(CONCILIÇÃO_COM_CERVEJA!$B65,CONTAGEM!B:G,6,0) -> 0 | K65: =SUMIF(SISTEMA!B:B,CONCILIÇÃO_COM_CERVEJA!$B65,SISTEMA!I:I)/G65 -> 0 | L65: =SUMIF(SISTEMA!B:B,CONCILIÇÃO_COM_CERVEJA!$C65,SISTEMA!I:I) -> 0 | M65: =K65+L65 -> 0 | N65: =IFERROR(SUM(CONCILIÇÃO_COM_CERVEJA!$M65*CONCILIÇÃO_COM_CERVEJA!$R65),0) -> 0 | O65: =IFERROR(VLOOKUP(CONCILIÇÃO_COM_CERVEJA!$B65,DIF_ANTE!A:D,4,0),"0")/CONCILIÇÃO_COM_CERVEJA!$G65 -> -6.24 | P65: =J65-M65 -> 0 | Q65: =CONCILIÇÃO_COM_CERVEJA!$P65-CONCILIÇÃO_COM_CERVEJA!$O65 -> 6.24 | R65: =IFERROR(VLOOKUP(CONCILIÇÃO_COM_CERVEJA!$B65,CUSTO!E:H,4,0),(VLOOKUP(CONCILIÇÃO_COM_CERVEJA!$A65,CUSTO!A:H,8,0))) -> 14.8664 | S65: =IFERROR(SUM(CONCILIÇÃO_COM_CERVEJA!$P65*CONCILIÇÃO_COM_CERVEJA!$R65),0) -> 0 | T65: =IFERROR(#REF!/CONCILIÇÃO_COM_CERVEJA!$M65,"") | U65: =IFERROR(#REF!*CONCILIÇÃO_COM_CERVEJA!$R65,"-") -> - | V65: OK
A66: 112 | B66: 2701090002 | C66: - | D66: ACIDO CITRICO | E66: =IFERROR(VLOOKUP(B66,[1]AGLUTINADO!$A:$C,3,0),0)/G66 -> 3850.29 | F66: CONSERVANTE | G66: 1 | H66: =VLOOKUP(CONCILIÇÃO_COM_CERVEJA!$B66,CONT_ANTE!A:D,4,0) -> 5375 | I66: =IF(AND(E66=0,H66<>J66),"!@##@!","ok") -> ok | J66: =VLOOKUP(CONCILIÇÃO_COM_CERVEJA!$B66,CONTAGEM!B:G,6,0) -> 16103.5 | K66: =SUMIF(SISTEMA!B:B,CONCILIÇÃO_COM_CERVEJA!$B66,SISTEMA!I:I)/G66 -> 16115.727 | L66: =SUMIF(SISTEMA!B:B,CONCILIÇÃO_COM_CERVEJA!$C66,SISTEMA!I:I) -> 0 | M66: =K66+L66 -> 16115.727 | N66: =IFERROR(SUM(CONCILIÇÃO_COM_CERVEJA!$M66*CONCILIÇÃO_COM_CERVEJA!$R66),0) -> 118185.05 | O66: =IFERROR(VLOOKUP(CONCILIÇÃO_COM_CERVEJA!$B66,DIF_ANTE!A:D,4,0),"0")/CONCILIÇÃO_COM_CERVEJA!$G66 -> -591.01675 | P66: =J66-M66 -> -12.22675 | Q66: =CONCILIÇÃO_COM_CERVEJA!$P66-CONCILIÇÃO_COM_CERVEJA!$O66 -> 578.79 | R66: =IFERROR(VLOOKUP(CONCILIÇÃO_COM_CERVEJA!$B66,CUSTO!E:H,4,0),(VLOOKUP(CONCILIÇÃO_COM_CERVEJA!$A66,CUSTO!A:H,8,0))) -> 7.3335229 | S66: =IFERROR(SUM(CONCILIÇÃO_COM_CERVEJA!$P66*CONCILIÇÃO_COM_CERVEJA!$R66),0) -> -89.665151 | T66: =IFERROR(#REF!/CONCILIÇÃO_COM_CERVEJA!$M66,"") | U66: =IFERROR(#REF!*CONCILIÇÃO_COM_CERVEJA!$R66,"-") -> -
B67: 2701090007 | C67: - | D67: ACIDO MALICO | E67: =IFERROR(VLOOKUP(B67,[1]AGLUTINADO!$A:$C,3,0),0)/G67 -> 0 | F67: CONSERVANTE | G67: 1 | H67: =VLOOKUP(CONCILIÇÃO_COM_CERVEJA!$B67,CONT_ANTE!A:D,4,0) -> 0 | I67: =IF(AND(E67=0,H67<>J67),"!@##@!","ok") -> ok | J67: =VLOOKUP(CONCILIÇÃO_COM_CERVEJA!$B67,CONTAGEM!B:G,6,0) -> 0 | K67: =SUMIF(SISTEMA!B:B,CONCILIÇÃO_COM_CERVEJA!$B67,SISTEMA!I:I)/G67 -> 4e-05 | L67: =SUMIF(SISTEMA!B:B,CONCILIÇÃO_COM_CERVEJA!$C67,SISTEMA!I:I) -> 0 | M67: =K67+L67 -> 4e-05 | N67: =IFERROR(SUM(CONCILIÇÃO_COM_CERVEJA!$M67*CONCILIÇÃO_COM_CERVEJA!$R67),0) -> 0.000356128 | O67: =IFERROR(VLOOKUP(CONCILIÇÃO_COM_CERVEJA!$B67,DIF_ANTE!A:D,4,0),"0")/CONCILIÇÃO_COM_CERVEJA!$G67 -> -4e-05 | P67: =J67-M67 -> -4e-05 | Q67: =CONCILIÇÃO_COM_CERVEJA!$P67-CONCILIÇÃO_COM_CERVEJA!$O67 -> 0 | R67: =IFERROR(VLOOKUP(CONCILIÇÃO_COM_CERVEJA!$B67,CUSTO!E:H,4,0),(VLOOKUP(CONCILIÇÃO_COM_CERVEJA!$A67,CUSTO!A:H,8,0))) -> 8.9032 | S67: =IFERROR(SUM(CONCILIÇÃO_COM_CERVEJA!$P67*CONCILIÇÃO_COM_CERVEJA!$R67),0) -> -0.000356128 | T67: =IFERROR(#REF!/CONCILIÇÃO_COM_CERVEJA!$M67,"") | U67: =IFERROR(#REF!*CONCILIÇÃO_COM_CERVEJA!$R67,"-") -> - | V67: OK
A68: 771 | B68: 2701090004 | C68: - | D68: ACIDO TARTARICO | E68: =IFERROR(VLOOKUP(B68,[1]AGLUTINADO!$A:$C,3,0),0)/G68 -> 67 | F68: CONSERVANTE | G68: 1 | H68: =VLOOKUP(CONCILIÇÃO_COM_CERVEJA!$B68,CONT_ANTE!A:D,4,0) -> 147 | I68: =IF(AND(E68=0,H68<>J68),"!@##@!","ok") -> ok | J68: =VLOOKUP(CONCILIÇÃO_COM_CERVEJA!$B68,CONTAGEM!B:G,6,0) -> 282.5 | K68: =SUMIF(SISTEMA!B:B,CONCILIÇÃO_COM_CERVEJA!$B68,SISTEMA!I:I)/G68 -> 260.47 | L68: =SUMIF(SISTEMA!B:B,CONCILIÇÃO_COM_CERVEJA!$C68,SISTEMA!I:I) -> 0 | M68: =K68+L68 -> 260.47 | N68: =IFERROR(SUM(CONCILIÇÃO_COM_CERVEJA!$M68*CONCILIÇÃO_COM_CERVEJA!$R68),0) -> 8695.1202 | O68: =IFERROR(VLOOKUP(CONCILIÇÃO_COM_CERVEJA!$B68,DIF_ANTE!A:D,4,0),"0")/CONCILIÇÃO_COM_CERVEJA!$G68 -> 19.53 | P68: =J68-M68 -> 22.03 | Q68: =CONCILIÇÃO_COM_CERVEJA!$P68-CONCILIÇÃO_COM_CERVEJA!$O68 -> 2.5 | R68: =IFERROR(VLOOKUP(CONCILIÇÃO_COM_CERVEJA!$B68,CUSTO!E:H,4,0),(VLOOKUP(CONCILIÇÃO_COM_CERVEJA!$A68,CUSTO!A:H,8,0))) -> 33.382425 | S68: =IFERROR(SUM(CONCILIÇÃO_COM_CERVEJA!$P68*CONCILIÇÃO_COM_CERVEJA!$R68),0) -> 735.41482 | T68: =IFERROR(#REF!/CONCILIÇÃO_COM_CERVEJA!$M68,"") | U68: =IFERROR(#REF!*CONCILIÇÃO_COM_CERVEJA!$R68,"-") -> -
A69: 36 | B69: 2701100002 | C69: - | D69: BENZOATO SODIO | E69: =IFERROR(VLOOKUP(B69,[1]AGLUTINADO!$A:$C,3,0),0)/G69 -> 413.97 | F69: CONSERVANTE | G69: 1 | H69: =VLOOKUP(CONCILIÇÃO_COM_CERVEJA!$B69,CONT_ANTE!A:D,4,0) -> 194.5 | I69: =IF(AND(E69=0,H69<>J69),"!@##@!","ok") -> ok | J69: =VLOOKUP(CONCILIÇÃO_COM_CERVEJA!$B69,CONTAGEM!B:G,6,0) -> 1436.5 | K69: =SUMIF(SISTEMA!B:B,CONCILIÇÃO_COM_CERVEJA!$B69,SISTEMA!I:I)/G69 -> 2937.607 | L69: =SUMIF(SISTEMA!B:B,CONCILIÇÃO_COM_CERVEJA!$C69,SISTEMA!I:I) -> 0 | M69: =K69+L69 -> 2937.607 | N69: =IFERROR(SUM(CONCILIÇÃO_COM_CERVEJA!$M69*CONCILIÇÃO_COM_CERVEJA!$R69),0) -> 29027.513 | O69: =IFERROR(VLOOKUP(CONCILIÇÃO_COM_CERVEJA!$B69,DIF_ANTE!A:D,4,0),"0")/CONCILIÇÃO_COM_CERVEJA!$G69 -> -1537.037 | P69: =J69-M69 -> -1501.107 | Q69: =CONCILIÇÃO_COM_CERVEJA!$P69-CONCILIÇÃO_COM_CERVEJA!$O69 -> 35.93 | R69: =IFERROR(VLOOKUP(CONCILIÇÃO_COM_CERVEJA!$B69,CUSTO!E:H,4,0),(VLOOKUP(CONCILIÇÃO_COM_CERVEJA!$A69,CUSTO!A:H,8,0))) -> 9.8813467 | S69: =IFERROR(SUM(CONCILIÇÃO_COM_CERVEJA!$P69*CONCILIÇÃO_COM_CERVEJA!$R69),0) -> -14832.959 | T69: =IFERROR(#REF!/CONCILIÇÃO_COM_CERVEJA!$M69,"") | U69: =IFERROR(#REF!*CONCILIÇÃO_COM_CERVEJA!$R69,"-") -> -
A70: 31340 | B70: 2701090006 | C70: - | D70: CITRATO SODIO | E70: =IFERROR(VLOOKUP(B70,[1]AGLUTINADO!$A:$C,3,0),0)/G70 -> 301.23 | F70: CONSERVANTE | G70: 1 | H70: =VLOOKUP(CONCILIÇÃO_COM_CERVEJA!$B70,CONT_ANTE!A:D,4,0) -> 1188 | I70: =IF(AND(E70=0,H70<>J70),"!@##@!","ok") -> ok | J70: =VLOOKUP(CONCILIÇÃO_COM_CERVEJA!$B70,CONTAGEM!B:G,6,0) -> 901.5 | K70: =SUMIF(SISTEMA!B:B,CONCILIÇÃO_COM_CERVEJA!$B70,SISTEMA!I:I)/G70 -> 855.0048 | L70: =SUMIF(SISTEMA!B:B,CONCILIÇÃO_COM_CERVEJA!$C70,SISTEMA!I:I) -> 0 | M70: =K70+L70 -> 855.0048 | N70: =IFERROR(SUM(CONCILIÇÃO_COM_CERVEJA!$M70*CONCILIÇÃO_COM_CERVEJA!$R70),0) -> 6034.0938 | O70: =IFERROR(VLOOKUP(CONCILIÇÃO_COM_CERVEJA!$B70,DIF_ANTE!A:D,4,0),"0")/CONCILIÇÃO_COM_CERVEJA!$G70 -> 31.7652 | P70: =J70-M70 -> 46.4952 | Q70: =CONCILIÇÃO_COM_CERVEJA!$P70-CONCILIÇÃO_COM_CERVEJA!$O70 -> 14.73 | R70: =IFERROR(VLOOKUP(CONCILIÇÃO_COM_CERVEJA!$B70,CUSTO!E:H,4,0),(VLOOKUP(CONCILIÇÃO_COM_CERVEJA!$A70,CUSTO!A:H,8,0))) -> 7.05738 | S70: =IFERROR(SUM(CONCILIÇÃO_COM_CERVEJA!$P70*CONCILIÇÃO_COM_CERVEJA!$R70),0) -> 328.13429 | T70: =IFERROR(#REF!/CONCILIÇÃO_COM_CERVEJA!$M70,"") | U70: =IFERROR(#REF!*CONCILIÇÃO_COM_CERVEJA!$R70,"-") -> -
A71: 31338 | B71: 2701120001 | C71: - | D71: PREMIX CAFEINA/ TAURINA/ VITAMINAS ENERGETICO | E71: =IFERROR(VLOOKUP(B71,[1]AGLUTINADO!$A:$C,3,0),0)/G71 -> 1128.25 | F71: CONSERVANTE | G71: 1 | H71: =VLOOKUP(CONCILIÇÃO_COM_CERVEJA!$B71,CONT_ANTE!A:D,4,0) -> 3098 | I71: =IF(AND(E71=0,H71<>J71),"!@##@!","ok") -> ok | J71: =VLOOKUP(CONCILIÇÃO_COM_CERVEJA!$B71,CONTAGEM!B:G,6,0) -> 3705 | K71: =SUMIF(SISTEMA!B:B,CONCILIÇÃO_COM_CERVEJA!$B71,SISTEMA!I:I)/G71 -> 2036.1 | L71: =SUMIF(SISTEMA!B:B,CONCILIÇÃO_COM_CERVEJA!$C71,SISTEMA!I:I) -> 0 | M71: =K71+L71 -> 2036.1 | N71: =IFERROR(SUM(CONCILIÇÃO_COM_CERVEJA!$M71*CONCILIÇÃO_COM_CERVEJA!$R71),0) -> 31704.799 | O71: =IFERROR(VLOOKUP(CONCILIÇÃO_COM_CERVEJA!$B71,DIF_ANTE!A:D,4,0),"0")/CONCILIÇÃO_COM_CERVEJA!$G71 -> -66.35 | P71: =J71-M71 -> 1668.9 | Q71: =CONCILIÇÃO_COM_CERVEJA!$P71-CONCILIÇÃO_COM_CERVEJA!$O71 -> 1735.25 | R71: =IFERROR(VLOOKUP(CONCILIÇÃO_COM_CERVEJA!$B71,CUSTO!E:H,4,0),(VLOOKUP(CONCILIÇÃO_COM_CERVEJA!$A71,CUSTO!A:H,8,0))) -> 15.571337 | S71: =IFERROR(SUM(CONCILIÇÃO_COM_CERVEJA!$P71*CONCILIÇÃO_COM_CERVEJA!$R71),0) -> 25987.004 | T71: =IFERROR(#REF!/CONCILIÇÃO_COM_CERVEJA!$M71,"") | U71: =IFERROR(#REF!*CONCILIÇÃO_COM_CERVEJA!$R71,"-") -> -
A72: 34 | B72: 2701100001 | C72: - | D72: SORBATO POTASSIO | E72: =IFERROR(VLOOKUP(B72,[1]AGLUTINADO!$A:$C,3,0),0)/G72 -> 38.47 | F72: CONSERVANTE | G72: 1 | H72: =VLOOKUP(CONCILIÇÃO_COM_CERVEJA!$B72,CONT_ANTE!A:D,4,0) -> 404.5 | I72: =IF(AND(E72=0,H72<>J72),"!@##@!","ok") -> ok | J72: =VLOOKUP(CONCILIÇÃO_COM_CERVEJA!$B72,CONTAGEM!B:G,6,0) -> 367.5 | K72: =SUMIF(SISTEMA!B:B,CONCILIÇÃO_COM_CERVEJA!$B72,SISTEMA!I:I)/G72 -> 401.06889 | L72: =SUMIF(SISTEMA!B:B,CONCILIÇÃO_COM_CERVEJA!$C72,SISTEMA!I:I) -> 0 | M72: =K72+L72 -> 401.06889 | N72: =IFERROR(SUM(CONCILIÇÃO_COM_CERVEJA!$M72*CONCILIÇÃO_COM_CERVEJA!$R72),0) -> 5563.5341 | O72: =IFERROR(VLOOKUP(CONCILIÇÃO_COM_CERVEJA!$B72,DIF_ANTE!A:D,4,0),"0")/CONCILIÇÃO_COM_CERVEJA!$G72 -> -36.73889 | P72: =J72-M72 -> -33.56889 | Q72: =CONCILIÇÃO_COM_CERVEJA!$P72-CONCILIÇÃO_COM_CERVEJA!$O72 -> 3.17 | R72: =IFERROR(VLOOKUP(CONCILIÇÃO_COM_CERVEJA!$B72,CUSTO!E:H,4,0),(VLOOKUP(CONCILIÇÃO_COM_CERVEJA!$A72,CUSTO!A:H,8,0))) -> 13.871767 | S72: =IFERROR(SUM(CONCILIÇÃO_COM_CERVEJA!$P72*CONCILIÇÃO_COM_CERVEJA!$R72),0) -> -465.65981 | T72: =IFERROR(#REF!/CONCILIÇÃO_COM_CERVEJA!$M72,"") | U72: =IFERROR(#REF!*CONCILIÇÃO_COM_CERVEJA!$R72,"-") -> -
A73: 31332 | B73: 2701060009 | C73: - | D73: CORANTE AMARELO SUNSET | E73: =IFERROR(VLOOKUP(B73,[1]AGLUTINADO!$A:$C,3,0),0)/G73 -> 3.23044 | F73: CORANTE | G73: 1 | H73: =VLOOKUP(CONCILIÇÃO_COM_CERVEJA!$B73,CONT_ANTE!A:D,4,0) -> 20 | I73: =IF(AND(E73=0,H73<>J73),"!@##@!","ok") -> ok | J73: =VLOOKUP(CONCILIÇÃO_COM_CERVEJA!$B73,CONTAGEM!B:G,6,0) -> 15 | K73: =SUMIF(SISTEMA!B:B,CONCILIÇÃO_COM_CERVEJA!$B73,SISTEMA!I:I)/G73 -> 17.6931 | L73: =SUMIF(SISTEMA!B:B,CONCILIÇÃO_COM_CERVEJA!$C73,SISTEMA!I:I) -> 0 | M73: =K73+L73 -> 17.6931 | N73: =IFERROR(SUM(CONCILIÇÃO_COM_CERVEJA!$M73*CONCILIÇÃO_COM_CERVEJA!$R73),0) -> 733.41438 | O73: =IFERROR(VLOOKUP(CONCILIÇÃO_COM_CERVEJA!$B73,DIF_ANTE!A:D,4,0),"0")/CONCILIÇÃO_COM_CERVEJA!$G73 -> -0.92354 | P73: =J73-M73 -> -2.6931 | Q73: =CONCILIÇÃO_COM_CERVEJA!$P73-CONCILIÇÃO_COM_CERVEJA!$O73 -> -1.76956 | R73: =IFERROR(VLOOKUP(CONCILIÇÃO_COM_CERVEJA!$B73,CUSTO!E:H,4,0),(VLOOKUP(CONCILIÇÃO_COM_CERVEJA!$A73,CUSTO!A:H,8,0))) -> 41.452 | S73: =IFERROR(SUM(CONCILIÇÃO_COM_CERVEJA!$P73*CONCILIÇÃO_COM_CERVEJA!$R73),0) -> -111.63438 | T73: =IFERROR(#REF!/CONCILIÇÃO_COM_CERVEJA!$M73,"") | U73: =IFERROR(#REF!*CONCILIÇÃO_COM_CERVEJA!$R73,"-") -> -
A74: 31333 | B74: 2701060003 | C74: - | D74: CORANTE AMARELO TARTRAZINA | E74: =IFERROR(VLOOKUP(B74,[1]AGLUTINADO!$A:$C,3,0),0)/G74 -> 1.29073 | F74: CORANTE | G74: 1 | H74: =VLOOKUP(CONCILIÇÃO_COM_CERVEJA!$B74,CONT_ANTE!A:D,4,0) -> 6.2 | I74: =IF(AND(E74=0,H74<>J74),"!@##@!","ok") -> ok | J74: =VLOOKUP(CONCILIÇÃO_COM_CERVEJA!$B74,CONTAGEM!B:G,6,0) -> 5 | K74: =SUMIF(SISTEMA!B:B,CONCILIÇÃO_COM_CERVEJA!$B74,SISTEMA!I:I)/G74 -> 4.74757 | L74: =SUMIF(SISTEMA!B:B,CONCILIÇÃO_COM_CERVEJA!$C74,SISTEMA!I:I) -> 0 | M74: =K74+L74 -> 4.74757 | N74: =IFERROR(SUM(CONCILIÇÃO_COM_CERVEJA!$M74*CONCILIÇÃO_COM_CERVEJA!$R74),0) -> 211.37131 | O74: =IFERROR(VLOOKUP(CONCILIÇÃO_COM_CERVEJA!$B74,DIF_ANTE!A:D,4,0),"0")/CONCILIÇÃO_COM_CERVEJA!$G74 -> 0.1617 | P74: =J74-M74 -> 0.25243 | Q74: =CONCILIÇÃO_COM_CERVEJA!$P74-CONCILIÇÃO_COM_CERVEJA!$O74 -> 0.09073 | R74: =IFERROR(VLOOKUP(CONCILIÇÃO_COM_CERVEJA!$B74,CUSTO!E:H,4,0),(VLOOKUP(CONCILIÇÃO_COM_CERVEJA!$A74,CUSTO!A:H,8,0))) -> 44.522 | S74: =IFERROR(SUM(CONCILIÇÃO_COM_CERVEJA!$P74*CONCILIÇÃO_COM_CERVEJA!$R74),0) -> 11.238688 | T74: =IFERROR(#REF!/CONCILIÇÃO_COM_CERVEJA!$M74,"") | U74: =IFERROR(#REF!*CONCILIÇÃO_COM_CERVEJA!$R74,"-") -> -
A75: 31339 | B75: 2701060008 | C75: - | D75: CORANTE AZUL BRILHANTE | E75: =IFERROR(VLOOKUP(B75,[1]AGLUTINADO!$A:$C,3,0),0)/G75 -> 2.29402 | F75: CORANTE | G75: 1 | H75: =VLOOKUP(CONCILIÇÃO_COM_CERVEJA!$B75,CONT_ANTE!A:D,4,0) -> 9.195 | I75: =IF(AND(E75=0,H75<>J75),"!@##@!","ok") -> ok | J75: =VLOOKUP(CONCILIÇÃO_COM_CERVEJA!$B75,CONTAGEM!B:G,6,0) -> 5 | K75: =SUMIF(SISTEMA!B:B,CONCILIÇÃO_COM_CERVEJA!$B75,SISTEMA!I:I)/G75 -> 1.85788 | L75: =SUMIF(SISTEMA!B:B,CONCILIÇÃO_COM_CERVEJA!$C75,SISTEMA!I:I) -> 0 | M75: =K75+L75 -> 1.85788 | N75: =IFERROR(SUM(CONCILIÇÃO_COM_CERVEJA!$M75*CONCILIÇÃO_COM_CERVEJA!$R75),0) -> 190.33609 | O75: =IFERROR(VLOOKUP(CONCILIÇÃO_COM_CERVEJA!$B75,DIF_ANTE!A:D,4,0),"0")/CONCILIÇÃO_COM_CERVEJA!$G75 -> 5.0431 | P75: =J75-M75 -> 3.14212 | Q75: =CONCILIÇÃO_COM_CERVEJA!$P75-CONCILIÇÃO_COM_CERVEJA!$O75 -> -1.90098 | R75: =IFERROR(VLOOKUP(CONCILIÇÃO_COM_CERVEJA!$B75,CUSTO!E:H,4,0),(VLOOKUP(CONCILIÇÃO_COM_CERVEJA!$A75,CUSTO!A:H,8,0))) -> 102.448 | S75: =IFERROR(SUM(CONCILIÇÃO_COM_CERVEJA!$P75*CONCILIÇÃO_COM_CERVEJA!$R75),0) -> 321.90391 | T75: =IFERROR(#REF!/CONCILIÇÃO_COM_CERVEJA!$M75,"") | U75: =IFERROR(#REF!*CONCILIÇÃO_COM_CERVEJA!$R75,"-") -> -
A76: 37 | B76: 2701060007 | C76: - | D76: CORANTE CARAMELO CLASSE IV DPC | E76: =IFERROR(VLOOKUP(B76,[1]AGLUTINADO!$A:$C,3,0),0)/G76 -> 179.64 | F76: CORANTE | G76: 1 | H76: =VLOOKUP(CONCILIÇÃO_COM_CERVEJA!$B76,CONT_ANTE!A:D,4,0) -> 452 | I76: =IF(AND(E76=0,H76<>J76),"!@##@!","ok") -> ok | J76: =VLOOKUP(CONCILIÇÃO_COM_CERVEJA!$B76,CONTAGEM!B:G,6,0) -> 1268 | K76: =SUMIF(SISTEMA!B:B,CONCILIÇÃO_COM_CERVEJA!$B76,SISTEMA!I:I)/G76 -> 1291.99 | L76: =SUMIF(SISTEMA!B:B,CONCILIÇÃO_COM_CERVEJA!$C76,SISTEMA!I:I) -> 0 | M76: =K76+L76 -> 1291.99 | N76: =IFERROR(SUM(CONCILIÇÃO_COM_CERVEJA!$M76*CONCILIÇÃO_COM_CERVEJA!$R76),0) -> 8488.2128 | O76: =IFERROR(VLOOKUP(CONCILIÇÃO_COM_CERVEJA!$B76,DIF_ANTE!A:D,4,0),"0")/CONCILIÇÃO_COM_CERVEJA!$G76 -> -19.63 | P76: =J76-M76 -> -23.99 | Q76: =CONCILIÇÃO_COM_CERVEJA!$P76-CONCILIÇÃO_COM_CERVEJA!$O76 -> -4.36 | R76: =IFERROR(VLOOKUP(CONCILIÇÃO_COM_CERVEJA!$B76,CUSTO!E:H,4,0),(VLOOKUP(CONCILIÇÃO_COM_CERVEJA!$A76,CUSTO!A:H,8,0))) -> 6.569875 | S76: =IFERROR(SUM(CONCILIÇÃO_COM_CERVEJA!$P76*CONCILIÇÃO_COM_CERVEJA!$R76),0) -> -157.6113 | T76: =IFERROR(#REF!/CONCILIÇÃO_COM_CERVEJA!$M76,"") | U76: =IFERROR(#REF!*CONCILIÇÃO_COM_CERVEJA!$R76,"-") -> -
A77: 31785 | B77: 2701060004 | C77: - | D77: CORANTE MARACUJA 6035 SAPORITI | E77: =IFERROR(VLOOKUP(B77,[1]AGLUTINADO!$A:$C,3,0),0)/G77 -> 0 | F77: CORANTE | G77: 1 | H77: =VLOOKUP(CONCILIÇÃO_COM_CERVEJA!$B77,CONT_ANTE!A:D,4,0) -> 0 | I77: =IF(AND(E77=0,H77<>J77),"!@##@!","ok") -> ok | J77: =VLOOKUP(CONCILIÇÃO_COM_CERVEJA!$B77,CONTAGEM!B:G,6,0) -> 0 | K77: =SUMIF(SISTEMA!B:B,CONCILIÇÃO_COM_CERVEJA!$B77,SISTEMA!I:I)/G77 -> 0 | L77: =SUMIF(SISTEMA!B:B,CONCILIÇÃO_COM_CERVEJA!$C77,SISTEMA!I:I) -> 0 | M77: =K77+L77 -> 0 | N77: =IFERROR(SUM(CONCILIÇÃO_COM_CERVEJA!$M77*CONCILIÇÃO_COM_CERVEJA!$R77),0) -> 0 | O77: =IFERROR(VLOOKUP(CONCILIÇÃO_COM_CERVEJA!$B77,DIF_ANTE!A:D,4,0),"0")/CONCILIÇÃO_COM_CERVEJA!$G77 -> 0 | P77: =J77-M77 -> 0 | Q77: =CONCILIÇÃO_COM_CERVEJA!$P77-CONCILIÇÃO_COM_CERVEJA!$O77 -> 0 | R77: =IFERROR(VLOOKUP(CONCILIÇÃO_COM_CERVEJA!$B77,CUSTO!E:H,4,0),(VLOOKUP(CONCILIÇÃO_COM_CERVEJA!$A77,CUSTO!A:H,8,0))) -> 24.0075 | S77: =IFERROR(SUM(CONCILIÇÃO_COM_CERVEJA!$P77*CONCILIÇÃO_COM_CERVEJA!$R77),0) -> 0 | T77: =IFERROR(#REF!/CONCILIÇÃO_COM_CERVEJA!$M77,"") | U77: =IFERROR(#REF!*CONCILIÇÃO_COM_CERVEJA!$R77,"-") -> - | V77: OK
A78: 38 | B78: 2701060002 | C78: - | D78: CORANTE VERMELHO 3167 SAPORITI | E78: =IFERROR(VLOOKUP(B78,[1]AGLUTINADO!$A:$C,3,0),0)/G78 -> 0 | F78: CORANTE | G78: 1 | H78: =VLOOKUP(CONCILIÇÃO_COM_CERVEJA!$B78,CONT_ANTE!A:D,4,0) -> 0 | I78: =IF(AND(E78=0,H78<>J78),"!@##@!","ok") -> ok | J78: =VLOOKUP(CONCILIÇÃO_COM_CERVEJA!$B78,CONTAGEM!B:G,6,0) -> 0 | K78: =SUMIF(SISTEMA!B:B,CONCILIÇÃO_COM_CERVEJA!$B78,SISTEMA!I:I)/G78 -> 4 | L78: =SUMIF(SISTEMA!B:B,CONCILIÇÃO_COM_CERVEJA!$C78,SISTEMA!I:I) -> 0 | M78: =K78+L78 -> 4 | N78: =IFERROR(SUM(CONCILIÇÃO_COM_CERVEJA!$M78*CONCILIÇÃO_COM_CERVEJA!$R78),0) -> 67.745 | O78: =IFERROR(VLOOKUP(CONCILIÇÃO_COM_CERVEJA!$B78,DIF_ANTE!A:D,4,0),"0")/CONCILIÇÃO_COM_CERVEJA!$G78 -> -4 | P78: =J78-M78 -> -4 | Q78: =CONCILIÇÃO_COM_CERVEJA!$P78-CONCILIÇÃO_COM_CERVEJA!$O78 -> 0 | R78: =IFERROR(VLOOKUP(CONCILIÇÃO_COM_CERVEJA!$B78,CUSTO!E:H,4,0),(VLOOKUP(CONCILIÇÃO_COM_CERVEJA!$A78,CUSTO!A:H,8,0))) -> 16.93625 | S78: =IFERROR(SUM(CONCILIÇÃO_COM_CERVEJA!$P78*CONCILIÇÃO_COM_CERVEJA!$R78),0) -> -67.745 | T78: =IFERROR(#REF!/CONCILIÇÃO_COM_CERVEJA!$M78,"") | U78: =IFERROR(#REF!*CONCILIÇÃO_COM_CERVEJA!$R78,"-") -> - | V78: OK
A79: 31396 | B79: 2701060010 | C79: - | D79: CORANTE VERMELHO AMARANTO | E79: =IFERROR(VLOOKUP(B79,[1]AGLUTINADO!$A:$C,3,0),0)/G79 -> 4.56737 | F79: CORANTE | G79: 1 | H79: =VLOOKUP(CONCILIÇÃO_COM_CERVEJA!$B79,CONT_ANTE!A:D,4,0) -> 30 | I79: =IF(AND(E79=0,H79<>J79),"!@##@!","ok") -> ok | J79: =VLOOKUP(CONCILIÇÃO_COM_CERVEJA!$B79,CONTAGEM!B:G,6,0) -> 25 | K79: =SUMIF(SISTEMA!B:B,CONCILIÇÃO_COM_CERVEJA!$B79,SISTEMA!I:I)/G79 -> 28.40159 | L79: =SUMIF(SISTEMA!B:B,CONCILIÇÃO_COM_CERVEJA!$C79,SISTEMA!I:I) -> 0 | M79: =K79+L79 -> 28.40159 | N79: =IFERROR(SUM(CONCILIÇÃO_COM_CERVEJA!$M79*CONCILIÇÃO_COM_CERVEJA!$R79),0) -> 2189.3224 | O79: =IFERROR(VLOOKUP(CONCILIÇÃO_COM_CERVEJA!$B79,DIF_ANTE!A:D,4,0),"0")/CONCILIÇÃO_COM_CERVEJA!$G79 -> -2.96896 | P79: =J79-M79 -> -3.40159 | Q79: =CONCILIÇÃO_COM_CERVEJA!$P79-CONCILIÇÃO_COM_CERVEJA!$O79 -> -0.43263 | R79: =IFERROR(VLOOKUP(CONCILIÇÃO_COM_CERVEJA!$B79,CUSTO!E:H,4,0),(VLOOKUP(CONCILIÇÃO_COM_CERVEJA!$A79,CUSTO!A:H,8,0))) -> 77.0845 | S79: =IFERROR(SUM(CONCILIÇÃO_COM_CERVEJA!$P79*CONCILIÇÃO_COM_CERVEJA!$R79),0) -> -262.20986 | T79: =IFERROR(#REF!/CONCILIÇÃO_COM_CERVEJA!$M79,"") | U79: =IFERROR(#REF!*CONCILIÇÃO_COM_CERVEJA!$R79,"-") -> -
A80: 2199 | B80: 2701060001 | C80: - | D80: CORANTE VERMELHO PONCEAU | E80: =IFERROR(VLOOKUP(B80,[1]AGLUTINADO!$A:$C,3,0),0)/G80 -> 0.97441 | F80: CORANTE | G80: 1 | H80: =VLOOKUP(CONCILIÇÃO_COM_CERVEJA!$B80,CONT_ANTE!A:D,4,0) -> 9.2 | I80: =IF(AND(E80=0,H80<>J80),"!@##@!","ok") -> ok | J80: =VLOOKUP(CONCILIÇÃO_COM_CERVEJA!$B80,CONTAGEM!B:G,6,0) -> 5 | K80: =SUMIF(SISTEMA!B:B,CONCILIÇÃO_COM_CERVEJA!$B80,SISTEMA!I:I)/G80 -> 7.034 | L80: =SUMIF(SISTEMA!B:B,CONCILIÇÃO_COM_CERVEJA!$C80,SISTEMA!I:I) -> 0 | M80: =K80+L80 -> 7.034 | N80: =IFERROR(SUM(CONCILIÇÃO_COM_CERVEJA!$M80*CONCILIÇÃO_COM_CERVEJA!$R80),0) -> 382.53002 | O80: =IFERROR(VLOOKUP(CONCILIÇÃO_COM_CERVEJA!$B80,DIF_ANTE!A:D,4,0),"0")/CONCILIÇÃO_COM_CERVEJA!$G80 -> 1.19159 | P80: =J80-M80 -> -2.034 | Q80: =CONCILIÇÃO_COM_CERVEJA!$P80-CONCILIÇÃO_COM_CERVEJA!$O80 -> -3.22559 | R80: =IFERROR(VLOOKUP(CONCILIÇÃO_COM_CERVEJA!$B80,CUSTO!E:H,4,0),(VLOOKUP(CONCILIÇÃO_COM_CERVEJA!$A80,CUSTO!A:H,8,0))) -> 54.383 | S80: =IFERROR(SUM(CONCILIÇÃO_COM_CERVEJA!$P80*CONCILIÇÃO_COM_CERVEJA!$R80),0) -> -110.61502 | T80: =IFERROR(#REF!/CONCILIÇÃO_COM_CERVEJA!$M80,"") | U80: =IFERROR(#REF!*CONCILIÇÃO_COM_CERVEJA!$R80,"-") -> -
A81: 32718 | B81: 2701050002 | C81: - | D81: COMPOSTO DESTILADO DE ERVAS AROMATICAS GIN BRUNHOLI | E81: =IFERROR(VLOOKUP(B81,[1]AGLUTINADO!$A:$C,3,0),0)/G81 -> 346 | F81: DESTILADO | G81: 1 | H81: =VLOOKUP(CONCILIÇÃO_COM_CERVEJA!$B81,CONT_ANTE!A:D,4,0) -> 1400 | I81: =IF(AND(E81=0,H81<>J81),"!@##@!","ok") -> ok | J81: =VLOOKUP(CONCILIÇÃO_COM_CERVEJA!$B81,CONTAGEM!B:G,6,0) -> 0 | K81: =SUMIF(SISTEMA!B:B,CONCILIÇÃO_COM_CERVEJA!$B81,SISTEMA!I:I)/G81 -> 86 | L81: =SUMIF(SISTEMA!B:B,CONCILIÇÃO_COM_CERVEJA!$C81,SISTEMA!I:I) -> 0 | M81: =K81+L81 -> 86 | N81: =IFERROR(SUM(CONCILIÇÃO_COM_CERVEJA!$M81*CONCILIÇÃO_COM_CERVEJA!$R81),0) -> 1535.96 | O81: =IFERROR(VLOOKUP(CONCILIÇÃO_COM_CERVEJA!$B81,DIF_ANTE!A:D,4,0),"0")/CONCILIÇÃO_COM_CERVEJA!$G81 -> 968 | P81: =J81-M81 -> -86 | Q81: =CONCILIÇÃO_COM_CERVEJA!$P81-CONCILIÇÃO_COM_CERVEJA!$O81 -> -1054 | R81: =IFERROR(VLOOKUP(CONCILIÇÃO_COM_CERVEJA!$B81,CUSTO!E:H,4,0),(VLOOKUP(CONCILIÇÃO_COM_CERVEJA!$A81,CUSTO!A:H,8,0))) -> 17.86 | S81: =IFERROR(SUM(CONCILIÇÃO_COM_CERVEJA!$P81*CONCILIÇÃO_COM_CERVEJA!$R81),0) -> -1535.96 | T81: =IFERROR(#REF!/CONCILIÇÃO_COM_CERVEJA!$M81,"") | U81: =IFERROR(#REF!*CONCILIÇÃO_COM_CERVEJA!$R81,"-") -> -
A82: 1768 | B82: 2701070006 | C82: - | D82: ACESULFAME POTASSIO | E82: =IFERROR(VLOOKUP(B82,[1]AGLUTINADO!$A:$C,3,0),0)/G82 -> 34.25 | F82: EDUCORANTE | G82: 1 | H82: =VLOOKUP(CONCILIÇÃO_COM_CERVEJA!$B82,CONT_ANTE!A:D,4,0) -> 109 | I82: =IF(AND(E82=0,H82<>J82),"!@##@!","ok") -> ok | J82: =VLOOKUP(CONCILIÇÃO_COM_CERVEJA!$B82,CONTAGEM!B:G,6,0) -> 177.3 | K82: =SUMIF(SISTEMA!B:B,CONCILIÇÃO_COM_CERVEJA!$B82,SISTEMA!I:I)/G82 -> 177.73506 | L82: =SUMIF(SISTEMA!B:B,CONCILIÇÃO_COM_CERVEJA!$C82,SISTEMA!I:I) -> 0 | M82: =K82+L82 -> 177.73506 | N82: =IFERROR(SUM(CONCILIÇÃO_COM_CERVEJA!$M82*CONCILIÇÃO_COM_CERVEJA!$R82),0) -> 4279.6203 | O82: =IFERROR(VLOOKUP(CONCILIÇÃO_COM_CERVEJA!$B82,DIF_ANTE!A:D,4,0),"0")/CONCILIÇÃO_COM_CERVEJA!$G82 -> -2.98506 | P82: =J82-M82 -> -0.43506 | Q82: =CONCILIÇÃO_COM_CERVEJA!$P82-CONCILIÇÃO_COM_CERVEJA!$O82 -> 2.55 | R82: =IFERROR(VLOOKUP(CONCILIÇÃO_COM_CERVEJA!$B82,CUSTO!E:H,4,0),(VLOOKUP(CONCILIÇÃO_COM_CERVEJA!$A82,CUSTO!A:H,8,0))) -> 24.07865 | S82: =IFERROR(SUM(CONCILIÇÃO_COM_CERVEJA!$P82*CONCILIÇÃO_COM_CERVEJA!$R82),0) -> -10.475657 | T82: =IFERROR(#REF!/CONCILIÇÃO_COM_CERVEJA!$M82,"") | U82: =IFERROR(#REF!*CONCILIÇÃO_COM_CERVEJA!$R82,"-") -> -
A83: 32420 | B83: 2701070005 | C83: - | D83: ASPARTAME | E83: =IFERROR(VLOOKUP(B83,[1]AGLUTINADO!$A:$C,3,0),0)/G83 -> 26.93 | F83: EDUCORANTE | G83: 1 | H83: =VLOOKUP(CONCILIÇÃO_COM_CERVEJA!$B83,CONT_ANTE!A:D,4,0) -> 26.5 | I83: =IF(AND(E83=0,H83<>J83),"!@##@!","ok") -> ok | J83: =VLOOKUP(CONCILIÇÃO_COM_CERVEJA!$B83,CONTAGEM!B:G,6,0) -> 75 | K83: =SUMIF(SISTEMA!B:B,CONCILIÇÃO_COM_CERVEJA!$B83,SISTEMA!I:I)/G83 -> 75.76 | L83: =SUMIF(SISTEMA!B:B,CONCILIÇÃO_COM_CERVEJA!$C83,SISTEMA!I:I) -> 0 | M83: =K83+L83 -> 75.76 | N83: =IFERROR(SUM(CONCILIÇÃO_COM_CERVEJA!$M83*CONCILIÇÃO_COM_CERVEJA!$R83),0) -> 3706.3459 | O83: =IFERROR(VLOOKUP(CONCILIÇÃO_COM_CERVEJA!$B83,DIF_ANTE!A:D,4,0),"0")/CONCILIÇÃO_COM_CERVEJA!$G83 -> -1.19 | P83: =J83-M83 -> -0.76 | Q83: =CONCILIÇÃO_COM_CERVEJA!$P83-CONCILIÇÃO_COM_CERVEJA!$O83 -> 0.43 | R83: =IFERROR(VLOOKUP(CONCILIÇÃO_COM_CERVEJA!$B83,CUSTO!E:H,4,0),(VLOOKUP(CONCILIÇÃO_COM_CERVEJA!$A83,CUSTO!A:H,8,0))) -> 48.9222 | S83: =IFERROR(SUM(CONCILIÇÃO_COM_CERVEJA!$P83*CONCILIÇÃO_COM_CERVEJA!$R83),0) -> -37.180872 | T83: =IFERROR(#REF!/CONCILIÇÃO_COM_CERVEJA!$M83,"") | U83: =IFERROR(#REF!*CONCILIÇÃO_COM_CERVEJA!$R83,"-") -> -
A84: 2205 | B84: 2701070004 | C84: - | D84: CICLAMATO SODIO | E84: =IFERROR(VLOOKUP(B84,[1]AGLUTINADO!$A:$C,3,0),0)/G84 -> 62.85 | F84: EDUCORANTE | G84: 1 | H84: =VLOOKUP(CONCILIÇÃO_COM_CERVEJA!$B84,CONT_ANTE!A:D,4,0) -> 143 | I84: =IF(AND(E84=0,H84<>J84),"!@##@!","ok") -> ok | J84: =VLOOKUP(CONCILIÇÃO_COM_CERVEJA!$B84,CONTAGEM!B:G,6,0) -> 78 | K84: =SUMIF(SISTEMA!B:B,CONCILIÇÃO_COM_CERVEJA!$B84,SISTEMA!I:I)/G84 -> 92.985 | L84: =SUMIF(SISTEMA!B:B,CONCILIÇÃO_COM_CERVEJA!$C84,SISTEMA!I:I) -> 0 | M84: =K84+L84 -> 92.985 | N84: =IFERROR(SUM(CONCILIÇÃO_COM_CERVEJA!$M84*CONCILIÇÃO_COM_CERVEJA!$R84),0) -> 1052.9761 | O84: =IFERROR(VLOOKUP(CONCILIÇÃO_COM_CERVEJA!$B84,DIF_ANTE!A:D,4,0),"0")/CONCILIÇÃO_COM_CERVEJA!$G84 -> -12.835 | P84: =J84-M84 -> -14.985 | Q84: =CONCILIÇÃO_COM_CERVEJA!$P84-CONCILIÇÃO_COM_CERVEJA!$O84 -> -2.15 | R84: =IFERROR(VLOOKUP(CONCILIÇÃO_COM_CERVEJA!$B84,CUSTO!E:H,4,0),(VLOOKUP(CONCILIÇÃO_COM_CERVEJA!$A84,CUSTO!A:H,8,0))) -> 11.32415 | S84: =IFERROR(SUM(CONCILIÇÃO_COM_CERVEJA!$P84*CONCILIÇÃO_COM_CERVEJA!$R84),0) -> -169.69239 | T84: =IFERROR(#REF!/CONCILIÇÃO_COM_CERVEJA!$M84,"") | U84: =IFERROR(#REF!*CONCILIÇÃO_COM_CERVEJA!$R84,"-") -> -
A85: 2092 | B85: 2701070003 | C85: - | D85: NEOTAME | E85: =IFERROR(VLOOKUP(B85,[1]AGLUTINADO!$A:$C,3,0),0)/G85 -> 0.96 | F85: EDUCORANTE | G85: 1 | H85: =VLOOKUP(CONCILIÇÃO_COM_CERVEJA!$B85,CONT_ANTE!A:D,4,0) -> 2 | I85: =IF(AND(E85=0,H85<>J85),"!@##@!","ok") -> ok | J85: =VLOOKUP(CONCILIÇÃO_COM_CERVEJA!$B85,CONTAGEM!B:G,6,0) -> 21 | K85: =SUMIF(SISTEMA!B:B,CONCILIÇÃO_COM_CERVEJA!$B85,SISTEMA!I:I)/G85 -> 20.47051 | L85: =SUMIF(SISTEMA!B:B,CONCILIÇÃO_COM_CERVEJA!$C85,SISTEMA!I:I) -> 0 | M85: =K85+L85 -> 20.47051 | N85: =IFERROR(SUM(CONCILIÇÃO_COM_CERVEJA!$M85*CONCILIÇÃO_COM_CERVEJA!$R85),0) -> 3176.3681 | O85: =IFERROR(VLOOKUP(CONCILIÇÃO_COM_CERVEJA!$B85,DIF_ANTE!A:D,4,0),"0")/CONCILIÇÃO_COM_CERVEJA!$G85 -> 0.56949 | P85: =J85-M85 -> 0.52949 | Q85: =CONCILIÇÃO_COM_CERVEJA!$P85-CONCILIÇÃO_COM_CERVEJA!$O85 -> -0.04 | R85: =IFERROR(VLOOKUP(CONCILIÇÃO_COM_CERVEJA!$B85,CUSTO!E:H,4,0),(VLOOKUP(CONCILIÇÃO_COM_CERVEJA!$A85,CUSTO!A:H,8,0))) -> 155.168 | S85: =IFERROR(SUM(CONCILIÇÃO_COM_CERVEJA!$P85*CONCILIÇÃO_COM_CERVEJA!$R85),0) -> 82.159904 | T85: =IFERROR(#REF!/CONCILIÇÃO_COM_CERVEJA!$M85,"") | U85: =IFERROR(#REF!*CONCILIÇÃO_COM_CERVEJA!$R85,"-") -> -
A86: 2206 | B86: 2701070002 | C86: - | D86: SACARINA | E86: =IFERROR(VLOOKUP(B86,[1]AGLUTINADO!$A:$C,3,0),0)/G86 -> 17.83 | F86: EDUCORANTE | G86: 1 | H86: =VLOOKUP(CONCILIÇÃO_COM_CERVEJA!$B86,CONT_ANTE!A:D,4,0) -> 41.5 | I86: =IF(AND(E86=0,H86<>J86),"!@##@!","ok") -> ok | J86: =VLOOKUP(CONCILIÇÃO_COM_CERVEJA!$B86,CONTAGEM!B:G,6,0) -> 122 | K86: =SUMIF(SISTEMA!B:B,CONCILIÇÃO_COM_CERVEJA!$B86,SISTEMA!I:I)/G86 -> 130.547 | L86: =SUMIF(SISTEMA!B:B,CONCILIÇÃO_COM_CERVEJA!$C86,SISTEMA!I:I) -> 0 | M86: =K86+L86 -> 130.547 | N86: =IFERROR(SUM(CONCILIÇÃO_COM_CERVEJA!$M86*CONCILIÇÃO_COM_CERVEJA!$R86),0) -> 3484.0731 | O86: =IFERROR(VLOOKUP(CONCILIÇÃO_COM_CERVEJA!$B86,DIF_ANTE!A:D,4,0),"0")/CONCILIÇÃO_COM_CERVEJA!$G86 -> -6.877 | P86: =J86-M86 -> -8.547 | Q86: =CONCILIÇÃO_COM_CERVEJA!$P86-CONCILIÇÃO_COM_CERVEJA!$O86 -> -1.67 | R86: =IFERROR(VLOOKUP(CONCILIÇÃO_COM_CERVEJA!$B86,CUSTO!E:H,4,0),(VLOOKUP(CONCILIÇÃO_COM_CERVEJA!$A86,CUSTO!A:H,8,0))) -> 26.688267 | S86: =IFERROR(SUM(CONCILIÇÃO_COM_CERVEJA!$P86*CONCILIÇÃO_COM_CERVEJA!$R86),0) -> -228.10462 | T86: =IFERROR(#REF!/CONCILIÇÃO_COM_CERVEJA!$M86,"") | U86: =IFERROR(#REF!*CONCILIÇÃO_COM_CERVEJA!$R86,"-") -> -
A87: 1770 | B87: 2701070001 | C87: - | D87: SUCRALOSE | E87: =IFERROR(VLOOKUP(B87,[1]AGLUTINADO!$A:$C,3,0),0)/G87 -> 57.6 | F87: EDUCORANTE | G87: 1 | H87: =VLOOKUP(CONCILIÇÃO_COM_CERVEJA!$B87,CONT_ANTE!A:D,4,0) -> 215.5 | I87: =IF(AND(E87=0,H87<>J87),"!@##@!","ok") -> ok | J87: =VLOOKUP(CONCILIÇÃO_COM_CERVEJA!$B87,CONTAGEM!B:G,6,0) -> 205.3 | K87: =SUMIF(SISTEMA!B:B,CONCILIÇÃO_COM_CERVEJA!$B87,SISTEMA!I:I)/G87 -> 265.739 | L87: =SUMIF(SISTEMA!B:B,CONCILIÇÃO_COM_CERVEJA!$C87,SISTEMA!I:I) -> 0 | M87: =K87+L87 -> 265.739 | N87: =IFERROR(SUM(CONCILIÇÃO_COM_CERVEJA!$M87*CONCILIÇÃO_COM_CERVEJA!$R87),0) -> 19191.862 | O87: =IFERROR(VLOOKUP(CONCILIÇÃO_COM_CERVEJA!$B87,DIF_ANTE!A:D,4,0),"0")/CONCILIÇÃO_COM_CERVEJA!$G87 -> -7.839 | P87: =J87-M87 -> -60.439 | Q87: =CONCILIÇÃO_COM_CERVEJA!$P87-CONCILIÇÃO_COM_CERVEJA!$O87 -> -52.6 | R87: =IFERROR(VLOOKUP(CONCILIÇÃO_COM_CERVEJA!$B87,CUSTO!E:H,4,0),(VLOOKUP(CONCILIÇÃO_COM_CERVEJA!$A87,CUSTO!A:H,8,0))) -> 72.22072 | S87: =IFERROR(SUM(CONCILIÇÃO_COM_CERVEJA!$P87*CONCILIÇÃO_COM_CERVEJA!$R87),0) -> -4364.9481 | T87: =IFERROR(#REF!/CONCILIÇÃO_COM_CERVEJA!$M87,"") | U87: =IFERROR(#REF!*CONCILIÇÃO_COM_CERVEJA!$R87,"-") -> -
A88: 30816 | B88: 2701230040 | C88: - | D88: CERVEJA FILTRADA BAMBOA LAGER | E88: =IFERROR(VLOOKUP(B88,[1]AGLUTINADO!$A:$C,3,0),0)/G88 -> 134375.1 | F88: ELABORAÇÃO | G88: 1 | H88: =VLOOKUP(CONCILIÇÃO_COM_CERVEJA!$B88,CONT_ANTE!A:D,4,0) -> 0 | I88: =IF(AND(E88=0,H88<>J88),"!@##@!","ok") -> ok | J88: =VLOOKUP(CONCILIÇÃO_COM_CERVEJA!$B88,CONTAGEM!B:G,6,0) -> 0 | K88: =SUMIF(SISTEMA!B:B,CONCILIÇÃO_COM_CERVEJA!$B88,SISTEMA!I:I)/G88 -> 18154.9 | L88: =SUMIF(SISTEMA!B:B,CONCILIÇÃO_COM_CERVEJA!$C88,SISTEMA!I:I) -> 0 | M88: =K88+L88 -> 18154.9 | N88: =IFERROR(SUM(CONCILIÇÃO_COM_CERVEJA!$M88*CONCILIÇÃO_COM_CERVEJA!$R88),0) -> 13473.167 | O88: =IFERROR(VLOOKUP(CONCILIÇÃO_COM_CERVEJA!$B88,DIF_ANTE!A:D,4,0),"0")/CONCILIÇÃO_COM_CERVEJA!$G88 -> 0 | P88: =J88-M88 -> -18154.9 | Q88: =CONCILIÇÃO_COM_CERVEJA!$P88-CONCILIÇÃO_COM_CERVEJA!$O88 -> -18154.9 | R88: =IFERROR(VLOOKUP(CONCILIÇÃO_COM_CERVEJA!$B88,CUSTO!E:H,4,0),(VLOOKUP(CONCILIÇÃO_COM_CERVEJA!$A88,CUSTO!A:H,8,0))) -> 0.74212291 | S88: =IFERROR(SUM(CONCILIÇÃO_COM_CERVEJA!$P88*CONCILIÇÃO_COM_CERVEJA!$R88),0) -> -13473.167 | T88: =IFERROR(#REF!/CONCILIÇÃO_COM_CERVEJA!$M88,"") | U88: =IFERROR(#REF!*CONCILIÇÃO_COM_CERVEJA!$R88,"-") -> -
A89: 30258 | B89: 2701230041 | C89: - | D89: CERVEJA FILTRADA BAMBOA PILSEN | E89: =IFERROR(VLOOKUP(B89,[1]AGLUTINADO!$A:$C,3,0),0)/G89 -> 0 | F89: ELABORAÇÃO | G89: 1 | H89: =VLOOKUP(CONCILIÇÃO_COM_CERVEJA!$B89,CONT_ANTE!A:D,4,0) -> 0 | I89: =IF(AND(E89=0,H89<>J89),"!@##@!","ok") -> ok | J89: =VLOOKUP(CONCILIÇÃO_COM_CERVEJA!$B89,CONTAGEM!B:G,6,0) -> 0 | K89: =SUMIF(SISTEMA!B:B,CONCILIÇÃO_COM_CERVEJA!$B89,SISTEMA!I:I)/G89 -> 0 | L89: =SUMIF(SISTEMA!B:B,CONCILIÇÃO_COM_CERVEJA!$C89,SISTEMA!I:I) -> 0 | M89: =K89+L89 -> 0 | N89: =IFERROR(SUM(CONCILIÇÃO_COM_CERVEJA!$M89*CONCILIÇÃO_COM_CERVEJA!$R89),0) -> 0 | O89: =IFERROR(VLOOKUP(CONCILIÇÃO_COM_CERVEJA!$B89,DIF_ANTE!A:D,4,0),"0")/CONCILIÇÃO_COM_CERVEJA!$G89 -> 0 | P89: =J89-M89 -> 0 | Q89: =CONCILIÇÃO_COM_CERVEJA!$P89-CONCILIÇÃO_COM_CERVEJA!$O89 -> 0 | R89: =IFERROR(VLOOKUP(CONCILIÇÃO_COM_CERVEJA!$B89,CUSTO!E:H,4,0),(VLOOKUP(CONCILIÇÃO_COM_CERVEJA!$A89,CUSTO!A:H,8,0))) -> 0.74212291 | S89: =IFERROR(SUM(CONCILIÇÃO_COM_CERVEJA!$P89*CONCILIÇÃO_COM_CERVEJA!$R89),0) -> 0 | T89: =IFERROR(#REF!/CONCILIÇÃO_COM_CERVEJA!$M89,"") | U89: =IFERROR(#REF!*CONCILIÇÃO_COM_CERVEJA!$R89,"-") -> - | V89: OK
A90: 30353 | B90: 2701230038 | C90: - | D90: CERVEJA FILTRADA MOEMA | E90: =IFERROR(VLOOKUP(B90,[1]AGLUTINADO!$A:$C,3,0),0)/G90 -> 887973.17 | F90: ELABORAÇÃO | G90: 1 | H90: =VLOOKUP(CONCILIÇÃO_COM_CERVEJA!$B90,CONT_ANTE!A:D,4,0) -> 102975 | I90: =IF(AND(E90=0,H90<>J90),"!@##@!","ok") -> ok | J90: =VLOOKUP(CONCILIÇÃO_COM_CERVEJA!$B90,CONTAGEM!B:G,6,0) -> 0 | K90: =SUMIF(SISTEMA!B:B,CONCILIÇÃO_COM_CERVEJA!$B90,SISTEMA!I:I)/G90 -> 43296 | L90: =SUMIF(SISTEMA!B:B,CONCILIÇÃO_COM_CERVEJA!$C90,SISTEMA!I:I) -> 0 | M90: =K90+L90 -> 43296 | N90: =IFERROR(SUM(CONCILIÇÃO_COM_CERVEJA!$M90*CONCILIÇÃO_COM_CERVEJA!$R90),0) -> 22807.533 | O90: =IFERROR(VLOOKUP(CONCILIÇÃO_COM_CERVEJA!$B90,DIF_ANTE!A:D,4,0),"0")/CONCILIÇÃO_COM_CERVEJA!$G90 -> -88119.644 | P90: =J90-M90 -> -43296 | Q90: =CONCILIÇÃO_COM_CERVEJA!$P90-CONCILIÇÃO_COM_CERVEJA!$O90 -> 44823.644 | R90: =IFERROR(VLOOKUP(CONCILIÇÃO_COM_CERVEJA!$B90,CUSTO!E:H,4,0),(VLOOKUP(CONCILIÇÃO_COM_CERVEJA!$A90,CUSTO!A:H,8,0))) -> 0.52678153 | S90: =IFERROR(SUM(CONCILIÇÃO_COM_CERVEJA!$P90*CONCILIÇÃO_COM_CERVEJA!$R90),0) -> -22807.533 | T90: =IFERROR(#REF!/CONCILIÇÃO_COM_CERVEJA!$M90,"") | U90: =IFERROR(#REF!*CONCILIÇÃO_COM_CERVEJA!$R90,"-") -> -
A91: 30783 | B91: 2701230036 | C91: - | D91: CERVEJA MATURADA BAMBOA LAGER | E91: =IFERROR(VLOOKUP(B91,[1]AGLUTINADO!$A:$C,3,0),0)/G91 -> 153220 | F91: ELABORAÇÃO | G91: 1 | H91: =VLOOKUP(CONCILIÇÃO_COM_CERVEJA!$B91,CONT_ANTE!A:D,4,0) -> 50780 | I91: =IF(AND(E91=0,H91<>J91),"!@##@!","ok") -> ok | J91: =VLOOKUP(CONCILIÇÃO_COM_CERVEJA!$B91,CONTAGEM!B:G,6,0) -> 0 | K91: =SUMIF(SISTEMA!B:B,CONCILIÇÃO_COM_CERVEJA!$B91,SISTEMA!I:I)/G91 -> 0 | L91: =SUMIF(SISTEMA!B:B,CONCILIÇÃO_COM_CERVEJA!$C91,SISTEMA!I:I) -> 0 | M91: =K91+L91 -> 0 | N91: =IFERROR(SUM(CONCILIÇÃO_COM_CERVEJA!$M91*CONCILIÇÃO_COM_CERVEJA!$R91),0) -> 0 | O91: =IFERROR(VLOOKUP(CONCILIÇÃO_COM_CERVEJA!$B91,DIF_ANTE!A:D,4,0),"0")/CONCILIÇÃO_COM_CERVEJA!$G91 -> 0 | P91: =J91-M91 -> 0 | Q91: =CONCILIÇÃO_COM_CERVEJA!$P91-CONCILIÇÃO_COM_CERVEJA!$O91 -> 0 | R91: =IFERROR(VLOOKUP(CONCILIÇÃO_COM_CERVEJA!$B91,CUSTO!E:H,4,0),(VLOOKUP(CONCILIÇÃO_COM_CERVEJA!$A91,CUSTO!A:H,8,0))) -> 0.7194998 | S91: =IFERROR(SUM(CONCILIÇÃO_COM_CERVEJA!$P91*CONCILIÇÃO_COM_CERVEJA!$R91),0) -> 0 | T91: =IFERROR(#REF!/CONCILIÇÃO_COM_CERVEJA!$M91,"") | U91: =IFERROR(#REF!*CONCILIÇÃO_COM_CERVEJA!$R91,"-") -> - | V91: OK
A92: 30249 | B92: 2701230035 | C92: - | D92: CERVEJA MATURADA BAMBOA PILSEN | E92: =IFERROR(VLOOKUP(B92,[1]AGLUTINADO!$A:$C,3,0),0)/G92 -> 0 | F92: ELABORAÇÃO | G92: 1 | H92: =VLOOKUP(CONCILIÇÃO_COM_CERVEJA!$B92,CONT_ANTE!A:D,4,0) -> 0 | I92: =IF(AND(E92=0,H92<>J92),"!@##@!","ok") -> ok | J92: =VLOOKUP(CONCILIÇÃO_COM_CERVEJA!$B92,CONTAGEM!B:G,6,0) -> 0 | K92: =SUMIF(SISTEMA!B:B,CONCILIÇÃO_COM_CERVEJA!$B92,SISTEMA!I:I)/G92 -> 0 | L92: =SUMIF(SISTEMA!B:B,CONCILIÇÃO_COM_CERVEJA!$C92,SISTEMA!I:I) -> 0 | M92: =K92+L92 -> 0 | N92: =IFERROR(SUM(CONCILIÇÃO_COM_CERVEJA!$M92*CONCILIÇÃO_COM_CERVEJA!$R92),0) -> 0 | O92: =IFERROR(VLOOKUP(CONCILIÇÃO_COM_CERVEJA!$B92,DIF_ANTE!A:D,4,0),"0")/CONCILIÇÃO_COM_CERVEJA!$G92 -> 0 | P92: =J92-M92 -> 0 | Q92: =CONCILIÇÃO_COM_CERVEJA!$P92-CONCILIÇÃO_COM_CERVEJA!$O92 -> 0 | R92: =IFERROR(VLOOKUP(CONCILIÇÃO_COM_CERVEJA!$B92,CUSTO!E:H,4,0),(VLOOKUP(CONCILIÇÃO_COM_CERVEJA!$A92,CUSTO!A:H,8,0))) -> 0.7194998 | S92: =IFERROR(SUM(CONCILIÇÃO_COM_CERVEJA!$P92*CONCILIÇÃO_COM_CERVEJA!$R92),0) -> 0 | T92: =IFERROR(#REF!/CONCILIÇÃO_COM_CERVEJA!$M92,"") | U92: =IFERROR(#REF!*CONCILIÇÃO_COM_CERVEJA!$R92,"-") -> - | V92: OK
A93: 30352 | B93: 2701230037 | C93: - | D93: CERVEJA MATURADA MOEMA | E93: =IFERROR(VLOOKUP(B93,[1]AGLUTINADO!$A:$C,3,0),0)/G93 -> 647976 | F93: ELABORAÇÃO | G93: 1 | H93: =VLOOKUP(CONCILIÇÃO_COM_CERVEJA!$B93,CONT_ANTE!A:D,4,0) -> 691030 | I93: =IF(AND(E93=0,H93<>J93),"!@##@!","ok") -> ok | J93: =VLOOKUP(CONCILIÇÃO_COM_CERVEJA!$B93,CONTAGEM!B:G,6,0) -> 0 | K93: =SUMIF(SISTEMA!B:B,CONCILIÇÃO_COM_CERVEJA!$B93,SISTEMA!I:I)/G93 -> 1009840 | L93: =SUMIF(SISTEMA!B:B,CONCILIÇÃO_COM_CERVEJA!$C93,SISTEMA!I:I) -> 0 | M93: =K93+L93 -> 1009840 | N93: =IFERROR(SUM(CONCILIÇÃO_COM_CERVEJA!$M93*CONCILIÇÃO_COM_CERVEJA!$R93),0) -> 494692.84 | O93: =IFERROR(VLOOKUP(CONCILIÇÃO_COM_CERVEJA!$B93,DIF_ANTE!A:D,4,0),"0")/CONCILIÇÃO_COM_CERVEJA!$G93 -> 0 | P93: =J93-M93 -> -1009840 | Q93: =CONCILIÇÃO_COM_CERVEJA!$P93-CONCILIÇÃO_COM_CERVEJA!$O93 -> -1009840 | R93: =IFERROR(VLOOKUP(CONCILIÇÃO_COM_CERVEJA!$B93,CUSTO!E:H,4,0),(VLOOKUP(CONCILIÇÃO_COM_CERVEJA!$A93,CUSTO!A:H,8,0))) -> 0.4898725 | S93: =IFERROR(SUM(CONCILIÇÃO_COM_CERVEJA!$P93*CONCILIÇÃO_COM_CERVEJA!$R93),0) -> -494692.84 | T93: =IFERROR(#REF!/CONCILIÇÃO_COM_CERVEJA!$M93,"") | U93: =IFERROR(#REF!*CONCILIÇÃO_COM_CERVEJA!$R93,"-") -> -
A94: 1861 | B94: 2701230042 | C94: - | D94: COMPOSTO COQUETEL CV BELLA ROMA | E94: =IFERROR(VLOOKUP(B94,[1]AGLUTINADO!$A:$C,3,0),0)/G94 -> 486797 | F94: ELABORAÇÃO | G94: 1 | H94: =VLOOKUP(CONCILIÇÃO_COM_CERVEJA!$B94,CONT_ANTE!A:D,4,0) -> 12207 | I94: =IF(AND(E94=0,H94<>J94),"!@##@!","ok") -> ok | J94: =VLOOKUP(CONCILIÇÃO_COM_CERVEJA!$B94,CONTAGEM!B:G,6,0) -> 0 | K94: =SUMIF(SISTEMA!B:B,CONCILIÇÃO_COM_CERVEJA!$B94,SISTEMA!I:I)/G94 -> 31425 | L94: =SUMIF(SISTEMA!B:B,CONCILIÇÃO_COM_CERVEJA!$C94,SISTEMA!I:I) -> 0 | M94: =K94+L94 -> 31425 | N94: =IFERROR(SUM(CONCILIÇÃO_COM_CERVEJA!$M94*CONCILIÇÃO_COM_CERVEJA!$R94),0) -> 0 | O94: =IFERROR(VLOOKUP(CONCILIÇÃO_COM_CERVEJA!$B94,DIF_ANTE!A:D,4,0),"0")/CONCILIÇÃO_COM_CERVEJA!$G94 -> -670 | P94: =J94-M94 -> -31425 | Q94: =CONCILIÇÃO_COM_CERVEJA!$P94-CONCILIÇÃO_COM_CERVEJA!$O94 -> -30755 | R94: =IFERROR(VLOOKUP(CONCILIÇÃO_COM_CERVEJA!$B94,CUSTO!E:H,4,0),(VLOOKUP(CONCILIÇÃO_COM_CERVEJA!$A94,CUSTO!A:H,8,0))) -> 0 | S94: =IFERROR(SUM(CONCILIÇÃO_COM_CERVEJA!$P94*CONCILIÇÃO_COM_CERVEJA!$R94),0) -> 0 | T94: =IFERROR(#REF!/CONCILIÇÃO_COM_CERVEJA!$M94,"") | U94: =IFERROR(#REF!*CONCILIÇÃO_COM_CERVEJA!$R94,"-") -> -
B95: 2701230011 | C95: - | D95: COMPOSTO COQUETEL NOCH LIMAO | E95: =IFERROR(VLOOKUP(B95,[1]AGLUTINADO!$A:$C,3,0),0)/G95 -> 0 | F95: ELABORAÇÃO | G95: 1 | H95: =VLOOKUP(CONCILIÇÃO_COM_CERVEJA!$B95,CONT_ANTE!A:D,4,0) -> 0 | I95: =IF(AND(E95=0,H95<>J95),"!@##@!","ok") -> ok | J95: =VLOOKUP(CONCILIÇÃO_COM_CERVEJA!$B95,CONTAGEM!B:G,6,0) -> 0 | K95: =SUMIF(SISTEMA!B:B,CONCILIÇÃO_COM_CERVEJA!$B95,SISTEMA!I:I)/G95 -> 0 | L95: =SUMIF(SISTEMA!B:B,CONCILIÇÃO_COM_CERVEJA!$C95,SISTEMA!I:I) -> 0 | M95: =K95+L95 -> 0 | N95: =IFERROR(SUM(CONCILIÇÃO_COM_CERVEJA!$M95*CONCILIÇÃO_COM_CERVEJA!$R95),0) -> 0 | O95: =IFERROR(VLOOKUP(CONCILIÇÃO_COM_CERVEJA!$B95,DIF_ANTE!A:D,4,0),"0")/CONCILIÇÃO_COM_CERVEJA!$G95 -> 0 | P95: =J95-M95 -> 0 | Q95: =CONCILIÇÃO_COM_CERVEJA!$P95-CONCILIÇÃO_COM_CERVEJA!$O95 -> 0 | R95: =IFERROR(VLOOKUP(CONCILIÇÃO_COM_CERVEJA!$B95,CUSTO!E:H,4,0),(VLOOKUP(CONCILIÇÃO_COM_CERVEJA!$A95,CUSTO!A:H,8,0))) -> 0.11037425 | S95: =IFERROR(SUM(CONCILIÇÃO_COM_CERVEJA!$P95*CONCILIÇÃO_COM_CERVEJA!$R95),0) -> 0 | T95: =IFERROR(#REF!/CONCILIÇÃO_COM_CERVEJA!$M95,"") | U95: =IFERROR(#REF!*CONCILIÇÃO_COM_CERVEJA!$R95,"-") -> - | V95: OK
B96: 2701230012 | C96: - | D96: COMPOSTO COQUETEL NOCH MARACUJA | E96: =IFERROR(VLOOKUP(B96,[1]AGLUTINADO!$A:$C,3,0),0)/G96 -> 0 | F96: ELABORAÇÃO | G96: 1 | H96: =VLOOKUP(CONCILIÇÃO_COM_CERVEJA!$B96,CONT_ANTE!A:D,4,0) -> 0 | I96: =IF(AND(E96=0,H96<>J96),"!@##@!","ok") -> ok | J96: =VLOOKUP(CONCILIÇÃO_COM_CERVEJA!$B96,CONTAGEM!B:G,6,0) -> 0 | K96: =SUMIF(SISTEMA!B:B,CONCILIÇÃO_COM_CERVEJA!$B96,SISTEMA!I:I)/G96 -> 0 | L96: =SUMIF(SISTEMA!B:B,CONCILIÇÃO_COM_CERVEJA!$C96,SISTEMA!I:I) -> 0 | M96: =K96+L96 -> 0 | N96: =IFERROR(SUM(CONCILIÇÃO_COM_CERVEJA!$M96*CONCILIÇÃO_COM_CERVEJA!$R96),0) -> 0 | O96: =IFERROR(VLOOKUP(CONCILIÇÃO_COM_CERVEJA!$B96,DIF_ANTE!A:D,4,0),"0")/CONCILIÇÃO_COM_CERVEJA!$G96 -> 0 | P96: =J96-M96 -> 0 | Q96: =CONCILIÇÃO_COM_CERVEJA!$P96-CONCILIÇÃO_COM_CERVEJA!$O96 -> 0 | R96: =IFERROR(VLOOKUP(CONCILIÇÃO_COM_CERVEJA!$B96,CUSTO!E:H,4,0),(VLOOKUP(CONCILIÇÃO_COM_CERVEJA!$A96,CUSTO!A:H,8,0))) -> 0.11037425 | S96: =IFERROR(SUM(CONCILIÇÃO_COM_CERVEJA!$P96*CONCILIÇÃO_COM_CERVEJA!$R96),0) -> 0 | T96: =IFERROR(#REF!/CONCILIÇÃO_COM_CERVEJA!$M96,"") | U96: =IFERROR(#REF!*CONCILIÇÃO_COM_CERVEJA!$R96,"-") -> - | V96: OK
B97: 2701230013 | C97: - | D97: COMPOSTO COQUETEL NOCH MELANCIA/ MORANGO | E97: =IFERROR(VLOOKUP(B97,[1]AGLUTINADO!$A:$C,3,0),0)/G97 -> 0 | F97: ELABORAÇÃO | G97: 1 | H97: =VLOOKUP(CONCILIÇÃO_COM_CERVEJA!$B97,CONT_ANTE!A:D,4,0) -> 0 | I97: =IF(AND(E97=0,H97<>J97),"!@##@!","ok") -> ok | J97: =VLOOKUP(CONCILIÇÃO_COM_CERVEJA!$B97,CONTAGEM!B:G,6,0) -> 0 | K97: =SUMIF(SISTEMA!B:B,CONCILIÇÃO_COM_CERVEJA!$B97,SISTEMA!I:I)/G97 -> 0 | L97: =SUMIF(SISTEMA!B:B,CONCILIÇÃO_COM_CERVEJA!$C97,SISTEMA!I:I) -> 0 | M97: =K97+L97 -> 0 | N97: =IFERROR(SUM(CONCILIÇÃO_COM_CERVEJA!$M97*CONCILIÇÃO_COM_CERVEJA!$R97),0) -> 0 | O97: =IFERROR(VLOOKUP(CONCILIÇÃO_COM_CERVEJA!$B97,DIF_ANTE!A:D,4,0),"0")/CONCILIÇÃO_COM_CERVEJA!$G97 -> 0 | P97: =J97-M97 -> 0 | Q97: =CONCILIÇÃO_COM_CERVEJA!$P97-CONCILIÇÃO_COM_CERVEJA!$O97 -> 0 | R97: =IFERROR(VLOOKUP(CONCILIÇÃO_COM_CERVEJA!$B97,CUSTO!E:H,4,0),(VLOOKUP(CONCILIÇÃO_COM_CERVEJA!$A97,CUSTO!A:H,8,0))) -> 0.11037425 | S97: =IFERROR(SUM(CONCILIÇÃO_COM_CERVEJA!$P97*CONCILIÇÃO_COM_CERVEJA!$R97),0) -> 0 | T97: =IFERROR(#REF!/CONCILIÇÃO_COM_CERVEJA!$M97,"") | U97: =IFERROR(#REF!*CONCILIÇÃO_COM_CERVEJA!$R97,"-") -> - | V97: OK
A98: 31344 | B98: 2701230031 | C98: - | D98: COMPOSTO FURIOSO MACA VERDE E MELAO | E98: =IFERROR(VLOOKUP(B98,[1]AGLUTINADO!$A:$C,3,0),0)/G98 -> 83313 | F98: ELABORAÇÃO | G98: 1 | H98: =VLOOKUP(CONCILIÇÃO_COM_CERVEJA!$B98,CONT_ANTE!A:D,4,0) -> 0 | I98: =IF(AND(E98=0,H98<>J98),"!@##@!","ok") -> ok | J98: =VLOOKUP(CONCILIÇÃO_COM_CERVEJA!$B98,CONTAGEM!B:G,6,0) -> 0 | K98: =SUMIF(SISTEMA!B:B,CONCILIÇÃO_COM_CERVEJA!$B98,SISTEMA!I:I)/G98 -> 0 | L98: =SUMIF(SISTEMA!B:B,CONCILIÇÃO_COM_CERVEJA!$C98,SISTEMA!I:I) -> 0 | M98: =K98+L98 -> 0 | N98: =IFERROR(SUM(CONCILIÇÃO_COM_CERVEJA!$M98*CONCILIÇÃO_COM_CERVEJA!$R98),0) -> 0 | O98: =IFERROR(VLOOKUP(CONCILIÇÃO_COM_CERVEJA!$B98,DIF_ANTE!A:D,4,0),"0")/CONCILIÇÃO_COM_CERVEJA!$G98 -> 0 | P98: =J98-M98 -> 0 | Q98: =CONCILIÇÃO_COM_CERVEJA!$P98-CONCILIÇÃO_COM_CERVEJA!$O98 -> 0 | R98: =IFERROR(VLOOKUP(CONCILIÇÃO_COM_CERVEJA!$B98,CUSTO!E:H,4,0),(VLOOKUP(CONCILIÇÃO_COM_CERVEJA!$A98,CUSTO!A:H,8,0))) -> #N/A | S98: =IFERROR(SUM(CONCILIÇÃO_COM_CERVEJA!$P98*CONCILIÇÃO_COM_CERVEJA!$R98),0) -> 0 | T98: =IFERROR(#REF!/CONCILIÇÃO_COM_CERVEJA!$M98,"") | U98: =IFERROR(#REF!*CONCILIÇÃO_COM_CERVEJA!$R98,"-") -> - | V98: OK
A99: 1961 | B99: 2701230034 | C99: - | D99: COMPOSTO FURIOSO MELANCIA E MORANGO | E99: =IFERROR(VLOOKUP(B99,[1]AGLUTINADO!$A:$C,3,0),0)/G99 -> 50040 | F99: ELABORAÇÃO | G99: 1 | H99: =VLOOKUP(CONCILIÇÃO_COM_CERVEJA!$B99,CONT_ANTE!A:D,4,0) -> 0 | I99: =IF(AND(E99=0,H99<>J99),"!@##@!","ok") -> ok | J99: =VLOOKUP(CONCILIÇÃO_COM_CERVEJA!$B99,CONTAGEM!B:G,6,0) -> 0 | K99: =SUMIF(SISTEMA!B:B,CONCILIÇÃO_COM_CERVEJA!$B99,SISTEMA!I:I)/G99 -> 0 | L99: =SUMIF(SISTEMA!B:B,CONCILIÇÃO_COM_CERVEJA!$C99,SISTEMA!I:I) -> 0 | M99: =K99+L99 -> 0 | N99: =IFERROR(SUM(CONCILIÇÃO_COM_CERVEJA!$M99*CONCILIÇÃO_COM_CERVEJA!$R99),0) -> 0 | O99: =IFERROR(VLOOKUP(CONCILIÇÃO_COM_CERVEJA!$B99,DIF_ANTE!A:D,4,0),"0")/CONCILIÇÃO_COM_CERVEJA!$G99 -> 0 | P99: =J99-M99 -> 0 | Q99: =CONCILIÇÃO_COM_CERVEJA!$P99-CONCILIÇÃO_COM_CERVEJA!$O99 -> 0 | R99: =IFERROR(VLOOKUP(CONCILIÇÃO_COM_CERVEJA!$B99,CUSTO!E:H,4,0),(VLOOKUP(CONCILIÇÃO_COM_CERVEJA!$A99,CUSTO!A:H,8,0))) -> #N/A | S99: =IFERROR(SUM(CONCILIÇÃO_COM_CERVEJA!$P99*CONCILIÇÃO_COM_CERVEJA!$R99),0) -> 0 | T99: =IFERROR(#REF!/CONCILIÇÃO_COM_CERVEJA!$M99,"") | U99: =IFERROR(#REF!*CONCILIÇÃO_COM_CERVEJA!$R99,"-") -> - | V99: OK
B100: 2701230043 | C100: - | D100: COMPOSTO FURIOSO MELANCIA E MORANGO ZERO | E100: =IFERROR(VLOOKUP(B100,[1]AGLUTINADO!$A:$C,3,0),0)/G100 -> 15000 | F100: ELABORAÇÃO | G100: 1 | H100: =VLOOKUP(CONCILIÇÃO_COM_CERVEJA!$B100,CONT_ANTE!A:D,4,0) -> 0 | I100: =IF(AND(E100=0,H100<>J100),"!@##@!","ok") -> ok | J100: =VLOOKUP(CONCILIÇÃO_COM_CERVEJA!$B100,CONTAGEM!B:G,6,0) -> 0 | K100: =SUMIF(SISTEMA!B:B,CONCILIÇÃO_COM_CERVEJA!$B100,SISTEMA!I:I)/G100 -> 0 | L100: =SUMIF(SISTEMA!B:B,CONCILIÇÃO_COM_CERVEJA!$C100,SISTEMA!I:I) -> 0 | M100: =K100+L100 -> 0 | N100: =IFERROR(SUM(CONCILIÇÃO_COM_CERVEJA!$M100*CONCILIÇÃO_COM_CERVEJA!$R100),0) -> 0 | O100: =IFERROR(VLOOKUP(CONCILIÇÃO_COM_CERVEJA!$B100,DIF_ANTE!A:D,4,0),"0")/CONCILIÇÃO_COM_CERVEJA!$G100 -> 0 | P100: =J100-M100 -> 0 | Q100: =CONCILIÇÃO_COM_CERVEJA!$P100-CONCILIÇÃO_COM_CERVEJA!$O100 -> 0 | R100: =IFERROR(VLOOKUP(CONCILIÇÃO_COM_CERVEJA!$B100,CUSTO!E:H,4,0),(VLOOKUP(CONCILIÇÃO_COM_CERVEJA!$A100,CUSTO!A:H,8,0))) -> 0.11037425 | S100: =IFERROR(SUM(CONCILIÇÃO_COM_CERVEJA!$P100*CONCILIÇÃO_COM_CERVEJA!$R100),0) -> 0 | T100: =IFERROR(#REF!/CONCILIÇÃO_COM_CERVEJA!$M100,"") | U100: =IFERROR(#REF!*CONCILIÇÃO_COM_CERVEJA!$R100,"-") -> - | V100: OK
A101: 1846 | B101: 2701230017 | C101: - | D101: COMPOSTO FURIOSO TRADICIONAL | E101: =IFERROR(VLOOKUP(B101,[1]AGLUTINADO!$A:$C,3,0),0)/G101 -> 263963 | F101: ELABORAÇÃO | G101: 1 | H101: =VLOOKUP(CONCILIÇÃO_COM_CERVEJA!$B101,CONT_ANTE!A:D,4,0) -> 0 | I101: =IF(AND(E101=0,H101<>J101),"!@##@!","ok") -> ok | J101: =VLOOKUP(CONCILIÇÃO_COM_CERVEJA!$B101,CONTAGEM!B:G,6,0) -> 0 | K101: =SUMIF(SISTEMA!B:B,CONCILIÇÃO_COM_CERVEJA!$B101,SISTEMA!I:I)/G101 -> 2718 | L101: =SUMIF(SISTEMA!B:B,CONCILIÇÃO_COM_CERVEJA!$C101,SISTEMA!I:I) -> 0 | M101: =K101+L101 -> 2718 | N101: =IFERROR(SUM(CONCILIÇÃO_COM_CERVEJA!$M101*CONCILIÇÃO_COM_CERVEJA!$R101),0) -> 0 | O101: =IFERROR(VLOOKUP(CONCILIÇÃO_COM_CERVEJA!$B101,DIF_ANTE!A:D,4,0),"0")/CONCILIÇÃO_COM_CERVEJA!$G101 -> 0 | P101: =J101-M101 -> -2718 | Q101: =CONCILIÇÃO_COM_CERVEJA!$P101-CONCILIÇÃO_COM_CERVEJA!$O101 -> -2718 | R101: =IFERROR(VLOOKUP(CONCILIÇÃO_COM_CERVEJA!$B101,CUSTO!E:H,4,0),(VLOOKUP(CONCILIÇÃO_COM_CERVEJA!$A101,CUSTO!A:H,8,0))) -> 0 | S101: =IFERROR(SUM(CONCILIÇÃO_COM_CERVEJA!$P101*CONCILIÇÃO_COM_CERVEJA!$R101),0) -> 0 | T101: =IFERROR(#REF!/CONCILIÇÃO_COM_CERVEJA!$M101,"") | U101: =IFERROR(#REF!*CONCILIÇÃO_COM_CERVEJA!$R101,"-") -> -
...

Sheet Planilha2
L2: Sistema | M2: Produção
K3: Saldo em 31/12 | L3: 2311041 | M3: 2311041
I4: Entradas | J4: jan | K4: =1460160*3 -> 4380480 | L4: =SUM(K4:K6) -> 11681280 | M4: =SUM(L4:L6) -> 11681280
J5: Fev | K5: =1460160*2 -> 2920320
J6: Mar | K6: =1460160*3 -> 4380480
I7: Saidas | J7: Jan | K7: 4929395 | L7: =SUM(K7:K9) -> 11807538 | M7: =4916976+17762 -> 4934738
J8: Fev | K8: 1593143 | M8: =1588356+6231 -> 1594587
J9: Mar | K9: 5285000 | M9: =4641756+16653 -> 4658409
K10: Saldo em 31/03 | L10: =L3+L4-L7 -> 2184783 | M10: =M3+M4-M7-M8-M9 -> 2804587
K11: Contagem 31/03 | L11: 3047780
K14: Saldo em 31/12 | L14: 12830 | M14: 723648 | Q14: jan | R14: fev | S14: mar
K15: Compra | L15: 66340 | M15: 341760 | Q15: 74826 | R15: 50448 | S15: 109824
K16: Consumo | L16: 53770 | M16: 291655 | N16: 298428 | O16: =M16-N16 -> -6773 | Q16: 188964 | R16: 73944 | S16: 198246
K17: Saldo em 31/01 | L17: =L14+L15-L16 -> 25400 | M17: =M14+M15-M16 -> 773753 | Q17: 8478 | R17: 12342 | S17: 13976
K18: Compra | L18: 28070 | M18: 0 | Q18: 26160 | R18: 42078 | S18: 50784
K19: Consumo | L19: 33510 | M19: 179241 | N19: 178812 | O19: =M19-N19 -> 429 | P19: total | Q19: =SUM(Q15:Q18) -> 298428 | R19: =SUM(R15:R18) -> 178812 | S19: =SUM(S15:S18) -> 372830
K20: Saldo em 28/02 | L20: =L17+L18-L19 -> 19960 | M20: =M17+M18-M19 -> 594512
K21: Compra | L21: 70440 | M21: 0
K22: Consumo | L22: 72300 | M22: =433062-59808 -> 373254 | N22: 372830 | O22: =M22-N22 -> 424
K23: Saldo em 31/03 | L23: =L20+L21-L22 -> 18100 | M23: =M20-M22+M21 -> 221258

Sheet CONCILIÇÃO_SEM_VASILHAME
L1: Valor Estoque Físico | O1: Valor Estoque Sistema | T1: Acuracidade Qualitativa | U1: Custo Diferença | V1: Percentual Diferença
L2: =SUBTOTAL(9,BASE_CONCILI12[CUSTO FÍSICO]) -> 395987.7 | O2: =SUBTOTAL(9,BASE_CONCILI12[CUSTO SISTEMA]) -> 0 | T2: =(COUNTIF(BASE_CONCILI12[30/jun],">0")-COUNTIF(BASE_CONCILI12[ACURACIDADE],">1,05")-COUNTIF(BASE_CONCILI12[ACURACIDADE],"<0,95"))/COUNTIF(BASE_CONCILI12[30/jun],">0") -> 1 | U2: =SUBTOTAL(9,BASE_CONCILI12[CUSTO DIVERGÊNCIA]) -> 0 | V2: =U2/O2 -> #DIV/0!
A4: CÓD. SAIB | B4: CÓD. PRODUTO | C4: DESCRIÇÃO | D4: CLASSE | E4: 30/mai | F4: CONSUMO REAL | G4: CONSUMO TEORICO | H4: DIFERENÇA CONSUMO | I4: RECEBIMENTO | J4: TRANSFERÊNCIA | K4: QTDE. FINAL | L4: 30/jun | M4: CUSTO FÍSICO | N4: 01/fev | O4: SISTEMA | P4: CUSTO SISTEMA | Q4: DIFERENÇA ANTERIOR | R4: DIFERENÇA ATUAL | S4: DIFERENÇA MÊS | T4: CUSTO MP (UN) | U4: CUSTO DIVERGÊNCIA | V4: ACURACIDADE | W4: DIFERENÇA VALOR | X4: OBSERVAÇÃO
A5: 55 | C5: ACUCAR CRISTAL | D5: AÇUCAR | E5: =VLOOKUP(BASE_CONCILI12[[#This Row],[CÓD. SAIB]],CONT_ANTE!A:D,4,0) -> #N/A | F5: =SUMIF(#REF!,BASE_CONCILI12[[#This Row],[CÓD. SAIB]],#REF!) -> #REF! | G5: =SUMIF(#REF!,BASE_CONCILI12[[#This Row],[CÓD. SAIB]],#REF!) -> #REF! | H5: =BASE_CONCILI12[[#This Row],[CONSUMO REAL]]-BASE_CONCILI12[[#This Row],[CONSUMO TEORICO]] -> #REF! | I5: =SUMIF(#REF!,BASE_CONCILI12[[#This Row],[CÓD. SAIB]],#REF!) -> #REF! | J5: =SUMIF(#REF!,BASE_CONCILI12[[#This Row],[CÓD. SAIB]],#REF!) -> #REF! | K5: =BASE_CONCILI12[[#This Row],[30/mai]]+BASE_CONCILI12[[#This Row],[RECEBIMENTO]]-BASE_CONCILI12[[#This Row],[TRANSFERÊNCIA]]-BASE_CONCILI12[[#This Row],[CONSUMO REAL]] -> #N/A | L5: =IFERROR(VLOOKUP(BASE_CONCILI12[[#This Row],[CÓD. SAIB]],BASE_CONTAG[[LAVRE]:[CONTAGEM FINAL]],7,0),0) -> 70 | M5: =IFERROR(SUM(BASE_CONCILI12[[#This Row],[30/jun]]*BASE_CONCILI12[[#This Row],[CUSTO MP (UN)]]),0) -> 0 | N5: =IFERROR(VLOOKUP(BASE_CONCILI12[[#This Row],[CÓD. SAIB]],BASE_CONTAG[],5,0),"") -> 70 | O5: =SUMIF(SISTEMA!#REF!,BASE_CONCILI12[[#This Row],[CÓD. SAIB]],SISTEMA!#REF!) -> #REF! | P5: =IFERROR(SUM(BASE_CONCILI12[[#This Row],[SISTEMA]]*BASE_CONCILI12[[#This Row],[CUSTO MP (UN)]]),0) -> 0 | Q5: =IFERROR(VLOOKUP(BASE_CONCILI12[[#This Row],[CÓD. SAIB]],BASE_DIFERENÇA[],4,0),"0") -> 0 | R5: =BASE_CONCILI12[[#This Row],[30/jun]]-BASE_CONCILI12[[#This Row],[SISTEMA]] -> #REF! | S5: =IFERROR(BASE_CONCILI12[[#This Row],[DIFERENÇA ANTERIOR]]-BASE_CONCILI12[[#This Row],[DIFERENÇA ATUAL]],"-") -> - | T5: =VLOOKUP(BASE_CONCILI12[[#This Row],[CÓD. SAIB]],CUSTO!A:C,3,0) -> 0 | U5: =IFERROR(SUM(BASE_CONCILI12[[#This Row],[DIFERENÇA ATUAL]]*BASE_CONCILI12[[#This Row],[CUSTO MP (UN)]]),0) -> 0 | V5: =IFERROR(BASE_CONCILI12[[#This Row],[30/jun]]/BASE_CONCILI12[[#This Row],[SISTEMA]],"") | W5: =IFERROR(BASE_CONCILI12[[#This Row],[DIFERENÇA MÊS]]*BASE_CONCILI12[[#This Row],[CUSTO MP (UN)]],"-") -> - | X5: OK
A6: 31395 | C6: ETANOL HIDRATADO | D6: ALCOOL | E6: =VLOOKUP(BASE_CONCILI12[[#This Row],[CÓD. SAIB]],CONT_ANTE!A:D,4,0) -> #N/A | F6: =SUMIF(#REF!,BASE_CONCILI12[[#This Row],[CÓD. SAIB]],#REF!) -> #REF! | G6: =SUMIF(#REF!,BASE_CONCILI12[[#This Row],[CÓD. SAIB]],#REF!) -> #REF! | H6: =BASE_CONCILI12[[#This Row],[CONSUMO REAL]]-BASE_CONCILI12[[#This Row],[CONSUMO TEORICO]] -> #REF! | I6: =SUMIF(#REF!,BASE_CONCILI12[[#This Row],[CÓD. SAIB]],#REF!) -> #REF! | J6: =SUMIF(#REF!,BASE_CONCILI12[[#This Row],[CÓD. SAIB]],#REF!) -> #REF! | K6: =BASE_CONCILI12[[#This Row],[30/mai]]+BASE_CONCILI12[[#This Row],[RECEBIMENTO]]-BASE_CONCILI12[[#This Row],[TRANSFERÊNCIA]]-BASE_CONCILI12[[#This Row],[CONSUMO REAL]] -> #N/A | L6: =IFERROR(VLOOKUP(BASE_CONCILI12[[#This Row],[CÓD. SAIB]],BASE_CONTAG[[LAVRE]:[CONTAGEM FINAL]],7,0),0) -> 110 | M6: =IFERROR(SUM(BASE_CONCILI12[[#This Row],[30/jun]]*BASE_CONCILI12[[#This Row],[CUSTO MP (UN)]]),0) -> 0 | N6: =IFERROR(VLOOKUP(BASE_CONCILI12[[#This Row],[CÓD. SAIB]],BASE_CONTAG[],5,0),"") -> 110 | O6: =SUMIF(SISTEMA!#REF!,BASE_CONCILI12[[#This Row],[CÓD. SAIB]],SISTEMA!#REF!) -> #REF! | P6: =IFERROR(SUM(BASE_CONCILI12[[#This Row],[SISTEMA]]*BASE_CONCILI12[[#This Row],[CUSTO MP (UN)]]),0) -> 0 | Q6: =IFERROR(VLOOKUP(BASE_CONCILI12[[#This Row],[CÓD. SAIB]],BASE_DIFERENÇA[],4,0),"0") -> 0 | R6: =BASE_CONCILI12[[#This Row],[30/jun]]-BASE_CONCILI12[[#This Row],[SISTEMA]] -> #REF! | S6: =IFERROR(BASE_CONCILI12[[#This Row],[DIFERENÇA ANTERIOR]]-BASE_CONCILI12[[#This Row],[DIFERENÇA ATUAL]],"-") -> - | T6: =VLOOKUP(BASE_CONCILI12[[#This Row],[CÓD. SAIB]],CUSTO!A:C,3,0) -> 0 | U6: =IFERROR(SUM(BASE_CONCILI12[[#This Row],[DIFERENÇA ATUAL]]*BASE_CONCILI12[[#This Row],[CUSTO MP (UN)]]),0) -> 0 | V6: =IFERROR(BASE_CONCILI12[[#This Row],[30/jun]]/BASE_CONCILI12[[#This Row],[SISTEMA]],"") | W6: =IFERROR(BASE_CONCILI12[[#This Row],[DIFERENÇA MÊS]]*BASE_CONCILI12[[#This Row],[CUSTO MP (UN)]],"-") -> - | X6: OK
A7: 31352 | C7: AA ENERGY FLAVOR | D7: AROMA | E7: =VLOOKUP(BASE_CONCILI12[[#This Row],[CÓD. SAIB]],CONT_ANTE!A:D,4,0) -> #N/A | F7: =SUMIF(#REF!,BASE_CONCILI12[[#This Row],[CÓD. SAIB]],#REF!) -> #REF! | G7: =SUMIF(#REF!,BASE_CONCILI12[[#This Row],[CÓD. SAIB]],#REF!) -> #REF! | H7: =BASE_CONCILI12[[#This Row],[CONSUMO REAL]]-BASE_CONCILI12[[#This Row],[CONSUMO TEORICO]] -> #REF! | I7: =SUMIF(#REF!,BASE_CONCILI12[[#This Row],[CÓD. SAIB]],#REF!) -> #REF! | J7: =SUMIF(#REF!,BASE_CONCILI12[[#This Row],[CÓD. SAIB]],#REF!) -> #REF! | K7: =BASE_CONCILI12[[#This Row],[30/mai]]+BASE_CONCILI12[[#This Row],[RECEBIMENTO]]-BASE_CONCILI12[[#This Row],[TRANSFERÊNCIA]]-BASE_CONCILI12[[#This Row],[CONSUMO REAL]] -> #N/A | L7: =IFERROR(VLOOKUP(BASE_CONCILI12[[#This Row],[CÓD. SAIB]],BASE_CONTAG[[LAVRE]:[CONTAGEM FINAL]],7,0),0) -> 0 | M7: =IFERROR(SUM(BASE_CONCILI12[[#This Row],[30/jun]]*BASE_CONCILI12[[#This Row],[CUSTO MP (UN)]]),0) -> 0 | N7: =IFERROR(VLOOKUP(BASE_CONCILI12[[#This Row],[CÓD. SAIB]],BASE_CONTAG[],5,0),"") -> 0 | O7: =SUMIF(SISTEMA!#REF!,BASE_CONCILI12[[#This Row],[CÓD. SAIB]],SISTEMA!#REF!) -> #REF! | P7: =IFERROR(SUM(BASE_CONCILI12[[#This Row],[SISTEMA]]*BASE_CONCILI12[[#This Row],[CUSTO MP (UN)]]),0) -> 0 | Q7: =IFERROR(VLOOKUP(BASE_CONCILI12[[#This Row],[CÓD. SAIB]],BASE_DIFERENÇA[],4,0),"0") -> 0 | R7: =BASE_CONCILI12[[#This Row],[30/jun]]-BASE_CONCILI12[[#This Row],[SISTEMA]] -> #REF! | S7: =IFERROR(BASE_CONCILI12[[#This Row],[DIFERENÇA ANTERIOR]]-BASE_CONCILI12[[#This Row],[DIFERENÇA ATUAL]],"-") -> - | T7: =VLOOKUP(BASE_CONCILI12[[#This Row],[CÓD. SAIB]],CUSTO!A:C,3,0) -> 31352CB01 | U7: =IFERROR(SUM(BASE_CONCILI12[[#This Row],[DIFERENÇA ATUAL]]*BASE_CONCILI12[[#This Row],[CUSTO MP (UN)]]),0) -> 0 | V7: =IFERROR(BASE_CONCILI12[[#This Row],[30/jun]]/BASE_CONCILI12[[#This Row],[SISTEMA]],"") | W7: =IFERROR(BASE_CONCILI12[[#This Row],[DIFERENÇA MÊS]]*BASE_CONCILI12[[#This Row],[CUSTO MP (UN)]],"-") -> - | X7: OK
A8: 2089 | C8: AROMA ART DE TUTTI FRUTTI RB 10766 | D8: AROMA | E8: =VLOOKUP(BASE_CONCILI12[[#This Row],[CÓD. SAIB]],CONT_ANTE!A:D,4,0) -> #N/A | F8: =SUMIF(#REF!,BASE_CONCILI12[[#This Row],[CÓD. SAIB]],#REF!) -> #REF! | G8: =SUMIF(#REF!,BASE_CONCILI12[[#This Row],[CÓD. SAIB]],#REF!) -> #REF! | H8: =BASE_CONCILI12[[#This Row],[CONSUMO REAL]]-BASE_CONCILI12[[#This Row],[CONSUMO TEORICO]] -> #REF! | I8: =SUMIF(#REF!,BASE_CONCILI12[[#This Row],[CÓD. SAIB]],#REF!) -> #REF! | J8: =SUMIF(#REF!,BASE_CONCILI12[[#This Row],[CÓD. SAIB]],#REF!) -> #REF! | K8: =BASE_CONCILI12[[#This Row],[30/mai]]+BASE_CONCILI12[[#This Row],[RECEBIMENTO]]-BASE_CONCILI12[[#This Row],[TRANSFERÊNCIA]]-BASE_CONCILI12[[#This Row],[CONSUMO REAL]] -> #N/A | L8: =IFERROR(VLOOKUP(BASE_CONCILI12[[#This Row],[CÓD. SAIB]],BASE_CONTAG[[LAVRE]:[CONTAGEM FINAL]],7,0),0) -> 0 | M8: =IFERROR(SUM(BASE_CONCILI12[[#This Row],[30/jun]]*BASE_CONCILI12[[#This Row],[CUSTO MP (UN)]]),0) -> 0 | N8: =IFERROR(VLOOKUP(BASE_CONCILI12[[#This Row],[CÓD. SAIB]],BASE_CONTAG[],5,0),"") | O8: =SUMIF(SISTEMA!#REF!,BASE_CONCILI12[[#This Row],[CÓD. SAIB]],SISTEMA!#REF!) -> #REF! | P8: =IFERROR(SUM(BASE_CONCILI12[[#This Row],[SISTEMA]]*BASE_CONCILI12[[#This Row],[CUSTO MP (UN)]]),0) -> 0 | Q8: =IFERROR(VLOOKUP(BASE_CONCILI12[[#This Row],[CÓD. SAIB]],BASE_DIFERENÇA[],4,0),"0") -> 0 | R8: =BASE_CONCILI12[[#This Row],[30/jun]]-BASE_CONCILI12[[#This Row],[SISTEMA]] -> #REF! | S8: =IFERROR(BASE_CONCILI12[[#This Row],[DIFERENÇA ANTERIOR]]-BASE_CONCILI12[[#This Row],[DIFERENÇA ATUAL]],"-") -> - | T8: =VLOOKUP(BASE_CONCILI12[[#This Row],[CÓD. SAIB]],CUSTO!A:C,3,0) -> 2089CB01 | U8: =IFERROR(SUM(BASE_CONCILI12[[#This Row],[DIFERENÇA ATUAL]]*BASE_CONCILI12[[#This Row],[CUSTO MP (UN)]]),0) -> 0 | V8: =IFERROR(BASE_CONCILI12[[#This Row],[30/jun]]/BASE_CONCILI12[[#This Row],[SISTEMA]],"") | W8: =IFERROR(BASE_CONCILI12[[#This Row],[DIFERENÇA MÊS]]*BASE_CONCILI12[[#This Row],[CUSTO MP (UN)]],"-") -> - | X8: OK
A9: 31351 | C9: AROMA ARTIFICIAL GUARANA | D9: AROMA | E9: =VLOOKUP(BASE_CONCILI12[[#This Row],[CÓD. SAIB]],CONT_ANTE!A:D,4,0) -> #N/A | F9: =SUMIF(#REF!,BASE_CONCILI12[[#This Row],[CÓD. SAIB]],#REF!) -> #REF! | G9: =SUMIF(#REF!,BASE_CONCILI12[[#This Row],[CÓD. SAIB]],#REF!) -> #REF! | H9: =BASE_CONCILI12[[#This Row],[CONSUMO REAL]]-BASE_CONCILI12[[#This Row],[CONSUMO TEORICO]] -> #REF! | I9: =SUMIF(#REF!,BASE_CONCILI12[[#This Row],[CÓD. SAIB]],#REF!) -> #REF! | J9: =SUMIF(#REF!,BASE_CONCILI12[[#This Row],[CÓD. SAIB]],#REF!) -> #REF! | K9: =BASE_CONCILI12[[#This Row],[30/mai]]+BASE_CONCILI12[[#This Row],[RECEBIMENTO]]-BASE_CONCILI12[[#This Row],[TRANSFERÊNCIA]]-BASE_CONCILI12[[#This Row],[CONSUMO REAL]] -> #N/A | L9: =IFERROR(VLOOKUP(BASE_CONCILI12[[#This Row],[CÓD. SAIB]],BASE_CONTAG[[LAVRE]:[CONTAGEM FINAL]],7,0),0) -> 0 | M9: =IFERROR(SUM(BASE_CONCILI12[[#This Row],[30/jun]]*BASE_CONCILI12[[#This Row],[CUSTO MP (UN)]]),0) -> 0 | N9: =IFERROR(VLOOKUP(BASE_CONCILI12[[#This Row],[CÓD. SAIB]],BASE_CONTAG[],5,0),"") -> 0 | O9: =SUMIF(SISTEMA!#REF!,BASE_CONCILI12[[#This Row],[CÓD. SAIB]],SISTEMA!#REF!) -> #REF! | P9: =IFERROR(SUM(BASE_CONCILI12[[#This Row],[SISTEMA]]*BASE_CONCILI12[[#This Row],[CUSTO MP (UN)]]),0) -> 0 | Q9: =IFERROR(VLOOKUP(BASE_CONCILI12[[#This Row],[CÓD. SAIB]],BASE_DIFERENÇA[],4,0),"0") -> 0 | R9: =BASE_CONCILI12[[#This Row],[30/jun]]-BASE_CONCILI12[[#This Row],[SISTEMA]] -> #REF! | S9: =IFERROR(BASE_CONCILI12[[#This Row],[DIFERENÇA ANTERIOR]]-BASE_CONCILI12[[#This Row],[DIFERENÇA ATUAL]],"-") -> - | T9: =VLOOKUP(BASE_CONCILI12[[#This Row],[CÓD. SAIB]],CUSTO!A:C,3,0) -> 31351CB01 | U9: =IFERROR(SUM(BASE_CONCILI12[[#This Row],[DIFERENÇA ATUAL]]*BASE_CONCILI12[[#This Row],[CUSTO MP (UN)]]),0) -> 0 | V9: =IFERROR(BASE_CONCILI12[[#This Row],[30/jun]]/BASE_CONCILI12[[#This Row],[SISTEMA]],"") | W9: =IFERROR(BASE_CONCILI12[[#This Row],[DIFERENÇA MÊS]]*BASE_CONCILI12[[#This Row],[CUSTO MP (UN)]],"-") -> - | X9: OK
A10: 31355 | C10: AROMA BAUNILHA | D10: AROMA | E10: =VLOOKUP(BASE_CONCILI12[[#This Row],[CÓD. SAIB]],CONT_ANTE!A:D,4,0) -> #N/A | F10: =SUMIF(#REF!,BASE_CONCILI12[[#This Row],[CÓD. SAIB]],#REF!) -> #REF! | G10: =SUMIF(#REF!,BASE_CONCILI12[[#This Row],[CÓD. SAIB]],#REF!) -> #REF! | H10: =BASE_CONCILI12[[#This Row],[CONSUMO REAL]]-BASE_CONCILI12[[#This Row],[CONSUMO TEORICO]] -> #REF! | I10: =SUMIF(#REF!,BASE_CONCILI12[[#This Row],[CÓD. SAIB]],#REF!) -> #REF! | J10: =SUMIF(#REF!,BASE_CONCILI12[[#This Row],[CÓD. SAIB]],#REF!) -> #REF! | K10: =BASE_CONCILI12[[#This Row],[30/mai]]+BASE_CONCILI12[[#This Row],[RECEBIMENTO]]-BASE_CONCILI12[[#This Row],[TRANSFERÊNCIA]]-BASE_CONCILI12[[#This Row],[CONSUMO REAL]] -> #N/A | L10: =IFERROR(VLOOKUP(BASE_CONCILI12[[#This Row],[CÓD. SAIB]],BASE_CONTAG[[LAVRE]:[CONTAGEM FINAL]],7,0),0) -> 41 | M10: =IFERROR(SUM(BASE_CONCILI12[[#This Row],[30/jun]]*BASE_CONCILI12[[#This Row],[CUSTO MP (UN)]]),0) -> 0 | N10: =IFERROR(VLOOKUP(BASE_CONCILI12[[#This Row],[CÓD. SAIB]],BASE_CONTAG[],5,0),"") -> 41 | O10: =SUMIF(SISTEMA!#REF!,BASE_CONCILI12[[#This Row],[CÓD. SAIB]],SISTEMA!#REF!) -> #REF! | P10: =IFERROR(SUM(BASE_CONCILI12[[#This Row],[SISTEMA]]*BASE_CONCILI12[[#This Row],[CUSTO MP (UN)]]),0) -> 0 | Q10: =IFERROR(VLOOKUP(BASE_CONCILI12[[#This Row],[CÓD. SAIB]],BASE_DIFERENÇA[],4,0),"0") -> 0 | R10: =BASE_CONCILI12[[#This Row],[30/jun]]-BASE_CONCILI12[[#This Row],[SISTEMA]] -> #REF! | S10: =IFERROR(BASE_CONCILI12[[#This Row],[DIFERENÇA ANTERIOR]]-BASE_CONCILI12[[#This Row],[DIFERENÇA ATUAL]],"-") -> - | T10: =VLOOKUP(BASE_CONCILI12[[#This Row],[CÓD. SAIB]],CUSTO!A:C,3,0) -> 31355CB01 | U10: =IFERROR(SUM(BASE_CONCILI12[[#This Row],[DIFERENÇA ATUAL]]*BASE_CONCILI12[[#This Row],[CUSTO MP (UN)]]),0) -> 0 | V10: =IFERROR(BASE_CONCILI12[[#This Row],[30/jun]]/BASE_CONCILI12[[#This Row],[SISTEMA]],"") | W10: =IFERROR(BASE_CONCILI12[[#This Row],[DIFERENÇA MÊS]]*BASE_CONCILI12[[#This Row],[CUSTO MP (UN)]],"-") -> - | X10: OK
A11: 31354 | C11: AROMA BLUEBERRY | D11: AROMA | E11: =VLOOKUP(BASE_CONCILI12[[#This Row],[CÓD. SAIB]],CONT_ANTE!A:D,4,0) -> #N/A | F11: =SUMIF(#REF!,BASE_CONCILI12[[#This Row],[CÓD. SAIB]],#REF!) -> #REF! | G11: =SUMIF(#REF!,BASE_CONCILI12[[#This Row],[CÓD. SAIB]],#REF!) -> #REF! | H11: =BASE_CONCILI12[[#This Row],[CONSUMO REAL]]-BASE_CONCILI12[[#This Row],[CONSUMO TEORICO]] -> #REF! | I11: =SUMIF(#REF!,BASE_CONCILI12[[#This Row],[CÓD. SAIB]],#REF!) -> #REF! | J11: =SUMIF(#REF!,BASE_CONCILI12[[#This Row],[CÓD. SAIB]],#REF!) -> #REF! | K11: =BASE_CONCILI12[[#This Row],[30/mai]]+BASE_CONCILI12[[#This Row],[RECEBIMENTO]]-BASE_CONCILI12[[#This Row],[TRANSFERÊNCIA]]-BASE_CONCILI12[[#This Row],[CONSUMO REAL]] -> #N/A | L11: =IFERROR(VLOOKUP(BASE_CONCILI12[[#This Row],[CÓD. SAIB]],BASE_CONTAG[[LAVRE]:[CONTAGEM FINAL]],7,0),0) -> 0 | M11: =IFERROR(SUM(BASE_CONCILI12[[#This Row],[30/jun]]*BASE_CONCILI12[[#This Row],[CUSTO MP (UN)]]),0) -> 0 | N11: =IFERROR(VLOOKUP(BASE_CONCILI12[[#This Row],[CÓD. SAIB]],BASE_CONTAG[],5,0),"") -> 0 | O11: =SUMIF(SISTEMA!#REF!,BASE_CONCILI12[[#This Row],[CÓD. SAIB]],SISTEMA!#REF!) -> #REF! | P11: =IFERROR(SUM(BASE_CONCILI12[[#This Row],[SISTEMA]]*BASE_CONCILI12[[#This Row],[CUSTO MP (UN)]]),0) -> 0 | Q11: =IFERROR(VLOOKUP(BASE_CONCILI12[[#This Row],[CÓD. SAIB]],BASE_DIFERENÇA[],4,0),"0") -> 0 | R11: =BASE_CONCILI12[[#This Row],[30/jun]]-BASE_CONCILI12[[#This Row],[SISTEMA]] -> #REF! | S11: =IFERROR(BASE_CONCILI12[[#This Row],[DIFERENÇA ANTERIOR]]-BASE_CONCILI12[[#This Row],[DIFERENÇA ATUAL]],"-") -> - | T11: =VLOOKUP(BASE_CONCILI12[[#This Row],[CÓD. SAIB]],CUSTO!A:C,3,0) -> 31354CB01 | U11: =IFERROR(SUM(BASE_CONCILI12[[#This Row],[DIFERENÇA ATUAL]]*BASE_CONCILI12[[#This Row],[CUSTO MP (UN)]]),0) -> 0 | V11: =IFERROR(BASE_CONCILI12[[#This Row],[30/jun]]/BASE_CONCILI12[[#This Row],[SISTEMA]],"") | W11: =IFERROR(BASE_CONCILI12[[#This Row],[DIFERENÇA MÊS]]*BASE_CONCILI12[[#This Row],[CUSTO MP (UN)]],"-") -> - | X11: OK
A12: 1820 | C12: AROMA DE LARANJA IDENTICO AO NATURAL | D12: AROMA | E12: =VLOOKUP(BASE_CONCILI12[[#This Row],[CÓD. SAIB]],CONT_ANTE!A:D,4,0) -> #N/A | F12: =SUMIF(#REF!,BASE_CONCILI12[[#This Row],[CÓD. SAIB]],#REF!) -> #REF! | G12: =SUMIF(#REF!,BASE_CONCILI12[[#This Row],[CÓD. SAIB]],#REF!) -> #REF! | H12: =BASE_CONCILI12[[#This Row],[CONSUMO REAL]]-BASE_CONCILI12[[#This Row],[CONSUMO TEORICO]] -> #REF! | I12: =SUMIF(#REF!,BASE_CONCILI12[[#This Row],[CÓD. SAIB]],#REF!) -> #REF! | J12: =SUMIF(#REF!,BASE_CONCILI12[[#This Row],[CÓD. SAIB]],#REF!) -> #REF! | K12: =BASE_CONCILI12[[#This Row],[30/mai]]+BASE_CONCILI12[[#This Row],[RECEBIMENTO]]-BASE_CONCILI12[[#This Row],[TRANSFERÊNCIA]]-BASE_CONCILI12[[#This Row],[CONSUMO REAL]] -> #N/A | L12: =IFERROR(VLOOKUP(BASE_CONCILI12[[#This Row],[CÓD. SAIB]],BASE_CONTAG[[LAVRE]:[CONTAGEM FINAL]],7,0),0) -> 14.5 | M12: =IFERROR(SUM(BASE_CONCILI12[[#This Row],[30/jun]]*BASE_CONCILI12[[#This Row],[CUSTO MP (UN)]]),0) -> 0 | N12: =IFERROR(VLOOKUP(BASE_CONCILI12[[#This Row],[CÓD. SAIB]],BASE_CONTAG[],5,0),"") -> 14.5 | O12: =SUMIF(SISTEMA!#REF!,BASE_CONCILI12[[#This Row],[CÓD. SAIB]],SISTEMA!#REF!) -> #REF! | P12: =IFERROR(SUM(BASE_CONCILI12[[#This Row],[SISTEMA]]*BASE_CONCILI12[[#This Row],[CUSTO MP (UN)]]),0) -> 0 | Q12: =IFERROR(VLOOKUP(BASE_CONCILI12[[#This Row],[CÓD. SAIB]],BASE_DIFERENÇA[],4,0),"0") -> 0 | R12: =BASE_CONCILI12[[#This Row],[30/jun]]-BASE_CONCILI12[[#This Row],[SISTEMA]] -> #REF! | S12: =IFERROR(BASE_CONCILI12[[#This Row],[DIFERENÇA ANTERIOR]]-BASE_CONCILI12[[#This Row],[DIFERENÇA ATUAL]],"-") -> - | T12: =VLOOKUP(BASE_CONCILI12[[#This Row],[CÓD. SAIB]],CUSTO!A:C,3,0) -> 0 | U12: =IFERROR(SUM(BASE_CONCILI12[[#This Row],[DIFERENÇA ATUAL]]*BASE_CONCILI12[[#This Row],[CUSTO MP (UN)]]),0) -> 0 | V12: =IFERROR(BASE_CONCILI12[[#This Row],[30/jun]]/BASE_CONCILI12[[#This Row],[SISTEMA]],"") | W12: =IFERROR(BASE_CONCILI12[[#This Row],[DIFERENÇA MÊS]]*BASE_CONCILI12[[#This Row],[CUSTO MP (UN)]],"-") -> - | X12: OK
A13: 31312 | C13: AROMA DE LIMAO VERDE | D13: AROMA | E13: =VLOOKUP(BASE_CONCILI12[[#This Row],[CÓD. SAIB]],CONT_ANTE!A:D,4,0) -> #N/A | F13: =SUMIF(#REF!,BASE_CONCILI12[[#This Row],[CÓD. SAIB]],#REF!) -> #REF! | G13: =SUMIF(#REF!,BASE_CONCILI12[[#This Row],[CÓD. SAIB]],#REF!) -> #REF! | H13: =BASE_CONCILI12[[#This Row],[CONSUMO REAL]]-BASE_CONCILI12[[#This Row],[CONSUMO TEORICO]] -> #REF! | I13: =SUMIF(#REF!,BASE_CONCILI12[[#This Row],[CÓD. SAIB]],#REF!) -> #REF! | J13: =SUMIF(#REF!,BASE_CONCILI12[[#This Row],[CÓD. SAIB]],#REF!) -> #REF! | K13: =BASE_CONCILI12[[#This Row],[30/mai]]+BASE_CONCILI12[[#This Row],[RECEBIMENTO]]-BASE_CONCILI12[[#This Row],[TRANSFERÊNCIA]]-BASE_CONCILI12[[#This Row],[CONSUMO REAL]] -> #N/A | L13: =IFERROR(VLOOKUP(BASE_CONCILI12[[#This Row],[CÓD. SAIB]],BASE_CONTAG[[LAVRE]:[CONTAGEM FINAL]],7,0),0) -> 0 | M13: =IFERROR(SUM(BASE_CONCILI12[[#This Row],[30/jun]]*BASE_CONCILI12[[#This Row],[CUSTO MP (UN)]]),0) -> 0 | N13: =IFERROR(VLOOKUP(BASE_CONCILI12[[#This Row],[CÓD. SAIB]],BASE_CONTAG[],5,0),"") -> 0 | O13: =SUMIF(SISTEMA!#REF!,BASE_CONCILI12[[#This Row],[CÓD. SAIB]],SISTEMA!#REF!) -> #REF! | P13: =IFERROR(SUM(BASE_CONCILI12[[#This Row],[SISTEMA]]*BASE_CONCILI12[[#This Row],[CUSTO MP (UN)]]),0) -> 0 | Q13: =IFERROR(VLOOKUP(BASE_CONCILI12[[#This Row],[CÓD. SAIB]],BASE_DIFERENÇA[],4,0),"0") -> 0 | R13: =BASE_CONCILI12[[#This Row],[30/jun]]-BASE_CONCILI12[[#This Row],[SISTEMA]] -> #REF! | S13: =IFERROR(BASE_CONCILI12[[#This Row],[DIFERENÇA ANTERIOR]]-BASE_CONCILI12[[#This Row],[DIFERENÇA ATUAL]],"-") -> - | T13: =VLOOKUP(BASE_CONCILI12[[#This Row],[CÓD. SAIB]],CUSTO!A:C,3,0) -> 31312CB01 | U13: =IFERROR(SUM(BASE_CONCILI12[[#This Row],[DIFERENÇA ATUAL]]*BASE_CONCILI12[[#This Row],[CUSTO MP (UN)]]),0) -> 0 | V13: =IFERROR(BASE_CONCILI12[[#This Row],[30/jun]]/BASE_CONCILI12[[#This Row],[SISTEMA]],"") | W13: =IFERROR(BASE_CONCILI12[[#This Row],[DIFERENÇA MÊS]]*BASE_CONCILI12[[#This Row],[CUSTO MP (UN)]],"-") -> - | X13: OK, AJUSTAR EM OP
A14: 31335 | C14: AROMA FRUTAS TROPICAIS | D14: AROMA | E14: =VLOOKUP(BASE_CONCILI12[[#This Row],[CÓD. SAIB]],CONT_ANTE!A:D,4,0) -> #N/A | F14: =SUMIF(#REF!,BASE_CONCILI12[[#This Row],[CÓD. SAIB]],#REF!) -> #REF! | G14: =SUMIF(#REF!,BASE_CONCILI12[[#This Row],[CÓD. SAIB]],#REF!) -> #REF! | H14: =BASE_CONCILI12[[#This Row],[CONSUMO REAL]]-BASE_CONCILI12[[#This Row],[CONSUMO TEORICO]] -> #REF! | I14: =SUMIF(#REF!,BASE_CONCILI12[[#This Row],[CÓD. SAIB]],#REF!) -> #REF! | J14: =SUMIF(#REF!,BASE_CONCILI12[[#This Row],[CÓD. SAIB]],#REF!) -> #REF! | K14: =BASE_CONCILI12[[#This Row],[30/mai]]+BASE_CONCILI12[[#This Row],[RECEBIMENTO]]-BASE_CONCILI12[[#This Row],[TRANSFERÊNCIA]]-BASE_CONCILI12[[#This Row],[CONSUMO REAL]] -> #N/A | L14: =IFERROR(VLOOKUP(BASE_CONCILI12[[#This Row],[CÓD. SAIB]],BASE_CONTAG[[LAVRE]:[CONTAGEM FINAL]],7,0),0) -> 0 | M14: =IFERROR(SUM(BASE_CONCILI12[[#This Row],[30/jun]]*BASE_CONCILI12[[#This Row],[CUSTO MP (UN)]]),0) -> 0 | N14: =IFERROR(VLOOKUP(BASE_CONCILI12[[#This Row],[CÓD. SAIB]],BASE_CONTAG[],5,0),"") -> 0 | O14: =SUMIF(SISTEMA!#REF!,BASE_CONCILI12[[#This Row],[CÓD. SAIB]],SISTEMA!#REF!) -> #REF! | P14: =IFERROR(SUM(BASE_CONCILI12[[#This Row],[SISTEMA]]*BASE_CONCILI12[[#This Row],[CUSTO MP (UN)]]),0) -> 0 | Q14: =IFERROR(VLOOKUP(BASE_CONCILI12[[#This Row],[CÓD. SAIB]],BASE_DIFERENÇA[],4,0),"0") -> 0 | R14: =BASE_CONCILI12[[#This Row],[30/jun]]-BASE_CONCILI12[[#This Row],[SISTEMA]] -> #REF! | S14: =IFERROR(BASE_CONCILI12[[#This Row],[DIFERENÇA ANTERIOR]]-BASE_CONCILI12[[#This Row],[DIFERENÇA ATUAL]],"-") -> - | T14: =VLOOKUP(BASE_CONCILI12[[#This Row],[CÓD. SAIB]],CUSTO!A:C,3,0) -> 31335CB01 | U14: =IFERROR(SUM(BASE_CONCILI12[[#This Row],[DIFERENÇA ATUAL]]*BASE_CONCILI12[[#This Row],[CUSTO MP (UN)]]),0) -> 0 | V14: =IFERROR(BASE_CONCILI12[[#This Row],[30/jun]]/BASE_CONCILI12[[#This Row],[SISTEMA]],"") | W14: =IFERROR(BASE_CONCILI12[[#This Row],[DIFERENÇA MÊS]]*BASE_CONCILI12[[#This Row],[CUSTO MP (UN)]],"-") -> - | X14: OK
A15: 31348 | C15: AROMA ID. AO NATURAL MARACUJA | D15: AROMA | E15: =VLOOKUP(BASE_CONCILI12[[#This Row],[CÓD. SAIB]],CONT_ANTE!A:D,4,0) -> #N/A | F15: =SUMIF(#REF!,BASE_CONCILI12[[#This Row],[CÓD. SAIB]],#REF!) -> #REF! | G15: =SUMIF(#REF!,BASE_CONCILI12[[#This Row],[CÓD. SAIB]],#REF!) -> #REF! | H15: =BASE_CONCILI12[[#This Row],[CONSUMO REAL]]-BASE_CONCILI12[[#This Row],[CONSUMO TEORICO]] -> #REF! | I15: =SUMIF(#REF!,BASE_CONCILI12[[#This Row],[CÓD. SAIB]],#REF!) -> #REF! | J15: =SUMIF(#REF!,BASE_CONCILI12[[#This Row],[CÓD. SAIB]],#REF!) -> #REF! | K15: =BASE_CONCILI12[[#This Row],[30/mai]]+BASE_CONCILI12[[#This Row],[RECEBIMENTO]]-BASE_CONCILI12[[#This Row],[TRANSFERÊNCIA]]-BASE_CONCILI12[[#This Row],[CONSUMO REAL]] -> #N/A | L15: =IFERROR(VLOOKUP(BASE_CONCILI12[[#This Row],[CÓD. SAIB]],BASE_CONTAG[[LAVRE]:[CONTAGEM FINAL]],7,0),0) -> 184 | M15: =IFERROR(SUM(BASE_CONCILI12[[#This Row],[30/jun]]*BASE_CONCILI12[[#This Row],[CUSTO MP (UN)]]),0) -> 0 | N15: =IFERROR(VLOOKUP(BASE_CONCILI12[[#This Row],[CÓD. SAIB]],BASE_CONTAG[],5,0),"") -> 184 | O15: =SUMIF(SISTEMA!#REF!,BASE_CONCILI12[[#This Row],[CÓD. SAIB]],SISTEMA!#REF!) -> #REF! | P15: =IFERROR(SUM(BASE_CONCILI12[[#This Row],[SISTEMA]]*BASE_CONCILI12[[#This Row],[CUSTO MP (UN)]]),0) -> 0 | Q15: =IFERROR(VLOOKUP(BASE_CONCILI12[[#This Row],[CÓD. SAIB]],BASE_DIFERENÇA[],4,0),"0") -> 0 | R15: =BASE_CONCILI12[[#This Row],[30/jun]]-BASE_CONCILI12[[#This Row],[SISTEMA]] -> #REF! | S15: =IFERROR(BASE_CONCILI12[[#This Row],[DIFERENÇA ANTERIOR]]-BASE_CONCILI12[[#This Row],[DIFERENÇA ATUAL]],"-") -> - | T15: =VLOOKUP(BASE_CONCILI12[[#This Row],[CÓD. SAIB]],CUSTO!A:C,3,0) -> #N/A | U15: =IFERROR(SUM(BASE_CONCILI12[[#This Row],[DIFERENÇA ATUAL]]*BASE_CONCILI12[[#This Row],[CUSTO MP (UN)]]),0) -> 0 | V15: =IFERROR(BASE_CONCILI12[[#This Row],[30/jun]]/BASE_CONCILI12[[#This Row],[SISTEMA]],"") | W15: =IFERROR(BASE_CONCILI12[[#This Row],[DIFERENÇA MÊS]]*BASE_CONCILI12[[#This Row],[CUSTO MP (UN)]],"-") -> - | X15: OK
A16: 31349 | C16: AROMA ID. AO NATURAL MELANCIA | D16: AROMA | E16: =VLOOKUP(BASE_CONCILI12[[#This Row],[CÓD. SAIB]],CONT_ANTE!A:D,4,0) -> #N/A | F16: =SUMIF(#REF!,BASE_CONCILI12[[#This Row],[CÓD. SAIB]],#REF!) -> #REF! | G16: =SUMIF(#REF!,BASE_CONCILI12[[#This Row],[CÓD. SAIB]],#REF!) -> #REF! | H16: =BASE_CONCILI12[[#This Row],[CONSUMO REAL]]-BASE_CONCILI12[[#This Row],[CONSUMO TEORICO]] -> #REF! | I16: =SUMIF(#REF!,BASE_CONCILI12[[#This Row],[CÓD. SAIB]],#REF!) -> #REF! | J16: =SUMIF(#REF!,BASE_CONCILI12[[#This Row],[CÓD. SAIB]],#REF!) -> #REF! | K16: =BASE_CONCILI12[[#This Row],[30/mai]]+BASE_CONCILI12[[#This Row],[RECEBIMENTO]]-BASE_CONCILI12[[#This Row],[TRANSFERÊNCIA]]-BASE_CONCILI12[[#This Row],[CONSUMO REAL]] -> #N/A | L16: =IFERROR(VLOOKUP(BASE_CONCILI12[[#This Row],[CÓD. SAIB]],BASE_CONTAG[[LAVRE]:[CONTAGEM FINAL]],7,0),0) -> 240 | M16: =IFERROR(SUM(BASE_CONCILI12[[#This Row],[30/jun]]*BASE_CONCILI12[[#This Row],[CUSTO MP (UN)]]),0) -> 0 | N16: =IFERROR(VLOOKUP(BASE_CONCILI12[[#This Row],[CÓD. SAIB]],BASE_CONTAG[],5,0),"") -> 240 | O16: =SUMIF(SISTEMA!#REF!,BASE_CONCILI12[[#This Row],[CÓD. SAIB]],SISTEMA!#REF!) -> #REF! | P16: =IFERROR(SUM(BASE_CONCILI12[[#This Row],[SISTEMA]]*BASE_CONCILI12[[#This Row],[CUSTO MP (UN)]]),0) -> 0 | Q16: =IFERROR(VLOOKUP(BASE_CONCILI12[[#This Row],[CÓD. SAIB]],BASE_DIFERENÇA[],4,0),"0") -> 0 | R16: =BASE_CONCILI12[[#This Row],[30/jun]]-BASE_CONCILI12[[#This Row],[SISTEMA]] -> #REF! | S16: =IFERROR(BASE_CONCILI12[[#This Row],[DIFERENÇA ANTERIOR]]-BASE_CONCILI12[[#This Row],[DIFERENÇA ATUAL]],"-") -> - | T16: =VLOOKUP(BASE_CONCILI12[[#This Row],[CÓD. SAIB]],CUSTO!A:C,3,0) -> 31349CB01 | U16: =IFERROR(SUM(BASE_CONCILI12[[#This Row],[DIFERENÇA ATUAL]]*BASE_CONCILI12[[#This Row],[CUSTO MP (UN)]]),0) -> 0 | V16: =IFERROR(BASE_CONCILI12[[#This Row],[30/jun]]/BASE_CONCILI12[[#This Row],[SISTEMA]],"") | W16: =IFERROR(BASE_CONCILI12[[#This Row],[DIFERENÇA MÊS]]*BASE_CONCILI12[[#This Row],[CUSTO MP (UN)]],"-") -> - | X16: OK
... A28: 1124 | C28: CHAPA SEM IMPRESSAO | D28: CAIXA | E28: =VLOOKUP(BASE_CONCILI12[[#This Row],[CÓD. SAIB]],CONT_ANTE!A:D,4,0) -> #N/A | F28: =SUMIF(#REF!,BASE_CONCILI12[[#This Row],[CÓD. SAIB]],#REF!) -> #REF! | G28: =SUMIF(#REF!,BASE_CONCILI12[[#This Row],[CÓD. SAIB]],#REF!) -> #REF! | H28: =BASE_CONCILI12[[#This Row],[CONSUMO REAL]]-BASE_CONCILI12[[#This Row],[CONSUMO TEORICO]] -> #REF! | I28: =SUMIF(#REF!,BASE_CONCILI12[[#This Row],[CÓD. SAIB]],#REF!) -> #REF! | J28: =SUMIF(#REF!,BASE_CONCILI12[[#This Row],[CÓD. SAIB]],#REF!) -> #REF! | K28: =BASE_CONCILI12[[#This Row],[30/mai]]+BASE_CONCILI12[[#This Row],[RECEBIMENTO]]-BASE_CONCILI12[[#This Row],[TRANSFERÊNCIA]]-BASE_CONCILI12[[#This Row],[CONSUMO REAL]] -> #N/A | L28: =IFERROR(VLOOKUP(BASE_CONCILI12[[#This Row],[CÓD. SAIB]],BASE_CONTAG[[LAVRE]:[CONTAGEM FINAL]],7,0),0) -> 0 | M28: =IFERROR(SUM(BASE_CONCILI12[[#This Row],[30/jun]]*BASE_CONCILI12[[#This Row],[CUSTO MP (UN)]]),0) -> 0 | N28: =IFERROR(VLOOKUP(BASE_CONCILI12[[#This Row],[CÓD. SAIB]],BASE_CONTAG[],5,0),"") -> 0 | O28: =SUMIF(SISTEMA!#REF!,BASE_CONCILI12[[#This Row],[CÓD. SAIB]],SISTEMA!#REF!) -> #REF! | P28: =IFERROR(SUM(BASE_CONCILI12[[#This Row],[SISTEMA]]*BASE_CONCILI12[[#This Row],[CUSTO MP (UN)]]),0) -> 0 | Q28: =IFERROR(VLOOKUP(BASE_CONCILI12[[#This Row],[CÓD. SAIB]],BASE_DIFERENÇA[],4,0),"0") -> 0 | R28: =BASE_CONCILI12[[#This Row],[30/jun]]-BASE_CONCILI12[[#This Row],[SISTEMA]] -> #REF! | S28: =IFERROR(BASE_CONCILI12[[#This Row],[DIFERENÇA ANTERIOR]]-BASE_CONCILI12[[#This Row],[DIFERENÇA ATUAL]],"-") -> - | T28: =VLOOKUP(BASE_CONCILI12[[#This Row],[CÓD. SAIB]],CUSTO!A:C,3,0) -> 1124CB01 | U28: =IFERROR(SUM(BASE_CONCILI12[[#This Row],[DIFERENÇA ATUAL]]*BASE_CONCILI12[[#This Row],[CUSTO MP (UN)]]),0) -> 0 | V28: =IFERROR(BASE_CONCILI12[[#This Row],[30/jun]]/BASE_CONCILI12[[#This Row],[SISTEMA]],"") | W28: =IFERROR(BASE_CONCILI12[[#This Row],[DIFERENÇA MÊS]]*BASE_CONCILI12[[#This Row],[CUSTO MP (UN)]],"-") -> - | X28: CORREÇÃO DE APONTAMENTO - ACUMULO PERDA
A29: 32711 | C29: CX AUTO GIN JAMES COOK 6X1-IND | D29: CAIXA | E29: =VLOOKUP(BASE_CONCILI12[[#This Row],[CÓD. SAIB]],CONT_ANTE!A:D,4,0) -> #N/A | F29: =SUMIF(#REF!,BASE_CONCILI12[[#This Row],[CÓD. SAIB]],#REF!) -> #REF! | G29: =SUMIF(#REF!,BASE_CONCILI12[[#This Row],[CÓD. SAIB]],#REF!) -> #REF! | H29: =BASE_CONCILI12[[#This Row],[CONSUMO REAL]]-BASE_CONCILI12[[#This Row],[CONSUMO TEORICO]] -> #REF! | I29: =SUMIF(#REF!,BASE_CONCILI12[[#This Row],[CÓD. SAIB]],#REF!) -> #REF! | J29: =SUMIF(#REF!,BASE_CONCILI12[[#This Row],[CÓD. SAIB]],#REF!) -> #REF! | K29: =BASE_CONCILI12[[#This Row],[30/mai]]+BASE_CONCILI12[[#This Row],[RECEBIMENTO]]-BASE_CONCILI12[[#This Row],[TRANSFERÊNCIA]]-BASE_CONCILI12[[#This Row],[CONSUMO REAL]] -> #N/A | L29: =IFERROR(VLOOKUP(BASE_CONCILI12[[#This Row],[CÓD. SAIB]],BASE_CONTAG[[LAVRE]:[CONTAGEM FINAL]],7,0),0) -> 25425 | M29: =IFERROR(SUM(BASE_CONCILI12[[#This Row],[30/jun]]*BASE_CONCILI12[[#This Row],[CUSTO MP (UN)]]),0) -> 94566.432 | N29: =IFERROR(VLOOKUP(BASE_CONCILI12[[#This Row],[CÓD. SAIB]],BASE_CONTAG[],5,0),"") -> 25425 | O29: =SUMIF(SISTEMA!#REF!,BASE_CONCILI12[[#This Row],[CÓD. SAIB]],SISTEMA!#REF!) -> #REF! | P29: =IFERROR(SUM(BASE_CONCILI12[[#This Row],[SISTEMA]]*BASE_CONCILI12[[#This Row],[CUSTO MP (UN)]]),0) -> 0 | Q29: =IFERROR(VLOOKUP(BASE_CONCILI12[[#This Row],[CÓD. SAIB]],BASE_DIFERENÇA[],4,0),"0") -> 0 | R29: =BASE_CONCILI12[[#This Row],[30/jun]]-BASE_CONCILI12[[#This Row],[SISTEMA]] -> #REF! | S29: =IFERROR(BASE_CONCILI12[[#This Row],[DIFERENÇA ANTERIOR]]-BASE_CONCILI12[[#This Row],[DIFERENÇA ATUAL]],"-") -> - | T29: 3.719427 | U29: =IFERROR(SUM(BASE_CONCILI12[[#This Row],[DIFERENÇA ATUAL]]*BASE_CONCILI12[[#This Row],[CUSTO MP (UN)]]),0) -> 0 | V29: =IFERROR(BASE_CONCILI12[[#This Row],[30/jun]]/BASE_CONCILI12[[#This Row],[SISTEMA]],"") | W29: =IFERROR(BASE_CONCILI12[[#This Row],[DIFERENÇA MÊS]]*BASE_CONCILI12[[#This Row],[CUSTO MP (UN)]],"-") -> - | X29: OK
A30: 32714 | C30: CX FUNDO AUTO VODKA JAMES COOK 6X1-IND | D30: CAIXA | E30: =VLOOKUP(BASE_CONCILI12[[#This Row],[CÓD. SAIB]],CONT_ANTE!A:D,4,0) -> #N/A | F30: =SUMIF(#REF!,BASE_CONCILI12[[#This Row],[CÓD. SAIB]],#REF!) -> #REF! | G30: =SUMIF(#REF!,BASE_CONCILI12[[#This Row],[CÓD. SAIB]],#REF!) -> #REF! | H30: =BASE_CONCILI12[[#This Row],[CONSUMO REAL]]-BASE_CONCILI12[[#This Row],[CONSUMO TEORICO]] -> #REF! | I30: =SUMIF(#REF!,BASE_CONCILI12[[#This Row],[CÓD. SAIB]],#REF!) -> #REF! | J30: =SUMIF(#REF!,BASE_CONCILI12[[#This Row],[CÓD. SAIB]],#REF!) -> #REF! | K30: =BASE_CONCILI12[[#This Row],[30/mai]]+BASE_CONCILI12[[#This Row],[RECEBIMENTO]]-BASE_CONCILI12[[#This Row],[TRANSFERÊNCIA]]-BASE_CONCILI12[[#This Row],[CONSUMO REAL]] -> #N/A | L30: =IFERROR(VLOOKUP(BASE_CONCILI12[[#This Row],[CÓD. SAIB]],BASE_CONTAG[[LAVRE]:[CONTAGEM FINAL]],7,0),0) -> 40650 | M30: =IFERROR(SUM(BASE_CONCILI12[[#This Row],[30/jun]]*BASE_CONCILI12[[#This Row],[CUSTO MP (UN)]]),0) -> 151194.71 | N30: =IFERROR(VLOOKUP(BASE_CONCILI12[[#This Row],[CÓD. SAIB]],BASE_CONTAG[],5,0),"") -> 40650 | O30: =SUMIF(SISTEMA!#REF!,BASE_CONCILI12[[#This Row],[CÓD. SAIB]],SISTEMA!#REF!) -> #REF! | P30: =IFERROR(SUM(BASE_CONCILI12[[#This Row],[SISTEMA]]*BASE_CONCILI12[[#This Row],[CUSTO MP (UN)]]),0) -> 0 | Q30: =IFERROR(VLOOKUP(BASE_CONCILI12[[#This Row],[CÓD. SAIB]],BASE_DIFERENÇA[],4,0),"0") -> 0 | R30: =BASE_CONCILI12[[#This Row],[30/jun]]-BASE_CONCILI12[[#This Row],[SISTEMA]] -> #REF! | S30: =IFERROR(BASE_CONCILI12[[#This Row],[DIFERENÇA ANTERIOR]]-BASE_CONCILI12[[#This Row],[DIFERENÇA ATUAL]],"-") -> - | T30: 3.719427 | U30: =IFERROR(SUM(BASE_CONCILI12[[#This Row],[DIFERENÇA ATUAL]]*BASE_CONCILI12[[#This Row],[CUSTO MP (UN)]]),0) -> 0 | V30: =IFERROR(BASE_CONCILI12[[#This Row],[30/jun]]/BASE_CONCILI12[[#This Row],[SISTEMA]],"") | W30: =IFERROR(BASE_CONCILI12[[#This Row],[DIFERENÇA MÊS]]*BASE_CONCILI12[[#This Row],[CUSTO MP (UN)]],"-") -> - | X30: OK
A31: 30756 | C31: CX ONE WAY BAMBOA 12X300ML | D31: CAIXA | E31: =VLOOKUP(BASE_CONCILI12[[#This Row],[CÓD. SAIB]],CONT_ANTE!A:D,4,0) -> #N/A | F31: =SUMIF(#REF!,BASE_CONCILI12[[#This Row],[CÓD. SAIB]],#REF!) -> #REF! | G31: =SUMIF(#REF!,BASE_CONCILI12[[#This Row],[CÓD. SAIB]],#REF!) -> #REF! | H31: =BASE_CONCILI12[[#This Row],[CONSUMO REAL]]-BASE_CONCILI12[[#This Row],[CONSUMO TEORICO]] -> #REF! | I31: =SUMIF(#REF!,BASE_CONCILI12[[#This Row],[CÓD. SAIB]],#REF!) -> #REF! | J31: =SUMIF(#REF!,BASE_CONCILI12[[#This Row],[CÓD. SAIB]],#REF!) -> #REF! | K31: =BASE_CONCILI12[[#This Row],[30/mai]]+BASE_CONCILI12[[#This Row],[RECEBIMENTO]]-BASE_CONCILI12[[#This Row],[TRANSFERÊNCIA]]-BASE_CONCILI12[[#This Row],[CONSUMO REAL]] -> #N/A | L31: =IFERROR(VLOOKUP(BASE_CONCILI12[[#This Row],[CÓD. SAIB]],BASE_CONTAG[[LAVRE]:[CONTAGEM FINAL]],7,0),0) -> 4400 | M31: =IFERROR(SUM(BASE_CONCILI12[[#This Row],[30/jun]]*BASE_CONCILI12[[#This Row],[CUSTO MP (UN)]]),0) -> 0 | N31: =IFERROR(VLOOKUP(BASE_CONCILI12[[#This Row],[CÓD. SAIB]],BASE_CONTAG[],5,0),"") -> 4400 | O31: =SUMIF(SISTEMA!#REF!,BASE_CONCILI12[[#This Row],[CÓD. SAIB]],SISTEMA!#REF!) -> #REF! | P31: =IFERROR(SUM(BASE_CONCILI12[[#This Row],[SISTEMA]]*BASE_CONCILI12[[#This Row],[CUSTO MP (UN)]]),0) -> 0 | Q31: =IFERROR(VLOOKUP(BASE_CONCILI12[[#This Row],[CÓD. SAIB]],BASE_DIFERENÇA[],4,0),"0") -> 0 | R31: =BASE_CONCILI12[[#This Row],[30/jun]]-BASE_CONCILI12[[#This Row],[SISTEMA]] -> #REF! | S31: =IFERROR(BASE_CONCILI12[[#This Row],[DIFERENÇA ANTERIOR]]-BASE_CONCILI12[[#This Row],[DIFERENÇA ATUAL]],"-") -> - | T31: =VLOOKUP(BASE_CONCILI12[[#This Row],[CÓD. SAIB]],CUSTO!A:C,3,0) -> 30756CB01 | U31: =IFERROR(SUM(BASE_CONCILI12[[#This Row],[DIFERENÇA ATUAL]]*BASE_CONCILI12[[#This Row],[CUSTO MP (UN)]]),0) -> 0 | V31: =IFERROR(BASE_CONCILI12[[#This Row],[30/jun]]/BASE_CONCILI12[[#This Row],[SISTEMA]],"") | W31: =IFERROR(BASE_CONCILI12[[#This Row],[DIFERENÇA MÊS]]*BASE_CONCILI12[[#This Row],[CUSTO MP (UN)]],"-") -> - | X31: OK
A32: 30758 | C32: CX ONE WAY BAMBOA 12X330ML | D32: CAIXA | E32: =VLOOKUP(BASE_CONCILI12[[#This Row],[CÓD. SAIB]],CONT_ANTE!A:D,4,0) -> #N/A | F32: =SUMIF(#REF!,BASE_CONCILI12[[#This Row],[CÓD. SAIB]],#REF!) -> #REF! | G32: =SUMIF(#REF!,BASE_CONCILI12[[#This Row],[CÓD. SAIB]],#REF!) -> #REF! | H32: =BASE_CONCILI12[[#This Row],[CONSUMO REAL]]-BASE_CONCILI12[[#This Row],[CONSUMO TEORICO]] -> #REF! | I32: =SUMIF(#REF!,BASE_CONCILI12[[#This Row],[CÓD. SAIB]],#REF!) -> #REF! | J32: =SUMIF(#REF!,BASE_CONCILI12[[#This Row],[CÓD. SAIB]],#REF!) -> #REF! | K32: =BASE_CONCILI12[[#This Row],[30/mai]]+BASE_CONCILI12[[#This Row],[RECEBIMENTO]]-BASE_CONCILI12[[#This Row],[TRANSFERÊNCIA]]-BASE_CONCILI12[[#This Row],[CONSUMO REAL]] -> #N/A | L32: =IFERROR(VLOOKUP(BASE_CONCILI12[[#This Row],[CÓD. SAIB]],BASE_CONTAG[[LAVRE]:[CONTAGEM FINAL]],7,0),0) -> 10537 | M32: =IFERROR(SUM(BASE_CONCILI12[[#This Row],[30/jun]]*BASE_CONCILI12[[#This Row],[CUSTO MP (UN)]]),0) -> 0 | N32: =IFERROR(VLOOKUP(BASE_CONCILI12[[#This Row],[CÓD. SAIB]],BASE_CONTAG[],5,0),"") -> 10537 | O32: =SUMIF(SISTEMA!#REF!,BASE_CONCILI12[[#This Row],[CÓD. SAIB]],SISTEMA!#REF!) -> #REF! | P32: =IFERROR(SUM(BASE_CONCILI12[[#This Row],[SISTEMA]]*BASE_CONCILI12[[#This Row],[CUSTO MP (UN)]]),0) -> 0 | Q32: =IFERROR(VLOOKUP(BASE_CONCILI12[[#This Row],[CÓD. SAIB]],BASE_DIFERENÇA[],4,0),"0") -> 0 | R32: =BASE_CONCILI12[[#This Row],[30/jun]]-BASE_CONCILI12[[#This Row],[SISTEMA]] -> #REF! | S32: =IFERROR(BASE_CONCILI12[[#This Row],[DIFERENÇA ANTERIOR]]-BASE_CONCILI12[[#This Row],[DIFERENÇA ATUAL]],"-") -> - | T32: =VLOOKUP(BASE_CONCILI12[[#This Row],[CÓD. SAIB]],CUSTO!A:C,3,0) -> 30758CB01 | U32: =IFERROR(SUM(BASE_CONCILI12[[#This Row],[DIFERENÇA ATUAL]]*BASE_CONCILI12[[#This Row],[CUSTO MP (UN)]]),0) -> 0 | V32: =IFERROR(BASE_CONCILI12[[#This Row],[30/jun]]/BASE_CONCILI12[[#This Row],[SISTEMA]],"") | W32: =IFERROR(BASE_CONCILI12[[#This Row],[DIFERENÇA MÊS]]*BASE_CONCILI12[[#This Row],[CUSTO MP (UN)]],"-") -> - | X32: OK
A33: 1444 | C33: CX ONE WAY BAMBOA 6X600ML | D33: CAIXA | E33: =VLOOKUP(BASE_CONCILI12[[#This Row],[CÓD. SAIB]],CONT_ANTE!A:D,4,0) -> #N/A | F33: =SUMIF(#REF!,BASE_CONCILI12[[#This Row],[CÓD. SAIB]],#REF!) -> #REF! | G33: =SUMIF(#REF!,BASE_CONCILI12[[#This Row],[CÓD. SAIB]],#REF!) -> #REF! | H33: =BASE_CONCILI12[[#This Row],[CONSUMO REAL]]-BASE_CONCILI12[[#This Row],[CONSUMO TEORICO]] -> #REF! | I33: =SUMIF(#REF!,BASE_CONCILI12[[#This Row],[CÓD. SAIB]],#REF!) -> #REF! | J33: =SUMIF(#REF!,BASE_CONCILI12[[#This Row],[CÓD. SAIB]],#REF!) -> #REF! | K33: =BASE_CONCILI12[[#This Row],[30/mai]]+BASE_CONCILI12[[#This Row],[RECEBIMENTO]]-BASE_CONCILI12[[#This Row],[TRANSFERÊNCIA]]-BASE_CONCILI12[[#This Row],[CONSUMO REAL]] -> #N/A | L33: =IFERROR(VLOOKUP(BASE_CONCILI12[[#This Row],[CÓD. SAIB]],BASE_CONTAG[[LAVRE]:[CONTAGEM FINAL]],7,0),0) -> 0 | M33: =IFERROR(SUM(BASE_CONCILI12[[#This Row],[30/jun]]*BASE_CONCILI12[[#This Row],[CUSTO MP (UN)]]),0) -> 0 | N33: =IFERROR(VLOOKUP(BASE_CONCILI12[[#This Row],[CÓD. SAIB]],BASE_CONTAG[],5,0),"") -> 0 | O33: =SUMIF(SISTEMA!#REF!,BASE_CONCILI12[[#This Row],[CÓD. SAIB]],SISTEMA!#REF!) -> #REF! | P33: =IFERROR(SUM(BASE_CONCILI12[[#This Row],[SISTEMA]]*BASE_CONCILI12[[#This Row],[CUSTO MP (UN)]]),0) -> 0 | Q33: =IFERROR(VLOOKUP(BASE_CONCILI12[[#This Row],[CÓD. SAIB]],BASE_DIFERENÇA[],4,0),"0") -> 0 | R33: =BASE_CONCILI12[[#This Row],[30/jun]]-BASE_CONCILI12[[#This Row],[SISTEMA]] -> #REF! | S33: =IFERROR(BASE_CONCILI12[[#This Row],[DIFERENÇA ANTERIOR]]-BASE_CONCILI12[[#This Row],[DIFERENÇA ATUAL]],"-") -> - | T33: =VLOOKUP(BASE_CONCILI12[[#This Row],[CÓD. SAIB]],CUSTO!A:C,3,0) -> 1444CB01 | U33: =IFERROR(SUM(BASE_CONCILI12[[#This Row],[DIFERENÇA ATUAL]]*BASE_CONCILI12[[#This Row],[CUSTO MP (UN)]]),0) -> 0 | V33: =IFERROR(BASE_CONCILI12[[#This Row],[30/jun]]/BASE_CONCILI12[[#This Row],[SISTEMA]],"") | W33: =IFERROR(BASE_CONCILI12[[#This Row],[DIFERENÇA MÊS]]*BASE_CONCILI12[[#This Row],[CUSTO MP (UN)]],"-") -> - | X33: OK
A34: 30739 | C34: CX ONE WAY MOEMA 12X300ML | D34: CAIXA | E34: =VLOOKUP(BASE_CONCILI12[[#This Row],[CÓD. SAIB]],CONT_ANTE!A:D,4,0) -> #N/A | F34: =SUMIF(#REF!,BASE_CONCILI12[[#This Row],[CÓD. SAIB]],#REF!) -> #REF! | G34: =SUMIF(#REF!,BASE_CONCILI12[[#This Row],[CÓD. SAIB]],#REF!) -> #REF! | H34: =BASE_CONCILI12[[#This Row],[CONSUMO REAL]]-BASE_CONCILI12[[#This Row],[CONSUMO TEORICO]] -> #REF! | I34: =SUMIF(#REF!,BASE_CONCILI12[[#This Row],[CÓD. SAIB]],#REF!) -> #REF! | J34: =SUMIF(#REF!,BASE_CONCILI12[[#This Row],[CÓD. SAIB]],#REF!) -> #REF! | K34: =BASE_CONCILI12[[#This Row],[30/mai]]+BASE_CONCILI12[[#This Row],[RECEBIMENTO]]-BASE_CONCILI12[[#This Row],[TRANSFERÊNCIA]]-BASE_CONCILI12[[#This Row],[CONSUMO REAL]] -> #N/A | L34: =IFERROR(VLOOKUP(BASE_CONCILI12[[#This Row],[CÓD. SAIB]],BASE_CONTAG[[LAVRE]:[CONTAGEM FINAL]],7,0),0) -> 0 | M34: =IFERROR(SUM(BASE_CONCILI12[[#This Row],[30/jun]]*BASE_CONCILI12[[#This Row],[CUSTO MP (UN)]]),0) -> 0 | N34: =IFERROR(VLOOKUP(BASE_CONCILI12[[#This Row],[CÓD. SAIB]],BASE_CONTAG[],5,0),"") -> 0 | O34: =SUMIF(SISTEMA!#REF!,BASE_CONCILI12[[#This Row],[CÓD. SAIB]],SISTEMA!#REF!) -> #REF! | P34: =IFERROR(SUM(BASE_CONCILI12[[#This Row],[SISTEMA]]*BASE_CONCILI12[[#This Row],[CUSTO MP (UN)]]),0) -> 0 | Q34: =IFERROR(VLOOKUP(BASE_CONCILI12[[#This Row],[CÓD. SAIB]],BASE_DIFERENÇA[],4,0),"0") -> 0 | R34: =BASE_CONCILI12[[#This Row],[30/jun]]-BASE_CONCILI12[[#This Row],[SISTEMA]] -> #REF! | S34: =IFERROR(BASE_CONCILI12[[#This Row],[DIFERENÇA ANTERIOR]]-BASE_CONCILI12[[#This Row],[DIFERENÇA ATUAL]],"-") -> - | T34: =VLOOKUP(BASE_CONCILI12[[#This Row],[CÓD. SAIB]],CUSTO!A:C,3,0) -> 30739CB01 | U34: =IFERROR(SUM(BASE_CONCILI12[[#This Row],[DIFERENÇA ATUAL]]*BASE_CONCILI12[[#This Row],[CUSTO MP (UN)]]),0) -> 0 | V34: =IFERROR(BASE_CONCILI12[[#This Row],[30/jun]]/BASE_CONCILI12[[#This Row],[SISTEMA]],"") | W34: =IFERROR(BASE_CONCILI12[[#This Row],[DIFERENÇA MÊS]]*BASE_CONCILI12[[#This Row],[CUSTO MP (UN)]],"-") -> - | X34: OK
A35: 30738 | C35: CX ONE WAY MOEMA 6X600ML | D35: CAIXA | E35: =VLOOKUP(BASE_CONCILI12[[#This Row],[CÓD. SAIB]],CONT_ANTE!A:D,4,0) -> #N/A | F35: =SUMIF(#REF!,BASE_CONCILI12[[#This Row],[CÓD. SAIB]],#REF!) -> #REF! | G35: =SUMIF(#REF!,BASE_CONCILI12[[#This Row],[CÓD. SAIB]],#REF!) -> #REF! | H35: =BASE_CONCILI12[[#This Row],[CONSUMO REAL]]-BASE_CONCILI12[[#This Row],[CONSUMO TEORICO]] -> #REF! | I35: =SUMIF(#REF!,BASE_CONCILI12[[#This Row],[CÓD. SAIB]],#REF!) -> #REF! | J35: =SUMIF(#REF!,BASE_CONCILI12[[#This Row],[CÓD. SAIB]],#REF!) -> #REF! | K35: =BASE_CONCILI12[[#This Row],[30/mai]]+BASE_CONCILI12[[#This Row],[RECEBIMENTO]]-BASE_CONCILI12[[#This Row],[TRANSFERÊNCIA]]-BASE_CONCILI12[[#This Row],[CONSUMO REAL]] -> #N/A | L35: =IFERROR(VLOOKUP(BASE_CONCILI12[[#This Row],[CÓD. SAIB]],BASE_CONTAG[[LAVRE]:[CONTAGEM FINAL]],7,0),0) -> 32600 | M35: =IFERROR(SUM(BASE_CONCILI12[[#This Row],[30/jun]]*BASE_CONCILI12[[#This Row],[CUSTO MP (UN)]]),0) -> 0 | N35: =IFERROR(VLOOKUP(BASE_CONCILI12[[#This Row],[CÓD. SAIB]],BASE_CONTAG[],5,0),"") -> 32600 | O35: =SUMIF(SISTEMA!#REF!,BASE_CONCILI12[[#This Row],[CÓD. SAIB]],SISTEMA!#REF!) -> #REF! | P35: =IFERROR(SUM(BASE_CONCILI12[[#This Row],[SISTEMA]]*BASE_CONCILI12[[#This Row],[CUSTO MP (UN)]]),0) -> 0 | Q35: =IFERROR(VLOOKUP(BASE_CONCILI12[[#This Row],[CÓD. SAIB]],BASE_DIFERENÇA[],4,0),"0") -> 0 | R35: =BASE_CONCILI12[[#This Row],[30/jun]]-BASE_CONCILI12[[#This Row],[SISTEMA]] -> #REF! | S35: =IFERROR(BASE_CONCILI12[[#This Row],[DIFERENÇA ANTERIOR]]-BASE_CONCILI12[[#This Row],[DIFERENÇA ATUAL]],"-") -> - | T35: =VLOOKUP(BASE_CONCILI12[[#This Row],[CÓD. SAIB]],CUSTO!A:C,3,0) -> 30738CB01 | U35: =IFERROR(SUM(BASE_CONCILI12[[#This Row],[DIFERENÇA ATUAL]]*BASE_CONCILI12[[#This Row],[CUSTO MP (UN)]]),0) -> 0 | V35: =IFERROR(BASE_CONCILI12[[#This Row],[30/jun]]/BASE_CONCILI12[[#This Row],[SISTEMA]],"") | W35: =IFERROR(BASE_CONCILI12[[#This Row],[DIFERENÇA MÊS]]*BASE_CONCILI12[[#This Row],[CUSTO MP (UN)]],"-") -> - | X35: CORREÇÃO DE APONTAMENTO - ACUMULO PERDA
A36: 31584 | C36: CX PAPELAO TUBAINA 12X300ML | D36: CAIXA | E36: =VLOOKUP(BASE_CONCILI12[[#This Row],[CÓD. SAIB]],CONT_ANTE!A:D,4,0) -> #N/A | F36: =SUMIF(#REF!,BASE_CONCILI12[[#This Row],[CÓD. SAIB]],#REF!) -> #REF! | G36: =SUMIF(#REF!,BASE_CONCILI12[[#This Row],[CÓD. SAIB]],#REF!) -> #REF! | H36: =BASE_CONCILI12[[#This Row],[CONSUMO REAL]]-BASE_CONCILI12[[#This Row],[CONSUMO TEORICO]] -> #REF! | I36: =SUMIF(#REF!,BASE_CONCILI12[[#This Row],[CÓD. SAIB]],#REF!) -> #REF! | J36: =SUMIF(#REF!,BASE_CONCILI12[[#This Row],[CÓD. SAIB]],#REF!) -> #REF! | K36: =BASE_CONCILI12[[#This Row],[30/mai]]+BASE_CONCILI12[[#This Row],[RECEBIMENTO]]-BASE_CONCILI12[[#This Row],[TRANSFERÊNCIA]]-BASE_CONCILI12[[#This Row],[CONSUMO REAL]] -> #N/A | L36: =IFERROR(VLOOKUP(BASE_CONCILI12[[#This Row],[CÓD. SAIB]],BASE_CONTAG[[LAVRE]:[CONTAGEM FINAL]],7,0),0) -> 23945 | M36: =IFERROR(SUM(BASE_CONCILI12[[#This Row],[30/jun]]*BASE_CONCILI12[[#This Row],[CUSTO MP (UN)]]),0) -> 0 | N36: =IFERROR(VLOOKUP(BASE_CONCILI12[[#This Row],[CÓD. SAIB]],BASE_CONTAG[],5,0),"") -> 23945 | O36: =SUMIF(SISTEMA!#REF!,BASE_CONCILI12[[#This Row],[CÓD. SAIB]],SISTEMA!#REF!) -> #REF! | P36: =IFERROR(SUM(BASE_CONCILI12[[#This Row],[SISTEMA]]*BASE_CONCILI12[[#This Row],[CUSTO MP (UN)]]),0) -> 0 | Q36: =IFERROR(VLOOKUP(BASE_CONCILI12[[#This Row],[CÓD. SAIB]],BASE_DIFERENÇA[],4,0),"0") -> 0 | R36: =BASE_CONCILI12[[#This Row],[30/jun]]-BASE_CONCILI12[[#This Row],[SISTEMA]] -> #REF! | S36: =IFERROR(BASE_CONCILI12[[#This Row],[DIFERENÇA ANTERIOR]]-BASE_CONCILI12[[#This Row],[DIFERENÇA ATUAL]],"-") -> - | T36: =VLOOKUP(BASE_CONCILI12[[#This Row],[CÓD. SAIB]],CUSTO!A:C,3,0) -> 0 | U36: =IFERROR(SUM(BASE_CONCILI12[[#This Row],[DIFERENÇA ATUAL]]*BASE_CONCILI12[[#This Row],[CUSTO MP (UN)]]),0) -> 0 | V36: =IFERROR(BASE_CONCILI12[[#This Row],[30/jun]]/BASE_CONCILI12[[#This Row],[SISTEMA]],"") | W36: =IFERROR(BASE_CONCILI12[[#This Row],[DIFERENÇA MÊS]]*BASE_CONCILI12[[#This Row],[CUSTO MP (UN)]],"-") -> - | X36: OK
A37: 60 | C37: CARVAO ATIVADO | D37: CARVAO | E37: =VLOOKUP(BASE_CONCILI12[[#This Row],[CÓD. SAIB]],CONT_ANTE!A:D,4,0) -> #N/A | F37: =SUMIF(#REF!,BASE_CONCILI12[[#This Row],[CÓD. SAIB]],#REF!) -> #REF! | G37: =SUMIF(#REF!,BASE_CONCILI12[[#This Row],[CÓD. SAIB]],#REF!) -> #REF! | H37: =BASE_CONCILI12[[#This Row],[CONSUMO REAL]]-BASE_CONCILI12[[#This Row],[CONSUMO TEORICO]] -> #REF! | I37: =SUMIF(#REF!,BASE_CONCILI12[[#This Row],[CÓD. SAIB]],#REF!) -> #REF! | J37: =SUMIF(#REF!,BASE_CONCILI12[[#This Row],[CÓD. SAIB]],#REF!) -> #REF! | K37: =BASE_CONCILI12[[#This Row],[30/mai]]+BASE_CONCILI12[[#This Row],[RECEBIMENTO]]-BASE_CONCILI12[[#This Row],[TRANSFERÊNCIA]]-BASE_CONCILI12[[#This Row],[CONSUMO REAL]] -> #N/A | L37: =IFERROR(VLOOKUP(BASE_CONCILI12[[#This Row],[CÓD. SAIB]],BASE_CONTAG[[LAVRE]:[CONTAGEM FINAL]],7,0),0) -> 0 | M37: =IFERROR(SUM(BASE_CONCILI12[[#This Row],[30/jun]]*BASE_CONCILI12[[#This Row],[CUSTO MP (UN)]]),0) -> 0 | N37: =IFERROR(VLOOKUP(BASE_CONCILI12[[#This Row],[CÓD. SAIB]],BASE_CONTAG[],5,0),"") -> 0 | O37: =SUMIF(SISTEMA!#REF!,BASE_CONCILI12[[#This Row],[CÓD. SAIB]],SISTEMA!#REF!) -> #REF! | P37: =IFERROR(SUM(BASE_CONCILI12[[#This Row],[SISTEMA]]*BASE_CONCILI12[[#This Row],[CUSTO MP (UN)]]),0) -> 0 | Q37: =IFERROR(VLOOKUP(BASE_CONCILI12[[#This Row],[CÓD. SAIB]],BASE_DIFERENÇA[],4,0),"0") -> 0 | R37: =BASE_CONCILI12[[#This Row],[30/jun]]-BASE_CONCILI12[[#This Row],[SISTEMA]] -> #REF! | S37: =IFERROR(BASE_CONCILI12[[#This Row],[DIFERENÇA ANTERIOR]]-BASE_CONCILI12[[#This Row],[DIFERENÇA ATUAL]],"-") -> - | T37: =VLOOKUP(BASE_CONCILI12[[#This Row],[CÓD. SAIB]],CUSTO!A:C,3,0) -> 60CB01 | U37: =IFERROR(SUM(BASE_CONCILI12[[#This Row],[DIFERENÇA ATUAL]]*BASE_CONCILI12[[#This Row],[CUSTO MP (UN)]]),0) -> 0 | V37: =IFERROR(BASE_CONCILI12[[#This Row],[30/jun]]/BASE_CONCILI12[[#This Row],[SISTEMA]],"") | W37: =IFERROR(BASE_CONCILI12[[#This Row],[DIFERENÇA MÊS]]*BASE_CONCILI12[[#This Row],[CUSTO MP (UN)]],"-") -> - | X37: OK
A38: 30257 | C38: ACIDO LACTICO | D38: CERVEJARIA | E38: =VLOOKUP(BASE_CONCILI12[[#This Row],[CÓD. SAIB]],CONT_ANTE!A:D,4,0) -> #N/A | F38: =SUMIF(#REF!,BASE_CONCILI12[[#This Row],[CÓD. SAIB]],#REF!) -> #REF! | G38: =SUMIF(#REF!,BASE_CONCILI12[[#This Row],[CÓD. SAIB]],#REF!) -> #REF! | H38: =BASE_CONCILI12[[#This Row],[CONSUMO REAL]]-BASE_CONCILI12[[#This Row],[CONSUMO TEORICO]] -> #REF! | I38: =SUMIF(#REF!,BASE_CONCILI12[[#This Row],[CÓD. SAIB]],#REF!) -> #REF! | J38: =SUMIF(#REF!,BASE_CONCILI12[[#This Row],[CÓD. SAIB]],#REF!) -> #REF! | K38: =BASE_CONCILI12[[#This Row],[30/mai]]+BASE_CONCILI12[[#This Row],[RECEBIMENTO]]-BASE_CONCILI12[[#This Row],[TRANSFERÊNCIA]]-BASE_CONCILI12[[#This Row],[CONSUMO REAL]] -> #N/A | L38: =IFERROR(VLOOKUP(BASE_CONCILI12[[#This Row],[CÓD. SAIB]],BASE_CONTAG[[LAVRE]:[CONTAGEM FINAL]],7,0),0) -> 0 | M38: =IFERROR(SUM(BASE_CONCILI12[[#This Row],[30/jun]]*BASE_CONCILI12[[#This Row],[CUSTO MP (UN)]]),0) -> 0 | N38: =IFERROR(VLOOKUP(BASE_CONCILI12[[#This Row],[CÓD. SAIB]],BASE_CONTAG[],5,0),"") -> 0 | O38: =SUMIF(SISTEMA!#REF!,BASE_CONCILI12[[#This Row],[CÓD. SAIB]],SISTEMA!#REF!) -> #REF! | P38: =IFERROR(SUM(BASE_CONCILI12[[#This Row],[SISTEMA]]*BASE_CONCILI12[[#This Row],[CUSTO MP (UN)]]),0) -> 0 | Q38: =IFERROR(VLOOKUP(BASE_CONCILI12[[#This Row],[CÓD. SAIB]],BASE_DIFERENÇA[],4,0),"0") -> 0 | R38: =BASE_CONCILI12[[#This Row],[30/jun]]-BASE_CONCILI12[[#This Row],[SISTEMA]] -> #REF! | S38: =IFERROR(BASE_CONCILI12[[#This Row],[DIFERENÇA ANTERIOR]]-BASE_CONCILI12[[#This Row],[DIFERENÇA ATUAL]],"-") -> - | T38: =VLOOKUP(BASE_CONCILI12[[#This Row],[CÓD. SAIB]],CUSTO!A:C,3,0) -> 30257CB01 | U38: =IFERROR(SUM(BASE_CONCILI12[[#This Row],[DIFERENÇA ATUAL]]*BASE_CONCILI12[[#This Row],[CUSTO MP (UN)]]),0) -> 0 | V38: =IFERROR(BASE_CONCILI12[[#This Row],[30/jun]]/BASE_CONCILI12[[#This Row],[SISTEMA]],"") | W38: =IFERROR(BASE_CONCILI12[[#This Row],[DIFERENÇA MÊS]]*BASE_CONCILI12[[#This Row],[CUSTO MP (UN)]],"-") -> - | X38: CORREÇÃO DE APONTAMENTO - MANTÉM SOBRA
A39: 30247 | C39: ALGINATO DE PROPILENO GLICOL | D39: CERVEJARIA | E39: =VLOOKUP(BASE_CONCILI12[[#This Row],[CÓD. SAIB]],CONT_ANTE!A:D,4,0) -> #N/A | F39: =SUMIF(#REF!,BASE_CONCILI12[[#This Row],[CÓD. SAIB]],#REF!) -> #REF! | G39: =SUMIF(#REF!,BASE_CONCILI12[[#This Row],[CÓD. SAIB]],#REF!) -> #REF! | H39: =BASE_CONCILI12[[#This Row],[CONSUMO REAL]]-BASE_CONCILI12[[#This Row],[CONSUMO TEORICO]] -> #REF! | I39: =SUMIF(#REF!,BASE_CONCILI12[[#This Row],[CÓD. SAIB]],#REF!) -> #REF! | J39: =SUMIF(#REF!,BASE_CONCILI12[[#This Row],[CÓD. SAIB]],#REF!) -> #REF! | K39: =BASE_CONCILI12[[#This Row],[30/mai]]+BASE_CONCILI12[[#This Row],[RECEBIMENTO]]-BASE_CONCILI12[[#This Row],[TRANSFERÊNCIA]]-BASE_CONCILI12[[#This Row],[CONSUMO REAL]] -> #N/A | L39: =IFERROR(VLOOKUP(BASE_CONCILI12[[#This Row],[CÓD. SAIB]],BASE_CONTAG[[LAVRE]:[CONTAGEM FINAL]],7,0),0) -> 0 | M39: =IFERROR(SUM(BASE_CONCILI12[[#This Row],[30/jun]]*BASE_CONCILI12[[#This Row],[CUSTO MP (UN)]]),0) -> 0 | N39: =IFERROR(VLOOKUP(BASE_CONCILI12[[#This Row],[CÓD. SAIB]],BASE_CONTAG[],5,0),"") -> 0 | O39: =SUMIF(SISTEMA!#REF!,BASE_CONCILI12[[#This Row],[CÓD. SAIB]],SISTEMA!#REF!) -> #REF! | P39: =IFERROR(SUM(BASE_CONCILI12[[#This Row],[SISTEMA]]*BASE_CONCILI12[[#This Row],[CUSTO MP (UN)]]),0) -> 0 | Q39: =IFERROR(VLOOKUP(BASE_CONCILI12[[#This Row],[CÓD. SAIB]],BASE_DIFERENÇA[],4,0),"0") -> 0 | R39: =BASE_CONCILI12[[#This Row],[30/jun]]-BASE_CONCILI12[[#This Row],[SISTEMA]] -> #REF! | S39: =IFERROR(BASE_CONCILI12[[#This Row],[DIFERENÇA ANTERIOR]]-BASE_CONCILI12[[#This Row],[DIFERENÇA ATUAL]],"-") -> - | T39: =VLOOKUP(BASE_CONCILI12[[#This Row],[CÓD. SAIB]],CUSTO!A:C,3,0) -> 30247CB01 | U39: =IFERROR(SUM(BASE_CONCILI12[[#This Row],[DIFERENÇA ATUAL]]*BASE_CONCILI12[[#This Row],[CUSTO MP (UN)]]),0) -> 0 | V39: =IFERROR(BASE_CONCILI12[[#This Row],[30/jun]]/BASE_CONCILI12[[#This Row],[SISTEMA]],"") | W39: =IFERROR(BASE_CONCILI12[[#This Row],[DIFERENÇA MÊS]]*BASE_CONCILI12[[#This Row],[CUSTO MP (UN)]],"-") -> - | X39: CORREÇÃO DE APONTAMENTO - MANTÉM SOBRA
A40: 31998 | C40: ANTIOXIDANTE IS CX 25KG | D40: CERVEJARIA | E40: =VLOOKUP(BASE_CONCILI12[[#This Row],[CÓD. SAIB]],CONT_ANTE!A:D,4,0) -> #N/A | F40: =SUMIF(#REF!,BASE_CONCILI12[[#This Row],[CÓD. SAIB]],#REF!) -> #REF! | G40: =SUMIF(#REF!,BASE_CONCILI12[[#This Row],[CÓD. SAIB]],#REF!) -> #REF! | H40: =BASE_CONCILI12[[#This Row],[CONSUMO REAL]]-BASE_CONCILI12[[#This Row],[CONSUMO TEORICO]] -> #REF! | I40: =SUMIF(#REF!,BASE_CONCILI12[[#This Row],[CÓD. SAIB]],#REF!) -> #REF! | J40: =SUMIF(#REF!,BASE_CONCILI12[[#This Row],[CÓD. SAIB]],#REF!) -> #REF! | K40: =BASE_CONCILI12[[#This Row],[30/mai]]+BASE_CONCILI12[[#This Row],[RECEBIMENTO]]-BASE_CONCILI12[[#This Row],[TRANSFERÊNCIA]]-BASE_CONCILI12[[#This Row],[CONSUMO REAL]] -> #N/A | L40: =IFERROR(VLOOKUP(BASE_CONCILI12[[#This Row],[CÓD. SAIB]],BASE_CONTAG[[LAVRE]:[CONTAGEM FINAL]],7,0),0) -> 16103.5 | M40: =IFERROR(SUM(BASE_CONCILI12[[#This Row],[30/jun]]*BASE_CONCILI12[[#This Row],[CUSTO MP (UN)]]),0) -> 0 | N40: =IFERROR(VLOOKUP(BASE_CONCILI12[[#This Row],[CÓD. SAIB]],BASE_CONTAG[],5,0),"") -> 16103.5 | O40: =SUMIF(SISTEMA!#REF!,BASE_CONCILI12[[#This Row],[CÓD. SAIB]],SISTEMA!#REF!) -> #REF! | P40: =IFERROR(SUM(BASE_CONCILI12[[#This Row],[SISTEMA]]*BASE_CONCILI12[[#This Row],[CUSTO MP (UN)]]),0) -> 0 | Q40: =IFERROR(VLOOKUP(BASE_CONCILI12[[#This Row],[CÓD. SAIB]],BASE_DIFERENÇA[],4,0),"0") -> 0 | R40: =BASE_CONCILI12[[#This Row],[30/jun]]-BASE_CONCILI12[[#This Row],[SISTEMA]] -> #REF! | S40: =IFERROR(BASE_CONCILI12[[#This Row],[DIFERENÇA ANTERIOR]]-BASE_CONCILI12[[#This Row],[DIFERENÇA ATUAL]],"-") -> - | T40: =VLOOKUP(BASE_CONCILI12[[#This Row],[CÓD. SAIB]],CUSTO!A:C,3,0) -> 31998CB01 | U40: =IFERROR(SUM(BASE_CONCILI12[[#This Row],[DIFERENÇA ATUAL]]*BASE_CONCILI12[[#This Row],[CUSTO MP (UN)]]),0) -> 0 | V40: =IFERROR(BASE_CONCILI12[[#This Row],[30/jun]]/BASE_CONCILI12[[#This Row],[SISTEMA]],"") | W40: =IFERROR(BASE_CONCILI12[[#This Row],[DIFERENÇA MÊS]]*BASE_CONCILI12[[#This Row],[CUSTO MP (UN)]],"-") -> - | X40: CORREÇÃO DE APONTAMENTO - MANTÉM FALTA
A41: 31952 | C41: BIOMAX L | D41: CERVEJARIA | E41: =VLOOKUP(BASE_CONCILI12[[#This Row],[CÓD. SAIB]],CONT_ANTE!A:D,4,0) -> #N/A | F41: =SUMIF(#REF!,BASE_CONCILI12[[#This Row],[CÓD. SAIB]],#REF!) -> #REF! | G41: =SUMIF(#REF!,BASE_CONCILI12[[#This Row],[CÓD. SAIB]],#REF!) -> #REF! | H41: =BASE_CONCILI12[[#This Row],[CONSUMO REAL]]-BASE_CONCILI12[[#This Row],[CONSUMO TEORICO]] -> #REF! | I41: =SUMIF(#REF!,BASE_CONCILI12[[#This Row],[CÓD. SAIB]],#REF!) -> #REF! | J41: =SUMIF(#REF!,BASE_CONCILI12[[#This Row],[CÓD. SAIB]],#REF!) -> #REF! | K41: =BASE_CONCILI12[[#This Row],[30/mai]]+BASE_CONCILI12[[#This Row],[RECEBIMENTO]]-BASE_CONCILI12[[#This Row],[TRANSFERÊNCIA]]-BASE_CONCILI12[[#This Row],[CONSUMO REAL]] -> #N/A | L41: =IFERROR(VLOOKUP(BASE_CONCILI12[[#This Row],[CÓD. SAIB]],BASE_CONTAG[[LAVRE]:[CONTAGEM FINAL]],7,0),0) -> 0 | M41: =IFERROR(SUM(BASE_CONCILI12[[#This Row],[30/jun]]*BASE_CONCILI12[[#This Row],[CUSTO MP (UN)]]),0) -> 0 | N41: =IFERROR(VLOOKUP(BASE_CONCILI12[[#This Row],[CÓD. SAIB]],BASE_CONTAG[],5,0),"") | O41: =SUMIF(SISTEMA!#REF!,BASE_CONCILI12[[#This Row],[CÓD. SAIB]],SISTEMA!#REF!) -> #REF! | P41: =IFERROR(SUM(BASE_CONCILI12[[#This Row],[SISTEMA]]*BASE_CONCILI12[[#This Row],[CUSTO MP (UN)]]),0) -> 0 | Q41: =IFERROR(VLOOKUP(BASE_CONCILI12[[#This Row],[CÓD. SAIB]],BASE_DIFERENÇA[],4,0),"0") -> 0 | R41: =BASE_CONCILI12[[#This Row],[30/jun]]-BASE_CONCILI12[[#This Row],[SISTEMA]] -> #REF! | S41: =IFERROR(BASE_CONCILI12[[#This Row],[DIFERENÇA ANTERIOR]]-BASE_CONCILI12[[#This Row],[DIFERENÇA ATUAL]],"-") -> - | T41: 0 | U41: =IFERROR(SUM(BASE_CONCILI12[[#This Row],[DIFERENÇA ATUAL]]*BASE_CONCILI12[[#This Row],[CUSTO MP (UN)]]),0) -> 0 | V41: =IFERROR(BASE_CONCILI12[[#This Row],[30/jun]]/BASE_CONCILI12[[#This Row],[SISTEMA]],"") | W41: =IFERROR(BASE_CONCILI12[[#This Row],[DIFERENÇA MÊS]]*BASE_CONCILI12[[#This Row],[CUSTO MP (UN)]],"-") -> - | X41: OK
A42: 30254 | C42: CLEAR MAX PVPP | D42: CERVEJARIA | E42: =VLOOKUP(BASE_CONCILI12[[#This Row],[CÓD. SAIB]],CONT_ANTE!A:D,4,0) -> #N/A | F42: =SUMIF(#REF!,BASE_CONCILI12[[#This Row],[CÓD. SAIB]],#REF!) -> #REF! | G42: =SUMIF(#REF!,BASE_CONCILI12[[#This Row],[CÓD. SAIB]],#REF!) -> #REF! | H42: =BASE_CONCILI12[[#This Row],[CONSUMO REAL]]-BASE_CONCILI12[[#This Row],[CONSUMO TEORICO]] -> #REF! | I42: =SUMIF(#REF!,BASE_CONCILI12[[#This Row],[CÓD. SAIB]],#REF!) -> #REF! | J42: =SUMIF(#REF!,BASE_CONCILI12[[#This Row],[CÓD. SAIB]],#REF!) -> #REF! | K42: =BASE_CONCILI12[[#This Row],[30/mai]]+BASE_CONCILI12[[#This Row],[RECEBIMENTO]]-BASE_CONCILI12[[#This Row],[TRANSFERÊNCIA]]-BASE_CONCILI12[[#This Row],[CONSUMO REAL]] -> #N/A | L42: =IFERROR(VLOOKUP(BASE_CONCILI12[[#This Row],[CÓD. SAIB]],BASE_CONTAG[[LAVRE]:[CONTAGEM FINAL]],7,0),0) -> 3705 | M42: =IFERROR(SUM(BASE_CONCILI12[[#This Row],[30/jun]]*BASE_CONCILI12[[#This Row],[CUSTO MP (UN)]]),0) -> 0 | N42: =IFERROR(VLOOKUP(BASE_CONCILI12[[#This Row],[CÓD. SAIB]],BASE_CONTAG[],5,0),"") -> 3705 | O42: =SUMIF(SISTEMA!#REF!,BASE_CONCILI12[[#This Row],[CÓD. SAIB]],SISTEMA!#REF!) -> #REF! | P42: =IFERROR(SUM(BASE_CONCILI12[[#This Row],[SISTEMA]]*BASE_CONCILI12[[#This Row],[CUSTO MP (UN)]]),0) -> 0 | Q42: =IFERROR(VLOOKUP(BASE_CONCILI12[[#This Row],[CÓD. SAIB]],BASE_DIFERENÇA[],4,0),"0") -> 0 | R42: =BASE_CONCILI12[[#This Row],[30/jun]]-BASE_CONCILI12[[#This Row],[SISTEMA]] -> #REF! | S42: =IFERROR(BASE_CONCILI12[[#This Row],[DIFERENÇA ANTERIOR]]-BASE_CONCILI12[[#This Row],[DIFERENÇA ATUAL]],"-") -> - | T42: =VLOOKUP(BASE_CONCILI12[[#This Row],[CÓD. SAIB]],CUSTO!A:C,3,0) -> 30254CB01 | U42: =IFERROR(SUM(BASE_CONCILI12[[#This Row],[DIFERENÇA ATUAL]]*BASE_CONCILI12[[#This Row],[CUSTO MP (UN)]]),0) -> 0 | V42: =IFERROR(BASE_CONCILI12[[#This Row],[30/jun]]/BASE_CONCILI12[[#This Row],[SISTEMA]],"") | W42: =IFERROR(BASE_CONCILI12[[#This Row],[DIFERENÇA MÊS]]*BASE_CONCILI12[[#This Row],[CUSTO MP (UN)]],"-") -> - | X42: CORREÇÃO DE APONTAMENTO - MANTÉM SOBRA
A43: 31198 | C43: CLEARMAX MF - ACIDO TANICO | D43: CERVEJARIA | E43: =VLOOKUP(BASE_CONCILI12[[#This Row],[CÓD. SAIB]],CONT_ANTE!A:D,4,0) -> #N/A | F43: =SUMIF(#REF!,BASE_CONCILI12[[#This Row],[CÓD. SAIB]],#REF!) -> #REF! | G43: =SUMIF(#REF!,BASE_CONCILI12[[#This Row],[CÓD. SAIB]],#REF!) -> #REF! | H43: =BASE_CONCILI12[[#This Row],[CONSUMO REAL]]-BASE_CONCILI12[[#This Row],[CONSUMO TEORICO]] -> #REF! | I43: =SUMIF(#REF!,BASE_CONCILI12[[#This Row],[CÓD. SAIB]],#REF!) -> #REF! | J43: =SUMIF(#REF!,BASE_CONCILI12[[#This Row],[CÓD. SAIB]],#REF!) -> #REF! | K43: =BASE_CONCILI12[[#This Row],[30/mai]]+BASE_CONCILI12[[#This Row],[RECEBIMENTO]]-BASE_CONCILI12[[#This Row],[TRANSFERÊNCIA]]-BASE_CONCILI12[[#This Row],[CONSUMO REAL]] -> #N/A | L43: =IFERROR(VLOOKUP(BASE_CONCILI12[[#This Row],[CÓD. SAIB]],BASE_CONTAG[[LAVRE]:[CONTAGEM FINAL]],7,0),0) -> 0 | M43: =IFERROR(SUM(BASE_CONCILI12[[#This Row],[30/jun]]*BASE_CONCILI12[[#This Row],[CUSTO MP (UN)]]),0) -> 0 | N43: =IFERROR(VLOOKUP(BASE_CONCILI12[[#This Row],[CÓD. SAIB]],BASE_CONTAG[],5,0),"") -> 0 | O43: =SUMIF(SISTEMA!#REF!,BASE_CONCILI12[[#This Row],[CÓD. SAIB]],SISTEMA!#REF!) -> #REF! | P43: =IFERROR(SUM(BASE_CONCILI12[[#This Row],[SISTEMA]]*BASE_CONCILI12[[#This Row],[CUSTO MP (UN)]]),0) -> 0 | Q43: =IFERROR(VLOOKUP(BASE_CONCILI12[[#This Row],[CÓD. SAIB]],BASE_DIFERENÇA[],4,0),"0") -> 0 | R43: =BASE_CONCILI12[[#This Row],[30/jun]]-BASE_CONCILI12[[#This Row],[SISTEMA]] -> #REF! | S43: =IFERROR(BASE_CONCILI12[[#This Row],[DIFERENÇA ANTERIOR]]-BASE_CONCILI12[[#This Row],[DIFERENÇA ATUAL]],"-") -> - | T43: =VLOOKUP(BASE_CONCILI12[[#This Row],[CÓD. SAIB]],CUSTO!A:C,3,0) -> 31198CB01 | U43: =IFERROR(SUM(BASE_CONCILI12[[#This Row],[DIFERENÇA ATUAL]]*BASE_CONCILI12[[#This Row],[CUSTO MP (UN)]]),0) -> 0 | V43: =IFERROR(BASE_CONCILI12[[#This Row],[30/jun]]/BASE_CONCILI12[[#This Row],[SISTEMA]],"") | W43: =IFERROR(BASE_CONCILI12[[#This Row],[DIFERENÇA MÊS]]*BASE_CONCILI12[[#This Row],[CUSTO MP (UN)]],"-") -> - | X43: OK
A44: 30256 | C44: CLORETO DE CALCIO | D44: CERVEJARIA | E44: =VLOOKUP(BASE_CONCILI12[[#This Row],[CÓD. SAIB]],CONT_ANTE!A:D,4,0) -> #N/A | F44: =SUMIF(#REF!,BASE_CONCILI12[[#This Row],[CÓD. SAIB]],#REF!) -> #REF! | G44: =SUMIF(#REF!,BASE_CONCILI12[[#This Row],[CÓD. SAIB]],#REF!) -> #REF! | H44: =BASE_CONCILI12[[#This Row],[CONSUMO REAL]]-BASE_CONCILI12[[#This Row],[CONSUMO TEORICO]] -> #REF! | I44: =SUMIF(#REF!,BASE_CONCILI12[[#This Row],[CÓD. SAIB]],#REF!) -> #REF! | J44: =SUMIF(#REF!,BASE_CONCILI12[[#This Row],[CÓD. SAIB]],#REF!) -> #REF! | K44: =BASE_CONCILI12[[#This Row],[30/mai]]+BASE_CONCILI12[[#This Row],[RECEBIMENTO]]-BASE_CONCILI12[[#This Row],[TRANSFERÊNCIA]]-BASE_CONCILI12[[#This Row],[CONSUMO REAL]] -> #N/A | L44: =IFERROR(VLOOKUP(BASE_CONCILI12[[#This Row],[CÓD. SAIB]],BASE_CONTAG[[LAVRE]:[CONTAGEM FINAL]],7,0),0) -> 901.5 | M44: =IFERROR(SUM(BASE_CONCILI12[[#This Row],[30/jun]]*BASE_CONCILI12[[#This Row],[CUSTO MP (UN)]]),0) -> 0 | N44: =IFERROR(VLOOKUP(BASE_CONCILI12[[#This Row],[CÓD. SAIB]],BASE_CONTAG[],5,0),"") -> 901.5 | O44: =SUMIF(SISTEMA!#REF!,BASE_CONCILI12[[#This Row],[CÓD. SAIB]],SISTEMA!#REF!) -> #REF! | P44: =IFERROR(SUM(BASE_CONCILI12[[#This Row],[SISTEMA]]*BASE_CONCILI12[[#This Row],[CUSTO MP (UN)]]),0) -> 0 | Q44: =IFERROR(VLOOKUP(BASE_CONCILI12[[#This Row],[CÓD. SAIB]],BASE_DIFERENÇA[],4,0),"0") -> 0 | R44: =BASE_CONCILI12[[#This Row],[30/jun]]-BASE_CONCILI12[[#This Row],[SISTEMA]] -> #REF! | S44: =IFERROR(BASE_CONCILI12[[#This Row],[DIFERENÇA ANTERIOR]]-BASE_CONCILI12[[#This Row],[DIFERENÇA ATUAL]],"-") -> - | T44: =VLOOKUP(BASE_CONCILI12[[#This Row],[CÓD. SAIB]],CUSTO!A:C,3,0) -> 30256CB01 | U44: =IFERROR(SUM(BASE_CONCILI12[[#This Row],[DIFERENÇA ATUAL]]*BASE_CONCILI12[[#This Row],[CUSTO MP (UN)]]),0) -> 0 | V44: =IFERROR(BASE_CONCILI12[[#This Row],[30/jun]]/BASE_CONCILI12[[#This Row],[SISTEMA]],"") | W44: =IFERROR(BASE_CONCILI12[[#This Row],[DIFERENÇA MÊS]]*BASE_CONCILI12[[#This Row],[CUSTO MP (UN)]],"-") -> - | X44: CORREÇÃO DE APONTAMENTO - MANTÉM SOBRA
A45: 30356 | C45: CORANTE CARAMELO CERVEJA | D45: CERVEJARIA | E45: =VLOOKUP(BASE_CONCILI12[[#This Row],[CÓD. SAIB]],CONT_ANTE!A:D,4,0) -> #N/A | F45: =SUMIF(#REF!,BASE_CONCILI12[[#This Row],[CÓD. SAIB]],#REF!) -> #REF! | G45: =SUMIF(#REF!,BASE_CONCILI12[[#This Row],[CÓD. SAIB]],#REF!) -> #REF! | H45: =BASE_CONCILI12[[#This Row],[CONSUMO REAL]]-BASE_CONCILI12[[#This Row],[CONSUMO TEORICO]] -> #REF! | I45: =SUMIF(#REF!,BASE_CONCILI12[[#This Row],[CÓD. SAIB]],#REF!) -> #REF! | J45: =SUMIF(#REF!,BASE_CONCILI12[[#This Row],[CÓD. SAIB]],#REF!) -> #REF! | K45: =BASE_CONCILI12[[#This Row],[30/mai]]+BASE_CONCILI12[[#This Row],[RECEBIMENTO]]-BASE_CONCILI12[[#This Row],[TRANSFERÊNCIA]]-BASE_CONCILI12[[#This Row],[CONSUMO REAL]] -> #N/A | L45: =IFERROR(VLOOKUP(BASE_CONCILI12[[#This Row],[CÓD. SAIB]],BASE_CONTAG[[LAVRE]:[CONTAGEM FINAL]],7,0),0) -> 0 | M45: =IFERROR(SUM(BASE_CONCILI12[[#This Row],[30/jun]]*BASE_CONCILI12[[#This Row],[CUSTO MP (UN)]]),0) -> 0 | N45: =IFERROR(VLOOKUP(BASE_CONCILI12[[#This Row],[CÓD. SAIB]],BASE_CONTAG[],5,0),"") -> 0 | O45: =SUMIF(SISTEMA!#REF!,BASE_CONCILI12[[#This Row],[CÓD. SAIB]],SISTEMA!#REF!) -> #REF! | P45: =IFERROR(SUM(BASE_CONCILI12[[#This Row],[SISTEMA]]*BASE_CONCILI12[[#This Row],[CUSTO MP (UN)]]),0) -> 0 | Q45: =IFERROR(VLOOKUP(BASE_CONCILI12[[#This Row],[CÓD. SAIB]],BASE_DIFERENÇA[],4,0),"0") -> 0 | R45: =BASE_CONCILI12[[#This Row],[30/jun]]-BASE_CONCILI12[[#This Row],[SISTEMA]] -> #REF! | S45: =IFERROR(BASE_CONCILI12[[#This Row],[DIFERENÇA ANTERIOR]]-BASE_CONCILI12[[#This Row],[DIFERENÇA ATUAL]],"-") -> - | T45: =VLOOKUP(BASE_CONCILI12[[#This Row],[CÓD. SAIB]],CUSTO!A:C,3,0) -> 2701060006CB01 | U45: =IFERROR(SUM(BASE_CONCILI12[[#This Row],[DIFERENÇA ATUAL]]*BASE_CONCILI12[[#This Row],[CUSTO MP (UN)]]),0) -> 0 | V45: =IFERROR(BASE_CONCILI12[[#This Row],[30/jun]]/BASE_CONCILI12[[#This Row],[SISTEMA]],"") | W45: =IFERROR(BASE_CONCILI12[[#This Row],[DIFERENÇA MÊS]]*BASE_CONCILI12[[#This Row],[CUSTO MP (UN)]],"-") -> - | X45: CORREÇÃO DE APONTAMENTO - MANTÉM FALTA
A46: 31828 | C46: ENZIMAS ULTRAFLO | D46: CERVEJARIA | E46: =VLOOKUP(BASE_CONCILI12[[#This Row],[CÓD. SAIB]],CONT_ANTE!A:D,4,0) -> #N/A | F46: =SUMIF(#REF!,BASE_CONCILI12[[#This Row],[CÓD. SAIB]],#REF!) -> #REF! | G46: =SUMIF(#REF!,BASE_CONCILI12[[#This Row],[CÓD. SAIB]],#REF!) -> #REF! | H46: =BASE_CONCILI12[[#This Row],[CONSUMO REAL]]-BASE_CONCILI12[[#This Row],[CONSUMO TEORICO]] -> #REF! | I46: =SUMIF(#REF!,BASE_CONCILI12[[#This Row],[CÓD. SAIB]],#REF!) -> #REF! | J46: =SUMIF(#REF!,BASE_CONCILI12[[#This Row],[CÓD. SAIB]],#REF!) -> #REF! | K46: =BASE_CONCILI12[[#This Row],[30/mai]]+BASE_CONCILI12[[#This Row],[RECEBIMENTO]]-BASE_CONCILI12[[#This Row],[TRANSFERÊNCIA]]-BASE_CONCILI12[[#This Row],[CONSUMO REAL]] -> #N/A | L46: =IFERROR(VLOOKUP(BASE_CONCILI12[[#This Row],[CÓD. SAIB]],BASE_CONTAG[[LAVRE]:[CONTAGEM FINAL]],7,0),0) -> 1436.5 | M46: =IFERROR(SUM(BASE_CONCILI12[[#This Row],[30/jun]]*BASE_CONCILI12[[#This Row],[CUSTO MP (UN)]]),0) -> 0 | N46: =IFERROR(VLOOKUP(BASE_CONCILI12[[#This Row],[CÓD. SAIB]],BASE_CONTAG[],5,0),"") -> 1436.5 | O46: =SUMIF(SISTEMA!#REF!,BASE_CONCILI12[[#This Row],[CÓD. SAIB]],SISTEMA!#REF!) -> #REF! | P46: =IFERROR(SUM(BASE_CONCILI12[[#This Row],[SISTEMA]]*BASE_CONCILI12[[#This Row],[CUSTO MP (UN)]]),0) -> 0 | Q46: =IFERROR(VLOOKUP(BASE_CONCILI12[[#This Row],[CÓD. SAIB]],BASE_DIFERENÇA[],4,0),"0") -> 0 | R46: =BASE_CONCILI12[[#This Row],[30/jun]]-BASE_CONCILI12[[#This Row],[SISTEMA]] -> #REF! | S46: =IFERROR(BASE_CONCILI12[[#This Row],[DIFERENÇA ANTERIOR]]-BASE_CONCILI12[[#This Row],[DIFERENÇA ATUAL]],"-") -> - | T46: =VLOOKUP(BASE_CONCILI12[[#This Row],[CÓD. SAIB]],CUSTO!A:C,3,0) -> 31828CB01 | U46: =IFERROR(SUM(BASE_CONCILI12[[#This Row],[DIFERENÇA ATUAL]]*BASE_CONCILI12[[#This Row],[CUSTO MP (UN)]]),0) -> 0 | V46: =IFERROR(BASE_CONCILI12[[#This Row],[30/jun]]/BASE_CONCILI12[[#This Row],[SISTEMA]],"") | W46: =IFERROR(BASE_CONCILI12[[#This Row],[DIFERENÇA MÊS]]*BASE_CONCILI12[[#This Row],[CUSTO MP (UN)]],"-") -> - | X46: CORREÇÃO DE APONTAMENTO - MANTÉM FALTA
A47: 2041 | C47: FERMENTO CERVEJEIRO FERMENTIS W-34/70 | D47: CERVEJARIA | E47: =VLOOKUP(BASE_CONCILI12[[#This Row],[CÓD. SAIB]],CONT_ANTE!A:D,4,0) -> #N/A | F47: =SUMIF(#REF!,BASE_CONCILI12[[#This Row],[CÓD. SAIB]],#REF!) -> #REF! | G47: =SUMIF(#REF!,BASE_CONCILI12[[#This Row],[CÓD. SAIB]],#REF!) -> #REF! | H47: =BASE_CONCILI12[[#This Row],[CONSUMO REAL]]-BASE_CONCILI12[[#This Row],[CONSUMO TEORICO]] -> #REF! | I47: =SUMIF(#REF!,BASE_CONCILI12[[#This Row],[CÓD. SAIB]],#REF!) -> #REF! | J47: =SUMIF(#REF!,BASE_CONCILI12[[#This Row],[CÓD. SAIB]],#REF!) -> #REF! | K47: =BASE_CONCILI12[[#This Row],[30/mai]]+BASE_CONCILI12[[#This Row],[RECEBIMENTO]]-BASE_CONCILI12[[#This Row],[TRANSFERÊNCIA]]-BASE_CONCILI12[[#This Row],[CONSUMO REAL]] -> #N/A | L47: =IFERROR(VLOOKUP(BASE_CONCILI12[[#This Row],[CÓD. SAIB]],BASE_CONTAG[[LAVRE]:[CONTAGEM FINAL]],7,0),0) -> 5 | M47: =IFERROR(SUM(BASE_CONCILI12[[#This Row],[30/jun]]*BASE_CONCILI12[[#This Row],[CUSTO MP (UN)]]),0) -> 0 | N47: =IFERROR(VLOOKUP(BASE_CONCILI12[[#This Row],[CÓD. SAIB]],BASE_CONTAG[],5,0),"") -> 5 | O47: =SUMIF(SISTEMA!#REF!,BASE_CONCILI12[[#This Row],[CÓD. SAIB]],SISTEMA!#REF!) -> #REF! | P47: =IFERROR(SUM(BASE_CONCILI12[[#This Row],[SISTEMA]]*BASE_CONCILI12[[#This Row],[CUSTO MP (UN)]]),0) -> 0 | Q47: =IFERROR(VLOOKUP(BASE_CONCILI12[[#This Row],[CÓD. SAIB]],BASE_DIFERENÇA[],4,0),"0") -> 0 | R47: =BASE_CONCILI12[[#This Row],[30/jun]]-BASE_CONCILI12[[#This Row],[SISTEMA]] -> #REF! | S47: =IFERROR(BASE_CONCILI12[[#This Row],[DIFERENÇA ANTERIOR]]-BASE_CONCILI12[[#This Row],[DIFERENÇA ATUAL]],"-") -> - | T47: =VLOOKUP(BASE_CONCILI12[[#This Row],[CÓD. SAIB]],CUSTO!A:C,3,0) -> 2041CB01 | U47: =IFERROR(SUM(BASE_CONCILI12[[#This Row],[DIFERENÇA ATUAL]]*BASE_CONCILI12[[#This Row],[CUSTO MP (UN)]]),0) -> 0 | V47: =IFERROR(BASE_CONCILI12[[#This Row],[30/jun]]/BASE_CONCILI12[[#This Row],[SISTEMA]],"") | W47: =IFERROR(BASE_CONCILI12[[#This Row],[DIFERENÇA MÊS]]*BASE_CONCILI12[[#This Row],[CUSTO MP (UN)]],"-") -> - | X47: NÃO CONSOME EM NENHUMA ESTRUTURA
A48: 30255 | C48: SILICA DARACLAR | D48: CERVEJARIA | E48: =VLOOKUP(BASE_CONCILI12[[#This Row],[CÓD. SAIB]],CONT_ANTE!A:D,4,0) -> #N/A | F48: =SUMIF(#REF!,BASE_CONCILI12[[#This Row],[CÓD. SAIB]],#REF!) -> #REF! | G48: =SUMIF(#REF!,BASE_CONCILI12[[#This Row],[CÓD. SAIB]],#REF!) -> #REF! | H48: =BASE_CONCILI12[[#This Row],[CONSUMO REAL]]-BASE_CONCILI12[[#This Row],[CONSUMO TEORICO]] -> #REF! | I48: =SUMIF(#REF!,BASE_CONCILI12[[#This Row],[CÓD. SAIB]],#REF!) -> #REF! | J48: =SUMIF(#REF!,BASE_CONCILI12[[#This Row],[CÓD. SAIB]],#REF!) -> #REF! | K48: =BASE_CONCILI12[[#This Row],[30/mai]]+BASE_CONCILI12[[#This Row],[RECEBIMENTO]]-BASE_CONCILI12[[#This Row],[TRANSFERÊNCIA]]-BASE_CONCILI12[[#This Row],[CONSUMO REAL]] -> #N/A | L48: =IFERROR(VLOOKUP(BASE_CONCILI12[[#This Row],[CÓD. SAIB]],BASE_CONTAG[[LAVRE]:[CONTAGEM FINAL]],7,0),0) -> 0 | M48: =IFERROR(SUM(BASE_CONCILI12[[#This Row],[30/jun]]*BASE_CONCILI12[[#This Row],[CUSTO MP (UN)]]),0) -> 0 | N48: =IFERROR(VLOOKUP(BASE_CONCILI12[[#This Row],[CÓD. SAIB]],BASE_CONTAG[],5,0),"") | O48: =SUMIF(SISTEMA!#REF!,BASE_CONCILI12[[#This Row],[CÓD. SAIB]],SISTEMA!#REF!) -> #REF! | P48: =IFERROR(SUM(BASE_CONCILI12[[#This Row],[SISTEMA]]*BASE_CONCILI12[[#This Row],[CUSTO MP (UN)]]),0) -> 0 | Q48: =IFERROR(VLOOKUP(BASE_CONCILI12[[#This Row],[CÓD. SAIB]],BASE_DIFERENÇA[],4,0),"0") -> 0 | R48: =BASE_CONCILI12[[#This Row],[30/jun]]-BASE_CONCILI12[[#This Row],[SISTEMA]] -> #REF! | S48: =IFERROR(BASE_CONCILI12[[#This Row],[DIFERENÇA ANTERIOR]]-BASE_CONCILI12[[#This Row],[DIFERENÇA ATUAL]],"-") -> - | T48: 0 | U48: =IFERROR(SUM(BASE_CONCILI12[[#This Row],[DIFERENÇA ATUAL]]*BASE_CONCILI12[[#This Row],[CUSTO MP (UN)]]),0) -> 0 | V48: =IFERROR(BASE_CONCILI12[[#This Row],[30/jun]]/BASE_CONCILI12[[#This Row],[SISTEMA]],"") | W48: =IFERROR(BASE_CONCILI12[[#This Row],[DIFERENÇA MÊS]]*BASE_CONCILI12[[#This Row],[CUSTO MP (UN)]],"-") -> - | X48: OK
A49: 30606 | C49: SILICA HP 9000 | D49: CERVEJARIA | E49: =VLOOKUP(BASE_CONCILI12[[#This Row],[CÓD. SAIB]],CONT_ANTE!A:D,4,0) -> #N/A | F49: =SUMIF(#REF!,BASE_CONCILI12[[#This Row],[CÓD. SAIB]],#REF!) -> #REF! | G49: =SUMIF(#REF!,BASE_CONCILI12[[#This Row],[CÓD. SAIB]],#REF!) -> #REF! | H49: =BASE_CONCILI12[[#This Row],[CONSUMO REAL]]-BASE_CONCILI12[[#This Row],[CONSUMO TEORICO]] -> #REF! | I49: =SUMIF(#REF!,BASE_CONCILI12[[#This Row],[CÓD. SAIB]],#REF!) -> #REF! | J49: =SUMIF(#REF!,BASE_CONCILI12[[#This Row],[CÓD. SAIB]],#REF!) -> #REF! | K49: =BASE_CONCILI12[[#This Row],[30/mai]]+BASE_CONCILI12[[#This Row],[RECEBIMENTO]]-BASE_CONCILI12[[#This Row],[TRANSFERÊNCIA]]-BASE_CONCILI12[[#This Row],[CONSUMO REAL]] -> #N/A | L49: =IFERROR(VLOOKUP(BASE_CONCILI12[[#This Row],[CÓD. SAIB]],BASE_CONTAG[[LAVRE]:[CONTAGEM FINAL]],7,0),0) -> 1268 | M49: =IFERROR(SUM(BASE_CONCILI12[[#This Row],[30/jun]]*BASE_CONCILI12[[#This Row],[CUSTO MP (UN)]]),0) -> 0 | N49: =IFERROR(VLOOKUP(BASE_CONCILI12[[#This Row],[CÓD. SAIB]],BASE_CONTAG[],5,0),"") -> 1268 | O49: =SUMIF(SISTEMA!#REF!,BASE_CONCILI12[[#This Row],[CÓD. SAIB]],SISTEMA!#REF!) -> #REF! | P49: =IFERROR(SUM(BASE_CONCILI12[[#This Row],[SISTEMA]]*BASE_CONCILI12[[#This Row],[CUSTO MP (UN)]]),0) -> 0 | Q49: =IFERROR(VLOOKUP(BASE_CONCILI12[[#This Row],[CÓD. SAIB]],BASE_DIFERENÇA[],4,0),"0") -> 0 | R49: =BASE_CONCILI12[[#This Row],[30/jun]]-BASE_CONCILI12[[#This Row],[SISTEMA]] -> #REF! | S49: =IFERROR(BASE_CONCILI12[[#This Row],[DIFERENÇA ANTERIOR]]-BASE_CONCILI12[[#This Row],[DIFERENÇA ATUAL]],"-") -> - | T49: =VLOOKUP(BASE_CONCILI12[[#This Row],[CÓD. SAIB]],CUSTO!A:C,3,0) -> 30606CB01 | U49: =IFERROR(SUM(BASE_CONCILI12[[#This Row],[DIFERENÇA ATUAL]]*BASE_CONCILI12[[#This Row],[CUSTO MP (UN)]]),0) -> 0 | V49: =IFERROR(BASE_CONCILI12[[#This Row],[30/jun]]/BASE_CONCILI12[[#This Row],[SISTEMA]],"") | W49: =IFERROR(BASE_CONCILI12[[#This Row],[DIFERENÇA MÊS]]*BASE_CONCILI12[[#This Row],[CUSTO MP (UN)]],"-") -> - | X49: CORREÇÃO DE APONTAMENTO - MANTÉM SOBRA
A50: 2032 | C50: XAROPE HIGH MALTOSE | D50: CERVEJARIA | E50: =VLOOKUP(BASE_CONCILI12[[#This Row],[CÓD. SAIB]],CONT_ANTE!A:D,4,0) -> #N/A | F50: =SUMIF(#REF!,BASE_CONCILI12[[#This Row],[CÓD. SAIB]],#REF!) -> #REF! | G50: =SUMIF(#REF!,BASE_CONCILI12[[#This Row],[CÓD. SAIB]],#REF!) -> #REF! | H50: =BASE_CONCILI12[[#This Row],[CONSUMO REAL]]-BASE_CONCILI12[[#This Row],[CONSUMO TEORICO]] -> #REF! | I50: =SUMIF(#REF!,BASE_CONCILI12[[#This Row],[CÓD. SAIB]],#REF!) -> #REF! | J50: =SUMIF(#REF!,BASE_CONCILI12[[#This Row],[CÓD. SAIB]],#REF!) -> #REF! | K50: =BASE_CONCILI12[[#This Row],[30/mai]]+BASE_CONCILI12[[#This Row],[RECEBIMENTO]]-BASE_CONCILI12[[#This Row],[TRANSFERÊNCIA]]-BASE_CONCILI12[[#This Row],[CONSUMO REAL]] -> #N/A | L50: =IFERROR(VLOOKUP(BASE_CONCILI12[[#This Row],[CÓD. SAIB]],BASE_CONTAG[[LAVRE]:[CONTAGEM FINAL]],7,0),0) -> 15 | M50: =IFERROR(SUM(BASE_CONCILI12[[#This Row],[30/jun]]*BASE_CONCILI12[[#This Row],[CUSTO MP (UN)]]),0) -> 0 | N50: =IFERROR(VLOOKUP(BASE_CONCILI12[[#This Row],[CÓD. SAIB]],BASE_CONTAG[],5,0),"") -> 15 | O50: =SUMIF(SISTEMA!#REF!,BASE_CONCILI12[[#This Row],[CÓD. SAIB]],SISTEMA!#REF!) -> #REF! | P50: =IFERROR(SUM(BASE_CONCILI12[[#This Row],[SISTEMA]]*BASE_CONCILI12[[#This Row],[CUSTO MP (UN)]]),0) -> 0 | Q50: =IFERROR(VLOOKUP(BASE_CONCILI12[[#This Row],[CÓD. SAIB]],BASE_DIFERENÇA[],4,0),"0") -> 0 | R50: =BASE_CONCILI12[[#This Row],[30/jun]]-BASE_CONCILI12[[#This Row],[SISTEMA]] -> #REF! | S50: =IFERROR(BASE_CONCILI12[[#This Row],[DIFERENÇA ANTERIOR]]-BASE_CONCILI12[[#This Row],[DIFERENÇA ATUAL]],"-") -> - | T50: =VLOOKUP(BASE_CONCILI12[[#This Row],[CÓD. SAIB]],CUSTO!A:C,3,0) -> 2032CB01 | U50: =IFERROR(SUM(BASE_CONCILI12[[#This Row],[DIFERENÇA ATUAL]]*BASE_CONCILI12[[#This Row],[CUSTO MP (UN)]]),0) -> 0 | V50: =IFERROR(BASE_CONCILI12[[#This Row],[30/jun]]/BASE_CONCILI12[[#This Row],[SISTEMA]],"") | W50: =IFERROR(BASE_CONCILI12[[#This Row],[DIFERENÇA MÊS]]*BASE_CONCILI12[[#This Row],[CUSTO MP (UN)]],"-") -> - | X50: OK
A51: 31334 | C51: CONCENTRADO B. ENERGETICA AÇAI | D51: CONCENTRADO | E51: =VLOOKUP(BASE_CONCILI12[[#This Row],[CÓD. SAIB]],CONT_ANTE!A:D,4,0) -> #N/A | F51: =SUMIF(#REF!,BASE_CONCILI12[[#This Row],[CÓD. SAIB]],#REF!) -> #REF! | G51: =SUMIF(#REF!,BASE_CONCILI12[[#This Row],[CÓD. SAIB]],#REF!) -> #REF! | H51: =BASE_CONCILI12[[#This Row],[CONSUMO REAL]]-BASE_CONCILI12[[#This Row],[CONSUMO TEORICO]] -> #REF! | I51: =SUMIF(#REF!,BASE_CONCILI12[[#This Row],[CÓD. SAIB]],#REF!) -> #REF! | J51: =SUMIF(#REF!,BASE_CONCILI12[[#This Row],[CÓD. SAIB]],#REF!) -> #REF! | K51: =BASE_CONCILI12[[#This Row],[30/mai]]+BASE_CONCILI12[[#This Row],[RECEBIMENTO]]-BASE_CONCILI12[[#This Row],[TRANSFERÊNCIA]]-BASE_CONCILI12[[#This Row],[CONSUMO REAL]] -> #N/A | L51: =IFERROR(VLOOKUP(BASE_CONCILI12[[#This Row],[CÓD. SAIB]],BASE_CONTAG[[LAVRE]:[CONTAGEM FINAL]],7,0),0) -> 25 | M51: =IFERROR(SUM(BASE_CONCILI12[[#This Row],[30/jun]]*BASE_CONCILI12[[#This Row],[CUSTO MP (UN)]]),0) -> 0 | N51: =IFERROR(VLOOKUP(BASE_CONCILI12[[#This Row],[CÓD. SAIB]],BASE_CONTAG[],5,0),"") -> 25 | O51: =SUMIF(SISTEMA!#REF!,BASE_CONCILI12[[#This Row],[CÓD. SAIB]],SISTEMA!#REF!) -> #REF! | P51: =IFERROR(SUM(BASE_CONCILI12[[#This Row],[SISTEMA]]*BASE_CONCILI12[[#This Row],[CUSTO MP (UN)]]),0) -> 0 | Q51: =IFERROR(VLOOKUP(BASE_CONCILI12[[#This Row],[CÓD. SAIB]],BASE_DIFERENÇA[],4,0),"0") -> 0 | R51: =BASE_CONCILI12[[#This Row],[30/jun]]-BASE_CONCILI12[[#This Row],[SISTEMA]] -> #REF! | S51: =IFERROR(BASE_CONCILI12[[#This Row],[DIFERENÇA ANTERIOR]]-BASE_CONCILI12[[#This Row],[DIFERENÇA ATUAL]],"-") -> - | T51: =VLOOKUP(BASE_CONCILI12[[#This Row],[CÓD. SAIB]],CUSTO!A:C,3,0) -> 31334CB01 | U51: =IFERROR(SUM(BASE_CONCILI12[[#This Row],[DIFERENÇA ATUAL]]*BASE_CONCILI12[[#This Row],[CUSTO MP (UN)]]),0) -> 0 | V51: =IFERROR(BASE_CONCILI12[[#This Row],[30/jun]]/BASE_CONCILI12[[#This Row],[SISTEMA]],"") | W51: =IFERROR(BASE_CONCILI12[[#This Row],[DIFERENÇA MÊS]]*BASE_CONCILI12[[#This Row],[CUSTO MP (UN)]],"-") -> - | X51: OK
A52: 48 | C52: CONCENTRADO BEBIDAS ENERGETICA | D52: CONCENTRADO | E52: =VLOOKUP(BASE_CONCILI12[[#This Row],[CÓD. SAIB]],CONT_ANTE!A:D,4,0) -> #N/A | F52: =SUMIF(#REF!,BASE_CONCILI12[[#This Row],[CÓD. SAIB]],#REF!) -> #REF! | G52: =SUMIF(#REF!,BASE_CONCILI12[[#This Row],[CÓD. SAIB]],#REF!) -> #REF! | H52: =BASE_CONCILI12[[#This Row],[CONSUMO REAL]]-BASE_CONCILI12[[#This Row],[CONSUMO TEORICO]] -> #REF! | I52: =SUMIF(#REF!,BASE_CONCILI12[[#This Row],[CÓD. SAIB]],#REF!) -> #REF! | J52: =SUMIF(#REF!,BASE_CONCILI12[[#This Row],[CÓD. SAIB]],#REF!) -> #REF! | K52: =BASE_CONCILI12[[#This Row],[30/mai]]+BASE_CONCILI12[[#This Row],[RECEBIMENTO]]-BASE_CONCILI12[[#This Row],[TRANSFERÊNCIA]]-BASE_CONCILI12[[#This Row],[CONSUMO REAL]] -> #N/A | L52: =IFERROR(VLOOKUP(BASE_CONCILI12[[#This Row],[CÓD. SAIB]],BASE_CONTAG[[LAVRE]:[CONTAGEM FINAL]],7,0),0) -> 0 | M52: =IFERROR(SUM(BASE_CONCILI12[[#This Row],[30/jun]]*BASE_CONCILI12[[#This Row],[CUSTO MP (UN)]]),0) -> 0 | N52: =IFERROR(VLOOKUP(BASE_CONCILI12[[#This Row],[CÓD. SAIB]],BASE_CONTAG[],5,0),"") -> 0 | O52: =SUMIF(SISTEMA!#REF!,BASE_CONCILI12[[#This Row],[CÓD. SAIB]],SISTEMA!#REF!) -> #REF! | P52: =IFERROR(SUM(BASE_CONCILI12[[#This Row],[SISTEMA]]*BASE_CONCILI12[[#This Row],[CUSTO MP (UN)]]),0) -> 0 | Q52: =IFERROR(VLOOKUP(BASE_CONCILI12[[#This Row],[CÓD. SAIB]],BASE_DIFERENÇA[],4,0),"0") -> 0 | R52: =BASE_CONCILI12[[#This Row],[30/jun]]-BASE_CONCILI12[[#This Row],[SISTEMA]] -> #REF! | S52: =IFERROR(BASE_CONCILI12[[#This Row],[DIFERENÇA ANTERIOR]]-BASE_CONCILI12[[#This Row],[DIFERENÇA ATUAL]],"-") -> - | T52: =VLOOKUP(BASE_CONCILI12[[#This Row],[CÓD. SAIB]],CUSTO!A:C,3,0) -> 48CB01 | U52: =IFERROR(SUM(BASE_CONCILI12[[#This Row],[DIFERENÇA ATUAL]]*BASE_CONCILI12[[#This Row],[CUSTO MP (UN)]]),0) -> 0 | V52: =IFERROR(BASE_CONCILI12[[#This Row],[30/jun]]/BASE_CONCILI12[[#This Row],[SISTEMA]],"") | W52: =IFERROR(BASE_CONCILI12[[#This Row],[DIFERENÇA MÊS]]*BASE_CONCILI12[[#This Row],[CUSTO MP (UN)]],"-") -> - | X52: OK, SOBRA LOTE ANTIGO - SOLICITAR QUEBRA
A53: 30529 | C53: CONCENTRADO BEBIDAS ENERGETICA FIT | D53: CONCENTRADO | E53: =VLOOKUP(BASE_CONCILI12[[#This Row],[CÓD. SAIB]],CONT_ANTE!A:D,4,0) -> #N/A | F53: =SUMIF(#REF!,BASE_CONCILI12[[#This Row],[CÓD. SAIB]],#REF!) -> #REF! | G53: =SUMIF(#REF!,BASE_CONCILI12[[#This Row],[CÓD. SAIB]],#REF!) -> #REF! | H53: =BASE_CONCILI12[[#This Row],[CONSUMO REAL]]-BASE_CONCILI12[[#This Row],[CONSUMO TEORICO]] -> #REF! | I53: =SUMIF(#REF!,BASE_CONCILI12[[#This Row],[CÓD. SAIB]],#REF!) -> #REF! | J53: =SUMIF(#REF!,BASE_CONCILI12[[#This Row],[CÓD. SAIB]],#REF!) -> #REF! | K53: =BASE_CONCILI12[[#This Row],[30/mai]]+BASE_CONCILI12[[#This Row],[RECEBIMENTO]]-BASE_CONCILI12[[#This Row],[TRANSFERÊNCIA]]-BASE_CONCILI12[[#This Row],[CONSUMO REAL]] -> #N/A | L53: =IFERROR(VLOOKUP(BASE_CONCILI12[[#This Row],[CÓD. SAIB]],BASE_CONTAG[[LAVRE]:[CONTAGEM FINAL]],7,0),0) -> 0 | M53: =IFERROR(SUM(BASE_CONCILI12[[#This Row],[30/jun]]*BASE_CONCILI12[[#This Row],[CUSTO MP (UN)]]),0) -> 0 | N53: =IFERROR(VLOOKUP(BASE_CONCILI12[[#This Row],[CÓD. SAIB]],BASE_CONTAG[],5,0),"") | O53: =SUMIF(SISTEMA!#REF!,BASE_CONCILI12[[#This Row],[CÓD. SAIB]],SISTEMA!#REF!) -> #REF! | P53: =IFERROR(SUM(BASE_CONCILI12[[#This Row],[SISTEMA]]*BASE_CONCILI12[[#This Row],[CUSTO MP (UN)]]),0) -> 0 | Q53: =IFERROR(VLOOKUP(BASE_CONCILI12[[#This Row],[CÓD. SAIB]],BASE_DIFERENÇA[],4,0),"0") -> 0 | R53: =BASE_CONCILI12[[#This Row],[30/jun]]-BASE_CONCILI12[[#This Row],[SISTEMA]] -> #REF! | S53: =IFERROR(BASE_CONCILI12[[#This Row],[DIFERENÇA ANTERIOR]]-BASE_CONCILI12[[#This Row],[DIFERENÇA ATUAL]],"-") -> - | T53: =VLOOKUP(BASE_CONCILI12[[#This Row],[CÓD. SAIB]],CUSTO!A:C,3,0) -> 30529CB01 | U53: =IFERROR(SUM(BASE_CONCILI12[[#This Row],[DIFERENÇA ATUAL]]*BASE_CONCILI12[[#This Row],[CUSTO MP (UN)]]),0) -> 0 | V53: =IFERROR(BASE_CONCILI12[[#This Row],[30/jun]]/BASE_CONCILI12[[#This Row],[SISTEMA]],"") | W53: =IFERROR(BASE_CONCILI12[[#This Row],[DIFERENÇA MÊS]]*BASE_CONCILI12[[#This Row],[CUSTO MP (UN)]],"-") -> - | X53: OK
