Workbook

Sheet ANALISE
A3: Rótulos de Linha | B3: Soma de DIFERENÇA VALOR
A4: ROTULO | B4: -7616644.2
A5: ELABORAÇÃO | B5: -1848261.1
A6: RÓTULO | B6: -1393112.7
A7: FILME | B7: -155369
A8: MALTE | B8: -62468.37
A9: VASILHAME | B9: -19390.82
A10: CERVEJARIA | B10: -11524.321
A11: AÇUCAR | B11: -5345.3953
A12: Insumo Terc. | B12: 0
A13: VINHO | B13: 0
A14: INDUSTRIALIZAÇÃO | B14: 0
A15: LACRE | B15: 4.26173
... A35: Total Geral | B35: 2347321.2

Sheet KPI
B2: VALOR ESTOQUE FÍSICO (MP) | M2: CUSTO (R$) DIVERGÊNCIA (MP)
B3: MÊS | C3: VALOR (R$) | M3: MÊS | N3: VALOR (R$)
B4: JANEIRO | C4: 14484679 | M4: JANEIRO | N4: 118144.18
B5: FEVEREIRO | C5: 13521013 | M5: FEVEREIRO | N5: 267353.14
B6: MARÇO | C6: 14243064 | M6: MARÇO | N6: 281640.56
B7: ABRIL | C7: 12258289 | M7: ABRIL | N7: 206892.35
B8: MAIO | C8: 9350849.2 | M8: MAIO | N8: 85994.001
B9: JUNHO | C9: 8710025.7 | M9: JUNHO | N9: 100512.52
B10: JULHO | M10: JULHO
B11: AGOSTO | M11: AGOSTO
B12: SETEMBRO | M12: SETEMBRO
B13: OUTUBRO | C13: 9786201.2 | M13: OUTUBRO | N13: =C13-C29 -> -823245.49
B14: NOVEMBRO | C14: 11626525 | M14: NOVEMBRO | N14: =C14-C30 -> 47666.517
B15: DEZEMBRO | C15: 11050986 | M15: DEZEMBRO | N15: 55057.669
B16: MÉDIA | C16: =AVERAGE(C4:C15) -> 11670181 | M16: MÉDIA | N16: =AVERAGE(N4:N15) -> 37779.494
B18: VALOR ESTOQUE SISTEMA (MP) | M18: % DIVERGÊNCIA (MP)
B19: MÊS | C19: VALOR (R$) | M19: MÊS | N19: VALOR (R$)
B20: JANEIRO | C20: 14366535 | M20: JANEIRO | N20: 0.0082235682
B21: FEVEREIRO | C21: 13253660 | M21: FEVEREIRO | N21: 0.020172023
B22: MARÇO | C22: 13961423 | M22: MARÇO | N22: 0.020172769
B23: ABRIL | C23: 12051397 | M23: ABRIL | N23: 0.017167499
B24: MAIO | C24: 9264855.2 | M24: MAIO | N24: 0.0092817426
B25: JUNHO | C25: 8609513.2 | M25: JUNHO | N25: 0.011674588
B26: JULHO | M26: JULHO
B27: AGOSTO | M27: AGOSTO
B28: SETEMBRO | M28: SETEMBRO
B29: OUTUBRO | C29: 10609447 | M29: OUTUBRO | N29: =IFERROR(N13/C29,"") -> -0.077595516
B30: NOVEMBRO | C30: 11578858 | M30: NOVEMBRO | N30: =IFERROR(N14/C30,"") -> 0.0041166855
B31: DEZEMBRO | C31: 10995928 | M31: DEZEMBRO | N31: 0.0050070962
B32: MÉDIA | C32: =AVERAGE(C20:C31) -> 11632402 | M32: MÉDIA | N32: =AVERAGE(N20:N31) -> 0.0020244951
B34: VALOR ESTOQUE FÍSICO (PA) | M34: ACURACIDADE QUALITATIVA (MP)
B35: MÊS | C35: VALOR (R$) | M35: MÊS | N35: %
B36: JANEIRO | C36: 2390297.8 | M36: JANEIRO | N36: 0.64661654
B37: FEVEREIRO | C37: 3642342.8 | M37: FEVEREIRO | N37: 0.62737643
B38: MARÇO | C38: 1858028.3 | M38: MARÇO | N38: 0.6627907
B39: ABRIL | C39: 1454970.4 | M39: ABRIL | N39: 0.70342205
B40: MAIO | C40: 1203577.7 | M40: MAIO | N40: 0.73705179
B41: JUNHO | C41: 2240566.9 | M41: JUNHO | N41: 0.74501992
B42: JULHO | M42: JULHO
B43: AGOSTO | M43: AGOSTO
B44: SETEMBRO | M44: SETEMBRO
B45: OUTUBRO | C45: 3036154.1 | M45: OUTUBRO | N45: 0.338
B46: NOVEMBRO | C46: 1835764.6 | M46: NOVEMBRO | N46: 0.60661765
B47: DEZEMBRO | C47: 1838676.7 | M47: DEZEMBRO | N47: 0.61832061
B48: MÉDIA | C48: =AVERAGE(C36:C47) -> 2166708.8 | M48: MÉDIA | N48: =AVERAGE(N36:N47) -> 0.63169063
B50: VALOR ESTOQUE SISTEMA (PA) | M50: CUSTO (R$) DIVERGÊNCIA (PA)
B51: MÊS | C51: VALOR (R$) | M51: MÊS | N51: VALOR (R$)
B52: JANEIRO | C52: 2415675.3 | M52: JANEIRO | N52: -12823.707
B53: FEVEREIRO | C53: 3657759.1 | M53: FEVEREIRO | N53: -15416.318
B54: MARÇO | C54: 1875975.5 | M54: MARÇO | N54: -17947.256
B55: ABRIL | C55: 1472804.5 | M55: ABRIL | N55: -17834.113
B56: MAIO | C56: 1221473.1 | M56: MAIO | N56: -17895.359
B57: JUNHO | C57: 2240114.6 | M57: JUNHO | N57: 452.33174
B58: JULHO | M58: JULHO
B59: AGOSTO | M59: AGOSTO
B60: SETEMBRO | M60: SETEMBRO
B61: OUTUBRO | C61: 3089099.7 | M61: OUTUBRO | N61: -52945.61
B62: NOVEMBRO | C62: 1889315.3 | M62: NOVEMBRO | N62: -53550.63
B63: DEZEMBRO | C63: 1879873.3 | M63: DEZEMBRO | N63: -41196.64
B64: MÉDIA | C64: =AVERAGE(C52:C63) -> 2193565.6 | M64: MÉDIA | N64: =AVERAGE(N52:N63) -> -25461.922
B66: ACURACIDADE QUALITATIVA (PA) | M66: % DIVERGÊNCIA (PA)
B67: MÊS | C67: % | M67: MÊS | N67: VALOR (R$)
B68: JANEIRO | C68: 0.66666667 | M68: JANEIRO | N68: 0.07046603
B69: FEVEREIRO | C69: 0.87058824 | M69: FEVEREIRO | N69: 0.06068542
B70: MARÇO | C70: 0.84810127 | M70: MARÇO | N70: 0.012294521
B71: ABRIL | C71: 0.46099291 | M71: ABRIL | N71: 0.16666667
B72: MAIO | C72: 0.94029851 | M72: MAIO | N72: -0.014650638
B73: JUNHO | C73: 0.91954023 | M73: JUNHO | N73: 0.00020192348
B74: JULHO | M74: JULHO
B75: AGOSTO | M75: AGOSTO
B76: SETEMBRO | M76: SETEMBRO
B77: OUTUBRO | M77: OUTUBRO | N77: -0.0171
B78: NOVEMBRO | M78: NOVEMBRO | N78: 0.7531
B79: DEZEMBRO | M79: DEZEMBRO | N79: 0.1257
B80: MÉDIA | C80: =AVERAGE(C68:C79) -> 0.78436464 | M80: MÉDIA | N80: =AVERAGE(N68:N79) -> 0.12859599

Sheet BASE PRODUTOS
A1: BASE DE CADASTRO TOTVS
A2: Codigo | B2: Descricao | C2: Tipo | D2: Unidade | E2: Fator Conv.
A3: 2000010001 | B3: AT MALDIVES 12X250ML | C3: PA | D3: FD | E3: 12
A4: 2000010002 | B4: REFRIKO COLA 12X200ML | C4: PA | D4: FD | E4: 12
A5: 2000010003 | B5: REFRIKO COLA 12X500ML | C5: PA | D5: FD | E5: 12
A6: 2000010004 | B6: REFRIKO COLA 4X3LT | C6: PA | D6: FD | E6: 4
A7: 2000010005 | B7: REFRIKO COLA 6X2LT | C7: PA | D7: FD | E7: 6
A8: 2000010006 | B8: REFRIKO COLA 6X350ML | C8: PA | D8: FD | E8: 6
A9: 2000010007 | B9: REFRIKO FRAMBOESA 6X2LT | C9: PA | D9: FD | E9: 6
A10: 2000010008 | B10: REFRIKO GUARANA 12X200ML | C10: PA | D10: FD | E10: 12
A11: 2000010009 | B11: REFRIKO GUARANA 12X500ML | C11: PA | D11: FD | E11: 12
A12: 2000010010 | B12: REFRIKO GUARANA 24X600ML - RET | C12: PA | D12: CX | E12: 24
A13: 2000010011 | B13: REFRIKO GUARANA 4X3LT | C13: PA | D13: FD | E13: 4
A14: 2000010012 | B14: REFRIKO GUARANA 6X2LT | C14: PA | D14: FD | E14: 6
... A13198: 9999990006 | B13198: REEMBOLSO DE VIAGEM | C13198: OU | D13198: UN | E13198: 0
A13199: FL03040001 | B13199: FILTRO DE PAPEL MELITTA | C13199: MC | D13199: UN | E13199: 0
A13200: 2701010044 | B13200: ROTULO SLEEVE FURIOSO TANGERINA E LIMAO ZERO 473ML | E13200: 0.0020921

Sheet CONCILIÇÃO_COM_CERVEJA
M1: Valor Estoque Físico | Q1: Valor Estoque Sistema | V1: Acuracidade Qualitativa | W1: Custo Diferença | X1: Percentual Diferença | Y1: Acuracidade
M2: =SUBTOTAL(9,N5:N1048576) -> 13706820 | Q2: =SUBTOTAL(9,CONCILIÇÃO_COM_CERVEJA!$R$5:$R$373) -> 13592060 | V2: =(COUNTIF(CONCILIÇÃO_COM_CERVEJA!$M$5:$M$373,">0")-COUNTIF(CONCILIÇÃO_COM_CERVEJA!$X$5:$X$373,">1,05")-COUNTIF(CONCILIÇÃO_COM_CERVEJA!$X$5:$X$373,"<0,95"))/COUNTIF(CONCILIÇÃO_COM_CERVEJA!$M$5:$M$373,">0") -> -0.053497942 | W2: =SUBTOTAL(9,W5:W1048576) -> 114759.67 | X2: =W2/Q2 -> 0.0084431405 | Y2: =1-X2 -> 0.99155686
A4: CÓD. PRODUTO | B4: CODIGO NOVO | C4: DESCRIÇÃO | D4: Estoque Inicial | E4: Total de entrada | F4: Consumo total mês 8 (RxS) | G4: Total saidas | H4: Teorico Final | I4: CLASSE | J4: Fator Conv. | K4: 46265 | L4: ? | M4: Contagem | N4: CUSTO FISICO | O4: SIST COD KG | P4: SIST COD UND | Q4: SALDO SISTEMA TOTAL | R4: CUSTO SISTEMA | S4: DIFERENÇA ANTERIOR | T4: Diferença atual | U4: Diveregencia mês anterior | V4: CUSTO MP (UN) | W4: CUSTO DIVERGÊNCIA | X4: ACURACIDADE | Y4: DIFERENÇA VALOR | Z4: OBS
A5: 2701080001 | B5: - | C5: ACUCAR CRISTAL | D5: 63047.67 | E5: =IFERROR(IFERROR(VLOOKUP(B5,[1]Planilha1!$A$4:$C$277,3,0),VLOOKUP(A5,[1]Planilha1!$A$4:$C$277,3,0)),0) -> 229233.29 | F5: =IFERROR(IFERROR(VLOOKUP(A5,[2]Planilha1!$A$4:$C$258,3,0),VLOOKUP(B5,[2]Planilha1!$A$4:$C$258,3,0)),0) -> 165059.43 | G5: =IFERROR(IFERROR(VLOOKUP(A5,[1]Planilha1!$A$4:$D$277,4,0),VLOOKUP(B5,[1]Planilha1!$A$4:$D$277,4,0)),0) -> 230063.25 | H5: =D5+E5-G5 -> 62217.709 | I5: AÇUCAR | J5: 1 | K5: =VLOOKUP(A5,CONT_ANTE!A:D,4,0) -> 55200 | L5: =IF(AND(F5=0,K5<>M5),"!@##@!","ok") -> ok | M5: =IFERROR(VLOOKUP(A5,CONTAGEM!B:G,6,0),VLOOKUP(B5,CONTAGEM!B:G,6,0)) -> 50000 | N5: =IFERROR(SUM(M5*V5),0) -> 90292.635 | O5: =SUMIF(SISTEMA!B:B,A5,SISTEMA!I:I)/J5 -> 76826.709 | P5: =SUMIF(SISTEMA!B:B,B5,SISTEMA!I:I) -> 0 | Q5: =O5+P5 -> 76826.709 | R5: =IFERROR(SUM(Q5*V5),0) -> 138737.72 | S5: =IFERROR(VLOOKUP(A5,DIF_ANTE!A:D,4,0),"0")/J5 -> -7847.67 | T5: =M5-Q5 -> -26826.709 | U5: =T5-S5 -> -18979.039 | V5: =IFERROR(VLOOKUP(A5,CUSTO!A:C,3,0),VLOOKUP(B5,CUSTO!A:C,3,0)) -> 1.8058527 | W5: =IFERROR(SUM(T5*V5),0) -> -48445.086 | X5: =IFERROR(T5/Q5,"") -> -0.34918467 | Y5: =IFERROR(U5*V5,"-") -> -34273.35 | Z5: ok
A6: 2701170002 | B6: - | C6: ETANOL NEUTRO ALCOOL ETILICO POTAVEL 96° | D6: 65761 | E6: =IFERROR(IFERROR(VLOOKUP(B6,[1]Planilha1!$A$4:$C$277,3,0),VLOOKUP(A6,[1]Planilha1!$A$4:$C$277,3,0)),0) -> 45000 | F6: =IFERROR(IFERROR(VLOOKUP(A6,[2]Planilha1!$A$4:$C$258,3,0),VLOOKUP(B6,[2]Planilha1!$A$4:$C$258,3,0)),0) -> 52758 | G6: =IFERROR(IFERROR(VLOOKUP(A6,[1]Planilha1!$A$4:$D$277,4,0),VLOOKUP(B6,[1]Planilha1!$A$4:$D$277,4,0)),0) -> 52758 | H6: =D6+E6-G6 -> 58003 | I6: ALCOOL | J6: 1 | K6: =VLOOKUP(A6,CONT_ANTE!A:D,4,0) -> 52674 | L6: =IF(AND(F6=0,K6<>M6),"!@##@!","ok") -> ok | M6: =IFERROR(VLOOKUP(A6,CONTAGEM!B:G,6,0),VLOOKUP(B6,CONTAGEM!B:G,6,0)) -> 45000 | N6: =IFERROR(SUM(M6*V6),0) -> 169254.89 | O6: =SUMIF(SISTEMA!B:B,A6,SISTEMA!I:I)/J6 -> 46744 | P6: =SUMIF(SISTEMA!B:B,B6,SISTEMA!I:I) -> 0 | Q6: =O6+P6 -> 46744 | R6: =IFERROR(SUM(Q6*V6),0) -> 175814.46 | S6: =IFERROR(VLOOKUP(A6,DIF_ANTE!A:D,4,0),"0")/J6 -> -13087 | T6: =M6-Q6 -> -1744 | U6: =T6-S6 -> 11343 | V6: =IFERROR(VLOOKUP(A6,CUSTO!A:C,3,0),VLOOKUP(B6,CUSTO!A:C,3,0)) -> 3.7612199 | W6: =IFERROR(SUM(T6*V6),0) -> -6559.5674 | X6: =IFERROR(T6/Q6,"") -> -0.037309601 | Y6: =IFERROR(U6*V6,"-") -> 42663.517 | Z6: ok
A7: 2701050004 | B7: - | C7: AROMA ARTIFICIAL ENERGY SYMRISE | D7: 0 | E7: =IFERROR(IFERROR(VLOOKUP(B7,[1]Planilha1!$A$4:$C$277,3,0),VLOOKUP(A7,[1]Planilha1!$A$4:$C$277,3,0)),0) -> 0 | F7: =IFERROR(IFERROR(VLOOKUP(A7,[2]Planilha1!$A$4:$C$258,3,0),VLOOKUP(B7,[2]Planilha1!$A$4:$C$258,3,0)),0) -> 0 | G7: =IFERROR(IFERROR(VLOOKUP(A7,[1]Planilha1!$A$4:$D$277,4,0),VLOOKUP(B7,[1]Planilha1!$A$4:$D$277,4,0)),0) -> 0 | H7: =D7+E7-G7 -> 0 | I7: AROMA | J7: 1 | K7: =VLOOKUP(A7,CONT_ANTE!A:D,4,0) -> 0 | L7: =IF(AND(F7=0,K7<>M7),"!@##@!","ok") -> ok | M7: =IFERROR(VLOOKUP(A7,CONTAGEM!B:G,6,0),VLOOKUP(B7,CONTAGEM!B:G,6,0)) -> 0 | N7: =IFERROR(SUM(M7*V7),0) -> 0 | O7: =SUMIF(SISTEMA!B:B,A7,SISTEMA!I:I)/J7 -> 0 | P7: =SUMIF(SISTEMA!B:B,B7,SISTEMA!I:I) -> 0 | Q7: =O7+P7 -> 0 | R7: =IFERROR(SUM(Q7*V7),0) -> 0 | S7: =IFERROR(VLOOKUP(A7,DIF_ANTE!A:D,4,0),"0")/J7 -> 0 | T7: =M7-Q7 -> 0 | U7: =T7-S7 -> 0 | V7: =IFERROR(VLOOKUP(A7,CUSTO!A:C,3,0),VLOOKUP(B7,CUSTO!A:C,3,0)) -> 103.63169 | W7: =IFERROR(SUM(T7*V7),0) -> 0 | X7: =IFERROR(T7/Q7,"") | Y7: =IFERROR(U7*V7,"-") -> 0 | Z7: ok
A8: 2701050008 | B8: - | C8: AROMA ARTIFICIAL FRUTAS TROPICAIS MONARCH | D8: 241.65 | E8: =IFERROR(IFERROR(VLOOKUP(B8,[1]Planilha1!$A$4:$C$277,3,0),VLOOKUP(A8,[1]Planilha1!$A$4:$C$277,3,0)),0) -> 0 | F8: =IFERROR(IFERROR(VLOOKUP(A8,[2]Planilha1!$A$4:$C$258,3,0),VLOOKUP(B8,[2]Planilha1!$A$4:$C$258,3,0)),0) -> 112.73 | G8: =IFERROR(IFERROR(VLOOKUP(A8,[1]Planilha1!$A$4:$D$277,4,0),VLOOKUP(B8,[1]Planilha1!$A$4:$D$277,4,0)),0) -> 112.73 | H8: =D8+E8-G8 -> 128.92 | I8: AROMA | J8: 1 | K8: =VLOOKUP(A8,CONT_ANTE!A:D,4,0) -> 240 | L8: =IF(AND(F8=0,K8<>M8),"!@##@!","ok") -> ok | M8: =IFERROR(VLOOKUP(A8,CONTAGEM!B:G,6,0),VLOOKUP(B8,CONTAGEM!B:G,6,0)) -> 142.5 | N8: =IFERROR(SUM(M8*V8),0) -> 17987.775 | O8: =SUMIF(SISTEMA!B:B,A8,SISTEMA!I:I)/J8 -> 128.92 | P8: =SUMIF(SISTEMA!B:B,B8,SISTEMA!I:I) -> 0 | Q8: =O8+P8 -> 128.92 | R8: =IFERROR(SUM(Q8*V8),0) -> 16273.572 | S8: =IFERROR(VLOOKUP(A8,DIF_ANTE!A:D,4,0),"0")/J8 -> -1.65 | T8: =M8-Q8 -> 13.58 | U8: =T8-S8 -> 15.23 | V8: =IFERROR(VLOOKUP(A8,CUSTO!A:C,3,0),VLOOKUP(B8,CUSTO!A:C,3,0)) -> 126.23 | W8: =IFERROR(SUM(T8*V8),0) -> 1714.2034 | X8: =IFERROR(T8/Q8,"") -> 0.10533664 | Y8: =IFERROR(U8*V8,"-") -> 1922.4829 | Z8: ok
A9: 2701050009 | B9: - | C9: AROMA ARTIFICIAL GUARANA DUAS RODAS | D9: 0 | E9: =IFERROR(IFERROR(VLOOKUP(B9,[1]Planilha1!$A$4:$C$277,3,0),VLOOKUP(A9,[1]Planilha1!$A$4:$C$277,3,0)),0) -> 0 | F9: =IFERROR(IFERROR(VLOOKUP(A9,[2]Planilha1!$A$4:$C$258,3,0),VLOOKUP(B9,[2]Planilha1!$A$4:$C$258,3,0)),0) -> 0 | G9: =IFERROR(IFERROR(VLOOKUP(A9,[1]Planilha1!$A$4:$D$277,4,0),VLOOKUP(B9,[1]Planilha1!$A$4:$D$277,4,0)),0) -> 0 | H9: =D9+E9-G9 -> 0 | I9: AROMA | J9: 1 | K9: =VLOOKUP(A9,CONT_ANTE!A:D,4,0) -> 0 | L9: =IF(AND(F9=0,K9<>M9),"!@##@!","ok") -> ok | M9: =IFERROR(VLOOKUP(A9,CONTAGEM!B:G,6,0),VLOOKUP(B9,CONTAGEM!B:G,6,0)) -> 0 | N9: =IFERROR(SUM(M9*V9),0) -> 0 | O9: =SUMIF(SISTEMA!B:B,A9,SISTEMA!I:I)/J9 -> 0 | P9: =SUMIF(SISTEMA!B:B,B9,SISTEMA!I:I) -> 0 | Q9: =O9+P9 -> 0 | R9: =IFERROR(SUM(Q9*V9),0) -> 0 | S9: =IFERROR(VLOOKUP(A9,DIF_ANTE!A:D,4,0),"0")/J9 -> 0 | T9: =M9-Q9 -> 0 | U9: =T9-S9 -> 0 | V9: =IFERROR(VLOOKUP(A9,CUSTO!A:C,3,0),VLOOKUP(B9,CUSTO!A:C,3,0)) -> 49.614813 | W9: =IFERROR(SUM(T9*V9),0) -> 0 | X9: =IFERROR(T9/Q9,"") | Y9: =IFERROR(U9*V9,"-") -> 0 | Z9: ok
A10: 2701050035 | B10: - | C10: AROMA ARTIFICIAL GUARANA IFB | D10: 812.43 | E10: =IFERROR(IFERROR(VLOOKUP(B10,[1]Planilha1!$A$4:$C$277,3,0),VLOOKUP(A10,[1]Planilha1!$A$4:$C$277,3,0)),0) -> 0 | F10: =IFERROR(IFERROR(VLOOKUP(A10,[2]Planilha1!$A$4:$C$258,3,0),VLOOKUP(B10,[2]Planilha1!$A$4:$C$258,3,0)),0) -> 92.43 | G10: =IFERROR(IFERROR(VLOOKUP(A10,[1]Planilha1!$A$4:$D$277,4,0),VLOOKUP(B10,[1]Planilha1!$A$4:$D$277,4,0)),0) -> 77.52 | H10: =D10+E10-G10 -> 734.91 | I10: AROMA | J10: 1 | K10: =VLOOKUP(A10,CONT_ANTE!A:D,4,0) -> 797 | L10: =IF(AND(F10=0,K10<>M10),"!@##@!","ok") -> ok | M10: =IFERROR(VLOOKUP(A10,CONTAGEM!B:G,6,0),VLOOKUP(B10,CONTAGEM!B:G,6,0)) -> 720 | N10: =IFERROR(SUM(M10*V10),0) -> 27129.6 | O10: =SUMIF(SISTEMA!B:B,A10,SISTEMA!I:I)/J10 -> 734.91 | P10: =SUMIF(SISTEMA!B:B,B10,SISTEMA!I:I) -> 0 | Q10: =O10+P10 -> 734.91 | R10: =IFERROR(SUM(Q10*V10),0) -> 27691.409 | S10: =IFERROR(VLOOKUP(A10,DIF_ANTE!A:D,4,0),"0")/J10 -> -15.43 | T10: =M10-Q10 -> -14.91 | U10: =T10-S10 -> 0.52 | V10: =IFERROR(VLOOKUP(A10,CUSTO!A:C,3,0),VLOOKUP(B10,CUSTO!A:C,3,0)) -> 37.68 | W10: =IFERROR(SUM(T10*V10),0) -> -561.8088 | X10: =IFERROR(T10/Q10,"") -> -0.020288199 | Y10: =IFERROR(U10*V10,"-") -> 19.5936 | Z10: OK
A11: 2701050017 | B11: - | C11: AROMA ARTIFICIAL MELANCIA DUAS RODAS | D11: 204.1 | E11: =IFERROR(IFERROR(VLOOKUP(B11,[1]Planilha1!$A$4:$C$277,3,0),VLOOKUP(A11,[1]Planilha1!$A$4:$C$277,3,0)),0) -> 500 | F11: =IFERROR(IFERROR(VLOOKUP(A11,[2]Planilha1!$A$4:$C$258,3,0),VLOOKUP(B11,[2]Planilha1!$A$4:$C$258,3,0)),0) -> 150.54 | G11: =IFERROR(IFERROR(VLOOKUP(A11,[1]Planilha1!$A$4:$D$277,4,0),VLOOKUP(B11,[1]Planilha1!$A$4:$D$277,4,0)),0) -> 550.54 | H11: =D11+E11-G11 -> 153.56 | I11: AROMA | J11: 1 | K11: =VLOOKUP(A11,CONT_ANTE!A:D,4,0) -> 184 | L11: =IF(AND(F11=0,K11<>M11),"!@##@!","ok") -> ok | M11: =IFERROR(VLOOKUP(A11,CONTAGEM!B:G,6,0),VLOOKUP(B11,CONTAGEM!B:G,6,0)) -> 130 | N11: =IFERROR(SUM(M11*V11),0) -> 4078.399 | O11: =SUMIF(SISTEMA!B:B,A11,SISTEMA!I:I)/J11 -> 153.56 | P11: =SUMIF(SISTEMA!B:B,B11,SISTEMA!I:I) -> 0 | Q11: =O11+P11 -> 153.56 | R11: =IFERROR(SUM(Q11*V11),0) -> 4817.5304 | S11: =IFERROR(VLOOKUP(A11,DIF_ANTE!A:D,4,0),"0")/J11 -> -20.1 | T11: =M11-Q11 -> -23.56 | U11: =T11-S11 -> -3.46 | V11: =IFERROR(VLOOKUP(A11,CUSTO!A:C,3,0),VLOOKUP(B11,CUSTO!A:C,3,0)) -> 31.3723 | W11: =IFERROR(SUM(T11*V11),0) -> -739.13139 | X11: =IFERROR(T11/Q11,"") -> -0.15342537 | Y11: =IFERROR(U11*V11,"-") -> -108.54816 | Z11: OK, PERDA
A12: 2701050006 | B12: - | C12: AROMA IDENTICO AO NATURAL BLUEBERRY KALABROS | D12: 0 | E12: =IFERROR(IFERROR(VLOOKUP(B12,[1]Planilha1!$A$4:$C$277,3,0),VLOOKUP(A12,[1]Planilha1!$A$4:$C$277,3,0)),0) -> 0 | F12: =IFERROR(IFERROR(VLOOKUP(A12,[2]Planilha1!$A$4:$C$258,3,0),VLOOKUP(B12,[2]Planilha1!$A$4:$C$258,3,0)),0) -> 0 | G12: =IFERROR(IFERROR(VLOOKUP(A12,[1]Planilha1!$A$4:$D$277,4,0),VLOOKUP(B12,[1]Planilha1!$A$4:$D$277,4,0)),0) -> 0 | H12: =D12+E12-G12 -> 0 | I12: AROMA | J12: 1 | K12: =VLOOKUP(A12,CONT_ANTE!A:D,4,0) -> 0 | L12: =IF(AND(F12=0,K12<>M12),"!@##@!","ok") -> ok | M12: =IFERROR(VLOOKUP(A12,CONTAGEM!B:G,6,0),VLOOKUP(B12,CONTAGEM!B:G,6,0)) -> 0 | N12: =IFERROR(SUM(M12*V12),0) -> 0 | O12: =SUMIF(SISTEMA!B:B,A12,SISTEMA!I:I)/J12 -> 0 | P12: =SUMIF(SISTEMA!B:B,B12,SISTEMA!I:I) -> 0 | Q12: =O12+P12 -> 0 | R12: =IFERROR(SUM(Q12*V12),0) -> 0 | S12: =IFERROR(VLOOKUP(A12,DIF_ANTE!A:D,4,0),"0")/J12 -> 0 | T12: =M12-Q12 -> 0 | U12: =T12-S12 -> 0 | V12: =IFERROR(VLOOKUP(A12,CUSTO!A:C,3,0),VLOOKUP(B12,CUSTO!A:C,3,0)) -> 45.981938 | W12: =IFERROR(SUM(T12*V12),0) -> 0 | X12: =IFERROR(T12/Q12,"") | Y12: =IFERROR(U12*V12,"-") -> 0 | Z12: ok
A13: 2701050029 | B13: - | C13: AROMA IDENTICO AO NATURAL CLOUDING LEMON | D13: 0 | E13: =IFERROR(IFERROR(VLOOKUP(B13,[1]Planilha1!$A$4:$C$277,3,0),VLOOKUP(A13,[1]Planilha1!$A$4:$C$277,3,0)),0) -> 0 | F13: =IFERROR(IFERROR(VLOOKUP(A13,[2]Planilha1!$A$4:$C$258,3,0),VLOOKUP(B13,[2]Planilha1!$A$4:$C$258,3,0)),0) -> 0 | G13: =IFERROR(IFERROR(VLOOKUP(A13,[1]Planilha1!$A$4:$D$277,4,0),VLOOKUP(B13,[1]Planilha1!$A$4:$D$277,4,0)),0) -> 0 | H13: =D13+E13-G13 -> 0 | I13: AROMA | J13: 1 | K13: =VLOOKUP(A13,CONT_ANTE!A:D,4,0) -> 0 | L13: =IF(AND(F13=0,K13<>M13),"!@##@!","ok") -> ok | M13: =IFERROR(VLOOKUP(A13,CONTAGEM!B:G,6,0),VLOOKUP(B13,CONTAGEM!B:G,6,0)) -> 0 | N13: =IFERROR(SUM(M13*V13),0) -> 0 | O13: =SUMIF(SISTEMA!B:B,A13,SISTEMA!I:I)/J13 -> 0 | P13: =SUMIF(SISTEMA!B:B,B13,SISTEMA!I:I) -> 0 | Q13: =O13+P13 -> 0 | R13: =IFERROR(SUM(Q13*V13),0) -> 0 | S13: =IFERROR(VLOOKUP(A13,DIF_ANTE!A:D,4,0),"0")/J13 -> 0 | T13: =M13-Q13 -> 0 | U13: =T13-S13 -> 0 | V13: =IFERROR(VLOOKUP(A13,CUSTO!A:C,3,0),VLOOKUP(B13,CUSTO!A:C,3,0)) -> 3.726875 | W13: =IFERROR(SUM(T13*V13),0) -> 0 | X13: =IFERROR(T13/Q13,"") | Y13: =IFERROR(U13*V13,"-") -> 0 | Z13: ok
A14: 2701050010 | B14: - | C14: AROMA IDENTICO AO NATURAL DE LARANJA | D14: 15.31 | E14: =IFERROR(IFERROR(VLOOKUP(B14,[1]Planilha1!$A$4:$C$277,3,0),VLOOKUP(A14,[1]Planilha1!$A$4:$C$277,3,0)),0) -> 0 | F14: =IFERROR(IFERROR(VLOOKUP(A14,[2]Planilha1!$A$4:$C$258,3,0),VLOOKUP(B14,[2]Planilha1!$A$4:$C$258,3,0)),0) -> 7.09 | G14: =IFERROR(IFERROR(VLOOKUP(A14,[1]Planilha1!$A$4:$D$277,4,0),VLOOKUP(B14,[1]Planilha1!$A$4:$D$277,4,0)),0) -> 7.09 | H14: =D14+E14-G14 -> 8.22 | I14: AROMA | J14: 1 | K14: =VLOOKUP(A14,CONT_ANTE!A:D,4,0) -> 14.5 | L14: =IF(AND(F14=0,K14<>M14),"!@##@!","ok") -> ok | M14: 11 | N14: =IFERROR(SUM(M14*V14),0) -> 660.77733 | O14: =SUMIF(SISTEMA!B:B,A14,SISTEMA!I:I)/J14 -> 9 | P14: =SUMIF(SISTEMA!B:B,B14,SISTEMA!I:I) -> 0 | Q14: =O14+P14 -> 9 | R14: =IFERROR(SUM(Q14*V14),0) -> 540.636 | S14: =IFERROR(VLOOKUP(A14,DIF_ANTE!A:D,4,0),"0")/J14 -> -0.81 | T14: =M14-Q14 -> 2 | U14: =T14-S14 -> 2.81 | V14: =IFERROR(VLOOKUP(A14,CUSTO!A:C,3,0),VLOOKUP(B14,CUSTO!A:C,3,0)) -> 60.070667 | W14: =IFERROR(SUM(T14*V14),0) -> 120.14133 | X14: =IFERROR(T14/Q14,"") -> 0.22222222 | Y14: =IFERROR(U14*V14,"-") -> 168.79857 | Z14: OK
A15: 2701050011 | B15: - | C15: AROMA IDENTICO AO NATURAL DE LIMAO 41 SAPORITI | D15: 77.91 | E15: =IFERROR(IFERROR(VLOOKUP(B15,[1]Planilha1!$A$4:$C$277,3,0),VLOOKUP(A15,[1]Planilha1!$A$4:$C$277,3,0)),0) -> 0 | F15: =IFERROR(IFERROR(VLOOKUP(A15,[2]Planilha1!$A$4:$C$258,3,0),VLOOKUP(B15,[2]Planilha1!$A$4:$C$258,3,0)),0) -> 30.31 | G15: =IFERROR(IFERROR(VLOOKUP(A15,[1]Planilha1!$A$4:$D$277,4,0),VLOOKUP(B15,[1]Planilha1!$A$4:$D$277,4,0)),0) -> 30.31 | H15: =D15+E15-G15 -> 47.6 | I15: AROMA | J15: 1 | K15: =VLOOKUP(A15,CONT_ANTE!A:D,4,0) -> 61.5 | L15: =IF(AND(F15=0,K15<>M15),"!@##@!","ok") -> ok | M15: =IFERROR(VLOOKUP(A15,CONTAGEM!B:G,6,0),VLOOKUP(B15,CONTAGEM!B:G,6,0)) -> 37.6 | N15: =IFERROR(SUM(M15*V15),0) -> 1523.2073 | O15: =SUMIF(SISTEMA!B:B,A15,SISTEMA!I:I)/J15 -> 61.18 | P15: =SUMIF(SISTEMA!B:B,B15,SISTEMA!I:I) -> 0 | Q15: =O15+P15 -> 61.18 | R15: =IFERROR(SUM(Q15*V15),0) -> 2478.4528 | S15: =IFERROR(VLOOKUP(A15,DIF_ANTE!A:D,4,0),"0")/J15 -> -16.41 | T15: =M15-Q15 -> -23.58 | U15: =T15-S15 -> -7.17 | V15: =IFERROR(VLOOKUP(A15,CUSTO!A:C,3,0),VLOOKUP(B15,CUSTO!A:C,3,0)) -> 40.510833 | W15: =IFERROR(SUM(T15*V15),0) -> -955.24545 | X15: =IFERROR(T15/Q15,"") -> -0.38542007 | Y15: =IFERROR(U15*V15,"-") -> -290.46268 | Z15: OK, PERDA
A16: 2701050027 | B16: - | C16: AROMA IDENTICO AO NATURAL DE UVA SAPORITI | D16: 123.51 | E16: =IFERROR(IFERROR(VLOOKUP(B16,[1]Planilha1!$A$4:$C$277,3,0),VLOOKUP(A16,[1]Planilha1!$A$4:$C$277,3,0)),0) -> 0 | F16: =IFERROR(IFERROR(VLOOKUP(A16,[2]Planilha1!$A$4:$C$258,3,0),VLOOKUP(B16,[2]Planilha1!$A$4:$C$258,3,0)),0) -> 102.34 | G16: =IFERROR(IFERROR(VLOOKUP(A16,[1]Planilha1!$A$4:$D$277,4,0),VLOOKUP(B16,[1]Planilha1!$A$4:$D$277,4,0)),0) -> 102.34 | H16: =D16+E16-G16 -> 21.17 | I16: AROMA | J16: 1 | K16: =VLOOKUP(A16,CONT_ANTE!A:D,4,0) -> 113 | L16: =IF(AND(F16=0,K16<>M16),"!@##@!","ok") -> ok | M16: =IFERROR(VLOOKUP(A16,CONTAGEM!B:G,6,0),VLOOKUP(B16,CONTAGEM!B:G,6,0)) -> 72 | N16: =IFERROR(SUM(M16*V16),0) -> 1701.456 | O16: =SUMIF(SISTEMA!B:B,A16,SISTEMA!I:I)/J16 -> 72 | P16: =SUMIF(SISTEMA!B:B,B16,SISTEMA!I:I) -> 0 | Q16: =O16+P16 -> 72 | R16: =IFERROR(SUM(Q16*V16),0) -> 1701.456 | S16: =IFERROR(VLOOKUP(A16,DIF_ANTE!A:D,4,0),"0")/J16 -> -10.51 | T16: =M16-Q16 -> 0 | U16: =T16-S16 -> 10.51 | V16: =IFERROR(VLOOKUP(A16,CUSTO!A:C,3,0),VLOOKUP(B16,CUSTO!A:C,3,0)) -> 23.631333 | W16: =IFERROR(SUM(T16*V16),0) -> 0 | X16: =IFERROR(T16/Q16,"") -> 0 | Y16: =IFERROR(U16*V16,"-") -> 248.36531 | Z16: OK
A17: 2701050033 | B17: - | C17: AROMA IDENTICO AO NATURAL DE UVA VERDE SAPORITI | D17: 135.28 | E17: =IFERROR(IFERROR(VLOOKUP(B17,[1]Planilha1!$A$4:$C$277,3,0),VLOOKUP(A17,[1]Planilha1!$A$4:$C$277,3,0)),0) -> 108 | F17: =IFERROR(IFERROR(VLOOKUP(A17,[2]Planilha1!$A$4:$C$258,3,0),VLOOKUP(B17,[2]Planilha1!$A$4:$C$258,3,0)),0) -> 45.28 | G17: =IFERROR(IFERROR(VLOOKUP(A17,[1]Planilha1!$A$4:$D$277,4,0),VLOOKUP(B17,[1]Planilha1!$A$4:$D$277,4,0)),0) -> 147.09 | H17: =D17+E17-G17 -> 96.19 | I17: AROMA | J17: 1 | K17: =VLOOKUP(A17,CONT_ANTE!A:D,4,0) -> 129.5 | L17: =IF(AND(F17=0,K17<>M17),"!@##@!","ok") -> ok | M17: =IFERROR(VLOOKUP(A17,CONTAGEM!B:G,6,0),VLOOKUP(B17,CONTAGEM!B:G,6,0)) -> 90 | N17: =IFERROR(SUM(M17*V17),0) -> 8431.975 | O17: =SUMIF(SISTEMA!B:B,A17,SISTEMA!I:I)/J17 -> 96.19 | P17: =SUMIF(SISTEMA!B:B,B17,SISTEMA!I:I) -> 0 | Q17: =O17+P17 -> 96.19 | R17: =IFERROR(SUM(Q17*V17),0) -> 9011.9075 | S17: =IFERROR(VLOOKUP(A17,DIF_ANTE!A:D,4,0),"0")/J17 -> -5.78 | T17: =M17-Q17 -> -6.19 | U17: =T17-S17 -> -0.41 | V17: =IFERROR(VLOOKUP(A17,CUSTO!A:C,3,0),VLOOKUP(B17,CUSTO!A:C,3,0)) -> 93.688611 | W17: =IFERROR(SUM(T17*V17),0) -> -579.9325 | X17: =IFERROR(T17/Q17,"") -> -0.064351804 | Y17: =IFERROR(U17*V17,"-") -> -38.412331 | Z17: OK, PERDA
A18: 2701050013 | B18: - | C18: AROMA IDENTICO AO NATURAL MACA VERDE DUAS RODAS | D18: 104.392 | E18: =IFERROR(IFERROR(VLOOKUP(B18,[1]Planilha1!$A$4:$C$277,3,0),VLOOKUP(A18,[1]Planilha1!$A$4:$C$277,3,0)),0) -> 306 | F18: =IFERROR(IFERROR(VLOOKUP(A18,[2]Planilha1!$A$4:$C$258,3,0),VLOOKUP(B18,[2]Planilha1!$A$4:$C$258,3,0)),0) -> 54.01 | G18: =IFERROR(IFERROR(VLOOKUP(A18,[1]Planilha1!$A$4:$D$277,4,0),VLOOKUP(B18,[1]Planilha1!$A$4:$D$277,4,0)),0) -> 258.01 | H18: =D18+E18-G18 -> 152.382 | I18: AROMA | J18: 1 | K18: =VLOOKUP(A18,CONT_ANTE!A:D,4,0) -> 98 | L18: =IF(AND(F18=0,K18<>M18),"!@##@!","ok") -> ok | M18: =IFERROR(VLOOKUP(A18,CONTAGEM!B:G,6,0),VLOOKUP(B18,CONTAGEM!B:G,6,0)) -> 155 | N18: =IFERROR(SUM(M18*V18),0) -> 6336.1994 | O18: =SUMIF(SISTEMA!B:B,A18,SISTEMA!I:I)/J18 -> 152.382 | P18: =SUMIF(SISTEMA!B:B,B18,SISTEMA!I:I) -> 0 | Q18: =O18+P18 -> 152.382 | R18: =IFERROR(SUM(Q18*V18),0) -> 6229.179 | S18: =IFERROR(VLOOKUP(A18,DIF_ANTE!A:D,4,0),"0")/J18 -> -6.392 | T18: =M18-Q18 -> 2.618 | U18: =T18-S18 -> 9.01 | V18: =IFERROR(VLOOKUP(A18,CUSTO!A:C,3,0),VLOOKUP(B18,CUSTO!A:C,3,0)) -> 40.878706 | W18: =IFERROR(SUM(T18*V18),0) -> 107.02045 | X18: =IFERROR(T18/Q18,"") -> 0.017180507 | Y18: =IFERROR(U18*V18,"-") -> 368.31714 | Z18: OK
A19: 2701050014 | B19: - | C19: AROMA IDENTICO AO NATURAL MANGA HS 25409 SAPORITI | D19: 0 | E19: =IFERROR(IFERROR(VLOOKUP(B19,[1]Planilha1!$A$4:$C$277,3,0),VLOOKUP(A19,[1]Planilha1!$A$4:$C$277,3,0)),0) -> 0 | F19: =IFERROR(IFERROR(VLOOKUP(A19,[2]Planilha1!$A$4:$C$258,3,0),VLOOKUP(B19,[2]Planilha1!$A$4:$C$258,3,0)),0) -> 0 | G19: =IFERROR(IFERROR(VLOOKUP(A19,[1]Planilha1!$A$4:$D$277,4,0),VLOOKUP(B19,[1]Planilha1!$A$4:$D$277,4,0)),0) -> 0 | H19: =D19+E19-G19 -> 0 | I19: AROMA | J19: 1 | K19: =VLOOKUP(A19,CONT_ANTE!A:D,4,0) -> 0 | L19: =IF(AND(F19=0,K19<>M19),"!@##@!","ok") -> ok | M19: =IFERROR(VLOOKUP(A19,CONTAGEM!B:G,6,0),VLOOKUP(B19,CONTAGEM!B:G,6,0)) -> 0 | N19: =IFERROR(SUM(M19*V19),0) -> 0 | O19: =SUMIF(SISTEMA!B:B,A19,SISTEMA!I:I)/J19 -> 0 | P19: =SUMIF(SISTEMA!B:B,B19,SISTEMA!I:I) -> 0 | Q19: =O19+P19 -> 0 | R19: =IFERROR(SUM(Q19*V19),0) -> 0 | S19: =IFERROR(VLOOKUP(A19,DIF_ANTE!A:D,4,0),"0")/J19 -> 0 | T19: =M19-Q19 -> 0 | U19: =T19-S19 -> 0 | V19: =IFERROR(VLOOKUP(A19,CUSTO!A:C,3,0),VLOOKUP(B19,CUSTO!A:C,3,0)) -> 3.726875 | W19: =IFERROR(SUM(T19*V19),0) -> 0 | X19: =IFERROR(T19/Q19,"") | Y19: =IFERROR(U19*V19,"-") -> 0 | Z19: OK
A20: 2701050015 | B20: - | C20: AROMA IDENTICO AO NATURAL MARACUJA DUAS RODAS | D20: 0.535 | E20: =IFERROR(IFERROR(VLOOKUP(B20,[1]Planilha1!$A$4:$C$277,3,0),VLOOKUP(A20,[1]Planilha1!$A$4:$C$277,3,0)),0) -> 0 | F20: =IFERROR(IFERROR(VLOOKUP(A20,[2]Planilha1!$A$4:$C$258,3,0),VLOOKUP(B20,[2]Planilha1!$A$4:$C$258,3,0)),0) -> 0 | G20: =IFERROR(IFERROR(VLOOKUP(A20,[1]Planilha1!$A$4:$D$277,4,0),VLOOKUP(B20,[1]Planilha1!$A$4:$D$277,4,0)),0) -> 0 | H20: =D20+E20-G20 -> 0.535 | I20: AROMA | J20: 1 | K20: =VLOOKUP(A20,CONT_ANTE!A:D,4,0) -> 0 | L20: =IF(AND(F20=0,K20<>M20),"!@##@!","ok") -> ok | M20: =IFERROR(VLOOKUP(A20,CONTAGEM!B:G,6,0),VLOOKUP(B20,CONTAGEM!B:G,6,0)) -> 0 | N20: =IFERROR(SUM(M20*V20),0) -> 0 | O20: =SUMIF(SISTEMA!B:B,A20,SISTEMA!I:I)/J20 -> 0.535 | P20: =SUMIF(SISTEMA!B:B,B20,SISTEMA!I:I) -> 0 | Q20: =O20+P20 -> 0.535 | R20: =IFERROR(SUM(Q20*V20),0) -> 25.525599 | S20: =IFERROR(VLOOKUP(A20,DIF_ANTE!A:D,4,0),"0")/J20 -> -0.535 | T20: =M20-Q20 -> -0.535 | U20: =T20-S20 -> 0 | V20: =IFERROR(VLOOKUP(A20,CUSTO!A:C,3,0),VLOOKUP(B20,CUSTO!A:C,3,0)) -> 47.7114 | W20: =IFERROR(SUM(T20*V20),0) -> -25.525599 | X20: =IFERROR(T20/Q20,"") -> -1 | Y20: =IFERROR(U20*V20,"-") -> 0 | Z20: OK, PERDA
A21: 2701050019 | B21: - | C21: AROMA IDENTICO AO NATURAL MELAO DUAS RODAS | D21: 353.7704 | E21: =IFERROR(IFERROR(VLOOKUP(B21,[1]Planilha1!$A$4:$C$277,3,0),VLOOKUP(A21,[1]Planilha1!$A$4:$C$277,3,0)),0) -> 255 | F21: =IFERROR(IFERROR(VLOOKUP(A21,[2]Planilha1!$A$4:$C$258,3,0),VLOOKUP(B21,[2]Planilha1!$A$4:$C$258,3,0)),0) -> 110.77 | G21: =IFERROR(IFERROR(VLOOKUP(A21,[1]Planilha1!$A$4:$D$277,4,0),VLOOKUP(B21,[1]Planilha1!$A$4:$D$277,4,0)),0) -> 263.77 | H21: =D21+E21-G21 -> 345.0004 | I21: AROMA | J21: 1 | K21: =VLOOKUP(A21,CONT_ANTE!A:D,4,0) -> 325 | L21: =IF(AND(F21=0,K21<>M21),"!@##@!","ok") -> ok | M21: =IFERROR(VLOOKUP(A21,CONTAGEM!B:G,6,0),VLOOKUP(B21,CONTAGEM!B:G,6,0)) -> 325 | N21: =IFERROR(SUM(M21*V21),0) -> 16175.951 | O21: =SUMIF(SISTEMA!B:B,A21,SISTEMA!I:I)/J21 -> 364.2404 | P21: =SUMIF(SISTEMA!B:B,B21,SISTEMA!I:I) -> 0 | Q21: =O21+P21 -> 364.2404 | R21: =IFERROR(SUM(Q21*V21),0) -> 18129.03 | S21: =IFERROR(VLOOKUP(A21,DIF_ANTE!A:D,4,0),"0")/J21 -> -28.7704 | T21: =M21-Q21 -> -39.2404 | U21: =T21-S21 -> -10.47 | V21: =IFERROR(VLOOKUP(A21,CUSTO!A:C,3,0),VLOOKUP(B21,CUSTO!A:C,3,0)) -> 49.772157 | W21: =IFERROR(SUM(T21*V21),0) -> -1953.0793 | X21: =IFERROR(T21/Q21,"") -> -0.10773215 | Y21: =IFERROR(U21*V21,"-") -> -521.11448 | Z21: OK, PERDA
A22: 2701050021 | B22: - | C22: AROMA IDENTICO AO NATURAL MORANGO DUAS RODAS | D22: 117.23 | E22: =IFERROR(IFERROR(VLOOKUP(B22,[1]Planilha1!$A$4:$C$277,3,0),VLOOKUP(A22,[1]Planilha1!$A$4:$C$277,3,0)),0) -> 250 | F22: =IFERROR(IFERROR(VLOOKUP(A22,[2]Planilha1!$A$4:$C$258,3,0),VLOOKUP(B22,[2]Planilha1!$A$4:$C$258,3,0)),0) -> 82.23 | G22: =IFERROR(IFERROR(VLOOKUP(A22,[1]Planilha1!$A$4:$D$277,4,0),VLOOKUP(B22,[1]Planilha1!$A$4:$D$277,4,0)),0) -> 282.23 | H22: =D22+E22-G22 -> 85 | I22: AROMA | J22: 1 | K22: =VLOOKUP(A22,CONT_ANTE!A:D,4,0) -> 121 | L22: =IF(AND(F22=0,K22<>M22),"!@##@!","ok") -> ok | M22: =IFERROR(VLOOKUP(A22,CONTAGEM!B:G,6,0),VLOOKUP(B22,CONTAGEM!B:G,6,0)) -> 88.5 | N22: =IFERROR(SUM(M22*V22),0) -> 5667.9294 | O22: =SUMIF(SISTEMA!B:B,A22,SISTEMA!I:I)/J22 -> 85 | P22: =SUMIF(SISTEMA!B:B,B22,SISTEMA!I:I) -> 0 | Q22: =O22+P22 -> 85 | R22: =IFERROR(SUM(Q22*V22),0) -> 5443.774 | S22: =IFERROR(VLOOKUP(A22,DIF_ANTE!A:D,4,0),"0")/J22 -> 3.77 | T22: =M22-Q22 -> 3.5 | U22: =T22-S22 -> -0.27 | V22: =IFERROR(VLOOKUP(A22,CUSTO!A:C,3,0),VLOOKUP(B22,CUSTO!A:C,3,0)) -> 64.0444 | W22: =IFERROR(SUM(T22*V22),0) -> 224.1554 | X22: =IFERROR(T22/Q22,"") -> 0.041176471 | Y22: =IFERROR(U22*V22,"-") -> -17.291988 | Z22: OK, PERDA
A23: 2701050026 | B23: - | C23: AROMA IDENTICO AO NATURAL PESSEGO RB 25049 SAPORITI | D23: 44.59 | E23: =IFERROR(IFERROR(VLOOKUP(B23,[1]Planilha1!$A$4:$C$277,3,0),VLOOKUP(A23,[1]Planilha1!$A$4:$C$277,3,0)),0) -> 0 | F23: =IFERROR(IFERROR(VLOOKUP(A23,[2]Planilha1!$A$4:$C$258,3,0),VLOOKUP(B23,[2]Planilha1!$A$4:$C$258,3,0)),0) -> 33.59 | G23: =IFERROR(IFERROR(VLOOKUP(A23,[1]Planilha1!$A$4:$D$277,4,0),VLOOKUP(B23,[1]Planilha1!$A$4:$D$277,4,0)),0) -> 29.4 | H23: =D23+E23-G23 -> 15.19 | I23: AROMA | J23: 1 | K23: =VLOOKUP(A23,CONT_ANTE!A:D,4,0) -> 41 | L23: =IF(AND(F23=0,K23<>M23),"!@##@!","ok") -> ok | M23: =IFERROR(VLOOKUP(A23,CONTAGEM!B:G,6,0),VLOOKUP(B23,CONTAGEM!B:G,6,0)) -> 11 | N23: =IFERROR(SUM(M23*V23),0) -> 538.4555 | O23: =SUMIF(SISTEMA!B:B,A23,SISTEMA!I:I)/J23 -> 15.19 | P23: =SUMIF(SISTEMA!B:B,B23,SISTEMA!I:I) -> 0 | Q23: =O23+P23 -> 15.19 | R23: =IFERROR(SUM(Q23*V23),0) -> 743.5581 | S23: =IFERROR(VLOOKUP(A23,DIF_ANTE!A:D,4,0),"0")/J23 -> -3.59 | T23: =M23-Q23 -> -4.19 | U23: =T23-S23 -> -0.6 | V23: =IFERROR(VLOOKUP(A23,CUSTO!A:C,3,0),VLOOKUP(B23,CUSTO!A:C,3,0)) -> 48.9505 | W23: =IFERROR(SUM(T23*V23),0) -> -205.1026 | X23: =IFERROR(T23/Q23,"") -> -0.27583937 | Y23: =IFERROR(U23*V23,"-") -> -29.3703 | Z23: OK, PERDA
A24: 2701050005 | B24: - | C24: AROMA NATURAL BAUNILHA KALABROS | D24: 0 | E24: =IFERROR(IFERROR(VLOOKUP(B24,[1]Planilha1!$A$4:$C$277,3,0),VLOOKUP(A24,[1]Planilha1!$A$4:$C$277,3,0)),0) -> 0 | F24: =IFERROR(IFERROR(VLOOKUP(A24,[2]Planilha1!$A$4:$C$258,3,0),VLOOKUP(B24,[2]Planilha1!$A$4:$C$258,3,0)),0) -> 0 | G24: =IFERROR(IFERROR(VLOOKUP(A24,[1]Planilha1!$A$4:$D$277,4,0),VLOOKUP(B24,[1]Planilha1!$A$4:$D$277,4,0)),0) -> 0 | H24: =D24+E24-G24 -> 0 | I24: AROMA | J24: 1 | K24: =VLOOKUP(A24,CONT_ANTE!A:D,4,0) -> 0 | L24: =IF(AND(F24=0,K24<>M24),"!@##@!","ok") -> ok | M24: =IFERROR(VLOOKUP(A24,CONTAGEM!B:G,6,0),VLOOKUP(B24,CONTAGEM!B:G,6,0)) -> 0 | N24: =IFERROR(SUM(M24*V24),0) -> 0 | O24: =SUMIF(SISTEMA!B:B,A24,SISTEMA!I:I)/J24 -> 0 | P24: =SUMIF(SISTEMA!B:B,B24,SISTEMA!I:I) -> 0 | Q24: =O24+P24 -> 0 | R24: =IFERROR(SUM(Q24*V24),0) -> 0 | S24: =IFERROR(VLOOKUP(A24,DIF_ANTE!A:D,4,0),"0")/J24 -> 0 | T24: =M24-Q24 -> 0 | U24: =T24-S24 -> 0 | V24: =IFERROR(VLOOKUP(A24,CUSTO!A:C,3,0),VLOOKUP(B24,CUSTO!A:C,3,0)) -> 45.476671 | W24: =IFERROR(SUM(T24*V24),0) -> 0 | X24: =IFERROR(T24/Q24,"") | Y24: =IFERROR(U24*V24,"-") -> 0 | Z24: OK
A25: 2701050007 | B25: - | C25: AROMA NATURAL DE CITRUS RB 25395 SAPORITI | D25: 0 | E25: =IFERROR(IFERROR(VLOOKUP(B25,[1]Planilha1!$A$4:$C$277,3,0),VLOOKUP(A25,[1]Planilha1!$A$4:$C$277,3,0)),0) -> 36 | F25: =IFERROR(IFERROR(VLOOKUP(A25,[2]Planilha1!$A$4:$C$258,3,0),VLOOKUP(B25,[2]Planilha1!$A$4:$C$258,3,0)),0) -> 0 | G25: =IFERROR(IFERROR(VLOOKUP(A25,[1]Planilha1!$A$4:$D$277,4,0),VLOOKUP(B25,[1]Planilha1!$A$4:$D$277,4,0)),0) -> 36 | H25: =D25+E25-G25 -> 0 | I25: AROMA | J25: 1 | K25: =VLOOKUP(A25,CONT_ANTE!A:D,4,0) -> 0 | L25: =IF(AND(F25=0,K25<>M25),"!@##@!","ok") -> ok | M25: =IFERROR(VLOOKUP(A25,CONTAGEM!B:G,6,0),VLOOKUP(B25,CONTAGEM!B:G,6,0)) -> 0 | N25: =IFERROR(SUM(M25*V25),0) -> 0 | O25: =SUMIF(SISTEMA!B:B,A25,SISTEMA!I:I)/J25 -> 0 | P25: =SUMIF(SISTEMA!B:B,B25,SISTEMA!I:I) -> 0 | Q25: =O25+P25 -> 0 | R25: =IFERROR(SUM(Q25*V25),0) -> 0 | S25: =IFERROR(VLOOKUP(A25,DIF_ANTE!A:D,4,0),"0")/J25 -> 0 | T25: =M25-Q25 -> 0 | U25: =T25-S25 -> 0 | V25: =IFERROR(VLOOKUP(A25,CUSTO!A:C,3,0),VLOOKUP(B25,CUSTO!A:C,3,0)) -> 88.617222 | W25: =IFERROR(SUM(T25*V25),0) -> 0 | X25: =IFERROR(T25/Q25,"") | Y25: =IFERROR(U25*V25,"-") -> 0 | Z25: OK
A26: 2701050036 | B26: - | C26: AROMA NATURAL DE TANGERINA DOHLER | D26: 119.11 | E26: =IFERROR(IFERROR(VLOOKUP(B26,[1]Planilha1!$A$4:$C$277,3,0),VLOOKUP(A26,[1]Planilha1!$A$4:$C$277,3,0)),0) -> 0 | F26: =IFERROR(IFERROR(VLOOKUP(A26,[2]Planilha1!$A$4:$C$258,3,0),VLOOKUP(B26,[2]Planilha1!$A$4:$C$258,3,0)),0) -> 35.11 | G26: =IFERROR(IFERROR(VLOOKUP(A26,[1]Planilha1!$A$4:$D$277,4,0),VLOOKUP(B26,[1]Planilha1!$A$4:$D$277,4,0)),0) -> 25.8 | H26: =D26+E26-G26 -> 93.31 | I26: AROMA | J26: 1 | K26: =VLOOKUP(A26,CONT_ANTE!A:D,4,0) -> 110 | L26: =IF(AND(F26=0,K26<>M26),"!@##@!","ok") -> ok | M26: =IFERROR(VLOOKUP(A26,CONTAGEM!B:G,6,0),VLOOKUP(B26,CONTAGEM!B:G,6,0)) -> 84 | N26: =IFERROR(SUM(M26*V26),0) -> 12167.98 | O26: =SUMIF(SISTEMA!B:B,A26,SISTEMA!I:I)/J26 -> 93.31 | P26: =SUMIF(SISTEMA!B:B,B26,SISTEMA!I:I) -> 0 | Q26: =O26+P26 -> 93.31 | R26: =IFERROR(SUM(Q26*V26),0) -> 13516.597 | S26: =IFERROR(VLOOKUP(A26,DIF_ANTE!A:D,4,0),"0")/J26 -> -9.11 | T26: =M26-Q26 -> -9.31 | U26: =T26-S26 -> -0.2 | V26: =IFERROR(VLOOKUP(A26,CUSTO!A:C,3,0),VLOOKUP(B26,CUSTO!A:C,3,0)) -> 144.8569 | W26: =IFERROR(SUM(T26*V26),0) -> -1348.6177 | X26: =IFERROR(T26/Q26,"") -> -0.099774944 | Y26: =IFERROR(U26*V26,"-") -> -28.97138 | Z26: OK, PERDA
... A31: 2701160011 | B31: - | C31: CAIXA CER BAMBOA LAGER 12X330ML | D31: 34779 | E31: =IFERROR(IFERROR(VLOOKUP(B31,[1]Planilha1!$A$4:$C$277,3,0),VLOOKUP(A31,[1]Planilha1!$A$4:$C$277,3,0)),0) -> 0 | F31: =IFERROR(IFERROR(VLOOKUP(A31,[2]Planilha1!$A$4:$C$258,3,0),VLOOKUP(B31,[2]Planilha1!$A$4:$C$258,3,0)),0) -> 0 | G31: =IFERROR(IFERROR(VLOOKUP(A31,[1]Planilha1!$A$4:$D$277,4,0),VLOOKUP(B31,[1]Planilha1!$A$4:$D$277,4,0)),0) -> 2179 | H31: =D31+E31-G31 -> 32600 | I31: CAIXA | J31: 1 | K31: =VLOOKUP(A31,CONT_ANTE!A:D,4,0) -> 32600 | L31: =IF(AND(F31=0,K31<>M31),"!@##@!","ok") -> !@##@! | M31: =IFERROR(VLOOKUP(A31,CONTAGEM!B:G,6,0),VLOOKUP(B31,CONTAGEM!B:G,6,0)) -> 32578 | N31: =IFERROR(SUM(M31*V31),0) -> 53251.06 | O31: =SUMIF(SISTEMA!B:B,A31,SISTEMA!I:I)/J31 -> 32600 | P31: =SUMIF(SISTEMA!B:B,B31,SISTEMA!I:I) -> 0 | Q31: =O31+P31 -> 32600 | R31: =IFERROR(SUM(Q31*V31),0) -> 53287.02 | S31: =IFERROR(VLOOKUP(A31,DIF_ANTE!A:D,4,0),"0")/J31 -> -2179 | T31: =M31-Q31 -> -22 | U31: =T31-S31 -> 2157 | V31: =IFERROR(VLOOKUP(A31,CUSTO!A:C,3,0),VLOOKUP(B31,CUSTO!A:C,3,0)) -> 1.6345712 | W31: =IFERROR(SUM(T31*V31),0) -> -35.960566 | X31: =IFERROR(T31/Q31,"") -> -0.00067484663 | Y31: =IFERROR(U31*V31,"-") -> 3525.77 | Z31: ok
A32: 2701160008 | B32: - | C32: CAIXA CER BAMBOA PILSEN 12X300ML | D32: 0 | E32: =IFERROR(IFERROR(VLOOKUP(B32,[1]Planilha1!$A$4:$C$277,3,0),VLOOKUP(A32,[1]Planilha1!$A$4:$C$277,3,0)),0) -> 0 | F32: =IFERROR(IFERROR(VLOOKUP(A32,[2]Planilha1!$A$4:$C$258,3,0),VLOOKUP(B32,[2]Planilha1!$A$4:$C$258,3,0)),0) -> 0 | G32: =IFERROR(IFERROR(VLOOKUP(A32,[1]Planilha1!$A$4:$D$277,4,0),VLOOKUP(B32,[1]Planilha1!$A$4:$D$277,4,0)),0) -> 0 | H32: =D32+E32-G32 -> 0 | I32: CAIXA | J32: 1 | K32: =VLOOKUP(A32,CONT_ANTE!A:D,4,0) -> 0 | L32: =IF(AND(F32=0,K32<>M32),"!@##@!","ok") -> ok | M32: 0 | N32: =IFERROR(SUM(M32*V32),0) -> 0 | O32: =SUMIF(SISTEMA!B:B,A32,SISTEMA!I:I)/J32 -> 0 | P32: =SUMIF(SISTEMA!B:B,B32,SISTEMA!I:I) -> 0 | Q32: =O32+P32 -> 0 | R32: =IFERROR(SUM(Q32*V32),0) -> 0 | S32: =IFERROR(VLOOKUP(A32,DIF_ANTE!A:D,4,0),"0")/J32 -> 0 | T32: =M32-Q32 -> 0 | U32: =T32-S32 -> 0 | V32: =IFERROR(VLOOKUP(A32,CUSTO!A:C,3,0),VLOOKUP(B32,CUSTO!A:C,3,0)) -> 3.726875 | W32: =IFERROR(SUM(T32*V32),0) -> 0 | X32: =IFERROR(T32/Q32,"") | Y32: =IFERROR(U32*V32,"-") -> 0 | Z32: ok
A33: 2701160007 | B33: - | C33: CAIXA CER BAMBOA PILSEN 6X600ML | D33: 0 | E33: =IFERROR(IFERROR(VLOOKUP(B33,[1]Planilha1!$A$4:$C$277,3,0),VLOOKUP(A33,[1]Planilha1!$A$4:$C$277,3,0)),0) -> 0 | F33: =IFERROR(IFERROR(VLOOKUP(A33,[2]Planilha1!$A$4:$C$258,3,0),VLOOKUP(B33,[2]Planilha1!$A$4:$C$258,3,0)),0) -> 0 | G33: =IFERROR(IFERROR(VLOOKUP(A33,[1]Planilha1!$A$4:$D$277,4,0),VLOOKUP(B33,[1]Planilha1!$A$4:$D$277,4,0)),0) -> 0 | H33: =D33+E33-G33 -> 0 | I33: CAIXA | J33: 1 | K33: =VLOOKUP(A33,CONT_ANTE!A:D,4,0) -> 0 | L33: =IF(AND(F33=0,K33<>M33),"!@##@!","ok") -> ok | M33: 0 | N33: =IFERROR(SUM(M33*V33),0) -> 0 | O33: =SUMIF(SISTEMA!B:B,A33,SISTEMA!I:I)/J33 -> 0 | P33: =SUMIF(SISTEMA!B:B,B33,SISTEMA!I:I) -> 0 | Q33: =O33+P33 -> 0 | R33: =IFERROR(SUM(Q33*V33),0) -> 0 | S33: =IFERROR(VLOOKUP(A33,DIF_ANTE!A:D,4,0),"0")/J33 -> 0 | T33: =M33-Q33 -> 0 | U33: =T33-S33 -> 0 | V33: =IFERROR(VLOOKUP(A33,CUSTO!A:C,3,0),VLOOKUP(B33,CUSTO!A:C,3,0)) -> 3.726875 | W33: =IFERROR(SUM(T33*V33),0) -> 0 | X33: =IFERROR(T33/Q33,"") | Y33: =IFERROR(U33*V33,"-") -> 0 | Z33: ok
A34: 2701160006 | B34: - | C34: CAIXA CER MOEMA 12X300ML | D34: 4400 | E34: =IFERROR(IFERROR(VLOOKUP(B34,[1]Planilha1!$A$4:$C$277,3,0),VLOOKUP(A34,[1]Planilha1!$A$4:$C$277,3,0)),0) -> 0 | F34: =IFERROR(IFERROR(VLOOKUP(A34,[2]Planilha1!$A$4:$C$258,3,0),VLOOKUP(B34,[2]Planilha1!$A$4:$C$258,3,0)),0) -> 0 | G34: =IFERROR(IFERROR(VLOOKUP(A34,[1]Planilha1!$A$4:$D$277,4,0),VLOOKUP(B34,[1]Planilha1!$A$4:$D$277,4,0)),0) -> 0 | H34: =D34+E34-G34 -> 4400 | I34: CAIXA | J34: 1 | K34: =VLOOKUP(A34,CONT_ANTE!A:D,4,0) -> 4400 | L34: =IF(AND(F34=0,K34<>M34),"!@##@!","ok") -> ok | M34: =IFERROR(VLOOKUP(A34,CONTAGEM!B:G,6,0),VLOOKUP(B34,CONTAGEM!B:G,6,0)) -> 4400 | N34: =IFERROR(SUM(M34*V34),0) -> 8173.3211 | O34: =SUMIF(SISTEMA!B:B,A34,SISTEMA!I:I)/J34 -> 4400 | P34: =SUMIF(SISTEMA!B:B,B34,SISTEMA!I:I) -> 0 | Q34: =O34+P34 -> 4400 | R34: =IFERROR(SUM(Q34*V34),0) -> 8173.3211 | S34: =IFERROR(VLOOKUP(A34,DIF_ANTE!A:D,4,0),"0")/J34 -> 0 | T34: =M34-Q34 -> 0 | U34: =T34-S34 -> 0 | V34: =IFERROR(VLOOKUP(A34,CUSTO!A:C,3,0),VLOOKUP(B34,CUSTO!A:C,3,0)) -> 1.857573 | W34: =IFERROR(SUM(T34*V34),0) -> 0 | X34: =IFERROR(T34/Q34,"") -> 0 | Y34: =IFERROR(U34*V34,"-") -> 0 | Z34: ok
A35: 2701160005 | B35: - | C35: CAIXA CER MOEMA 6X600ML | D35: 11537 | E35: =IFERROR(IFERROR(VLOOKUP(B35,[1]Planilha1!$A$4:$C$277,3,0),VLOOKUP(A35,[1]Planilha1!$A$4:$C$277,3,0)),0) -> 8705 | F35: =IFERROR(IFERROR(VLOOKUP(A35,[2]Planilha1!$A$4:$C$258,3,0),VLOOKUP(B35,[2]Planilha1!$A$4:$C$258,3,0)),0) -> 5057 | G35: =IFERROR(IFERROR(VLOOKUP(A35,[1]Planilha1!$A$4:$D$277,4,0),VLOOKUP(B35,[1]Planilha1!$A$4:$D$277,4,0)),0) -> 13762 | H35: =D35+E35-G35 -> 6480 | I35: CAIXA | J35: 1 | K35: =VLOOKUP(A35,CONT_ANTE!A:D,4,0) -> 10537 | L35: =IF(AND(F35=0,K35<>M35),"!@##@!","ok") -> ok | M35: =IFERROR(VLOOKUP(A35,CONTAGEM!B:G,6,0),VLOOKUP(B35,CONTAGEM!B:G,6,0)) -> 4950 | N35: =IFERROR(SUM(M35*V35),0) -> 6726.0581 | O35: =SUMIF(SISTEMA!B:B,A35,SISTEMA!I:I)/J35 -> 6480 | P35: =SUMIF(SISTEMA!B:B,B35,SISTEMA!I:I) -> 0 | Q35: =O35+P35 -> 6480 | R35: =IFERROR(SUM(Q35*V35),0) -> 8805.0215 | S35: =IFERROR(VLOOKUP(A35,DIF_ANTE!A:D,4,0),"0")/J35 -> -1000 | T35: =M35-Q35 -> -1530 | U35: =T35-S35 -> -530 | V35: =IFERROR(VLOOKUP(A35,CUSTO!A:C,3,0),VLOOKUP(B35,CUSTO!A:C,3,0)) -> 1.3587996 | W35: =IFERROR(SUM(T35*V35),0) -> -2078.9634 | X35: =IFERROR(T35/Q35,"") -> -0.23611111 | Y35: =IFERROR(U35*V35,"-") -> -720.16379 | Z35: OK
A36: 2701160001 | B36: - | C36: CAIXA GIN JAMES COOK 6X900ML | D36: 20 | E36: =IFERROR(IFERROR(VLOOKUP(B36,[1]Planilha1!$A$4:$C$277,3,0),VLOOKUP(A36,[1]Planilha1!$A$4:$C$277,3,0)),0) -> 0 | F36: =IFERROR(IFERROR(VLOOKUP(A36,[2]Planilha1!$A$4:$C$258,3,0),VLOOKUP(B36,[2]Planilha1!$A$4:$C$258,3,0)),0) -> 0 | G36: =IFERROR(IFERROR(VLOOKUP(A36,[1]Planilha1!$A$4:$D$277,4,0),VLOOKUP(B36,[1]Planilha1!$A$4:$D$277,4,0)),0) -> 0 | H36: =D36+E36-G36 -> 20 | I36: CAIXA | J36: 1 | K36: =VLOOKUP(A36,CONT_ANTE!A:D,4,0) -> 0 | L36: =IF(AND(F36=0,K36<>M36),"!@##@!","ok") -> ok | M36: =IFERROR(VLOOKUP(A36,CONTAGEM!B:G,6,0),VLOOKUP(B36,CONTAGEM!B:G,6,0)) -> 0 | N36: =IFERROR(SUM(M36*V36),0) -> 0 | O36: =SUMIF(SISTEMA!B:B,A36,SISTEMA!I:I)/J36 -> 20 | P36: =SUMIF(SISTEMA!B:B,B36,SISTEMA!I:I) -> 0 | Q36: =O36+P36 -> 20 | R36: =IFERROR(SUM(Q36*V36),0) -> 49.96335 | S36: =IFERROR(VLOOKUP(A36,DIF_ANTE!A:D,4,0),"0")/J36 -> -20 | T36: =M36-Q36 -> -20 | U36: =T36-S36 -> 0 | V36: =IFERROR(VLOOKUP(A36,CUSTO!A:C,3,0),VLOOKUP(B36,CUSTO!A:C,3,0)) -> 2.4981675 | W36: =IFERROR(SUM(T36*V36),0) -> -49.96335 | X36: =IFERROR(T36/Q36,"") -> -1 | Y36: =IFERROR(U36*V36,"-") -> 0 | Z36: ok
A37: 2701160012 | B37: - | C37: CAIXA REFRIGERANTE REFRIKO TUBAINA 12X300ML | D37: 28252 | E37: =IFERROR(IFERROR(VLOOKUP(B37,[1]Planilha1!$A$4:$C$277,3,0),VLOOKUP(A37,[1]Planilha1!$A$4:$C$277,3,0)),0) -> 13588 | F37: =IFERROR(IFERROR(VLOOKUP(A37,[2]Planilha1!$A$4:$C$258,3,0),VLOOKUP(B37,[2]Planilha1!$A$4:$C$258,3,0)),0) -> 9108 | G37: =IFERROR(IFERROR(VLOOKUP(A37,[1]Planilha1!$A$4:$D$277,4,0),VLOOKUP(B37,[1]Planilha1!$A$4:$D$277,4,0)),0) -> 22746 | H37: =D37+E37-G37 -> 19094 | I37: CAIXA | J37: 1 | K37: =VLOOKUP(A37,CONT_ANTE!A:D,4,0) -> 25425 | L37: =IF(AND(F37=0,K37<>M37),"!@##@!","ok") -> ok | M37: =IFERROR(VLOOKUP(A37,CONTAGEM!B:G,6,0),VLOOKUP(B37,CONTAGEM!B:G,6,0)) -> 18175 | N37: =IFERROR(SUM(M37*V37),0) -> 28648.695 | O37: =SUMIF(SISTEMA!B:B,A37,SISTEMA!I:I)/J37 -> 19094 | P37: =SUMIF(SISTEMA!B:B,B37,SISTEMA!I:I) -> 0 | Q37: =O37+P37 -> 19094 | R37: =IFERROR(SUM(Q37*V37),0) -> 30097.286 | S37: =IFERROR(VLOOKUP(A37,DIF_ANTE!A:D,4,0),"0")/J37 -> -2827 | T37: =M37-Q37 -> -919 | U37: =T37-S37 -> 1908 | V37: =IFERROR(VLOOKUP(A37,CUSTO!A:C,3,0),VLOOKUP(B37,CUSTO!A:C,3,0)) -> 1.5762693 | W37: =IFERROR(SUM(T37*V37),0) -> -1448.5915 | X37: =IFERROR(T37/Q37,"") -> -0.048130303 | Y37: =IFERROR(U37*V37,"-") -> 3007.5219 | Z37: OK
A38: 2701160013 | B38: - | C38: CAIXA REFRIGERANTE REFRIKO TUBAINA 12X355ML | D38: 18877 | E38: =IFERROR(IFERROR(VLOOKUP(B38,[1]Planilha1!$A$4:$C$277,3,0),VLOOKUP(A38,[1]Planilha1!$A$4:$C$277,3,0)),0) -> 8272 | F38: =IFERROR(IFERROR(VLOOKUP(A38,[2]Planilha1!$A$4:$C$258,3,0),VLOOKUP(B38,[2]Planilha1!$A$4:$C$258,3,0)),0) -> 1879 | G38: =IFERROR(IFERROR(VLOOKUP(A38,[1]Planilha1!$A$4:$D$277,4,0),VLOOKUP(B38,[1]Planilha1!$A$4:$D$277,4,0)),0) -> 10151 | H38: =D38+E38-G38 -> 16998 | I38: CAIXA | J38: 1 | K38: =VLOOKUP(A38,CONT_ANTE!A:D,4,0) -> 18812 | L38: =IF(AND(F38=0,K38<>M38),"!@##@!","ok") -> ok | M38: =IFERROR(VLOOKUP(A38,CONTAGEM!B:G,6,0),VLOOKUP(B38,CONTAGEM!B:G,6,0)) -> 16640 | N38: =IFERROR(SUM(M38*V38),0) -> 30145.913 | O38: =SUMIF(SISTEMA!B:B,A38,SISTEMA!I:I)/J38 -> 16998 | P38: =SUMIF(SISTEMA!B:B,B38,SISTEMA!I:I) -> 0 | Q38: =O38+P38 -> 16998 | R38: =IFERROR(SUM(Q38*V38),0) -> 30794.485 | S38: =IFERROR(VLOOKUP(A38,DIF_ANTE!A:D,4,0),"0")/J38 -> -65 | T38: =M38-Q38 -> -358 | U38: =T38-S38 -> -293 | V38: =IFERROR(VLOOKUP(A38,CUSTO!A:C,3,0),VLOOKUP(B38,CUSTO!A:C,3,0)) -> 1.8116534 | W38: =IFERROR(SUM(T38*V38),0) -> -648.57193 | X38: =IFERROR(T38/Q38,"") -> -0.021061301 | Y38: =IFERROR(U38*V38,"-") -> -530.81446 | Z38: ok
A39: 2701160009 | B39: - | C39: CAIXA REFRIGERANTE REFRIKO TUBAINA S/ ACUCARES 12X300ML | D39: 24182 | E39: =IFERROR(IFERROR(VLOOKUP(B39,[1]Planilha1!$A$4:$C$277,3,0),VLOOKUP(A39,[1]Planilha1!$A$4:$C$277,3,0)),0) -> 10718 | F39: =IFERROR(IFERROR(VLOOKUP(A39,[2]Planilha1!$A$4:$C$258,3,0),VLOOKUP(B39,[2]Planilha1!$A$4:$C$258,3,0)),0) -> 5674 | G39: =IFERROR(IFERROR(VLOOKUP(A39,[1]Planilha1!$A$4:$D$277,4,0),VLOOKUP(B39,[1]Planilha1!$A$4:$D$277,4,0)),0) -> 16417 | H39: =D39+E39-G39 -> 18483 | I39: CAIXA | J39: 1 | K39: =VLOOKUP(A39,CONT_ANTE!A:D,4,0) -> 23945 | L39: =IF(AND(F39=0,K39<>M39),"!@##@!","ok") -> ok | M39: =IFERROR(VLOOKUP(A39,CONTAGEM!B:G,6,0),VLOOKUP(B39,CONTAGEM!B:G,6,0)) -> 17600 | N39: =IFERROR(SUM(M39*V39),0) -> 27018.554 | O39: =SUMIF(SISTEMA!B:B,A39,SISTEMA!I:I)/J39 -> 18483 | P39: =SUMIF(SISTEMA!B:B,B39,SISTEMA!I:I) -> 0 | Q39: =O39+P39 -> 18483 | R39: =IFERROR(SUM(Q39*V39),0) -> 28374.088 | S39: =IFERROR(VLOOKUP(A39,DIF_ANTE!A:D,4,0),"0")/J39 -> -237 | T39: =M39-Q39 -> -883 | U39: =T39-S39 -> -646 | V39: =IFERROR(VLOOKUP(A39,CUSTO!A:C,3,0),VLOOKUP(B39,CUSTO!A:C,3,0)) -> 1.5351451 | W39: =IFERROR(SUM(T39*V39),0) -> -1355.5332 | X39: =IFERROR(T39/Q39,"") -> -0.04777363 | Y39: =IFERROR(U39*V39,"-") -> -991.70376 | Z39: ok
A40: 2701160002 | B40: - | C40: CAIXA VODKA JAMES COOK 6X900ML | D40: 3112 | E40: =IFERROR(IFERROR(VLOOKUP(B40,[1]Planilha1!$A$4:$C$277,3,0),VLOOKUP(A40,[1]Planilha1!$A$4:$C$277,3,0)),0) -> 950 | F40: =IFERROR(IFERROR(VLOOKUP(A40,[2]Planilha1!$A$4:$C$258,3,0),VLOOKUP(B40,[2]Planilha1!$A$4:$C$258,3,0)),0) -> 0 | G40: =IFERROR(IFERROR(VLOOKUP(A40,[1]Planilha1!$A$4:$D$277,4,0),VLOOKUP(B40,[1]Planilha1!$A$4:$D$277,4,0)),0) -> 975 | H40: =D40+E40-G40 -> 3087 | I40: CAIXA | J40: 1 | K40: =VLOOKUP(A40,CONT_ANTE!A:D,4,0) -> 3284 | L40: =IF(AND(F40=0,K40<>M40),"!@##@!","ok") -> !@##@! | M40: =IFERROR(VLOOKUP(A40,CONTAGEM!B:G,6,0),VLOOKUP(B40,CONTAGEM!B:G,6,0)) -> 3324 | N40: =IFERROR(SUM(M40*V40),0) -> 8303.8961 | O40: =SUMIF(SISTEMA!B:B,A40,SISTEMA!I:I)/J40 -> 3087 | P40: =SUMIF(SISTEMA!B:B,B40,SISTEMA!I:I) -> 0 | Q40: =O40+P40 -> 3087 | R40: =IFERROR(SUM(Q40*V40),0) -> 7711.8313 | S40: =IFERROR(VLOOKUP(A40,DIF_ANTE!A:D,4,0),"0")/J40 -> 172 | T40: =M40-Q40 -> 237 | U40: =T40-S40 -> 65 | V40: =IFERROR(VLOOKUP(A40,CUSTO!A:C,3,0),VLOOKUP(B40,CUSTO!A:C,3,0)) -> 2.4981637 | W40: =IFERROR(SUM(T40*V40),0) -> 592.06479 | X40: =IFERROR(T40/Q40,"") -> 0.076773567 | Y40: =IFERROR(U40*V40,"-") -> 162.38064 | Z40: ok
A41: 2701240002 | B41: - | C41: CANTONEIRA SIMPLES 100X100X1580MM | D41: 4126.6767 | E41: =IFERROR(IFERROR(VLOOKUP(B41,[1]Planilha1!$A$4:$C$277,3,0),VLOOKUP(A41,[1]Planilha1!$A$4:$C$277,3,0)),0) -> 1790.3036 | F41: =IFERROR(IFERROR(VLOOKUP(A41,[2]Planilha1!$A$4:$C$258,3,0),VLOOKUP(B41,[2]Planilha1!$A$4:$C$258,3,0)),0) -> 518.62057 | G41: =IFERROR(IFERROR(VLOOKUP(A41,[1]Planilha1!$A$4:$D$277,4,0),VLOOKUP(B41,[1]Planilha1!$A$4:$D$277,4,0)),0) -> 2308.9242 | H41: =D41+E41-G41 -> 3608.0561 | I41: CAIXA | J41: 1 | K41: =VLOOKUP(A41,CONT_ANTE!A:D,4,0) -> 6200 | L41: =IF(AND(F41=0,K41<>M41),"!@##@!","ok") -> ok | M41: =IFERROR(VLOOKUP(A41,CONTAGEM!B:G,6,0),VLOOKUP(B41,CONTAGEM!B:G,6,0)) -> 4960 | N41: =IFERROR(SUM(M41*V41),0) -> 6052.3065 | O41: =SUMIF(SISTEMA!B:B,A41,SISTEMA!I:I)/J41 -> 3608.0561 | P41: =SUMIF(SISTEMA!B:B,B41,SISTEMA!I:I) -> 0 | Q41: =O41+P41 -> 3608.0561 | R41: =IFERROR(SUM(Q41*V41),0) -> 4402.6333 | S41: =IFERROR(VLOOKUP(A41,DIF_ANTE!A:D,4,0),"0")/J41 -> 2073.3233 | T41: =M41-Q41 -> 1351.9439 | U41: =T41-S41 -> -721.37943 | V41: =IFERROR(VLOOKUP(A41,CUSTO!A:C,3,0),VLOOKUP(B41,CUSTO!A:C,3,0)) -> 1.2202231 | W41: =IFERROR(SUM(T41*V41),0) -> 1649.6731 | X41: =IFERROR(T41/Q41,"") -> 0.37470146 | Y41: =IFERROR(U41*V41,"-") -> -880.24383 | Z41: ok
A42: 2701240004 | B42: - | C42: CHAPA SEM IMPRESSAO 1000X1200MM | D42: 49041.124 | E42: =IFERROR(IFERROR(VLOOKUP(B42,[1]Planilha1!$A$4:$C$277,3,0),VLOOKUP(A42,[1]Planilha1!$A$4:$C$277,3,0)),0) -> 51411 | F42: =IFERROR(IFERROR(VLOOKUP(A42,[2]Planilha1!$A$4:$C$258,3,0),VLOOKUP(B42,[2]Planilha1!$A$4:$C$258,3,0)),0) -> 10014.537 | G42: =IFERROR(IFERROR(VLOOKUP(A42,[1]Planilha1!$A$4:$D$277,4,0),VLOOKUP(B42,[1]Planilha1!$A$4:$D$277,4,0)),0) -> 21425.537 | H42: =D42+E42-G42 -> 79026.587 | I42: CAIXA | J42: 1 | K42: =VLOOKUP(A42,CONT_ANTE!A:D,4,0) -> 40650 | L42: =IF(AND(F42=0,K42<>M42),"!@##@!","ok") -> ok | M42: =IFERROR(VLOOKUP(A42,CONTAGEM!B:G,6,0),VLOOKUP(B42,CONTAGEM!B:G,6,0)) -> 40700 | N42: =IFERROR(SUM(M42*V42),0) -> 35867.818 | O42: =SUMIF(SISTEMA!B:B,A42,SISTEMA!I:I)/J42 -> 51026.587 | P42: =SUMIF(SISTEMA!B:B,B42,SISTEMA!I:I) -> 0 | Q42: =O42+P42 -> 51026.587 | R42: =IFERROR(SUM(Q42*V42),0) -> 44968.362 | S42: =IFERROR(VLOOKUP(A42,DIF_ANTE!A:D,4,0),"0")/J42 -> -8391.1239 | T42: =M42-Q42 -> -10326.587 | U42: =T42-S42 -> -1935.4633 | V42: =IFERROR(VLOOKUP(A42,CUSTO!A:C,3,0),VLOOKUP(B42,CUSTO!A:C,3,0)) -> 0.88127317 | W42: =IFERROR(SUM(T42*V42),0) -> -9100.5442 | X42: =IFERROR(T42/Q42,"") -> -0.2023766 | Y42: =IFERROR(U42*V42,"-") -> -1705.6719 | Z42: ok
A43: 2701240005 | B43: - | C43: CHAPA SEM IMPRESSAO CORRUGADA 1000X1200MM | D43: 7715.0033 | E43: =IFERROR(IFERROR(VLOOKUP(B43,[1]Planilha1!$A$4:$C$277,3,0),VLOOKUP(A43,[1]Planilha1!$A$4:$C$277,3,0)),0) -> 0 | F43: =IFERROR(IFERROR(VLOOKUP(A43,[2]Planilha1!$A$4:$C$258,3,0),VLOOKUP(B43,[2]Planilha1!$A$4:$C$258,3,0)),0) -> 0 | G43: =IFERROR(IFERROR(VLOOKUP(A43,[1]Planilha1!$A$4:$D$277,4,0),VLOOKUP(B43,[1]Planilha1!$A$4:$D$277,4,0)),0) -> 0 | H43: =D43+E43-G43 -> 7715.0033 | I43: CAIXA | J43: 1 | K43: =VLOOKUP(A43,CONT_ANTE!A:D,4,0) -> 7600 | L43: =IF(AND(F43=0,K43<>M43),"!@##@!","ok") -> !@##@! | M43: =IFERROR(VLOOKUP(A43,CONTAGEM!B:G,6,0),VLOOKUP(B43,CONTAGEM!B:G,6,0)) -> 7500 | N43: =IFERROR(SUM(M43*V43),0) -> 25684.382 | O43: =SUMIF(SISTEMA!B:B,A43,SISTEMA!I:I)/J43 -> 7715.0033 | P43: =SUMIF(SISTEMA!B:B,B43,SISTEMA!I:I) -> 0 | Q43: =O43+P43 -> 7715.0033 | R43: =IFERROR(SUM(Q43*V43),0) -> 26420.679 | S43: =IFERROR(VLOOKUP(A43,DIF_ANTE!A:D,4,0),"0")/J43 -> -115.00326 | T43: =M43-Q43 -> -215.00326 | U43: =T43-S43 -> -100 | V43: =IFERROR(VLOOKUP(A43,CUSTO!A:C,3,0),VLOOKUP(B43,CUSTO!A:C,3,0)) -> 3.4245843 | W43: =IFERROR(SUM(T43*V43),0) -> -736.29679 | X43: =IFERROR(T43/Q43,"") -> -0.027868201 | Y43: =IFERROR(U43*V43,"-") -> -342.45843 | Z43: ok
A44: 3002020007 | B44: - | C44: CARVAO ATIVADO | D44: 860 | E44: =IFERROR(IFERROR(VLOOKUP(B44,[1]Planilha1!$A$4:$C$277,3,0),VLOOKUP(A44,[1]Planilha1!$A$4:$C$277,3,0)),0) -> 0 | F44: =IFERROR(IFERROR(VLOOKUP(A44,[2]Planilha1!$A$4:$C$258,3,0),VLOOKUP(B44,[2]Planilha1!$A$4:$C$258,3,0)),0) -> 90 | G44: =IFERROR(IFERROR(VLOOKUP(A44,[1]Planilha1!$A$4:$D$277,4,0),VLOOKUP(B44,[1]Planilha1!$A$4:$D$277,4,0)),0) -> 90 | H44: =D44+E44-G44 -> 770 | I44: CARVAO | J44: 1 | K44: =VLOOKUP(A44,CONT_ANTE!A:D,4,0) -> 800 | L44: =IF(AND(F44=0,K44<>M44),"!@##@!","ok") -> ok | M44: =IFERROR(VLOOKUP(A44,CONTAGEM!B:G,6,0),VLOOKUP(B44,CONTAGEM!B:G,6,0)) -> 770 | N44: =IFERROR(SUM(M44*V44),0) -> 2869.6937 | O44: =SUMIF(SISTEMA!B:B,A44,SISTEMA!I:I)/J44 -> 770 | P44: =SUMIF(SISTEMA!B:B,B44,SISTEMA!I:I) -> 0 | Q44: =O44+P44 -> 770 | R44: =IFERROR(SUM(Q44*V44),0) -> 2869.6937 | S44: =IFERROR(VLOOKUP(A44,DIF_ANTE!A:D,4,0),"0")/J44 -> -60 | T44: =M44-Q44 -> 0 | U44: =T44-S44 -> 60 | V44: =IFERROR(VLOOKUP(A44,CUSTO!A:C,3,0),VLOOKUP(B44,CUSTO!A:C,3,0)) -> 3.726875 | W44: =IFERROR(SUM(T44*V44),0) -> 0 | X44: =IFERROR(T44/Q44,"") -> 0 | Y44: =IFERROR(U44*V44,"-") -> 223.6125 | Z44: OK
A45: 2701090003 | B45: - | C45: ACIDO LACTICO | D45: 974.40009 | E45: =IFERROR(IFERROR(VLOOKUP(B45,[1]Planilha1!$A$4:$C$277,3,0),VLOOKUP(A45,[1]Planilha1!$A$4:$C$277,3,0)),0) -> 1000 | F45: =IFERROR(IFERROR(VLOOKUP(A45,[2]Planilha1!$A$4:$C$258,3,0),VLOOKUP(B45,[2]Planilha1!$A$4:$C$258,3,0)),0) -> 234.7 | G45: =IFERROR(IFERROR(VLOOKUP(A45,[1]Planilha1!$A$4:$D$277,4,0),VLOOKUP(B45,[1]Planilha1!$A$4:$D$277,4,0)),0) -> 234.7 | H45: =D45+E45-G45 -> 1739.7001 | I45: CERVEJARIA | J45: 1 | K45: =VLOOKUP(A45,CONT_ANTE!A:D,4,0) -> 900 | L45: =IF(AND(F45=0,K45<>M45),"!@##@!","ok") -> ok | M45: =IFERROR(VLOOKUP(A45,CONTAGEM!B:G,6,0),VLOOKUP(B45,CONTAGEM!B:G,6,0)) -> 1775 | N45: =IFERROR(SUM(M45*V45),0) -> 17580.097 | O45: =SUMIF(SISTEMA!B:B,A45,SISTEMA!I:I)/J45 -> 1739.7001 | P45: =SUMIF(SISTEMA!B:B,B45,SISTEMA!I:I) -> 0 | Q45: =O45+P45 -> 1739.7001 | R45: =IFERROR(SUM(Q45*V45),0) -> 17230.477 | S45: =IFERROR(VLOOKUP(A45,DIF_ANTE!A:D,4,0),"0")/J45 -> -74.40009 | T45: =M45-Q45 -> 35.29991 | U45: =T45-S45 -> 109.7 | V45: =IFERROR(VLOOKUP(A45,CUSTO!A:C,3,0),VLOOKUP(B45,CUSTO!A:C,3,0)) -> 9.90428 | W45: =IFERROR(SUM(T45*V45),0) -> 349.62019 | X45: =IFERROR(T45/Q45,"") -> 0.020290802 | Y45: =IFERROR(U45*V45,"-") -> 1086.4995 | Z45: OK
A46: 3103110072 | B46: - | C46: ACIDO TANICO | D46: 13 | E46: =IFERROR(IFERROR(VLOOKUP(B46,[1]Planilha1!$A$4:$C$277,3,0),VLOOKUP(A46,[1]Planilha1!$A$4:$C$277,3,0)),0) -> 0 | F46: =IFERROR(IFERROR(VLOOKUP(A46,[2]Planilha1!$A$4:$C$258,3,0),VLOOKUP(B46,[2]Planilha1!$A$4:$C$258,3,0)),0) -> 0 | G46: =IFERROR(IFERROR(VLOOKUP(A46,[1]Planilha1!$A$4:$D$277,4,0),VLOOKUP(B46,[1]Planilha1!$A$4:$D$277,4,0)),0) -> 0 | H46: =D46+E46-G46 -> 13 | I46: CERVEJARIA | J46: 1 | K46: =VLOOKUP(A46,CONT_ANTE!A:D,4,0) -> 13 | L46: =IF(AND(F46=0,K46<>M46),"!@##@!","ok") -> ok | M46: =IFERROR(VLOOKUP(A46,CONTAGEM!B:G,6,0),VLOOKUP(B46,CONTAGEM!B:G,6,0)) -> 13 | N46: =IFERROR(SUM(M46*V46),0) -> 48.449375 | O46: =SUMIF(SISTEMA!B:B,A46,SISTEMA!I:I)/J46 -> 0 | P46: =SUMIF(SISTEMA!B:B,B46,SISTEMA!I:I) -> 0 | Q46: 13 | R46: =IFERROR(SUM(Q46*V46),0) -> 48.449375 | S46: =IFERROR(VLOOKUP(A46,DIF_ANTE!A:D,4,0),"0")/J46 -> 0 | T46: =M46-Q46 -> 0 | U46: =T46-S46 -> 0 | V46: =IFERROR(VLOOKUP(A46,CUSTO!A:C,3,0),VLOOKUP(B46,CUSTO!A:C,3,0)) -> 3.726875 | W46: =IFERROR(SUM(T46*V46),0) -> 0 | X46: =IFERROR(T46/Q46,"") -> 0 | Y46: =IFERROR(U46*V46,"-") -> 0 | Z46: OK
A47: 2701210005 | B47: - | C47: ALGINATO PROPILENO GLICOL | D47: 838.1 | E47: =IFERROR(IFERROR(VLOOKUP(B47,[1]Planilha1!$A$4:$C$277,3,0),VLOOKUP(A47,[1]Planilha1!$A$4:$C$277,3,0)),0) -> 0 | F47: =IFERROR(IFERROR(VLOOKUP(A47,[2]Planilha1!$A$4:$C$258,3,0),VLOOKUP(B47,[2]Planilha1!$A$4:$C$258,3,0)),0) -> 17.91918 | G47: =IFERROR(IFERROR(VLOOKUP(A47,[1]Planilha1!$A$4:$D$277,4,0),VLOOKUP(B47,[1]Planilha1!$A$4:$D$277,4,0)),0) -> 17.91918 | H47: =D47+E47-G47 -> 820.18082 | I47: CERVEJARIA | J47: 1 | K47: =VLOOKUP(A47,CONT_ANTE!A:D,4,0) -> 950 | L47: =IF(AND(F47=0,K47<>M47),"!@##@!","ok") -> ok | M47: =IFERROR(VLOOKUP(A47,CONTAGEM!B:G,6,0),VLOOKUP(B47,CONTAGEM!B:G,6,0)) -> 875 | N47: =IFERROR(SUM(M47*V47),0) -> 183757 | O47: =SUMIF(SISTEMA!B:B,A47,SISTEMA!I:I)/J47 -> 821.9 | P47: =SUMIF(SISTEMA!B:B,B47,SISTEMA!I:I) -> 0 | Q47: =O47+P47 -> 821.9 | R47: =IFERROR(SUM(Q47*V47),0) -> 172605.58 | S47: =IFERROR(VLOOKUP(A47,DIF_ANTE!A:D,4,0),"0")/J47 -> 111.9 | T47: =M47-Q47 -> 53.1 | U47: =T47-S47 -> -58.8 | V47: =IFERROR(VLOOKUP(A47,CUSTO!A:C,3,0),VLOOKUP(B47,CUSTO!A:C,3,0)) -> 210.008 | W47: =IFERROR(SUM(T47*V47),0) -> 11151.425 | X47: =IFERROR(T47/Q47,"") -> 0.0646064 | Y47: =IFERROR(U47*V47,"-") -> -12348.47 | Z47: OK
A48: 2701090005 | B48: - | C48: ANTIOXIDANTE INNODOX BEER | D48: 65.08006 | E48: =IFERROR(IFERROR(VLOOKUP(B48,[1]Planilha1!$A$4:$C$277,3,0),VLOOKUP(A48,[1]Planilha1!$A$4:$C$277,3,0)),0) -> 100 | F48: =IFERROR(IFERROR(VLOOKUP(A48,[2]Planilha1!$A$4:$C$258,3,0),VLOOKUP(B48,[2]Planilha1!$A$4:$C$258,3,0)),0) -> 15 | G48: =IFERROR(IFERROR(VLOOKUP(A48,[1]Planilha1!$A$4:$D$277,4,0),VLOOKUP(B48,[1]Planilha1!$A$4:$D$277,4,0)),0) -> 15 | H48: =D48+E48-G48 -> 150.08006 | I48: CERVEJARIA | J48: 1 | K48: =VLOOKUP(A48,CONT_ANTE!A:D,4,0) -> 100 | L48: =IF(AND(F48=0,K48<>M48),"!@##@!","ok") -> ok | M48: =IFERROR(VLOOKUP(A48,CONTAGEM!B:G,6,0),VLOOKUP(B48,CONTAGEM!B:G,6,0)) -> 150.08 | N48: =IFERROR(SUM(M48*V48),0) -> 4109.5806 | O48: =SUMIF(SISTEMA!B:B,A48,SISTEMA!I:I)/J48 -> 150.08006 | P48: =SUMIF(SISTEMA!B:B,B48,SISTEMA!I:I) -> 0 | Q48: =O48+P48 -> 150.08006 | R48: =IFERROR(SUM(Q48*V48),0) -> 4109.5823 | S48: =IFERROR(VLOOKUP(A48,DIF_ANTE!A:D,4,0),"0")/J48 -> 34.91994 | T48: =M48-Q48 -> -6e-05 | U48: =T48-S48 -> -34.92 | V48: =IFERROR(VLOOKUP(A48,CUSTO!A:C,3,0),VLOOKUP(B48,CUSTO!A:C,3,0)) -> 27.3826 | W48: =IFERROR(SUM(T48*V48),0) -> -0.001642956 | X48: =IFERROR(T48/Q48,"") -> -3.9978662e-07 | Y48: =IFERROR(U48*V48,"-") -> -956.20039 | Z48: OK
A49: 2701210008 | B49: - | C49: BREWERS CLAREX | D49: 40 | E49: =IFERROR(IFERROR(VLOOKUP(B49,[1]Planilha1!$A$4:$C$277,3,0),VLOOKUP(A49,[1]Planilha1!$A$4:$C$277,3,0)),0) -> 0 | F49: =IFERROR(IFERROR(VLOOKUP(A49,[2]Planilha1!$A$4:$C$258,3,0),VLOOKUP(B49,[2]Planilha1!$A$4:$C$258,3,0)),0) -> 0 | G49: =IFERROR(IFERROR(VLOOKUP(A49,[1]Planilha1!$A$4:$D$277,4,0),VLOOKUP(B49,[1]Planilha1!$A$4:$D$277,4,0)),0) -> 0 | H49: =D49+E49-G49 -> 40 | I49: CERVEJARIA | J49: 1 | K49: =VLOOKUP(A49,CONT_ANTE!A:D,4,0) -> 50 | L49: =IF(AND(F49=0,K49<>M49),"!@##@!","ok") -> ok | M49: =IFERROR(VLOOKUP(A49,CONTAGEM!B:G,6,0),VLOOKUP(B49,CONTAGEM!B:G,6,0)) -> 50 | N49: =IFERROR(SUM(M49*V49),0) -> 15341.275 | O49: =SUMIF(SISTEMA!B:B,A49,SISTEMA!I:I)/J49 -> 40 | P49: =SUMIF(SISTEMA!B:B,B49,SISTEMA!I:I) -> 0 | Q49: =O49+P49 -> 40 | R49: =IFERROR(SUM(Q49*V49),0) -> 12273.02 | S49: =IFERROR(VLOOKUP(A49,DIF_ANTE!A:D,4,0),"0")/J49 -> 10 | T49: =M49-Q49 -> 10 | U49: =T49-S49 -> 0 | V49: =IFERROR(VLOOKUP(A49,CUSTO!A:C,3,0),VLOOKUP(B49,CUSTO!A:C,3,0)) -> 306.8255 | W49: =IFERROR(SUM(T49*V49),0) -> 3068.255 | X49: =IFERROR(T49/Q49,"") -> 0.25 | Y49: =IFERROR(U49*V49,"-") -> 0 | Z49: OK
A50: 2701250001 | B50: - | C50: CLORETO CALCIO | D50: 1113.83 | E50: =IFERROR(IFERROR(VLOOKUP(B50,[1]Planilha1!$A$4:$C$277,3,0),VLOOKUP(A50,[1]Planilha1!$A$4:$C$277,3,0)),0) -> 0 | F50: =IFERROR(IFERROR(VLOOKUP(A50,[2]Planilha1!$A$4:$C$258,3,0),VLOOKUP(B50,[2]Planilha1!$A$4:$C$258,3,0)),0) -> 246.73 | G50: =IFERROR(IFERROR(VLOOKUP(A50,[1]Planilha1!$A$4:$D$277,4,0),VLOOKUP(B50,[1]Planilha1!$A$4:$D$277,4,0)),0) -> 246.73 | H50: =D50+E50-G50 -> 867.1 | I50: CERVEJARIA | J50: 1 | K50: =VLOOKUP(A50,CONT_ANTE!A:D,4,0) -> 1050 | L50: =IF(AND(F50=0,K50<>M50),"!@##@!","ok") -> ok | M50: =IFERROR(VLOOKUP(A50,CONTAGEM!B:G,6,0),VLOOKUP(B50,CONTAGEM!B:G,6,0)) -> 900 | N50: =IFERROR(SUM(M50*V50),0) -> 4814.874 | O50: =SUMIF(SISTEMA!B:B,A50,SISTEMA!I:I)/J50 -> 867.1 | P50: =SUMIF(SISTEMA!B:B,B50,SISTEMA!I:I) -> 0 | Q50: =O50+P50 -> 867.1 | R50: =IFERROR(SUM(Q50*V50),0) -> 4638.8636 | S50: =IFERROR(VLOOKUP(A50,DIF_ANTE!A:D,4,0),"0")/J50 -> -63.83 | T50: =M50-Q50 -> 32.9 | U50: =T50-S50 -> 96.73 | V50: =IFERROR(VLOOKUP(A50,CUSTO!A:C,3,0),VLOOKUP(B50,CUSTO!A:C,3,0)) -> 5.34986 | W50: =IFERROR(SUM(T50*V50),0) -> 176.01039 | X50: =IFERROR(T50/Q50,"") -> 0.037942567 | Y50: =IFERROR(U50*V50,"-") -> 517.49196 | Z50: OK
A51: 2701060006 | B51: - | C51: CORANTE CARAMELO CERVEJA | D51: 363.25817 | E51: =IFERROR(IFERROR(VLOOKUP(B51,[1]Planilha1!$A$4:$C$277,3,0),VLOOKUP(A51,[1]Planilha1!$A$4:$C$277,3,0)),0) -> 504 | F51: =IFERROR(IFERROR(VLOOKUP(A51,[2]Planilha1!$A$4:$C$258,3,0),VLOOKUP(B51,[2]Planilha1!$A$4:$C$258,3,0)),0) -> 29 | G51: =IFERROR(IFERROR(VLOOKUP(A51,[1]Planilha1!$A$4:$D$277,4,0),VLOOKUP(B51,[1]Planilha1!$A$4:$D$277,4,0)),0) -> 29 | H51: =D51+E51-G51 -> 838.25817 | I51: CERVEJARIA | J51: 1 | K51: =VLOOKUP(A51,CONT_ANTE!A:D,4,0) -> 560 | L51: =IF(AND(F51=0,K51<>M51),"!@##@!","ok") -> ok | M51: =IFERROR(VLOOKUP(A51,CONTAGEM!B:G,6,0),VLOOKUP(B51,CONTAGEM!B:G,6,0)) -> 1008 | N51: =IFERROR(SUM(M51*V51),0) -> 7339.8 | O51: =SUMIF(SISTEMA!B:B,A51,SISTEMA!I:I)/J51 -> 838.25817 | P51: =SUMIF(SISTEMA!B:B,B51,SISTEMA!I:I) -> 0 | Q51: =O51+P51 -> 838.25817 | R51: =IFERROR(SUM(Q51*V51),0) -> 6103.8168 | S51: =IFERROR(VLOOKUP(A51,DIF_ANTE!A:D,4,0),"0")/J51 -> 196.74183 | T51: =M51-Q51 -> 169.74183 | U51: =T51-S51 -> -27 | V51: =IFERROR(VLOOKUP(A51,CUSTO!A:C,3,0),VLOOKUP(B51,CUSTO!A:C,3,0)) -> 7.2815476 | W51: =IFERROR(SUM(T51*V51),0) -> 1235.9832 | X51: =IFERROR(T51/Q51,"") -> 0.2024935 | Y51: =IFERROR(U51*V51,"-") -> -196.60179 | Z51: OK
A52: 2701210007 | B52: - | C52: ENZIMAS LISOBEER | D52: 5.5 | E52: =IFERROR(IFERROR(VLOOKUP(B52,[1]Planilha1!$A$4:$C$277,3,0),VLOOKUP(A52,[1]Planilha1!$A$4:$C$277,3,0)),0) -> 0 | F52: =IFERROR(IFERROR(VLOOKUP(A52,[2]Planilha1!$A$4:$C$258,3,0),VLOOKUP(B52,[2]Planilha1!$A$4:$C$258,3,0)),0) -> 5.5 | G52: =IFERROR(IFERROR(VLOOKUP(A52,[1]Planilha1!$A$4:$D$277,4,0),VLOOKUP(B52,[1]Planilha1!$A$4:$D$277,4,0)),0) -> 5.5 | H52: =D52+E52-G52 -> 0 | I52: CERVEJARIA | J52: 1 | K52: =VLOOKUP(A52,CONT_ANTE!A:D,4,0) -> 5.5 | L52: =IF(AND(F52=0,K52<>M52),"!@##@!","ok") -> ok | M52: =IFERROR(VLOOKUP(A52,CONTAGEM!B:G,6,0),VLOOKUP(B52,CONTAGEM!B:G,6,0)) -> 0 | N52: =IFERROR(SUM(M52*V52),0) -> 0 | O52: =SUMIF(SISTEMA!B:B,A52,SISTEMA!I:I)/J52 -> 0 | P52: =SUMIF(SISTEMA!B:B,B52,SISTEMA!I:I) -> 0 | Q52: =O52+P52 -> 0 | R52: =IFERROR(SUM(Q52*V52),0) -> 0 | S52: =IFERROR(VLOOKUP(A52,DIF_ANTE!A:D,4,0),"0")/J52 -> 0 | T52: =M52-Q52 -> 0 | U52: =T52-S52 -> 0 | V52: =IFERROR(VLOOKUP(A52,CUSTO!A:C,3,0),VLOOKUP(B52,CUSTO!A:C,3,0)) -> 657.806 | W52: =IFERROR(SUM(T52*V52),0) -> 0 | X52: =IFERROR(T52/Q52,"") | Y52: =IFERROR(U52*V52,"-") -> 0 | Z52: OK
A53: 2701210004 | B53: - | C53: ENZIMAS ULTRAFLO | D53: 82.3 | E53: =IFERROR(IFERROR(VLOOKUP(B53,[1]Planilha1!$A$4:$C$277,3,0),VLOOKUP(A53,[1]Planilha1!$A$4:$C$277,3,0)),0) -> 150 | F53: =IFERROR(IFERROR(VLOOKUP(A53,[2]Planilha1!$A$4:$C$258,3,0),VLOOKUP(B53,[2]Planilha1!$A$4:$C$258,3,0)),0) -> 52.3 | G53: =IFERROR(IFERROR(VLOOKUP(A53,[1]Planilha1!$A$4:$D$277,4,0),VLOOKUP(B53,[1]Planilha1!$A$4:$D$277,4,0)),0) -> 52.3 | H53: =D53+E53-G53 -> 180 | I53: CERVEJARIA | J53: 1 | K53: =VLOOKUP(A53,CONT_ANTE!A:D,4,0) -> 75 | L53: =IF(AND(F53=0,K53<>M53),"!@##@!","ok") -> ok | M53: =IFERROR(VLOOKUP(A53,CONTAGEM!B:G,6,0),VLOOKUP(B53,CONTAGEM!B:G,6,0)) -> 180 | N53: =IFERROR(SUM(M53*V53),0) -> 11384.94 | O53: =SUMIF(SISTEMA!B:B,A53,SISTEMA!I:I)/J53 -> 180 | P53: =SUMIF(SISTEMA!B:B,B53,SISTEMA!I:I) -> 0 | Q53: =O53+P53 -> 180 | R53: =IFERROR(SUM(Q53*V53),0) -> 11384.94 | S53: =IFERROR(VLOOKUP(A53,DIF_ANTE!A:D,4,0),"0")/J53 -> -7.3 | T53: =M53-Q53 -> 0 | U53: =T53-S53 -> 7.3 | V53: =IFERROR(VLOOKUP(A53,CUSTO!A:C,3,0),VLOOKUP(B53,CUSTO!A:C,3,0)) -> 63.249667 | W53: =IFERROR(SUM(T53*V53),0) -> 0 | X53: =IFERROR(T53/Q53,"") -> 0 | Y53: =IFERROR(U53*V53,"-") -> 461.72257 | Z53: OK
A54: 2701210003 | B54: - | C54: ESTABILIZANTE PVPP CLEAR MAX | D54: 98.1632 | E54: =IFERROR(IFERROR(VLOOKUP(B54,[1]Planilha1!$A$4:$C$277,3,0),VLOOKUP(A54,[1]Planilha1!$A$4:$C$277,3,0)),0) -> 80 | F54: =IFERROR(IFERROR(VLOOKUP(A54,[2]Planilha1!$A$4:$C$258,3,0),VLOOKUP(B54,[2]Planilha1!$A$4:$C$258,3,0)),0) -> 64.115 | G54: =IFERROR(IFERROR(VLOOKUP(A54,[1]Planilha1!$A$4:$D$277,4,0),VLOOKUP(B54,[1]Planilha1!$A$4:$D$277,4,0)),0) -> 64.115 | H54: =D54+E54-G54 -> 114.0482 | I54: CERVEJARIA | J54: 1 | K54: =VLOOKUP(A54,CONT_ANTE!A:D,4,0) -> 100 | L54: =IF(AND(F54=0,K54<>M54),"!@##@!","ok") -> ok | M54: =IFERROR(VLOOKUP(A54,CONTAGEM!B:G,6,0),VLOOKUP(B54,CONTAGEM!B:G,6,0)) -> 120 | N54: =IFERROR(SUM(M54*V54),0) -> 14756.856 | O54: =SUMIF(SISTEMA!B:B,A54,SISTEMA!I:I)/J54 -> 114.0482 | P54: =SUMIF(SISTEMA!B:B,B54,SISTEMA!I:I) -> 0 | Q54: =O54+P54 -> 114.0482 | R54: =IFERROR(SUM(Q54*V54),0) -> 14024.941 | S54: =IFERROR(VLOOKUP(A54,DIF_ANTE!A:D,4,0),"0")/J54 -> 1.8368 | T54: =M54-Q54 -> 5.9518 | U54: =T54-S54 -> 4.115 | V54: =IFERROR(VLOOKUP(A54,CUSTO!A:C,3,0),VLOOKUP(B54,CUSTO!A:C,3,0)) -> 122.9738 | W54: =IFERROR(SUM(T54*V54),0) -> 731.91546 | X54: =IFERROR(T54/Q54,"") -> 0.052186707 | Y54: =IFERROR(U54*V54,"-") -> 506.03719 | Z54: OK
A55: 2701220001 | B55: - | C55: FERMENTO CERVEJEIRO FERMENTIS W-34/70 | D55: 10.5 | E55: =IFERROR(IFERROR(VLOOKUP(B55,[1]Planilha1!$A$4:$C$277,3,0),VLOOKUP(A55,[1]Planilha1!$A$4:$C$277,3,0)),0) -> 0 | F55: =IFERROR(IFERROR(VLOOKUP(A55,[2]Planilha1!$A$4:$C$258,3,0),VLOOKUP(B55,[2]Planilha1!$A$4:$C$258,3,0)),0) -> 0 | G55: =IFERROR(IFERROR(VLOOKUP(A55,[1]Planilha1!$A$4:$D$277,4,0),VLOOKUP(B55,[1]Planilha1!$A$4:$D$277,4,0)),0) -> 0 | H55: =D55+E55-G55 -> 10.5 | I55: CERVEJARIA | J55: 1 | K55: =VLOOKUP(A55,CONT_ANTE!A:D,4,0) -> 12 | L55: =IF(AND(F55=0,K55<>M55),"!@##@!","ok") -> ok | M55: =IFERROR(VLOOKUP(A55,CONTAGEM!B:G,6,0),VLOOKUP(B55,CONTAGEM!B:G,6,0)) -> 12 | N55: =IFERROR(SUM(M55*V55),0) -> 10461.504 | O55: =SUMIF(SISTEMA!B:B,A55,SISTEMA!I:I)/J55 -> 10.5 | P55: =SUMIF(SISTEMA!B:B,B55,SISTEMA!I:I) -> 0 | Q55: =O55+P55 -> 10.5 | R55: =IFERROR(SUM(Q55*V55),0) -> 9153.816 | S55: =IFERROR(VLOOKUP(A55,DIF_ANTE!A:D,4,0),"0")/J55 -> 1.5 | T55: =M55-Q55 -> 1.5 | U55: =T55-S55 -> 0 | V55: =IFERROR(VLOOKUP(A55,CUSTO!A:C,3,0),VLOOKUP(B55,CUSTO!A:C,3,0)) -> 871.792 | W55: =IFERROR(SUM(T55*V55),0) -> 1307.688 | X55: =IFERROR(T55/Q55,"") -> 0.14285714 | Y55: =IFERROR(U55*V55,"-") -> 0 | Z55: OK
A56: 2701210009 | B56: - | C56: MATUFAST DIMETILPOLISILOXANO | D56: 21 | E56: =IFERROR(IFERROR(VLOOKUP(B56,[1]Planilha1!$A$4:$C$277,3,0),VLOOKUP(A56,[1]Planilha1!$A$4:$C$277,3,0)),0) -> 0 | F56: =IFERROR(IFERROR(VLOOKUP(A56,[2]Planilha1!$A$4:$C$258,3,0),VLOOKUP(B56,[2]Planilha1!$A$4:$C$258,3,0)),0) -> 0 | G56: =IFERROR(IFERROR(VLOOKUP(A56,[1]Planilha1!$A$4:$D$277,4,0),VLOOKUP(B56,[1]Planilha1!$A$4:$D$277,4,0)),0) -> 0 | H56: =D56+E56-G56 -> 21 | I56: CERVEJARIA | J56: 1 | K56: =VLOOKUP(A56,CONT_ANTE!A:D,4,0) -> 21 | L56: =IF(AND(F56=0,K56<>M56),"!@##@!","ok") -> ok | M56: =IFERROR(VLOOKUP(A56,CONTAGEM!B:G,6,0),VLOOKUP(B56,CONTAGEM!B:G,6,0)) -> 21 | N56: =IFERROR(SUM(M56*V56),0) -> 16306.97 | O56: =SUMIF(SISTEMA!B:B,A56,SISTEMA!I:I)/J56 -> 21 | P56: =SUMIF(SISTEMA!B:B,B56,SISTEMA!I:I) -> 0 | Q56: =O56+P56 -> 21 | R56: =IFERROR(SUM(Q56*V56),0) -> 16306.97 | S56: =IFERROR(VLOOKUP(A56,DIF_ANTE!A:D,4,0),"0")/J56 -> 0 | T56: =M56-Q56 -> 0 | U56: =T56-S56 -> 0 | V56: =IFERROR(VLOOKUP(A56,CUSTO!A:C,3,0),VLOOKUP(B56,CUSTO!A:C,3,0)) -> 776.5224 | W56: =IFERROR(SUM(T56*V56),0) -> 0 | X56: =IFERROR(T56/Q56,"") -> 0 | Y56: =IFERROR(U56*V56,"-") -> 0 | Z56: OK
A57: 2701210002 | B57: - | C57: SILICA HP 9000 DERACLAR | D57: 1247.0499 | E57: =IFERROR(IFERROR(VLOOKUP(B57,[1]Planilha1!$A$4:$C$277,3,0),VLOOKUP(A57,[1]Planilha1!$A$4:$C$277,3,0)),0) -> 0 | F57: =IFERROR(IFERROR(VLOOKUP(A57,[2]Planilha1!$A$4:$C$258,3,0),VLOOKUP(B57,[2]Planilha1!$A$4:$C$258,3,0)),0) -> 30 | G57: =IFERROR(IFERROR(VLOOKUP(A57,[1]Planilha1!$A$4:$D$277,4,0),VLOOKUP(B57,[1]Planilha1!$A$4:$D$277,4,0)),0) -> 30 | H57: =D57+E57-G57 -> 1217.0499 | I57: CERVEJARIA | J57: 1 | K57: =VLOOKUP(A57,CONT_ANTE!A:D,4,0) -> 3510 | L57: =IF(AND(F57=0,K57<>M57),"!@##@!","ok") -> ok | M57: =IFERROR(VLOOKUP(A57,CONTAGEM!B:G,6,0),VLOOKUP(B57,CONTAGEM!B:G,6,0)) -> 3480 | N57: =IFERROR(SUM(M57*V57),0) -> 103607.19 | O57: =SUMIF(SISTEMA!B:B,A57,SISTEMA!I:I)/J57 -> 1217.0499 | P57: =SUMIF(SISTEMA!B:B,B57,SISTEMA!I:I) -> 0 | Q57: =O57+P57 -> 1217.0499 | R57: =IFERROR(SUM(Q57*V57),0) -> 36234.231 | S57: =IFERROR(VLOOKUP(A57,DIF_ANTE!A:D,4,0),"0")/J57 -> 2262.9501 | T57: =M57-Q57 -> 2262.9501 | U57: =T57-S57 -> 0 | V57: =IFERROR(VLOOKUP(A57,CUSTO!A:C,3,0),VLOOKUP(B57,CUSTO!A:C,3,0)) -> 29.772182 | W57: =IFERROR(SUM(T57*V57),0) -> 67372.963 | X57: =IFERROR(T57/Q57,"") -> 1.8593734 | Y57: =IFERROR(U57*V57,"-") -> 0 | Z57: OK
A58: 2701210006 | B58: - | C58: TANINO SETABREW | D58: 12 | E58: =IFERROR(IFERROR(VLOOKUP(B58,[1]Planilha1!$A$4:$C$277,3,0),VLOOKUP(A58,[1]Planilha1!$A$4:$C$277,3,0)),0) -> 0 | F58: =IFERROR(IFERROR(VLOOKUP(A58,[2]Planilha1!$A$4:$C$258,3,0),VLOOKUP(B58,[2]Planilha1!$A$4:$C$258,3,0)),0) -> 0 | G58: =IFERROR(IFERROR(VLOOKUP(A58,[1]Planilha1!$A$4:$D$277,4,0),VLOOKUP(B58,[1]Planilha1!$A$4:$D$277,4,0)),0) -> 0 | H58: =D58+E58-G58 -> 12 | I58: CERVEJARIA | J58: =IFERROR(VLOOKUP(CONCILIÇÃO_COM_CERVEJA!$A58,'BASE PRODUTOS'!A:E,5,0),"") -> 1 | K58: =VLOOKUP(A58,CONT_ANTE!A:D,4,0) -> 14 | L58: =IF(AND(F58=0,K58<>M58),"!@##@!","ok") -> ok | M58: =IFERROR(VLOOKUP(A58,CONTAGEM!B:G,6,0),VLOOKUP(B58,CONTAGEM!B:G,6,0)) -> 14 | N58: =IFERROR(SUM(M58*V58),0) -> 5341.6533 | O58: =SUMIF(SISTEMA!B:B,A58,SISTEMA!I:I)/J58 -> 12 | P58: =SUMIF(SISTEMA!B:B,B58,SISTEMA!I:I) -> 0 | Q58: =O58+P58 -> 12 | R58: =IFERROR(SUM(Q58*V58),0) -> 4578.56 | S58: =IFERROR(VLOOKUP(A58,DIF_ANTE!A:D,4,0),"0")/J58 -> 2 | T58: =M58-Q58 -> 2 | U58: =T58-S58 -> 0 | V58: =IFERROR(VLOOKUP(A58,CUSTO!A:C,3,0),VLOOKUP(B58,CUSTO!A:C,3,0)) -> 381.54667 | W58: =IFERROR(SUM(T58*V58),0) -> 763.09333 | X58: =IFERROR(T58/Q58,"") -> 0.16666667 | Y58: =IFERROR(U58*V58,"-") -> 0 | Z58: OK
A59: 2701190004 | B59: - | C59: XAROPE HIGH MALTOSE | D59: 15106.295 | E59: =IFERROR(IFERROR(VLOOKUP(B59,[1]Planilha1!$A$4:$C$277,3,0),VLOOKUP(A59,[1]Planilha1!$A$4:$C$277,3,0)),0) -> 60330 | F59: =IFERROR(IFERROR(VLOOKUP(A59,[2]Planilha1!$A$4:$C$258,3,0),VLOOKUP(B59,[2]Planilha1!$A$4:$C$258,3,0)),0) -> 15920.52 | G59: =IFERROR(IFERROR(VLOOKUP(A59,[1]Planilha1!$A$4:$D$277,4,0),VLOOKUP(B59,[1]Planilha1!$A$4:$D$277,4,0)),0) -> 15920.52 | H59: =D59+E59-G59 -> 59515.775 | I59: CERVEJARIA | J59: 1 | K59: =VLOOKUP(A59,CONT_ANTE!A:D,4,0) -> 16464 | L59: =IF(AND(F59=0,K59<>M59),"!@##@!","ok") -> ok | M59: =IFERROR(VLOOKUP(A59,CONTAGEM!B:G,6,0),VLOOKUP(B59,CONTAGEM!B:G,6,0)) -> 60445 | N59: =IFERROR(SUM(M59*V59),0) -> 141673.71 | O59: =SUMIF(SISTEMA!B:B,A59,SISTEMA!I:I)/J59 -> 59543.045 | P59: =SUMIF(SISTEMA!B:B,B59,SISTEMA!I:I) -> 0 | Q59: =O59+P59 -> 59543.045 | R59: =IFERROR(SUM(Q59*V59),0) -> 139559.67 | S59: =IFERROR(VLOOKUP(A59,DIF_ANTE!A:D,4,0),"0")/J59 -> 1357.705 | T59: =M59-Q59 -> 901.955 | U59: =T59-S59 -> -455.75 | V59: =IFERROR(VLOOKUP(A59,CUSTO!A:C,3,0),VLOOKUP(B59,CUSTO!A:C,3,0)) -> 2.3438449 | W59: =IFERROR(SUM(T59*V59),0) -> 2114.0427 | X59: =IFERROR(T59/Q59,"") -> 0.015147949 | Y59: =IFERROR(U59*V59,"-") -> -1068.2073 | Z59: OK
A60: 2701050024 | B60: - | C60: CONCENTRADO BEBIDA ENERGETICA AF883 ACAI ADM | D60: 0.010249402 | E60: =IFERROR(IFERROR(VLOOKUP(B60,[1]Planilha1!$A$4:$C$277,3,0),VLOOKUP(A60,[1]Planilha1!$A$4:$C$277,3,0)),0) -> 0 | F60: =IFERROR(IFERROR(VLOOKUP(A60,[2]Planilha1!$A$4:$C$258,3,0),VLOOKUP(B60,[2]Planilha1!$A$4:$C$258,3,0)),0) -> 0 | G60: =IFERROR(IFERROR(VLOOKUP(A60,[1]Planilha1!$A$4:$D$277,4,0),VLOOKUP(B60,[1]Planilha1!$A$4:$D$277,4,0)),0) -> 0 | H60: =D60+E60-G60 -> 0.010249402 | I60: CONCENTRADO | J60: =IFERROR(VLOOKUP(CONCILIÇÃO_COM_CERVEJA!$A60,'BASE PRODUTOS'!A:E,5,0),"") -> 58.54 | K60: =VLOOKUP(A60,CONT_ANTE!A:D,4,0) -> 0 | L60: =IF(AND(F60=0,K60<>M60),"!@##@!","ok") -> ok | M60: =IFERROR(VLOOKUP(A60,CONTAGEM!B:G,6,0),VLOOKUP(B60,CONTAGEM!B:G,6,0)) -> 0 | N60: =IFERROR(SUM(M60*V60),0) -> 0 | O60: =SUMIF(SISTEMA!B:B,A60,SISTEMA!I:I)/J60 -> 0.010249402 | P60: =SUMIF(SISTEMA!B:B,B60,SISTEMA!I:I) -> 0 | Q60: =O60+P60 -> 0.010249402 | R60: =IFERROR(SUM(Q60*V60),0) -> 0.32787812 | S60: =IFERROR(VLOOKUP(A60,DIF_ANTE!A:D,4,0),"0")/J60 -> -0.00017508374 | T60: =M60-Q60 -> -0.010249402 | U60: =T60-S60 -> -0.010074318 | V60: =IFERROR(VLOOKUP(A60,CUSTO!A:C,3,0),VLOOKUP(B60,CUSTO!A:C,3,0)) -> 31.989975 | W60: =IFERROR(SUM(T60*V60),0) -> -0.32787812 | X60: =IFERROR(T60/Q60,"") -> -1 | Y60: =IFERROR(U60*V60,"-") -> -0.32227719 | Z60: OK
A61: 2701050025 | B61: 2701050040 | C61: CONCENTRADO BEBIDA ENERGETICA TRADICIONAL ADM | D61: 4.853778 | E61: =IFERROR(IFERROR(VLOOKUP(B61,[1]Planilha1!$A$4:$C$277,3,0),VLOOKUP(A61,[1]Planilha1!$A$4:$C$277,3,0)),0) -> 434 | F61: =IFERROR(IFERROR(VLOOKUP(A61,[2]Planilha1!$A$4:$C$258,3,0),VLOOKUP(B61,[2]Planilha1!$A$4:$C$258,3,0)),0) -> 123 | G61: =IFERROR(IFERROR(VLOOKUP(A61,[1]Planilha1!$A$4:$D$277,4,0),VLOOKUP(B61,[1]Planilha1!$A$4:$D$277,4,0)),0) -> 24537.65 | H61: =D61+E61-G61 -> -24098.796 | I61: CONCENTRADO | J61: =IFERROR(VLOOKUP(CONCILIÇÃO_COM_CERVEJA!$A61,'BASE PRODUTOS'!A:E,5,0),"") -> 57.44 | K61: =VLOOKUP(A61,CONT_ANTE!A:D,4,0) -> 226 | L61: =IF(AND(F61=0,K61<>M61),"!@##@!","ok") -> ok | M61: =IFERROR(VLOOKUP(A61,CONTAGEM!B:G,6,0),VLOOKUP(B61,CONTAGEM!B:G,6,0)) -> 120 | N61: =IFERROR(SUM(M61*V61),0) -> 3679.5245 | O61: =SUMIF(SISTEMA!B:B,A61,SISTEMA!I:I)/J61 -> 0 | P61: =SUMIF(SISTEMA!B:B,B61,SISTEMA!I:I) -> 76 | Q61: =(O61+P61) -> 76 | R61: =IFERROR(SUM(Q61*V61),0) -> 2330.3655 | S61: =IFERROR(VLOOKUP(A61,DIF_ANTE!A:D,4,0),"0")/J61 -> 3.8500387 | T61: =M61-Q61 -> 44 | U61: =T61-S61 -> 40.149961 | V61: =IFERROR(VLOOKUP(A61,CUSTO!A:C,3,0),VLOOKUP(B61,CUSTO!A:C,3,0)) -> 30.662704 | W61: =IFERROR(SUM(T61*V61),0) -> 1349.159 | X61: =IFERROR(T61/Q61,"") -> 0.57894737 | Y61: =IFERROR(U61*V61,"-") -> 1231.1064 | Z61: OK
A62: 2701050022 | B62: - | C62: CONCENTRADO TUBAINA 7205 INTERAMERICAS | D62: 2227.09 | E62: =IFERROR(IFERROR(VLOOKUP(B62,[1]Planilha1!$A$4:$C$277,3,0),VLOOKUP(A62,[1]Planilha1!$A$4:$C$277,3,0)),0) -> 0 | F62: =IFERROR(IFERROR(VLOOKUP(A62,[2]Planilha1!$A$4:$C$258,3,0),VLOOKUP(B62,[2]Planilha1!$A$4:$C$258,3,0)),0) -> 477.55 | G62: =IFERROR(IFERROR(VLOOKUP(A62,[1]Planilha1!$A$4:$D$277,4,0),VLOOKUP(B62,[1]Planilha1!$A$4:$D$277,4,0)),0) -> 477.55 | H62: =D62+E62-G62 -> 1749.54 | I62: CONCENTRADO | J62: 1 | K62: =VLOOKUP(A62,CONT_ANTE!A:D,4,0) -> 2158 | L62: =IF(AND(F62=0,K62<>M62),"!@##@!","ok") -> ok | M62: =IFERROR(VLOOKUP(A62,CONTAGEM!B:G,6,0),VLOOKUP(B62,CONTAGEM!B:G,6,0)) -> 1725 | N62: =IFERROR(SUM(M62*V62),0) -> 37662.391 | O62: =SUMIF(SISTEMA!B:B,A62,SISTEMA!I:I)/J62 -> 1724.84 | P62: =SUMIF(SISTEMA!B:B,B62,SISTEMA!I:I) -> 0 | Q62: =O62+P62 -> 1724.84 | R62: =IFERROR(SUM(Q62*V62),0) -> 37658.897 | S62: =IFERROR(VLOOKUP(A62,DIF_ANTE!A:D,4,0),"0")/J62 -> -69.09 | T62: =M62-Q62 -> 0.16 | U62: =T62-S62 -> 69.25 | V62: =IFERROR(VLOOKUP(A62,CUSTO!A:C,3,0),VLOOKUP(B62,CUSTO!A:C,3,0)) -> 21.83327 | W62: =IFERROR(SUM(T62*V62),0) -> 3.4933232 | X62: =IFERROR(T62/Q62,"") -> 9.2762227e-05 | Y62: =IFERROR(U62*V62,"-") -> 1511.9539 | Z62: OK
A63: 2901050016 | B63: - | C63: CONCENTRADO TUBAINA FUNADA | D63: 22.674902 | E63: =IFERROR(IFERROR(VLOOKUP(B63,[1]Planilha1!$A$4:$C$277,3,0),VLOOKUP(A63,[1]Planilha1!$A$4:$C$277,3,0)),0) -> 369.12 | F63: =IFERROR(IFERROR(VLOOKUP(A63,[2]Planilha1!$A$4:$C$258,3,0),VLOOKUP(B63,[2]Planilha1!$A$4:$C$258,3,0)),0) -> 234.7 | G63: =IFERROR(IFERROR(VLOOKUP(A63,[1]Planilha1!$A$4:$D$277,4,0),VLOOKUP(B63,[1]Planilha1!$A$4:$D$277,4,0)),0) -> 234.7 | H63: =D63+E63-G63 -> 157.0949 | I63: CONCENTRADO | J63: =IFERROR(VLOOKUP(CONCILIÇÃO_COM_CERVEJA!$A63,'BASE PRODUTOS'!A:E,5,0),"") -> 15.38 | K63: =VLOOKUP(A63,CONT_ANTE!A:D,4,0) -> 0 | L63: =IF(AND(F63=0,K63<>M63),"!@##@!","ok") -> ok | M63: =IFERROR(VLOOKUP(A63,CONTAGEM!B:G,6,0),VLOOKUP(B63,CONTAGEM!B:G,6,0)) -> 28 | N63: =IFERROR(SUM(M63*V63),0) -> 804.44 | O63: =SUMIF(SISTEMA!B:B,A63,SISTEMA!I:I)/J63 -> 31.414824 | P63: =SUMIF(SISTEMA!B:B,B63,SISTEMA!I:I) -> 0 | Q63: =O63+P63 -> 31.414824 | R63: =IFERROR(SUM(Q63*V63),0) -> 902.54791 | S63: =IFERROR(VLOOKUP(A63,DIF_ANTE!A:D,4,0),"0")/J63 -> -1.474311 | T63: =M63-Q63 -> -3.4148244 | U63: =T63-S63 -> -1.9405135 | V63: =IFERROR(VLOOKUP(A63,CUSTO!A:C,3,0),VLOOKUP(B63,CUSTO!A:C,3,0)) -> 28.73 | W63: =IFERROR(SUM(T63*V63),0) -> -98.107906 | X63: =IFERROR(T63/Q63,"") -> -0.10870105 | Y63: =IFERROR(U63*V63,"-") -> -55.750953 | Z63: OK
A64: 2701130008 | B64: - | C64: POLPA ACAI DESIDRATADA SOLUVEL | D64: 0 | E64: =IFERROR(IFERROR(VLOOKUP(B64,[1]Planilha1!$A$4:$C$277,3,0),VLOOKUP(A64,[1]Planilha1!$A$4:$C$277,3,0)),0) -> 100 | F64: =IFERROR(IFERROR(VLOOKUP(A64,[2]Planilha1!$A$4:$C$258,3,0),VLOOKUP(B64,[2]Planilha1!$A$4:$C$258,3,0)),0) -> 0 | G64: =IFERROR(IFERROR(VLOOKUP(A64,[1]Planilha1!$A$4:$D$277,4,0),VLOOKUP(B64,[1]Planilha1!$A$4:$D$277,4,0)),0) -> 100 | H64: =D64+E64-G64 -> 0 | I64: CONCENTRADO | J64: 1 | K64: =VLOOKUP(A64,CONT_ANTE!A:D,4,0) -> 0 | L64: =IF(AND(F64=0,K64<>M64),"!@##@!","ok") -> ok | M64: =IFERROR(VLOOKUP(A64,CONTAGEM!B:G,6,0),VLOOKUP(B64,CONTAGEM!B:G,6,0)) -> 0 | N64: =IFERROR(SUM(M64*V64),0) -> 0 | O64: =SUMIF(SISTEMA!B:B,A64,SISTEMA!I:I)/J64 -> 0 | P64: =SUMIF(SISTEMA!B:B,B64,SISTEMA!I:I) -> 0 | Q64: =O64+P64 -> 0 | R64: =IFERROR(SUM(Q64*V64),0) -> 0 | S64: =IFERROR(VLOOKUP(A64,DIF_ANTE!A:D,4,0),"0")/J64 -> 0 | T64: =M64-Q64 -> 0 | U64: =T64-S64 -> 0 | V64: =IFERROR(VLOOKUP(A64,CUSTO!A:C,3,0),VLOOKUP(B64,CUSTO!A:C,3,0)) -> 44.2232 | W64: =IFERROR(SUM(T64*V64),0) -> 0 | X64: =IFERROR(T64/Q64,"") | Y64: =IFERROR(U64*V64,"-") -> 0 | Z64: OK
A65: 2701090001 | B65: - | C65: ACIDO ASCORBICO | D65: 0 | E65: =IFERROR(IFERROR(VLOOKUP(B65,[1]Planilha1!$A$4:$C$277,3,0),VLOOKUP(A65,[1]Planilha1!$A$4:$C$277,3,0)),0) -> 50 | F65: =IFERROR(IFERROR(VLOOKUP(A65,[2]Planilha1!$A$4:$C$258,3,0),VLOOKUP(B65,[2]Planilha1!$A$4:$C$258,3,0)),0) -> 4 | G65: =IFERROR(IFERROR(VLOOKUP(A65,[1]Planilha1!$A$4:$D$277,4,0),VLOOKUP(B65,[1]Planilha1!$A$4:$D$277,4,0)),0) -> 3.05 | H65: =D65+E65-G65 -> 46.95 | I65: CONSERVANTE | J65: 1 | K65: =VLOOKUP(A65,CONT_ANTE!A:D,4,0) -> 0 | L65: =IF(AND(F65=0,K65<>M65),"!@##@!","ok") -> ok | M65: =IFERROR(VLOOKUP(A65,CONTAGEM!B:G,6,0),VLOOKUP(B65,CONTAGEM!B:G,6,0)) -> 46 | N65: =IFERROR(SUM(M65*V65),0) -> 683.8544 | O65: =SUMIF(SISTEMA!B:B,A65,SISTEMA!I:I)/J65 -> 46.95 | P65: =SUMIF(SISTEMA!B:B,B65,SISTEMA!I:I) -> 0 | Q65: =O65+P65 -> 46.95 | R65: =IFERROR(SUM(Q65*V65),0) -> 697.97748 | S65: =IFERROR(VLOOKUP(A65,DIF_ANTE!A:D,4,0),"0")/J65 -> 0 | T65: =M65-Q65 -> -0.95 | U65: =T65-S65 -> -0.95 | V65: =IFERROR(VLOOKUP(A65,CUSTO!A:C,3,0),VLOOKUP(B65,CUSTO!A:C,3,0)) -> 14.8664 | W65: =IFERROR(SUM(T65*V65),0) -> -14.12308 | X65: =IFERROR(T65/Q65,"") -> -0.020234292 | Y65: =IFERROR(U65*V65,"-") -> -14.12308 | Z65: OK
A66: 2701090002 | B66: - | C66: ACIDO CITRICO | D66: 16115.727 | E66: =IFERROR(IFERROR(VLOOKUP(B66,[1]Planilha1!$A$4:$C$277,3,0),VLOOKUP(A66,[1]Planilha1!$A$4:$C$277,3,0)),0) -> 3772.93 | F66: =IFERROR(IFERROR(VLOOKUP(A66,[2]Planilha1!$A$4:$C$258,3,0),VLOOKUP(B66,[2]Planilha1!$A$4:$C$258,3,0)),0) -> 4479.786 | G66: =IFERROR(IFERROR(VLOOKUP(A66,[1]Planilha1!$A$4:$D$277,4,0),VLOOKUP(B66,[1]Planilha1!$A$4:$D$277,4,0)),0) -> 8252.716 | H66: =D66+E66-G66 -> 11635.941 | I66: CONSERVANTE | J66: 1 | K66: =VLOOKUP(A66,CONT_ANTE!A:D,4,0) -> 16103.5 | L66: =IF(AND(F66=0,K66<>M66),"!@##@!","ok") -> ok | M66: =IFERROR(VLOOKUP(A66,CONTAGEM!B:G,6,0),VLOOKUP(B66,CONTAGEM!B:G,6,0)) -> 11714.5 | N66: =IFERROR(SUM(M66*V66),0) -> 90263.168 | O66: =SUMIF(SISTEMA!B:B,A66,SISTEMA!I:I)/J66 -> 11825.081 | P66: =SUMIF(SISTEMA!B:B,B66,SISTEMA!I:I) -> 0 | Q66: =O66+P66 -> 11825.081 | R66: =IFERROR(SUM(Q66*V66),0) -> 91115.22 | S66: =IFERROR(VLOOKUP(A66,DIF_ANTE!A:D,4,0),"0")/J66 -> -12.22675 | T66: =M66-Q66 -> -110.58075 | U66: =T66-S66 -> -98.354 | V66: =IFERROR(VLOOKUP(A66,CUSTO!A:C,3,0),VLOOKUP(B66,CUSTO!A:C,3,0)) -> 7.7052514 | W66: =IFERROR(SUM(T66*V66),0) -> -852.05248 | X66: =IFERROR(T66/Q66,"") -> -0.0093513738 | Y66: =IFERROR(U66*V66,"-") -> -757.8423 | Z66: OK
A67: 2701090007 | B67: - | C67: ACIDO MALICO | D67: 4e-05 | E67: =IFERROR(IFERROR(VLOOKUP(B67,[1]Planilha1!$A$4:$C$277,3,0),VLOOKUP(A67,[1]Planilha1!$A$4:$C$277,3,0)),0) -> 0 | F67: =IFERROR(IFERROR(VLOOKUP(A67,[2]Planilha1!$A$4:$C$258,3,0),VLOOKUP(B67,[2]Planilha1!$A$4:$C$258,3,0)),0) -> 0 | G67: =IFERROR(IFERROR(VLOOKUP(A67,[1]Planilha1!$A$4:$D$277,4,0),VLOOKUP(B67,[1]Planilha1!$A$4:$D$277,4,0)),0) -> 0 | H67: =D67+E67-G67 -> 4e-05 | I67: CONSERVANTE | J67: 1 | K67: =VLOOKUP(A67,CONT_ANTE!A:D,4,0) -> 0 | L67: =IF(AND(F67=0,K67<>M67),"!@##@!","ok") -> ok | M67: 0 | N67: =IFERROR(SUM(M67*V67),0) -> 0 | O67: =SUMIF(SISTEMA!B:B,A67,SISTEMA!I:I)/J67 -> 4e-05 | P67: =SUMIF(SISTEMA!B:B,B67,SISTEMA!I:I) -> 0 | Q67: =O67+P67 -> 4e-05 | R67: =IFERROR(SUM(Q67*V67),0) -> 0.000356128 | S67: =IFERROR(VLOOKUP(A67,DIF_ANTE!A:D,4,0),"0")/J67 -> -4e-05 | T67: =M67-Q67 -> -4e-05 | U67: =T67-S67 -> 0 | V67: =IFERROR(VLOOKUP(A67,CUSTO!A:C,3,0),VLOOKUP(B67,CUSTO!A:C,3,0)) -> 8.9032 | W67: =IFERROR(SUM(T67*V67),0) -> -0.000356128 | X67: =IFERROR(T67/Q67,"") -> -1 | Y67: =IFERROR(U67*V67,"-") -> 0 | Z67: ok
A68: 2701090004 | B68: - | C68: ACIDO TARTARICO | D68: 260.47 | E68: =IFERROR(IFERROR(VLOOKUP(B68,[1]Planilha1!$A$4:$C$277,3,0),VLOOKUP(A68,[1]Planilha1!$A$4:$C$277,3,0)),0) -> 100 | F68: =IFERROR(IFERROR(VLOOKUP(A68,[2]Planilha1!$A$4:$C$258,3,0),VLOOKUP(B68,[2]Planilha1!$A$4:$C$258,3,0)),0) -> 59.34 | G68: =IFERROR(IFERROR(VLOOKUP(A68,[1]Planilha1!$A$4:$D$277,4,0),VLOOKUP(B68,[1]Planilha1!$A$4:$D$277,4,0)),0) -> 59.34 | H68: =D68+E68-G68 -> 301.13 | I68: CONSERVANTE | J68: 1 | K68: =VLOOKUP(A68,CONT_ANTE!A:D,4,0) -> 282.5 | L68: =IF(AND(F68=0,K68<>M68),"!@##@!","ok") -> ok | M68: =IFERROR(VLOOKUP(A68,CONTAGEM!B:G,6,0),VLOOKUP(B68,CONTAGEM!B:G,6,0)) -> 320 | N68: =IFERROR(SUM(M68*V68),0) -> 10382.288 | O68: =SUMIF(SISTEMA!B:B,A68,SISTEMA!I:I)/J68 -> 307.83 | P68: =SUMIF(SISTEMA!B:B,B68,SISTEMA!I:I) -> 0 | Q68: =O68+P68 -> 307.83 | R68: =IFERROR(SUM(Q68*V68),0) -> 9987.4366 | S68: =IFERROR(VLOOKUP(A68,DIF_ANTE!A:D,4,0),"0")/J68 -> 22.03 | T68: =M68-Q68 -> 12.17 | U68: =T68-S68 -> -9.86 | V68: =IFERROR(VLOOKUP(A68,CUSTO!A:C,3,0),VLOOKUP(B68,CUSTO!A:C,3,0)) -> 32.44465 | W68: =IFERROR(SUM(T68*V68),0) -> 394.85139 | X68: =IFERROR(T68/Q68,"") -> 0.039534808 | Y68: =IFERROR(U68*V68,"-") -> -319.90425 | Z68: OK
A69: 2701100002 | B69: - | C69: BENZOATO SODIO | D69: 2937.607 | E69: =IFERROR(IFERROR(VLOOKUP(B69,[1]Planilha1!$A$4:$C$277,3,0),VLOOKUP(A69,[1]Planilha1!$A$4:$C$277,3,0)),0) -> 1500 | F69: =IFERROR(IFERROR(VLOOKUP(A69,[2]Planilha1!$A$4:$C$258,3,0),VLOOKUP(B69,[2]Planilha1!$A$4:$C$258,3,0)),0) -> 648.60247 | G69: =IFERROR(IFERROR(VLOOKUP(A69,[1]Planilha1!$A$4:$D$277,4,0),VLOOKUP(B69,[1]Planilha1!$A$4:$D$277,4,0)),0) -> 648.60247 | H69: =D69+E69-G69 -> 3789.0045 | I69: CONSERVANTE | J69: 1 | K69: =VLOOKUP(A69,CONT_ANTE!A:D,4,0) -> 1436.5 | L69: =IF(AND(F69=0,K69<>M69),"!@##@!","ok") -> ok | M69: =IFERROR(VLOOKUP(A69,CONTAGEM!B:G,6,0),VLOOKUP(B69,CONTAGEM!B:G,6,0)) -> 2324 | N69: =IFERROR(SUM(M69*V69),0) -> 27581.697 | O69: =SUMIF(SISTEMA!B:B,A69,SISTEMA!I:I)/J69 -> 3826.56 | P69: =SUMIF(SISTEMA!B:B,B69,SISTEMA!I:I) -> 0 | Q69: =O69+P69 -> 3826.56 | R69: =IFERROR(SUM(Q69*V69),0) -> 45414.379 | S69: =IFERROR(VLOOKUP(A69,DIF_ANTE!A:D,4,0),"0")/J69 -> -1501.107 | T69: =M69-Q69 -> -1502.56 | U69: =T69-S69 -> -1.453 | V69: =IFERROR(VLOOKUP(A69,CUSTO!A:C,3,0),VLOOKUP(B69,CUSTO!A:C,3,0)) -> 11.8682 | W69: =IFERROR(SUM(T69*V69),0) -> -17832.683 | X69: =IFERROR(T69/Q69,"") -> -0.392666 | Y69: =IFERROR(U69*V69,"-") -> -17.244495 | Z69: APONTAR CONSUMO
A70: 2701090006 | B70: - | C70: CITRATO SODIO | D70: 855.0048 | E70: =IFERROR(IFERROR(VLOOKUP(B70,[1]Planilha1!$A$4:$C$277,3,0),VLOOKUP(A70,[1]Planilha1!$A$4:$C$277,3,0)),0) -> 1375 | F70: =IFERROR(IFERROR(VLOOKUP(A70,[2]Planilha1!$A$4:$C$258,3,0),VLOOKUP(B70,[2]Planilha1!$A$4:$C$258,3,0)),0) -> 605.0048 | G70: =IFERROR(IFERROR(VLOOKUP(A70,[1]Planilha1!$A$4:$D$277,4,0),VLOOKUP(B70,[1]Planilha1!$A$4:$D$277,4,0)),0) -> 2105.0048 | H70: =D70+E70-G70 -> 125 | I70: CONSERVANTE | J70: 1 | K70: =VLOOKUP(A70,CONT_ANTE!A:D,4,0) -> 901.5 | L70: =IF(AND(F70=0,K70<>M70),"!@##@!","ok") -> ok | M70: =IFERROR(VLOOKUP(A70,CONTAGEM!B:G,6,0),VLOOKUP(B70,CONTAGEM!B:G,6,0)) -> 0 | N70: =IFERROR(SUM(M70*V70),0) -> 0 | O70: =SUMIF(SISTEMA!B:B,A70,SISTEMA!I:I)/J70 -> 0 | P70: =SUMIF(SISTEMA!B:B,B70,SISTEMA!I:I) -> 0 | Q70: =O70+P70 -> 0 | R70: =IFERROR(SUM(Q70*V70),0) -> 0 | S70: =IFERROR(VLOOKUP(A70,DIF_ANTE!A:D,4,0),"0")/J70 -> 46.4952 | T70: =M70-Q70 -> 0 | U70: =T70-S70 -> -46.4952 | V70: =IFERROR(VLOOKUP(A70,CUSTO!A:C,3,0),VLOOKUP(B70,CUSTO!A:C,3,0)) -> 7.05738 | W70: =IFERROR(SUM(T70*V70),0) -> 0 | X70: =IFERROR(T70/Q70,"") | Y70: =IFERROR(U70*V70,"-") -> -328.13429 | Z70: OK
A71: 2701120001 | B71: - | C71: PREMIX CAFEINA/ TAURINA/ VITAMINAS ENERGETICO | D71: 2036.1 | E71: =IFERROR(IFERROR(VLOOKUP(B71,[1]Planilha1!$A$4:$C$277,3,0),VLOOKUP(A71,[1]Planilha1!$A$4:$C$277,3,0)),0) -> 4660 | F71: =IFERROR(IFERROR(VLOOKUP(A71,[2]Planilha1!$A$4:$C$258,3,0),VLOOKUP(B71,[2]Planilha1!$A$4:$C$258,3,0)),0) -> 2081.95 | G71: =IFERROR(IFERROR(VLOOKUP(A71,[1]Planilha1!$A$4:$D$277,4,0),VLOOKUP(B71,[1]Planilha1!$A$4:$D$277,4,0)),0) -> 5581.95 | H71: =D71+E71-G71 -> 1114.15 | I71: CONSERVANTE | J71: 1 | K71: =VLOOKUP(A71,CONT_ANTE!A:D,4,0) -> 3705 | L71: =IF(AND(F71=0,K71<>M71),"!@##@!","ok") -> ok | M71: =IFERROR(VLOOKUP(A71,CONTAGEM!B:G,6,0),VLOOKUP(B71,CONTAGEM!B:G,6,0)) -> 2660 | N71: =IFERROR(SUM(M71*V71),0) -> 40521.775 | O71: =SUMIF(SISTEMA!B:B,A71,SISTEMA!I:I)/J71 -> 1114.15 | P71: =SUMIF(SISTEMA!B:B,B71,SISTEMA!I:I) -> 0 | Q71: =O71+P71 -> 1114.15 | R71: =IFERROR(SUM(Q71*V71),0) -> 16972.683 | S71: =IFERROR(VLOOKUP(A71,DIF_ANTE!A:D,4,0),"0")/J71 -> 1668.9 | T71: =M71-Q71 -> 1545.85 | U71: =T71-S71 -> -123.05 | V71: =IFERROR(VLOOKUP(A71,CUSTO!A:C,3,0),VLOOKUP(B71,CUSTO!A:C,3,0)) -> 15.23375 | W71: =IFERROR(SUM(T71*V71),0) -> 23549.092 | X71: =IFERROR(T71/Q71,"") -> 1.3874703 | Y71: =IFERROR(U71*V71,"-") -> -1874.5129 | Z71: OK
A72: 2701100001 | B72: - | C72: SORBATO POTASSIO | D72: 401.06889 | E72: =IFERROR(IFERROR(VLOOKUP(B72,[1]Planilha1!$A$4:$C$277,3,0),VLOOKUP(A72,[1]Planilha1!$A$4:$C$277,3,0)),0) -> 0 | F72: =IFERROR(IFERROR(VLOOKUP(A72,[2]Planilha1!$A$4:$C$258,3,0),VLOOKUP(B72,[2]Planilha1!$A$4:$C$258,3,0)),0) -> 73.13101 | G72: =IFERROR(IFERROR(VLOOKUP(A72,[1]Planilha1!$A$4:$D$277,4,0),VLOOKUP(B72,[1]Planilha1!$A$4:$D$277,4,0)),0) -> 73.13101 | H72: =D72+E72-G72 -> 327.93788 | I72: CONSERVANTE | J72: 1 | K72: =VLOOKUP(A72,CONT_ANTE!A:D,4,0) -> 367.5 | L72: =IF(AND(F72=0,K72<>M72),"!@##@!","ok") -> ok | M72: =IFERROR(VLOOKUP(A72,CONTAGEM!B:G,6,0),VLOOKUP(B72,CONTAGEM!B:G,6,0)) -> 332 | N72: =IFERROR(SUM(M72*V72),0) -> 4605.4265 | O72: =SUMIF(SISTEMA!B:B,A72,SISTEMA!I:I)/J72 -> 347.42889 | P72: =SUMIF(SISTEMA!B:B,B72,SISTEMA!I:I) -> 0 | Q72: =O72+P72 -> 347.42889 | R72: =IFERROR(SUM(Q72*V72),0) -> 4819.4525 | S72: =IFERROR(VLOOKUP(A72,DIF_ANTE!A:D,4,0),"0")/J72 -> -33.56889 | T72: =M72-Q72 -> -15.42889 | U72: =T72-S72 -> 18.14 | V72: =IFERROR(VLOOKUP(A72,CUSTO!A:C,3,0),VLOOKUP(B72,CUSTO!A:C,3,0)) -> 13.871767 | W72: =IFERROR(SUM(T72*V72),0) -> -214.02596 | X72: =IFERROR(T72/Q72,"") -> -0.044408771 | Y72: =IFERROR(U72*V72,"-") -> 251.63385 | Z72: OK
A73: 2701060009 | B73: - | C73: CORANTE AMARELO SUNSET | D73: 17.6931 | E73: =IFERROR(IFERROR(VLOOKUP(B73,[1]Planilha1!$A$4:$C$277,3,0),VLOOKUP(A73,[1]Planilha1!$A$4:$C$277,3,0)),0) -> 0 | F73: =IFERROR(IFERROR(VLOOKUP(A73,[2]Planilha1!$A$4:$C$258,3,0),VLOOKUP(B73,[2]Planilha1!$A$4:$C$258,3,0)),0) -> 2.10557 | G73: =IFERROR(IFERROR(VLOOKUP(A73,[1]Planilha1!$A$4:$D$277,4,0),VLOOKUP(B73,[1]Planilha1!$A$4:$D$277,4,0)),0) -> 4.79867 | H73: =D73+E73-G73 -> 12.89443 | I73: CORANTE | J73: 1 | K73: =VLOOKUP(A73,CONT_ANTE!A:D,4,0) -> 15 | L73: =IF(AND(F73=0,K73<>M73),"!@##@!","ok") -> ok | M73: =IFERROR(VLOOKUP(A73,CONTAGEM!B:G,6,0),VLOOKUP(B73,CONTAGEM!B:G,6,0)) -> 15 | N73: =IFERROR(SUM(M73*V73),0) -> 621.78 | O73: =SUMIF(SISTEMA!B:B,A73,SISTEMA!I:I)/J73 -> 13.53684 | P73: =SUMIF(SISTEMA!B:B,B73,SISTEMA!I:I) -> 0 | Q73: =O73+P73 -> 13.53684 | R73: =IFERROR(SUM(Q73*V73),0) -> 561.12909 | S73: =IFERROR(VLOOKUP(A73,DIF_ANTE!A:D,4,0),"0")/J73 -> -2.6931 | T73: =M73-Q73 -> 1.46316 | U73: =T73-S73 -> 4.15626 | V73: =IFERROR(VLOOKUP(A73,CUSTO!A:C,3,0),VLOOKUP(B73,CUSTO!A:C,3,0)) -> 41.452 | W73: =IFERROR(SUM(T73*V73),0) -> 60.650908 | X73: =IFERROR(T73/Q73,"") -> 0.10808726 | Y73: =IFERROR(U73*V73,"-") -> 172.28529 | Z73: OK, PERDA
A74: 2701060003 | B74: - | C74: CORANTE AMARELO TARTRAZINA | D74: 4.74757 | E74: =IFERROR(IFERROR(VLOOKUP(B74,[1]Planilha1!$A$4:$C$277,3,0),VLOOKUP(A74,[1]Planilha1!$A$4:$C$277,3,0)),0) -> 0 | F74: =IFERROR(IFERROR(VLOOKUP(A74,[2]Planilha1!$A$4:$C$258,3,0),VLOOKUP(B74,[2]Planilha1!$A$4:$C$258,3,0)),0) -> 0.83679 | G74: =IFERROR(IFERROR(VLOOKUP(A74,[1]Planilha1!$A$4:$D$277,4,0),VLOOKUP(B74,[1]Planilha1!$A$4:$D$277,4,0)),0) -> 0.83679 | H74: =D74+E74-G74 -> 3.91078 | I74: CORANTE | J74: 1 | K74: =VLOOKUP(A74,CONT_ANTE!A:D,4,0) -> 5 | L74: =IF(AND(F74=0,K74<>M74),"!@##@!","ok") -> ok | M74: =IFERROR(VLOOKUP(A74,CONTAGEM!B:G,6,0),VLOOKUP(B74,CONTAGEM!B:G,6,0)) -> 5 | N74: =IFERROR(SUM(M74*V74),0) -> 222.61 | O74: =SUMIF(SISTEMA!B:B,A74,SISTEMA!I:I)/J74 -> 3.91078 | P74: =SUMIF(SISTEMA!B:B,B74,SISTEMA!I:I) -> 0 | Q74: =O74+P74 -> 3.91078 | R74: =IFERROR(SUM(Q74*V74),0) -> 174.11575 | S74: =IFERROR(VLOOKUP(A74,DIF_ANTE!A:D,4,0),"0")/J74 -> 0.25243 | T74: =M74-Q74 -> 1.08922 | U74: =T74-S74 -> 0.83679 | V74: =IFERROR(VLOOKUP(A74,CUSTO!A:C,3,0),VLOOKUP(B74,CUSTO!A:C,3,0)) -> 44.522 | W74: =IFERROR(SUM(T74*V74),0) -> 48.494253 | X74: =IFERROR(T74/Q74,"") -> 0.27851733 | Y74: =IFERROR(U74*V74,"-") -> 37.255564 | Z74: OK, PERDA
A75: 2701060008 | B75: - | C75: CORANTE AZUL BRILHANTE | D75: 1.85788 | E75: =IFERROR(IFERROR(VLOOKUP(B75,[1]Planilha1!$A$4:$C$277,3,0),VLOOKUP(A75,[1]Planilha1!$A$4:$C$277,3,0)),0) -> 0 | F75: =IFERROR(IFERROR(VLOOKUP(A75,[2]Planilha1!$A$4:$C$258,3,0),VLOOKUP(B75,[2]Planilha1!$A$4:$C$258,3,0)),0) -> 0.3075 | G75: =IFERROR(IFERROR(VLOOKUP(A75,[1]Planilha1!$A$4:$D$277,4,0),VLOOKUP(B75,[1]Planilha1!$A$4:$D$277,4,0)),0) -> 0.3075 | H75: =D75+E75-G75 -> 1.55038 | I75: CORANTE | J75: 1 | K75: =VLOOKUP(A75,CONT_ANTE!A:D,4,0) -> 5 | L75: =IF(AND(F75=0,K75<>M75),"!@##@!","ok") -> ok | M75: =IFERROR(VLOOKUP(A75,CONTAGEM!B:G,6,0),VLOOKUP(B75,CONTAGEM!B:G,6,0)) -> 5 | N75: =IFERROR(SUM(M75*V75),0) -> 512.24 | O75: =SUMIF(SISTEMA!B:B,A75,SISTEMA!I:I)/J75 -> 1.704 | P75: =SUMIF(SISTEMA!B:B,B75,SISTEMA!I:I) -> 0 | Q75: =O75+P75 -> 1.704 | R75: =IFERROR(SUM(Q75*V75),0) -> 174.57139 | S75: =IFERROR(VLOOKUP(A75,DIF_ANTE!A:D,4,0),"0")/J75 -> 3.14212 | T75: =M75-Q75 -> 3.296 | U75: =T75-S75 -> 0.15388 | V75: =IFERROR(VLOOKUP(A75,CUSTO!A:C,3,0),VLOOKUP(B75,CUSTO!A:C,3,0)) -> 102.448 | W75: =IFERROR(SUM(T75*V75),0) -> 337.66861 | X75: =IFERROR(T75/Q75,"") -> 1.9342723 | Y75: =IFERROR(U75*V75,"-") -> 15.764698 | Z75: OK, PERDA
A76: 2701060007 | B76: - | C76: CORANTE CARAMELO CLASSE IV DPC | D76: 1291.99 | E76: =IFERROR(IFERROR(VLOOKUP(B76,[1]Planilha1!$A$4:$C$277,3,0),VLOOKUP(A76,[1]Planilha1!$A$4:$C$277,3,0)),0) -> 0 | F76: =IFERROR(IFERROR(VLOOKUP(A76,[2]Planilha1!$A$4:$C$258,3,0),VLOOKUP(B76,[2]Planilha1!$A$4:$C$258,3,0)),0) -> 262.66 | G76: =IFERROR(IFERROR(VLOOKUP(A76,[1]Planilha1!$A$4:$D$277,4,0),VLOOKUP(B76,[1]Planilha1!$A$4:$D$277,4,0)),0) -> 286.65 | H76: =D76+E76-G76 -> 1005.34 | I76: CORANTE | J76: 1 | K76: =VLOOKUP(A76,CONT_ANTE!A:D,4,0) -> 1268 | L76: =IF(AND(F76=0,K76<>M76),"!@##@!","ok") -> ok | M76: =IFERROR(VLOOKUP(A76,CONTAGEM!B:G,6,0),VLOOKUP(B76,CONTAGEM!B:G,6,0)) -> 1049 | N76: =IFERROR(SUM(M76*V76),0) -> 6639.9707 | O76: =SUMIF(SISTEMA!B:B,A76,SISTEMA!I:I)/J76 -> 1050.74 | P76: =SUMIF(SISTEMA!B:B,B76,SISTEMA!I:I) -> 0 | Q76: =O76+P76 -> 1050.74 | R76: =IFERROR(SUM(Q76*V76),0) -> 6650.9846 | S76: =IFERROR(VLOOKUP(A76,DIF_ANTE!A:D,4,0),"0")/J76 -> -23.99 | T76: =M76-Q76 -> -1.74 | U76: =T76-S76 -> 22.25 | V76: =IFERROR(VLOOKUP(A76,CUSTO!A:C,3,0),VLOOKUP(B76,CUSTO!A:C,3,0)) -> 6.32981 | W76: =IFERROR(SUM(T76*V76),0) -> -11.013869 | X76: =IFERROR(T76/Q76,"") -> -0.0016559758 | Y76: =IFERROR(U76*V76,"-") -> 140.83827 | Z76: OK, PERDA
A77: 2701060004 | B77: - | C77: CORANTE MARACUJA 6035 SAPORITI | D77: 0 | E77: =IFERROR(IFERROR(VLOOKUP(B77,[1]Planilha1!$A$4:$C$277,3,0),VLOOKUP(A77,[1]Planilha1!$A$4:$C$277,3,0)),0) -> 0 | F77: =IFERROR(IFERROR(VLOOKUP(A77,[2]Planilha1!$A$4:$C$258,3,0),VLOOKUP(B77,[2]Planilha1!$A$4:$C$258,3,0)),0) -> 0 | G77: =IFERROR(IFERROR(VLOOKUP(A77,[1]Planilha1!$A$4:$D$277,4,0),VLOOKUP(B77,[1]Planilha1!$A$4:$D$277,4,0)),0) -> 0 | H77: =D77+E77-G77 -> 0 | I77: CORANTE | J77: 1 | K77: =VLOOKUP(A77,CONT_ANTE!A:D,4,0) -> 0 | L77: =IF(AND(F77=0,K77<>M77),"!@##@!","ok") -> ok | M77: =IFERROR(VLOOKUP(A77,CONTAGEM!B:G,6,0),VLOOKUP(B77,CONTAGEM!B:G,6,0)) -> 0 | N77: =IFERROR(SUM(M77*V77),0) -> 0 | O77: =SUMIF(SISTEMA!B:B,A77,SISTEMA!I:I)/J77 -> 0 | P77: =SUMIF(SISTEMA!B:B,B77,SISTEMA!I:I) -> 0 | Q77: =O77+P77 -> 0 | R77: =IFERROR(SUM(Q77*V77),0) -> 0 | S77: =IFERROR(VLOOKUP(A77,DIF_ANTE!A:D,4,0),"0")/J77 -> 0 | T77: =M77-Q77 -> 0 | U77: =T77-S77 -> 0 | V77: =IFERROR(VLOOKUP(A77,CUSTO!A:C,3,0),VLOOKUP(B77,CUSTO!A:C,3,0)) -> 3.726875 | W77: =IFERROR(SUM(T77*V77),0) -> 0 | X77: =IFERROR(T77/Q77,"") | Y77: =IFERROR(U77*V77,"-") -> 0 | Z77: OK
A78: 2701060002 | B78: - | C78: CORANTE VERMELHO 3167 SAPORITI | D78: 4 | E78: =IFERROR(IFERROR(VLOOKUP(B78,[1]Planilha1!$A$4:$C$277,3,0),VLOOKUP(A78,[1]Planilha1!$A$4:$C$277,3,0)),0) -> 0 | F78: =IFERROR(IFERROR(VLOOKUP(A78,[2]Planilha1!$A$4:$C$258,3,0),VLOOKUP(B78,[2]Planilha1!$A$4:$C$258,3,0)),0) -> 0 | G78: =IFERROR(IFERROR(VLOOKUP(A78,[1]Planilha1!$A$4:$D$277,4,0),VLOOKUP(B78,[1]Planilha1!$A$4:$D$277,4,0)),0) -> 0 | H78: =D78+E78-G78 -> 4 | I78: CORANTE | J78: 1 | K78: =VLOOKUP(A78,CONT_ANTE!A:D,4,0) -> 0 | L78: =IF(AND(F78=0,K78<>M78),"!@##@!","ok") -> ok | M78: =IFERROR(VLOOKUP(A78,CONTAGEM!B:G,6,0),VLOOKUP(B78,CONTAGEM!B:G,6,0)) -> 0 | N78: =IFERROR(SUM(M78*V78),0) -> 0 | O78: =SUMIF(SISTEMA!B:B,A78,SISTEMA!I:I)/J78 -> 4 | P78: =SUMIF(SISTEMA!B:B,B78,SISTEMA!I:I) -> 0 | Q78: =O78+P78 -> 4 | R78: =IFERROR(SUM(Q78*V78),0) -> 67.745 | S78: =IFERROR(VLOOKUP(A78,DIF_ANTE!A:D,4,0),"0")/J78 -> -4 | T78: =M78-Q78 -> -4 | U78: =T78-S78 -> 0 | V78: =IFERROR(VLOOKUP(A78,CUSTO!A:C,3,0),VLOOKUP(B78,CUSTO!A:C,3,0)) -> 16.93625 | W78: =IFERROR(SUM(T78*V78),0) -> -67.745 | X78: =IFERROR(T78/Q78,"") -> -1 | Y78: =IFERROR(U78*V78,"-") -> 0 | Z78: OK
A79: 2701060010 | B79: - | C79: CORANTE VERMELHO AMARANTO | D79: 28.40159 | E79: =IFERROR(IFERROR(VLOOKUP(B79,[1]Planilha1!$A$4:$C$277,3,0),VLOOKUP(A79,[1]Planilha1!$A$4:$C$277,3,0)),0) -> 0 | F79: =IFERROR(IFERROR(VLOOKUP(A79,[2]Planilha1!$A$4:$C$258,3,0),VLOOKUP(B79,[2]Planilha1!$A$4:$C$258,3,0)),0) -> 3.44523 | G79: =IFERROR(IFERROR(VLOOKUP(A79,[1]Planilha1!$A$4:$D$277,4,0),VLOOKUP(B79,[1]Planilha1!$A$4:$D$277,4,0)),0) -> 21.84682 | H79: =D79+E79-G79 -> 6.55477 | I79: CORANTE | J79: 1 | K79: =VLOOKUP(A79,CONT_ANTE!A:D,4,0) -> 25 | L79: =IF(AND(F79=0,K79<>M79),"!@##@!","ok") -> ok | M79: =IFERROR(VLOOKUP(A79,CONTAGEM!B:G,6,0),VLOOKUP(B79,CONTAGEM!B:G,6,0)) -> 5 | N79: =IFERROR(SUM(M79*V79),0) -> 385.4225 | O79: =SUMIF(SISTEMA!B:B,A79,SISTEMA!I:I)/J79 -> 8.46804 | P79: =SUMIF(SISTEMA!B:B,B79,SISTEMA!I:I) -> 0 | Q79: =O79+P79 -> 8.46804 | R79: =IFERROR(SUM(Q79*V79),0) -> 652.75463 | S79: =IFERROR(VLOOKUP(A79,DIF_ANTE!A:D,4,0),"0")/J79 -> -3.40159 | T79: =M79-Q79 -> -3.46804 | U79: =T79-S79 -> -0.06645 | V79: =IFERROR(VLOOKUP(A79,CUSTO!A:C,3,0),VLOOKUP(B79,CUSTO!A:C,3,0)) -> 77.0845 | W79: =IFERROR(SUM(T79*V79),0) -> -267.33213 | X79: =IFERROR(T79/Q79,"") -> -0.40954459 | Y79: =IFERROR(U79*V79,"-") -> -5.122265 | Z79: OK, PERDA
... A126: 2701040020 | B126: - | C126: FILME TERMOENCOLHIVEL CER BAMBOA 269ML 350X0,06MM | D126: 556.1392 | E126: =IFERROR(IFERROR(VLOOKUP(B126,[1]Planilha1!$A$4:$C$277,3,0),VLOOKUP(A126,[1]Planilha1!$A$4:$C$277,3,0)),0) -> 0 | F126: =IFERROR(IFERROR(VLOOKUP(A126,[2]Planilha1!$A$4:$C$258,3,0),VLOOKUP(B126,[2]Planilha1!$A$4:$C$258,3,0)),0) -> 0 | G126: =IFERROR(IFERROR(VLOOKUP(A126,[1]Planilha1!$A$4:$D$277,4,0),VLOOKUP(B126,[1]Planilha1!$A$4:$D$277,4,0)),0) -> 0 | H126: =D126+E126-G126 -> 556.1392 | I126: FILME | J126: 1 | K126: =VLOOKUP(A126,CONT_ANTE!A:D,4,0) -> 493.4 | L126: =IF(AND(F126=0,K126<>M126),"!@##@!","ok") -> ok | M126: =IFERROR(VLOOKUP(A126,CONTAGEM!B:G,6,0),VLOOKUP(B126,CONTAGEM!B:G,6,0)) -> 493.4 | N126: =IFERROR(SUM(M126*V126),0) -> 6038.0531 | O126: =SUMIF(SISTEMA!B:B,A126,SISTEMA!I:I)/J126 -> 556.1392 | P126: =SUMIF(SISTEMA!B:B,B126,SISTEMA!I:I) -> 0 | Q126: =O126+P126 -> 556.1392 | R126: =IFERROR(SUM(Q126*V126),0) -> 6805.833 | S126: =IFERROR(VLOOKUP(A126,DIF_ANTE!A:D,4,0),"0")/J126 -> -62.7392 | T126: =M126-Q126 -> -62.7392 | U126: =T126-S126 -> 0 | V126: =IFERROR(VLOOKUP(A126,CUSTO!A:C,3,0),VLOOKUP(B126,CUSTO!A:C,3,0)) -> 12.237643 | W126: =IFERROR(SUM(T126*V126),0) -> -767.77993 | X126: =IFERROR(T126/Q126,"") -> -0.11281204 | Y126: =IFERROR(U126*V126,"-") -> 0 | Z126: OK, PERDA
A127: 2701040018 | B127: - | C127: FILME TERMOENCOLHIVEL CER BAMBOA 350ML 380X0,06MM | D127: 0 | E127: =IFERROR(IFERROR(VLOOKUP(B127,[1]Planilha1!$A$4:$C$277,3,0),VLOOKUP(A127,[1]Planilha1!$A$4:$C$277,3,0)),0) -> 0 | F127: =IFERROR(IFERROR(VLOOKUP(A127,[2]Planilha1!$A$4:$C$258,3,0),VLOOKUP(B127,[2]Planilha1!$A$4:$C$258,3,0)),0) -> 0 | G127: =IFERROR(IFERROR(VLOOKUP(A127,[1]Planilha1!$A$4:$D$277,4,0),VLOOKUP(B127,[1]Planilha1!$A$4:$D$277,4,0)),0) -> 0 | H127: =D127+E127-G127 -> 0 | I127: FILME | J127: 1 | K127: =VLOOKUP(A127,CONT_ANTE!A:D,4,0) -> 0 | L127: =IF(AND(F127=0,K127<>M127),"!@##@!","ok") -> ok | M127: 0 | N127: =IFERROR(SUM(M127*V127),0) -> 0 | O127: =SUMIF(SISTEMA!B:B,A127,SISTEMA!I:I)/J127 -> 0 | P127: =SUMIF(SISTEMA!B:B,B127,SISTEMA!I:I) -> 0 | Q127: =O127+P127 -> 0 | R127: =IFERROR(SUM(Q127*V127),0) -> 0 | S127: =IFERROR(VLOOKUP(A127,DIF_ANTE!A:D,4,0),"0")/J127 -> 0 | T127: =M127-Q127 -> 0 | U127: =T127-S127 -> 0 | V127: =IFERROR(VLOOKUP(A127,CUSTO!A:C,3,0),VLOOKUP(B127,CUSTO!A:C,3,0)) -> 13.056287 | W127: =IFERROR(SUM(T127*V127),0) -> 0 | X127: =IFERROR(T127/Q127,"") | Y127: =IFERROR(U127*V127,"-") -> 0 | Z127: OK
A128: 2701040017 | B128: - | C128: FILME TERMOENCOLHIVEL CER BAMBOA 473ML 400X0,06MM | D128: 536.72422 | E128: =IFERROR(IFERROR(VLOOKUP(B128,[1]Planilha1!$A$4:$C$277,3,0),VLOOKUP(A128,[1]Planilha1!$A$4:$C$277,3,0)),0) -> 0 | F128: =IFERROR(IFERROR(VLOOKUP(A128,[2]Planilha1!$A$4:$C$258,3,0),VLOOKUP(B128,[2]Planilha1!$A$4:$C$258,3,0)),0) -> 0 | G128: =IFERROR(IFERROR(VLOOKUP(A128,[1]Planilha1!$A$4:$D$277,4,0),VLOOKUP(B128,[1]Planilha1!$A$4:$D$277,4,0)),0) -> 0 | H128: =D128+E128-G128 -> 536.72422 | I128: FILME | J128: 1 | K128: =VLOOKUP(A128,CONT_ANTE!A:D,4,0) -> 545.85 | L128: =IF(AND(F128=0,K128<>M128),"!@##@!","ok") -> !@##@! | M128: =IFERROR(VLOOKUP(A128,CONTAGEM!B:G,6,0),VLOOKUP(B128,CONTAGEM!B:G,6,0)) -> 536.72 | N128: =IFERROR(SUM(M128*V128),0) -> 6296.4017 | O128: =SUMIF(SISTEMA!B:B,A128,SISTEMA!I:I)/J128 -> 536.72422 | P128: =SUMIF(SISTEMA!B:B,B128,SISTEMA!I:I) -> 0 | Q128: =O128+P128 -> 536.72422 | R128: =IFERROR(SUM(Q128*V128),0) -> 6296.4513 | S128: =IFERROR(VLOOKUP(A128,DIF_ANTE!A:D,4,0),"0")/J128 -> 9.12578 | T128: =M128-Q128 -> -0.00422 | U128: =T128-S128 -> -9.13 | V128: =IFERROR(VLOOKUP(A128,CUSTO!A:C,3,0),VLOOKUP(B128,CUSTO!A:C,3,0)) -> 11.73126 | W128: =IFERROR(SUM(T128*V128),0) -> -0.049505916 | X128: =IFERROR(T128/Q128,"") -> -7.8625108e-06 | Y128: =IFERROR(U128*V128,"-") -> -107.1064 | Z128: OK
A129: 2701040019 | B129: - | C129: FILME TERMOENCOLHIVEL CER BAMBOA SLIM 350ML 360X0,06MM | D129: 119.69 | E129: =IFERROR(IFERROR(VLOOKUP(B129,[1]Planilha1!$A$4:$C$277,3,0),VLOOKUP(A129,[1]Planilha1!$A$4:$C$277,3,0)),0) -> 119.69 | F129: =IFERROR(IFERROR(VLOOKUP(A129,[2]Planilha1!$A$4:$C$258,3,0),VLOOKUP(B129,[2]Planilha1!$A$4:$C$258,3,0)),0) -> 0 | G129: =IFERROR(IFERROR(VLOOKUP(A129,[1]Planilha1!$A$4:$D$277,4,0),VLOOKUP(B129,[1]Planilha1!$A$4:$D$277,4,0)),0) -> 119.69 | H129: =D129+E129-G129 -> 119.69 | I129: FILME | J129: 1 | K129: =VLOOKUP(A129,CONT_ANTE!A:D,4,0) -> 200.7 | L129: =IF(AND(F129=0,K129<>M129),"!@##@!","ok") -> !@##@! | M129: =IFERROR(VLOOKUP(A129,CONTAGEM!B:G,6,0),VLOOKUP(B129,CONTAGEM!B:G,6,0)) -> 234.05 | N129: =IFERROR(SUM(M129*V129),0) -> 2745.6996 | O129: =SUMIF(SISTEMA!B:B,A129,SISTEMA!I:I)/J129 -> 119.69 | P129: =SUMIF(SISTEMA!B:B,B129,SISTEMA!I:I) -> 0 | Q129: =O129+P129 -> 119.69 | R129: =IFERROR(SUM(Q129*V129),0) -> 1404.1136 | S129: =IFERROR(VLOOKUP(A129,DIF_ANTE!A:D,4,0),"0")/J129 -> 81.01 | T129: =M129-Q129 -> 114.36 | U129: =T129-S129 -> 33.35 | V129: =IFERROR(VLOOKUP(A129,CUSTO!A:C,3,0),VLOOKUP(B129,CUSTO!A:C,3,0)) -> 11.731252 | W129: =IFERROR(SUM(T129*V129),0) -> 1341.586 | X129: =IFERROR(T129/Q129,"") -> 0.95546829 | Y129: =IFERROR(U129*V129,"-") -> 391.23726 | Z129: VALIDAR CONSUMOS
A130: 2701040008 | B130: - | C130: FILME TERMOENCOLHIVEL CER DEL PUERTO 269ML | D130: 594.6616 | E130: =IFERROR(IFERROR(VLOOKUP(B130,[1]Planilha1!$A$4:$C$277,3,0),VLOOKUP(A130,[1]Planilha1!$A$4:$C$277,3,0)),0) -> 1917.44 | F130: =IFERROR(IFERROR(VLOOKUP(A130,[2]Planilha1!$A$4:$C$258,3,0),VLOOKUP(B130,[2]Planilha1!$A$4:$C$258,3,0)),0) -> 0 | G130: =IFERROR(IFERROR(VLOOKUP(A130,[1]Planilha1!$A$4:$D$277,4,0),VLOOKUP(B130,[1]Planilha1!$A$4:$D$277,4,0)),0) -> 0 | H130: =D130+E130-G130 -> 2512.1016 | I130: FILME | J130: 1 | K130: =VLOOKUP(A130,CONT_ANTE!A:D,4,0) -> 2533.34 | L130: =IF(AND(F130=0,K130<>M130),"!@##@!","ok") -> !@##@! | M130: =IFERROR(VLOOKUP(A130,CONTAGEM!B:G,6,0),VLOOKUP(B130,CONTAGEM!B:G,6,0)) -> 2512.1 | N130: =IFERROR(SUM(M130*V130),0) -> 33239.161 | O130: =SUMIF(SISTEMA!B:B,A130,SISTEMA!I:I)/J130 -> 2512.1016 | P130: =SUMIF(SISTEMA!B:B,B130,SISTEMA!I:I) -> 0 | Q130: =O130+P130 -> 2512.1016 | R130: =IFERROR(SUM(Q130*V130),0) -> 33239.182 | S130: =IFERROR(VLOOKUP(A130,DIF_ANTE!A:D,4,0),"0")/J130 -> 1938.6784 | T130: =M130-Q130 -> -0.0016 | U130: =T130-S130 -> -1938.68 | V130: =IFERROR(VLOOKUP(A130,CUSTO!A:C,3,0),VLOOKUP(B130,CUSTO!A:C,3,0)) -> 13.231623 | W130: =IFERROR(SUM(T130*V130),0) -> -0.021170598 | X130: =IFERROR(T130/Q130,"") -> -6.3691691e-07 | Y130: =IFERROR(U130*V130,"-") -> -25651.884 | Z130: OK
A131: 2701040013 | B131: - | C131: FILME TERMOENCOLHIVEL CER DEL PUERTO 350ML | D131: 79.1 | E131: =IFERROR(IFERROR(VLOOKUP(B131,[1]Planilha1!$A$4:$C$277,3,0),VLOOKUP(A131,[1]Planilha1!$A$4:$C$277,3,0)),0) -> 0 | F131: =IFERROR(IFERROR(VLOOKUP(A131,[2]Planilha1!$A$4:$C$258,3,0),VLOOKUP(B131,[2]Planilha1!$A$4:$C$258,3,0)),0) -> 0 | G131: =IFERROR(IFERROR(VLOOKUP(A131,[1]Planilha1!$A$4:$D$277,4,0),VLOOKUP(B131,[1]Planilha1!$A$4:$D$277,4,0)),0) -> 0 | H131: =D131+E131-G131 -> 79.1 | I131: FILME | J131: 1 | K131: =VLOOKUP(A131,CONT_ANTE!A:D,4,0) -> 84.5 | L131: =IF(AND(F131=0,K131<>M131),"!@##@!","ok") -> !@##@! | M131: =IFERROR(VLOOKUP(A131,CONTAGEM!B:G,6,0),VLOOKUP(B131,CONTAGEM!B:G,6,0)) -> 79.1 | N131: =IFERROR(SUM(M131*V131),0) -> 1001.3777 | O131: =SUMIF(SISTEMA!B:B,A131,SISTEMA!I:I)/J131 -> 79.1 | P131: =SUMIF(SISTEMA!B:B,B131,SISTEMA!I:I) -> 0 | Q131: =O131+P131 -> 79.1 | R131: =IFERROR(SUM(Q131*V131),0) -> 1001.3777 | S131: =IFERROR(VLOOKUP(A131,DIF_ANTE!A:D,4,0),"0")/J131 -> 5.4 | T131: =M131-Q131 -> 0 | U131: =T131-S131 -> -5.4 | V131: =IFERROR(VLOOKUP(A131,CUSTO!A:C,3,0),VLOOKUP(B131,CUSTO!A:C,3,0)) -> 12.659643 | W131: =IFERROR(SUM(T131*V131),0) -> 0 | X131: =IFERROR(T131/Q131,"") -> 0 | Y131: =IFERROR(U131*V131,"-") -> -68.362071 | Z131: OK
A132: 2901040001 | B132: - | C132: FILME TERMOENCOLHIVEL CER MARQUES 473ML 400X0,06MM | D132: 0 | E132: =IFERROR(IFERROR(VLOOKUP(B132,[1]Planilha1!$A$4:$C$277,3,0),VLOOKUP(A132,[1]Planilha1!$A$4:$C$277,3,0)),0) -> 0 | F132: =IFERROR(IFERROR(VLOOKUP(A132,[2]Planilha1!$A$4:$C$258,3,0),VLOOKUP(B132,[2]Planilha1!$A$4:$C$258,3,0)),0) -> 0 | G132: =IFERROR(IFERROR(VLOOKUP(A132,[1]Planilha1!$A$4:$D$277,4,0),VLOOKUP(B132,[1]Planilha1!$A$4:$D$277,4,0)),0) -> 0 | H132: =D132+E132-G132 -> 0 | I132: FILME | J132: 1 | K132: =VLOOKUP(A132,CONT_ANTE!A:D,4,0) -> 0 | L132: =IF(AND(F132=0,K132<>M132),"!@##@!","ok") -> ok | M132: =IFERROR(VLOOKUP(A132,CONTAGEM!B:G,6,0),VLOOKUP(B132,CONTAGEM!B:G,6,0)) -> 0 | N132: =IFERROR(SUM(M132*V132),0) -> 0 | O132: =SUMIF(SISTEMA!B:B,A132,SISTEMA!I:I)/J132 -> 0 | P132: =SUMIF(SISTEMA!B:B,B132,SISTEMA!I:I) -> 0 | Q132: =O132+P132 -> 0 | R132: =IFERROR(SUM(Q132*V132),0) -> 0 | S132: =IFERROR(VLOOKUP(A132,DIF_ANTE!A:D,4,0),"0")/J132 -> 0 | T132: =M132-Q132 -> 0 | U132: =T132-S132 -> 0 | V132: =IFERROR(VLOOKUP(A132,CUSTO!A:C,3,0),VLOOKUP(B132,CUSTO!A:C,3,0)) -> 16.080004 | W132: =IFERROR(SUM(T132*V132),0) -> 0 | X132: =IFERROR(T132/Q132,"") | Y132: =IFERROR(U132*V132,"-") -> 0 | Z132: OK
A133: 2701040012 | B133: - | C133: FILME TERMOENCOLHIVEL CER MOEMA 269ML 350X0,06MM | D133: 1929.051 | E133: =IFERROR(IFERROR(VLOOKUP(B133,[1]Planilha1!$A$4:$C$277,3,0),VLOOKUP(A133,[1]Planilha1!$A$4:$C$277,3,0)),0) -> 0 | F133: =IFERROR(IFERROR(VLOOKUP(A133,[2]Planilha1!$A$4:$C$258,3,0),VLOOKUP(B133,[2]Planilha1!$A$4:$C$258,3,0)),0) -> 0 | G133: =IFERROR(IFERROR(VLOOKUP(A133,[1]Planilha1!$A$4:$D$277,4,0),VLOOKUP(B133,[1]Planilha1!$A$4:$D$277,4,0)),0) -> 0 | H133: =D133+E133-G133 -> 1929.051 | I133: FILME | J133: 1 | K133: =VLOOKUP(A133,CONT_ANTE!A:D,4,0) -> 1980.05 | L133: =IF(AND(F133=0,K133<>M133),"!@##@!","ok") -> ok | M133: =IFERROR(VLOOKUP(A133,CONTAGEM!B:G,6,0),VLOOKUP(B133,CONTAGEM!B:G,6,0)) -> 1980.05 | N133: =IFERROR(SUM(M133*V133),0) -> 24231.128 | O133: =SUMIF(SISTEMA!B:B,A133,SISTEMA!I:I)/J133 -> 1929.051 | P133: =SUMIF(SISTEMA!B:B,B133,SISTEMA!I:I) -> 0 | Q133: =O133+P133 -> 1929.051 | R133: =IFERROR(SUM(Q133*V133),0) -> 23607.021 | S133: =IFERROR(VLOOKUP(A133,DIF_ANTE!A:D,4,0),"0")/J133 -> 50.999 | T133: =M133-Q133 -> 50.999 | U133: =T133-S133 -> 0 | V133: =IFERROR(VLOOKUP(A133,CUSTO!A:C,3,0),VLOOKUP(B133,CUSTO!A:C,3,0)) -> 12.237634 | W133: =IFERROR(SUM(T133*V133),0) -> 624.10711 | X133: =IFERROR(T133/Q133,"") -> 0.026437352 | Y133: =IFERROR(U133*V133,"-") -> 0 | Z133: OK
A134: 2701040011 | B134: - | C134: FILME TERMOENCOLHIVEL CER MOEMA 350ML 380X0,06MM | D134: 7414.5628 | E134: =IFERROR(IFERROR(VLOOKUP(B134,[1]Planilha1!$A$4:$C$277,3,0),VLOOKUP(A134,[1]Planilha1!$A$4:$C$277,3,0)),0) -> 7923.5712 | F134: =IFERROR(IFERROR(VLOOKUP(A134,[2]Planilha1!$A$4:$C$258,3,0),VLOOKUP(B134,[2]Planilha1!$A$4:$C$258,3,0)),0) -> 702.9376 | G134: =IFERROR(IFERROR(VLOOKUP(A134,[1]Planilha1!$A$4:$D$277,4,0),VLOOKUP(B134,[1]Planilha1!$A$4:$D$277,4,0)),0) -> 3395.5888 | H134: =D134+E134-G134 -> 11942.545 | I134: FILME | J134: 1 | K134: =VLOOKUP(A134,CONT_ANTE!A:D,4,0) -> 7360.07 | L134: =IF(AND(F134=0,K134<>M134),"!@##@!","ok") -> ok | M134: 11634.91 | N134: =IFERROR(SUM(M134*V134),0) -> 273427.6 | O134: =SUMIF(SISTEMA!B:B,A134,SISTEMA!I:I)/J134 -> 11942.545 | P134: =SUMIF(SISTEMA!B:B,B134,SISTEMA!I:I) -> 0 | Q134: =O134+P134 -> 11942.545 | R134: =IFERROR(SUM(Q134*V134),0) -> 280657.22 | S134: =IFERROR(VLOOKUP(A134,DIF_ANTE!A:D,4,0),"0")/J134 -> -54.4928 | T134: =M134-Q134 -> -307.6352 | U134: =T134-S134 -> -253.1424 | V134: =IFERROR(VLOOKUP(A134,CUSTO!A:C,3,0),VLOOKUP(B134,CUSTO!A:C,3,0)) -> 23.50062 | W134: =IFERROR(SUM(T134*V134),0) -> -7229.6181 | X134: =IFERROR(T134/Q134,"") -> -0.025759601 | Y134: =IFERROR(U134*V134,"-") -> -5949.0035 | Z134: OK
A135: 2701040010 | B135: - | C135: FILME TERMOENCOLHIVEL CER MOEMA 473ML 400X0,06MM | D135: 1751.5629 | E135: =IFERROR(IFERROR(VLOOKUP(B135,[1]Planilha1!$A$4:$C$277,3,0),VLOOKUP(A135,[1]Planilha1!$A$4:$C$277,3,0)),0) -> 1333.2333 | F135: =IFERROR(IFERROR(VLOOKUP(A135,[2]Planilha1!$A$4:$C$258,3,0),VLOOKUP(B135,[2]Planilha1!$A$4:$C$258,3,0)),0) -> 538.88446 | G135: =IFERROR(IFERROR(VLOOKUP(A135,[1]Planilha1!$A$4:$D$277,4,0),VLOOKUP(B135,[1]Planilha1!$A$4:$D$277,4,0)),0) -> 1872.1178 | H135: =D135+E135-G135 -> 1212.6784 | I135: FILME | J135: 1 | K135: =VLOOKUP(A135,CONT_ANTE!A:D,4,0) -> 1511.06 | L135: =IF(AND(F135=0,K135<>M135),"!@##@!","ok") -> ok | M135: =IFERROR(VLOOKUP(A135,CONTAGEM!B:G,6,0),VLOOKUP(B135,CONTAGEM!B:G,6,0)) -> 1212.67 | N135: =IFERROR(SUM(M135*V135),0) -> 28498.5 | O135: =SUMIF(SISTEMA!B:B,A135,SISTEMA!I:I)/J135 -> 1212.6784 | P135: =SUMIF(SISTEMA!B:B,B135,SISTEMA!I:I) -> 0 | Q135: =O135+P135 -> 1212.6784 | R135: =IFERROR(SUM(Q135*V135),0) -> 28498.699 | S135: =IFERROR(VLOOKUP(A135,DIF_ANTE!A:D,4,0),"0")/J135 -> -240.5029 | T135: =M135-Q135 -> -0.00844 | U135: =T135-S135 -> 240.49446 | V135: =IFERROR(VLOOKUP(A135,CUSTO!A:C,3,0),VLOOKUP(B135,CUSTO!A:C,3,0)) -> 23.500623 | W135: =IFERROR(SUM(T135*V135),0) -> -0.19834526 | X135: =IFERROR(T135/Q135,"") -> -6.9598005e-06 | Y135: =IFERROR(U135*V135,"-") -> 5651.7696 | Z135: OK
A136: 2901040004 | B136: - | C136: FILME TERMOENCOLHIVEL CER SURVA 269ML 350X0,06MM | D136: 12.85 | E136: =IFERROR(IFERROR(VLOOKUP(B136,[1]Planilha1!$A$4:$C$277,3,0),VLOOKUP(A136,[1]Planilha1!$A$4:$C$277,3,0)),0) -> 0 | F136: =IFERROR(IFERROR(VLOOKUP(A136,[2]Planilha1!$A$4:$C$258,3,0),VLOOKUP(B136,[2]Planilha1!$A$4:$C$258,3,0)),0) -> 0 | G136: =IFERROR(IFERROR(VLOOKUP(A136,[1]Planilha1!$A$4:$D$277,4,0),VLOOKUP(B136,[1]Planilha1!$A$4:$D$277,4,0)),0) -> 0 | H136: =D136+E136-G136 -> 12.85 | I136: FILME | J136: 1 | K136: =VLOOKUP(A136,CONT_ANTE!A:D,4,0) -> 0 | L136: =IF(AND(F136=0,K136<>M136),"!@##@!","ok") -> ok | M136: =IFERROR(VLOOKUP(A136,CONTAGEM!B:G,6,0),VLOOKUP(B136,CONTAGEM!B:G,6,0)) -> 0 | N136: =IFERROR(SUM(M136*V136),0) -> 0 | O136: =SUMIF(SISTEMA!B:B,A136,SISTEMA!I:I)/J136 -> 12.85 | P136: =SUMIF(SISTEMA!B:B,B136,SISTEMA!I:I) -> 0 | Q136: =O136+P136 -> 12.85 | R136: =IFERROR(SUM(Q136*V136),0) -> 0 | S136: =IFERROR(VLOOKUP(A136,DIF_ANTE!A:D,4,0),"0")/J136 -> -12.85 | T136: =M136-Q136 -> -12.85 | U136: =T136-S136 -> 0 | V136: =IFERROR(VLOOKUP(A136,CUSTO!A:C,3,0),VLOOKUP(B136,CUSTO!A:C,3,0)) -> 0 | W136: =IFERROR(SUM(T136*V136),0) -> 0 | X136: =IFERROR(T136/Q136,"") -> -1 | Y136: =IFERROR(U136*V136,"-") -> 0 | Z136: OK
A137: 2701040027 | B137: - | C137: FILME TERMOENCOLHIVEL LISO 330X0,04MM | D137: 1749.4728 | E137: =IFERROR(IFERROR(VLOOKUP(B137,[1]Planilha1!$A$4:$C$277,3,0),VLOOKUP(A137,[1]Planilha1!$A$4:$C$277,3,0)),0) -> 0 | F137: =IFERROR(IFERROR(VLOOKUP(A137,[2]Planilha1!$A$4:$C$258,3,0),VLOOKUP(B137,[2]Planilha1!$A$4:$C$258,3,0)),0) -> 0 | G137: =IFERROR(IFERROR(VLOOKUP(A137,[1]Planilha1!$A$4:$D$277,4,0),VLOOKUP(B137,[1]Planilha1!$A$4:$D$277,4,0)),0) -> 0 | H137: =D137+E137-G137 -> 1749.4728 | I137: FILME | J137: 1 | K137: =VLOOKUP(A137,CONT_ANTE!A:D,4,0) -> 1749.55 | L137: =IF(AND(F137=0,K137<>M137),"!@##@!","ok") -> ok | M137: =IFERROR(VLOOKUP(A137,CONTAGEM!B:G,6,0),VLOOKUP(B137,CONTAGEM!B:G,6,0)) -> 1749.55 | N137: =IFERROR(SUM(M137*V137),0) -> 16759.128 | O137: =SUMIF(SISTEMA!B:B,A137,SISTEMA!I:I)/J137 -> 1749.4728 | P137: =SUMIF(SISTEMA!B:B,B137,SISTEMA!I:I) -> 0 | Q137: =O137+P137 -> 1749.4728 | R137: =IFERROR(SUM(Q137*V137),0) -> 16758.389 | S137: =IFERROR(VLOOKUP(A137,DIF_ANTE!A:D,4,0),"0")/J137 -> 0.07719 | T137: =M137-Q137 -> 0.07719 | U137: =T137-S137 -> 0 | V137: =IFERROR(VLOOKUP(A137,CUSTO!A:C,3,0),VLOOKUP(B137,CUSTO!A:C,3,0)) -> 9.579108 | W137: =IFERROR(SUM(T137*V137),0) -> 0.73941135 | X137: =IFERROR(T137/Q137,"") -> 4.4121863e-05 | Y137: =IFERROR(U137*V137,"-") -> 0 | Z137: OK
A138: 2701040016 | B138: - | C138: FILME TERMOENCOLHIVEL LISO 350X0,06MM | D138: 1196.007 | E138: =IFERROR(IFERROR(VLOOKUP(B138,[1]Planilha1!$A$4:$C$277,3,0),VLOOKUP(A138,[1]Planilha1!$A$4:$C$277,3,0)),0) -> 0 | F138: =IFERROR(IFERROR(VLOOKUP(A138,[2]Planilha1!$A$4:$C$258,3,0),VLOOKUP(B138,[2]Planilha1!$A$4:$C$258,3,0)),0) -> 0 | G138: =IFERROR(IFERROR(VLOOKUP(A138,[1]Planilha1!$A$4:$D$277,4,0),VLOOKUP(B138,[1]Planilha1!$A$4:$D$277,4,0)),0) -> 0 | H138: =D138+E138-G138 -> 1196.007 | I138: FILME | J138: 1 | K138: =VLOOKUP(A138,CONT_ANTE!A:D,4,0) -> 1092.5 | L138: =IF(AND(F138=0,K138<>M138),"!@##@!","ok") -> ok | M138: =IFERROR(VLOOKUP(A138,CONTAGEM!B:G,6,0),VLOOKUP(B138,CONTAGEM!B:G,6,0)) -> 1092.5 | N138: =IFERROR(SUM(M138*V138),0) -> 11709.987 | O138: =SUMIF(SISTEMA!B:B,A138,SISTEMA!I:I)/J138 -> 1196.007 | P138: =SUMIF(SISTEMA!B:B,B138,SISTEMA!I:I) -> 0 | Q138: =O138+P138 -> 1196.007 | R138: =IFERROR(SUM(Q138*V138),0) -> 12819.429 | S138: =IFERROR(VLOOKUP(A138,DIF_ANTE!A:D,4,0),"0")/J138 -> -103.507 | T138: =M138-Q138 -> -103.507 | U138: =T138-S138 -> 0 | V138: =IFERROR(VLOOKUP(A138,CUSTO!A:C,3,0),VLOOKUP(B138,CUSTO!A:C,3,0)) -> 10.718524 | W138: =IFERROR(SUM(T138*V138),0) -> -1109.4422 | X138: =IFERROR(T138/Q138,"") -> -0.086543808 | Y138: =IFERROR(U138*V138,"-") -> 0 | Z138: OK
A139: 2701040025 | B139: - | C139: FILME TERMOENCOLHIVEL LISO 380X0,05MM | D139: 0 | E139: =IFERROR(IFERROR(VLOOKUP(B139,[1]Planilha1!$A$4:$C$277,3,0),VLOOKUP(A139,[1]Planilha1!$A$4:$C$277,3,0)),0) -> 0 | F139: =IFERROR(IFERROR(VLOOKUP(A139,[2]Planilha1!$A$4:$C$258,3,0),VLOOKUP(B139,[2]Planilha1!$A$4:$C$258,3,0)),0) -> 0 | G139: =IFERROR(IFERROR(VLOOKUP(A139,[1]Planilha1!$A$4:$D$277,4,0),VLOOKUP(B139,[1]Planilha1!$A$4:$D$277,4,0)),0) -> 0 | H139: =D139+E139-G139 -> 0 | I139: FILME | J139: 1 | K139: =VLOOKUP(A139,CONT_ANTE!A:D,4,0) -> 0 | L139: =IF(AND(F139=0,K139<>M139),"!@##@!","ok") -> ok | M139: =IFERROR(VLOOKUP(A139,CONTAGEM!B:G,6,0),VLOOKUP(B139,CONTAGEM!B:G,6,0)) -> 0 | N139: =IFERROR(SUM(M139*V139),0) -> 0 | O139: =SUMIF(SISTEMA!B:B,A139,SISTEMA!I:I)/J139 -> 0 | P139: =SUMIF(SISTEMA!B:B,B139,SISTEMA!I:I) -> 0 | Q139: =O139+P139 -> 0 | R139: =IFERROR(SUM(Q139*V139),0) -> 0 | S139: =IFERROR(VLOOKUP(A139,DIF_ANTE!A:D,4,0),"0")/J139 -> 0 | T139: =M139-Q139 -> 0 | U139: =T139-S139 -> 0 | V139: =IFERROR(VLOOKUP(A139,CUSTO!A:C,3,0),VLOOKUP(B139,CUSTO!A:C,3,0)) -> 9.579125 | W139: =IFERROR(SUM(T139*V139),0) -> 0 | X139: =IFERROR(T139/Q139,"") | Y139: =IFERROR(U139*V139,"-") -> 0 | Z139: OK
A140: 2701040015 | B140: - | C140: FILME TERMOENCOLHIVEL LISO 380X0,06MM | D140: 868.0198 | E140: =IFERROR(IFERROR(VLOOKUP(B140,[1]Planilha1!$A$4:$C$277,3,0),VLOOKUP(A140,[1]Planilha1!$A$4:$C$277,3,0)),0) -> 4132.1388 | F140: =IFERROR(IFERROR(VLOOKUP(A140,[2]Planilha1!$A$4:$C$258,3,0),VLOOKUP(B140,[2]Planilha1!$A$4:$C$258,3,0)),0) -> 792.6848 | G140: =IFERROR(IFERROR(VLOOKUP(A140,[1]Planilha1!$A$4:$D$277,4,0),VLOOKUP(B140,[1]Planilha1!$A$4:$D$277,4,0)),0) -> 2214.3236 | H140: =D140+E140-G140 -> 2785.835 | I140: FILME | J140: 1 | K140: =VLOOKUP(A140,CONT_ANTE!A:D,4,0) -> 1239 | L140: =IF(AND(F140=0,K140<>M140),"!@##@!","ok") -> ok | M140: =IFERROR(VLOOKUP(A140,CONTAGEM!B:G,6,0),VLOOKUP(B140,CONTAGEM!B:G,6,0)) -> 3001 | N140: =IFERROR(SUM(M140*V140),0) -> 50328.567 | O140: =SUMIF(SISTEMA!B:B,A140,SISTEMA!I:I)/J140 -> 2785.835 | P140: =SUMIF(SISTEMA!B:B,B140,SISTEMA!I:I) -> 0 | Q140: =O140+P140 -> 2785.835 | R140: =IFERROR(SUM(Q140*V140),0) -> 46720.121 | S140: =IFERROR(VLOOKUP(A140,DIF_ANTE!A:D,4,0),"0")/J140 -> 370.9802 | T140: =M140-Q140 -> 215.165 | U140: =T140-S140 -> -155.8152 | V140: =IFERROR(VLOOKUP(A140,CUSTO!A:C,3,0),VLOOKUP(B140,CUSTO!A:C,3,0)) -> 16.770599 | W140: =IFERROR(SUM(T140*V140),0) -> 3608.4459 | X140: =IFERROR(T140/Q140,"") -> 0.077235371 | Y140: =IFERROR(U140*V140,"-") -> -2613.1142 | Z140: OK, PERDA
A141: 2701040014 | B141: - | C141: FILME TERMOENCOLHIVEL LISO 390X0,06MM | D141: 0 | E141: =IFERROR(IFERROR(VLOOKUP(B141,[1]Planilha1!$A$4:$C$277,3,0),VLOOKUP(A141,[1]Planilha1!$A$4:$C$277,3,0)),0) -> 0 | F141: =IFERROR(IFERROR(VLOOKUP(A141,[2]Planilha1!$A$4:$C$258,3,0),VLOOKUP(B141,[2]Planilha1!$A$4:$C$258,3,0)),0) -> 0 | G141: =IFERROR(IFERROR(VLOOKUP(A141,[1]Planilha1!$A$4:$D$277,4,0),VLOOKUP(B141,[1]Planilha1!$A$4:$D$277,4,0)),0) -> 0 | H141: =D141+E141-G141 -> 0 | I141: FILME | J141: 1 | K141: =VLOOKUP(A141,CONT_ANTE!A:D,4,0) -> 0 | L141: =IF(AND(F141=0,K141<>M141),"!@##@!","ok") -> ok | M141: =IFERROR(VLOOKUP(A141,CONTAGEM!B:G,6,0),VLOOKUP(B141,CONTAGEM!B:G,6,0)) -> 0 | N141: =IFERROR(SUM(M141*V141),0) -> 0 | O141: =SUMIF(SISTEMA!B:B,A141,SISTEMA!I:I)/J141 -> 0 | P141: =SUMIF(SISTEMA!B:B,B141,SISTEMA!I:I) -> 0 | Q141: =O141+P141 -> 0 | R141: =IFERROR(SUM(Q141*V141),0) -> 0 | S141: =IFERROR(VLOOKUP(A141,DIF_ANTE!A:D,4,0),"0")/J141 -> 0 | T141: =M141-Q141 -> 0 | U141: =T141-S141 -> 0 | V141: =IFERROR(VLOOKUP(A141,CUSTO!A:C,3,0),VLOOKUP(B141,CUSTO!A:C,3,0)) -> 10.017993 | W141: =IFERROR(SUM(T141*V141),0) -> 0 | X141: =IFERROR(T141/Q141,"") | Y141: =IFERROR(U141*V141,"-") -> 0 | Z141: OK
A142: 2701040001 | B142: - | C142: FILME TERMOENCOLHIVEL LISO 420X0,05MM | D142: 3663.0503 | E142: =IFERROR(IFERROR(VLOOKUP(B142,[1]Planilha1!$A$4:$C$277,3,0),VLOOKUP(A142,[1]Planilha1!$A$4:$C$277,3,0)),0) -> 1562.6477 | F142: =IFERROR(IFERROR(VLOOKUP(A142,[2]Planilha1!$A$4:$C$258,3,0),VLOOKUP(B142,[2]Planilha1!$A$4:$C$258,3,0)),0) -> 307.30502 | G142: =IFERROR(IFERROR(VLOOKUP(A142,[1]Planilha1!$A$4:$D$277,4,0),VLOOKUP(B142,[1]Planilha1!$A$4:$D$277,4,0)),0) -> 1875.8718 | H142: =D142+E142-G142 -> 3349.8263 | I142: FILME | J142: 1 | K142: =VLOOKUP(A142,CONT_ANTE!A:D,4,0) -> 2894.8 | L142: =IF(AND(F142=0,K142<>M142),"!@##@!","ok") -> ok | M142: =IFERROR(VLOOKUP(A142,CONTAGEM!B:G,6,0),VLOOKUP(B142,CONTAGEM!B:G,6,0)) -> 2647.4 | N142: =IFERROR(SUM(M142*V142),0) -> 44398.484 | O142: =SUMIF(SISTEMA!B:B,A142,SISTEMA!I:I)/J142 -> 3349.8263 | P142: =SUMIF(SISTEMA!B:B,B142,SISTEMA!I:I) -> 0 | Q142: =O142+P142 -> 3349.8263 | R142: =IFERROR(SUM(Q142*V142),0) -> 56178.595 | S142: =IFERROR(VLOOKUP(A142,DIF_ANTE!A:D,4,0),"0")/J142 -> -768.25034 | T142: =M142-Q142 -> -702.42632 | U142: =T142-S142 -> 65.82402 | V142: =IFERROR(VLOOKUP(A142,CUSTO!A:C,3,0),VLOOKUP(B142,CUSTO!A:C,3,0)) -> 16.770599 | W142: =IFERROR(SUM(T142*V142),0) -> -11780.11 | X142: =IFERROR(T142/Q142,"") -> -0.20969037 | Y142: =IFERROR(U142*V142,"-") -> 1103.9083 | Z142: OK, PERDA
A143: 2701040002 | B143: - | C143: FILME TERMOENCOLHIVEL LISO 420X0,06MM | D143: 4081.1106 | E143: =IFERROR(IFERROR(VLOOKUP(B143,[1]Planilha1!$A$4:$C$277,3,0),VLOOKUP(A143,[1]Planilha1!$A$4:$C$277,3,0)),0) -> 5397.9158 | F143: =IFERROR(IFERROR(VLOOKUP(A143,[2]Planilha1!$A$4:$C$258,3,0),VLOOKUP(B143,[2]Planilha1!$A$4:$C$258,3,0)),0) -> 1915.8283 | G143: =IFERROR(IFERROR(VLOOKUP(A143,[1]Planilha1!$A$4:$D$277,4,0),VLOOKUP(B143,[1]Planilha1!$A$4:$D$277,4,0)),0) -> 7357.8441 | H143: =D143+E143-G143 -> 2121.1823 | I143: FILME | J143: 1 | K143: =VLOOKUP(A143,CONT_ANTE!A:D,4,0) -> 4421.4 | L143: =IF(AND(F143=0,K143<>M143),"!@##@!","ok") -> ok | M143: =IFERROR(VLOOKUP(A143,CONTAGEM!B:G,6,0),VLOOKUP(B143,CONTAGEM!B:G,6,0)) -> 2357.9 | N143: =IFERROR(SUM(M143*V143),0) -> 44250.934 | O143: =SUMIF(SISTEMA!B:B,A143,SISTEMA!I:I)/J143 -> 2121.1823 | P143: =SUMIF(SISTEMA!B:B,B143,SISTEMA!I:I) -> 0 | Q143: =O143+P143 -> 2121.1823 | R143: =IFERROR(SUM(Q143*V143),0) -> 39808.431 | S143: =IFERROR(VLOOKUP(A143,DIF_ANTE!A:D,4,0),"0")/J143 -> 340.28939 | T143: =M143-Q143 -> 236.71769 | U143: =T143-S143 -> -103.5717 | V143: =IFERROR(VLOOKUP(A143,CUSTO!A:C,3,0),VLOOKUP(B143,CUSTO!A:C,3,0)) -> 18.767095 | W143: =IFERROR(SUM(T143*V143),0) -> 4442.5034 | X143: =IFERROR(T143/Q143,"") -> 0.11159705 | Y143: =IFERROR(U143*V143,"-") -> -1943.74 | Z143: OK, PERDA
A144: 2701040028 | B144: - | C144: FILME TERMOENCOLHIVEL LISO 480X0,06MM | D144: 2990.535 | E144: =IFERROR(IFERROR(VLOOKUP(B144,[1]Planilha1!$A$4:$C$277,3,0),VLOOKUP(A144,[1]Planilha1!$A$4:$C$277,3,0)),0) -> 1867.0037 | F144: =IFERROR(IFERROR(VLOOKUP(A144,[2]Planilha1!$A$4:$C$258,3,0),VLOOKUP(B144,[2]Planilha1!$A$4:$C$258,3,0)),0) -> 217.08225 | G144: =IFERROR(IFERROR(VLOOKUP(A144,[1]Planilha1!$A$4:$D$277,4,0),VLOOKUP(B144,[1]Planilha1!$A$4:$D$277,4,0)),0) -> 2084.086 | H144: =D144+E144-G144 -> 2773.4527 | I144: FILME | J144: 1 | K144: =VLOOKUP(A144,CONT_ANTE!A:D,4,0) -> 3262.61 | L144: =IF(AND(F144=0,K144<>M144),"!@##@!","ok") -> ok | M144: =IFERROR(VLOOKUP(A144,CONTAGEM!B:G,6,0),VLOOKUP(B144,CONTAGEM!B:G,6,0)) -> 3067.91 | N144: =IFERROR(SUM(M144*V144),0) -> 31115.409 | O144: =SUMIF(SISTEMA!B:B,A144,SISTEMA!I:I)/J144 -> 2773.4527 | P144: =SUMIF(SISTEMA!B:B,B144,SISTEMA!I:I) -> 0 | Q144: =O144+P144 -> 2773.4527 | R144: =IFERROR(SUM(Q144*V144),0) -> 28128.96 | S144: =IFERROR(VLOOKUP(A144,DIF_ANTE!A:D,4,0),"0")/J144 -> 272.075 | T144: =M144-Q144 -> 294.45725 | U144: =T144-S144 -> 22.38225 | V144: =IFERROR(VLOOKUP(A144,CUSTO!A:C,3,0),VLOOKUP(B144,CUSTO!A:C,3,0)) -> 10.142217 | W144: =IFERROR(SUM(T144*V144),0) -> 2986.4494 | X144: =IFERROR(T144/Q144,"") -> 0.10616992 | Y144: =IFERROR(U144*V144,"-") -> 227.00564 | Z144: OK, PERDA
A145: 2701040023 | B145: - | C145: FILME TERMOENCOLHIVEL LISO 500X0,06MM | D145: 972.987 | E145: =IFERROR(IFERROR(VLOOKUP(B145,[1]Planilha1!$A$4:$C$277,3,0),VLOOKUP(A145,[1]Planilha1!$A$4:$C$277,3,0)),0) -> 494.1244 | F145: =IFERROR(IFERROR(VLOOKUP(A145,[2]Planilha1!$A$4:$C$258,3,0),VLOOKUP(B145,[2]Planilha1!$A$4:$C$258,3,0)),0) -> 0 | G145: =IFERROR(IFERROR(VLOOKUP(A145,[1]Planilha1!$A$4:$D$277,4,0),VLOOKUP(B145,[1]Planilha1!$A$4:$D$277,4,0)),0) -> 547.0444 | H145: =D145+E145-G145 -> 920.067 | I145: FILME | J145: 1 | K145: =VLOOKUP(A145,CONT_ANTE!A:D,4,0) -> 1193.4 | L145: =IF(AND(F145=0,K145<>M145),"!@##@!","ok") -> !@##@! | M145: =IFERROR(VLOOKUP(A145,CONTAGEM!B:G,6,0),VLOOKUP(B145,CONTAGEM!B:G,6,0)) -> 1228.24 | N145: =IFERROR(SUM(M145*V145),0) -> 11817.285 | O145: =SUMIF(SISTEMA!B:B,A145,SISTEMA!I:I)/J145 -> 920.067 | P145: =SUMIF(SISTEMA!B:B,B145,SISTEMA!I:I) -> 0 | Q145: =O145+P145 -> 920.067 | R145: =IFERROR(SUM(Q145*V145),0) -> 8852.255 | S145: =IFERROR(VLOOKUP(A145,DIF_ANTE!A:D,4,0),"0")/J145 -> 220.413 | T145: =M145-Q145 -> 308.173 | U145: =T145-S145 -> 87.76 | V145: =IFERROR(VLOOKUP(A145,CUSTO!A:C,3,0),VLOOKUP(B145,CUSTO!A:C,3,0)) -> 9.6213156 | W145: =IFERROR(SUM(T145*V145),0) -> 2965.0297 | X145: =IFERROR(T145/Q145,"") -> 0.33494626 | Y145: =IFERROR(U145*V145,"-") -> 844.36666 | Z145: ANALISAR CONSUMOS
A146: 2701040024 | B146: - | C146: FILME TERMOENCOLHIVEL LISO 560X0,05MM | D146: 0 | E146: =IFERROR(IFERROR(VLOOKUP(B146,[1]Planilha1!$A$4:$C$277,3,0),VLOOKUP(A146,[1]Planilha1!$A$4:$C$277,3,0)),0) -> 0 | F146: =IFERROR(IFERROR(VLOOKUP(A146,[2]Planilha1!$A$4:$C$258,3,0),VLOOKUP(B146,[2]Planilha1!$A$4:$C$258,3,0)),0) -> 0 | G146: =IFERROR(IFERROR(VLOOKUP(A146,[1]Planilha1!$A$4:$D$277,4,0),VLOOKUP(B146,[1]Planilha1!$A$4:$D$277,4,0)),0) -> 0 | H146: =D146+E146-G146 -> 0 | I146: FILME | J146: 1 | K146: =VLOOKUP(A146,CONT_ANTE!A:D,4,0) -> 0 | L146: =IF(AND(F146=0,K146<>M146),"!@##@!","ok") -> ok | M146: =IFERROR(VLOOKUP(A146,CONTAGEM!B:G,6,0),VLOOKUP(B146,CONTAGEM!B:G,6,0)) -> 0 | N146: =IFERROR(SUM(M146*V146),0) -> 0 | O146: =SUMIF(SISTEMA!B:B,A146,SISTEMA!I:I)/J146 -> 0 | P146: =SUMIF(SISTEMA!B:B,B146,SISTEMA!I:I) -> 0 | Q146: =O146+P146 -> 0 | R146: =IFERROR(SUM(Q146*V146),0) -> 0 | S146: =IFERROR(VLOOKUP(A146,DIF_ANTE!A:D,4,0),"0")/J146 -> 0 | T146: =M146-Q146 -> 0 | U146: =T146-S146 -> 0 | V146: =IFERROR(VLOOKUP(A146,CUSTO!A:C,3,0),VLOOKUP(B146,CUSTO!A:C,3,0)) -> 3.726875 | W146: =IFERROR(SUM(T146*V146),0) -> 0 | X146: =IFERROR(T146/Q146,"") | Y146: =IFERROR(U146*V146,"-") -> 0 | Z146: OK
... A150: 2701040007 | B150: - | C150: FILME TERMOENCOLHIVEL LISO 860X0,06MM | D150: 18.25 | E150: =IFERROR(IFERROR(VLOOKUP(B150,[1]Planilha1!$A$4:$C$277,3,0),VLOOKUP(A150,[1]Planilha1!$A$4:$C$277,3,0)),0) -> 0 | F150: =IFERROR(IFERROR(VLOOKUP(A150,[2]Planilha1!$A$4:$C$258,3,0),VLOOKUP(B150,[2]Planilha1!$A$4:$C$258,3,0)),0) -> 0 | G150: =IFERROR(IFERROR(VLOOKUP(A150,[1]Planilha1!$A$4:$D$277,4,0),VLOOKUP(B150,[1]Planilha1!$A$4:$D$277,4,0)),0) -> 0 | H150: =D150+E150-G150 -> 18.25 | I150: FILME | J150: 1 | K150: =VLOOKUP(A150,CONT_ANTE!A:D,4,0) -> 0 | L150: =IF(AND(F150=0,K150<>M150),"!@##@!","ok") -> ok | M150: =IFERROR(VLOOKUP(A150,CONTAGEM!B:G,6,0),VLOOKUP(B150,CONTAGEM!B:G,6,0)) -> 0 | N150: =IFERROR(SUM(M150*V150),0) -> 0 | O150: =SUMIF(SISTEMA!B:B,A150,SISTEMA!I:I)/J150 -> 18.25 | P150: =SUMIF(SISTEMA!B:B,B150,SISTEMA!I:I) -> 0 | Q150: =O150+P150 -> 18.25 | R150: =IFERROR(SUM(Q150*V150),0) -> 68.015468 | S150: =IFERROR(VLOOKUP(A150,DIF_ANTE!A:D,4,0),"0")/J150 -> -18.25 | T150: =M150-Q150 -> -18.25 | U150: =T150-S150 -> 0 | V150: =IFERROR(VLOOKUP(A150,CUSTO!A:C,3,0),VLOOKUP(B150,CUSTO!A:C,3,0)) -> 3.726875 | W150: =IFERROR(SUM(T150*V150),0) -> -68.015468 | X150: =IFERROR(T150/Q150,"") -> -1 | Y150: =IFERROR(U150*V150,"-") -> 0 | Z150: OK, PERDA
A151: 2701040026 | B151: - | C151: FILME TERMOENCOLHIVEL LISO 390X0,05MM | D151: 0 | E151: =IFERROR(IFERROR(VLOOKUP(B151,[1]Planilha1!$A$4:$C$277,3,0),VLOOKUP(A151,[1]Planilha1!$A$4:$C$277,3,0)),0) -> 4662.514 | F151: =IFERROR(IFERROR(VLOOKUP(A151,[2]Planilha1!$A$4:$C$258,3,0),VLOOKUP(B151,[2]Planilha1!$A$4:$C$258,3,0)),0) -> 0 | G151: =IFERROR(IFERROR(VLOOKUP(A151,[1]Planilha1!$A$4:$D$277,4,0),VLOOKUP(B151,[1]Planilha1!$A$4:$D$277,4,0)),0) -> 4662.514 | H151: =D151+E151-G151 -> 0 | I151: FILME | J151: 1 | K151: =VLOOKUP(A151,CONT_ANTE!A:D,4,0) -> 0 | L151: =IF(AND(F151=0,K151<>M151),"!@##@!","ok") -> ok | M151: 0 | N151: =IFERROR(SUM(M151*V151),0) -> 0 | O151: =SUMIF(SISTEMA!B:B,A151,SISTEMA!I:I)/J151 -> 0 | P151: =SUMIF(SISTEMA!B:B,B151,SISTEMA!I:I) -> 0 | Q151: =O151+P151 -> 0 | R151: =IFERROR(SUM(Q151*V151),0) -> 0 | S151: =IFERROR(VLOOKUP(A151,DIF_ANTE!A:D,4,0),"0")/J151 -> 0 | T151: =M151-Q151 -> 0 | U151: =T151-S151 -> 0 | V151: =IFERROR(VLOOKUP(A151,CUSTO!A:C,3,0),VLOOKUP(B151,CUSTO!A:C,3,0)) -> 18.7671 | W151: =IFERROR(SUM(T151*V151),0) -> 0 | X151: =IFERROR(T151/Q151,"") | Y151: =IFERROR(U151*V151,"-") -> 0 | Z151: OK
A152: 2701110001 | B152: - | C152: DIOXIDO CARBONO | D152: 79133.498 | E152: =IFERROR(IFERROR(VLOOKUP(B152,[1]Planilha1!$A$4:$C$277,3,0),VLOOKUP(A152,[1]Planilha1!$A$4:$C$277,3,0)),0) -> 86770 | F152: =IFERROR(IFERROR(VLOOKUP(A152,[2]Planilha1!$A$4:$C$258,3,0),VLOOKUP(B152,[2]Planilha1!$A$4:$C$258,3,0)),0) -> 134781.09 | G152: =IFERROR(IFERROR(VLOOKUP(A152,[1]Planilha1!$A$4:$D$277,4,0),VLOOKUP(B152,[1]Planilha1!$A$4:$D$277,4,0)),0) -> 134781.09 | H152: =D152+E152-G152 -> 31122.403 | I152: GASES | J152: 1 | K152: =VLOOKUP(A152,CONT_ANTE!A:D,4,0) -> 11650 | L152: =IF(AND(F152=0,K152<>M152),"!@##@!","ok") -> ok | M152: =IFERROR(VLOOKUP(A152,CONTAGEM!B:G,6,0),VLOOKUP(B152,CONTAGEM!B:G,6,0)) -> 13180 | N152: =IFERROR(SUM(M152*V152),0) -> 32734.379 | O152: =SUMIF(SISTEMA!B:B,A152,SISTEMA!I:I)/J152 -> 32807.26 | P152: =SUMIF(SISTEMA!B:B,B152,SISTEMA!I:I) -> 0 | Q152: =O152+P152 -> 32807.26 | R152: =IFERROR(SUM(Q152*V152),0) -> 81481.431 | S152: =IFERROR(VLOOKUP(A152,DIF_ANTE!A:D,4,0),"0")/J152 -> -67483.498 | T152: =M152-Q152 -> -19627.26 | U152: =T152-S152 -> 47856.238 | V152: =IFERROR(VLOOKUP(A152,CUSTO!A:C,3,0),VLOOKUP(B152,CUSTO!A:C,3,0)) -> 2.4836403 | W152: =IFERROR(SUM(T152*V152),0) -> -48747.052 | X152: =IFERROR(T152/Q152,"") -> -0.59825965 | Y152: =IFERROR(U152*V152,"-") -> 118857.68 | Z152: OK
A153: 2701110002 | B153: - | C153: NITROGENIO LIQUIDO | D153: 0 | E153: =IFERROR(IFERROR(VLOOKUP(B153,[1]Planilha1!$A$4:$C$277,3,0),VLOOKUP(A153,[1]Planilha1!$A$4:$C$277,3,0)),0) -> 0 | F153: =IFERROR(IFERROR(VLOOKUP(A153,[2]Planilha1!$A$4:$C$258,3,0),VLOOKUP(B153,[2]Planilha1!$A$4:$C$258,3,0)),0) -> 0 | G153: =IFERROR(IFERROR(VLOOKUP(A153,[1]Planilha1!$A$4:$D$277,4,0),VLOOKUP(B153,[1]Planilha1!$A$4:$D$277,4,0)),0) -> 0 | H153: =D153+E153-G153 -> 0 | I153: GASES | J153: 1 | K153: =VLOOKUP(A153,CONT_ANTE!A:D,4,0) -> 0 | L153: =IF(AND(F153=0,K153<>M153),"!@##@!","ok") -> ok | M153: 0 | N153: =IFERROR(SUM(M153*V153),0) -> 0 | O153: =SUMIF(SISTEMA!B:B,A153,SISTEMA!I:I)/J153 -> 0 | P153: =SUMIF(SISTEMA!B:B,B153,SISTEMA!I:I) -> 0 | Q153: =O153+P153 -> 0 | R153: =IFERROR(SUM(Q153*V153),0) -> 0 | S153: =IFERROR(VLOOKUP(A153,DIF_ANTE!A:D,4,0),"0")/J153 -> 0 | T153: =M153-Q153 -> 0 | U153: =T153-S153 -> 0 | V153: =IFERROR(VLOOKUP(A153,CUSTO!A:C,3,0),VLOOKUP(B153,CUSTO!A:C,3,0)) -> 3.726875 | W153: =IFERROR(SUM(T153*V153),0) -> 0 | X153: =IFERROR(T153/Q153,"") | Y153: =IFERROR(U153*V153,"-") -> 0 | Z153: OK
A154: 2701170001 | B154: - | C154: AGUARDENTE DE CANA | D154: 0 | E154: =IFERROR(IFERROR(VLOOKUP(B154,[1]Planilha1!$A$4:$C$277,3,0),VLOOKUP(A154,[1]Planilha1!$A$4:$C$277,3,0)),0) -> 0 | F154: =IFERROR(IFERROR(VLOOKUP(A154,[2]Planilha1!$A$4:$C$258,3,0),VLOOKUP(B154,[2]Planilha1!$A$4:$C$258,3,0)),0) -> 0 | G154: =IFERROR(IFERROR(VLOOKUP(A154,[1]Planilha1!$A$4:$D$277,4,0),VLOOKUP(B154,[1]Planilha1!$A$4:$D$277,4,0)),0) -> 0 | H154: =D154+E154-G154 -> 0 | I154: INDUSTRIALIZAÇÃO | J154: 1 | K154: =VLOOKUP(A154,CONT_ANTE!A:D,4,0) -> 0 | L154: =IF(AND(F154=0,K154<>M154),"!@##@!","ok") -> ok | M154: 0 | N154: =IFERROR(SUM(M154*V154),0) -> 0 | O154: =SUMIF(SISTEMA!B:B,A154,SISTEMA!I:I)/J154 -> 0 | P154: =SUMIF(SISTEMA!B:B,B154,SISTEMA!I:I) -> 0 | Q154: =O154+P154 -> 0 | R154: =IFERROR(SUM(Q154*V154),0) -> 0 | S154: =IFERROR(VLOOKUP(A154,DIF_ANTE!A:D,4,0),"0")/J154 -> 0 | T154: =M154-Q154 -> 0 | U154: =T154-S154 -> 0 | V154: =IFERROR(VLOOKUP(A154,CUSTO!A:C,3,0),VLOOKUP(B154,CUSTO!A:C,3,0)) -> 1.9056955 | W154: =IFERROR(SUM(T154*V154),0) -> 0 | X154: =IFERROR(T154/Q154,"") | Y154: =IFERROR(U154*V154,"-") -> 0 | Z154: OK
...

Sheet Planilha2
L2: Sistema | M2: Produção
K3: Saldo em 31/12 | L3: 2311041 | M3: 2311041
I4: Entradas | J4: jan | K4: =1460160*3 -> 4380480 | L4: =SUM(K4:K6) -> 11681280 | M4: =SUM(L4:L6) -> 11681280
J5: Fev | K5: =1460160*2 -> 2920320
J6: Mar | K6: =1460160*3 -> 4380480
I7: Saidas | J7: Jan | K7: 4929395 | L7: =SUM(K7:K9) -> 11807538 | M7: =4916976+17762 -> 4934738
J8: Fev | K8: 1593143 | M8: =1588356+6231 -> 1594587
J9: Mar | K9: 5285000 | M9: =4641756+16653 -> 4658409
K10: Saldo em 31/03 | L10: =L3+L4-L7 -> 2184783 | M10: =M3+M4-M7-M8-M9 -> 2804587
K11: Contagem 31/03 | L11: 3047780
K14: Saldo em 31/12 | L14: 12830 | M14: 723648 | Q14: jan | R14: fev | S14: mar
K15: Compra | L15: 66340 | M15: 341760 | Q15: 74826 | R15: 50448 | S15: 109824
K16: Consumo | L16: 53770 | M16: 291655 | N16: 298428 | O16: =M16-N16 -> -6773 | Q16: 188964 | R16: 73944 | S16: 198246
K17: Saldo em 31/01 | L17: =L14+L15-L16 -> 25400 | M17: =M14+M15-M16 -> 773753 | Q17: 8478 | R17: 12342 | S17: 13976
K18: Compra | L18: 28070 | M18: 0 | Q18: 26160 | R18: 42078 | S18: 50784
K19: Consumo | L19: 33510 | M19: 179241 | N19: 178812 | O19: =M19-N19 -> 429 | P19: total | Q19: =SUM(Q15:Q18) -> 298428 | R19: =SUM(R15:R18) -> 178812 | S19: =SUM(S15:S18) -> 372830
K20: Saldo em 28/02 | L20: =L17+L18-L19 -> 19960 | M20: =M17+M18-M19 -> 594512
K21: Compra | L21: 70440 | M21: 0
K22: Consumo | L22: 72300 | M22: =433062-59808 -> 373254 | N22: 372830 | O22: =M22-N22 -> 424
K23: Saldo em 31/03 | L23: =L20+L21-L22 -> 18100 | M23: =M20-M22+M21 -> 221258

Sheet CONCILIÇÃO_SEM_VASILHAME
L1: Valor Estoque Físico | O1: Valor Estoque Sistema | T1: Acuracidade Qualitativa | U1: Custo Diferença | V1: Percentual Diferença
L2: =SUBTOTAL(9,BASE_CONCILI12[CUSTO FÍSICO]) -> 207493.66 | O2: =SUBTOTAL(9,BASE_CONCILI12[CUSTO SISTEMA]) -> 0 | T2: =(COUNTIF(BASE_CONCILI12[30/jun],">0")-COUNTIF(BASE_CONCILI12[ACURACIDADE],">1,05")-COUNTIF(BASE_CONCILI12[ACURACIDADE],"<0,95"))/COUNTIF(BASE_CONCILI12[30/jun],">0") -> 1 | U2: =SUBTOTAL(9,BASE_CONCILI12[CUSTO DIVERGÊNCIA]) -> 0 | V2: =U2/O2 -> #DIV/0!
A4: CÓD. SAIB | B4: CÓD. PRODUTO | C4: DESCRIÇÃO | D4: CLASSE | E4: 30/mai | F4: CONSUMO REAL | G4: CONSUMO TEORICO | H4: DIFERENÇA CONSUMO | I4: RECEBIMENTO | J4: TRANSFERÊNCIA | K4: QTDE. FINAL | L4: 30/jun | M4: CUSTO FÍSICO | N4: 01/fev | O4: SISTEMA | P4: CUSTO SISTEMA | Q4: DIFERENÇA ANTERIOR | R4: DIFERENÇA ATUAL | S4: DIFERENÇA MÊS | T4: CUSTO MP (UN) | U4: CUSTO DIVERGÊNCIA | V4: ACURACIDADE | W4: DIFERENÇA VALOR | X4: OBSERVAÇÃO
A5: 55 | C5: ACUCAR CRISTAL | D5: AÇUCAR | E5: =VLOOKUP(BASE_CONCILI12[[#This Row],[CÓD. SAIB]],CONT_ANTE!A:D,4,0) -> #N/A | F5: =SUMIF(#REF!,BASE_CONCILI12[[#This Row],[CÓD. SAIB]],#REF!) -> #REF! | G5: =SUMIF(#REF!,BASE_CONCILI12[[#This Row],[CÓD. SAIB]],#REF!) -> #REF! | H5: =BASE_CONCILI12[[#This Row],[CONSUMO REAL]]-BASE_CONCILI12[[#This Row],[CONSUMO TEORICO]] -> #REF! | I5: =SUMIF(#REF!,BASE_CONCILI12[[#This Row],[CÓD. SAIB]],#REF!) -> #REF! | J5: =SUMIF(#REF!,BASE_CONCILI12[[#This Row],[CÓD. SAIB]],#REF!) -> #REF! | K5: =BASE_CONCILI12[[#This Row],[30/mai]]+BASE_CONCILI12[[#This Row],[RECEBIMENTO]]-BASE_CONCILI12[[#This Row],[TRANSFERÊNCIA]]-BASE_CONCILI12[[#This Row],[CONSUMO REAL]] -> #N/A | L5: =IFERROR(VLOOKUP(BASE_CONCILI12[[#This Row],[CÓD. SAIB]],BASE_CONTAG[[LAVRE]:[CONTAGEM FINAL]],7,0),0) -> 117.84 | M5: =IFERROR(SUM(BASE_CONCILI12[[#This Row],[30/jun]]*BASE_CONCILI12[[#This Row],[CUSTO MP (UN)]]),0) -> 0 | N5: =IFERROR(VLOOKUP(BASE_CONCILI12[[#This Row],[CÓD. SAIB]],BASE_CONTAG[],5,0),"") -> 117.84 | O5: =SUMIF(SISTEMA!#REF!,BASE_CONCILI12[[#This Row],[CÓD. SAIB]],SISTEMA!#REF!) -> #REF! | P5: =IFERROR(SUM(BASE_CONCILI12[[#This Row],[SISTEMA]]*BASE_CONCILI12[[#This Row],[CUSTO MP (UN)]]),0) -> 0 | Q5: =IFERROR(VLOOKUP(BASE_CONCILI12[[#This Row],[CÓD. SAIB]],BASE_DIFERENÇA[],4,0),"0") -> 0 | R5: =BASE_CONCILI12[[#This Row],[30/jun]]-BASE_CONCILI12[[#This Row],[SISTEMA]] -> #REF! | S5: =IFERROR(BASE_CONCILI12[[#This Row],[DIFERENÇA ANTERIOR]]-BASE_CONCILI12[[#This Row],[DIFERENÇA ATUAL]],"-") -> - | T5: =VLOOKUP(BASE_CONCILI12[[#This Row],[CÓD. SAIB]],CUSTO!#REF!,3,0) -> #REF! | U5: =IFERROR(SUM(BASE_CONCILI12[[#This Row],[DIFERENÇA ATUAL]]*BASE_CONCILI12[[#This Row],[CUSTO MP (UN)]]),0) -> 0 | V5: =IFERROR(BASE_CONCILI12[[#This Row],[30/jun]]/BASE_CONCILI12[[#This Row],[SISTEMA]],"") | W5: =IFERROR(BASE_CONCILI12[[#This Row],[DIFERENÇA MÊS]]*BASE_CONCILI12[[#This Row],[CUSTO MP (UN)]],"-") -> - | X5: OK
A6: 31395 | C6: ETANOL HIDRATADO | D6: ALCOOL | E6: =VLOOKUP(BASE_CONCILI12[[#This Row],[CÓD. SAIB]],CONT_ANTE!A:D,4,0) -> #N/A | F6: =SUMIF(#REF!,BASE_CONCILI12[[#This Row],[CÓD. SAIB]],#REF!) -> #REF! | G6: =SUMIF(#REF!,BASE_CONCILI12[[#This Row],[CÓD. SAIB]],#REF!) -> #REF! | H6: =BASE_CONCILI12[[#This Row],[CONSUMO REAL]]-BASE_CONCILI12[[#This Row],[CONSUMO TEORICO]] -> #REF! | I6: =SUMIF(#REF!,BASE_CONCILI12[[#This Row],[CÓD. SAIB]],#REF!) -> #REF! | J6: =SUMIF(#REF!,BASE_CONCILI12[[#This Row],[CÓD. SAIB]],#REF!) -> #REF! | K6: =BASE_CONCILI12[[#This Row],[30/mai]]+BASE_CONCILI12[[#This Row],[RECEBIMENTO]]-BASE_CONCILI12[[#This Row],[TRANSFERÊNCIA]]-BASE_CONCILI12[[#This Row],[CONSUMO REAL]] -> #N/A | L6: =IFERROR(VLOOKUP(BASE_CONCILI12[[#This Row],[CÓD. SAIB]],BASE_CONTAG[[LAVRE]:[CONTAGEM FINAL]],7,0),0) -> 84 | M6: =IFERROR(SUM(BASE_CONCILI12[[#This Row],[30/jun]]*BASE_CONCILI12[[#This Row],[CUSTO MP (UN)]]),0) -> 0 | N6: =IFERROR(VLOOKUP(BASE_CONCILI12[[#This Row],[CÓD. SAIB]],BASE_CONTAG[],5,0),"") -> 84 | O6: =SUMIF(SISTEMA!#REF!,BASE_CONCILI12[[#This Row],[CÓD. SAIB]],SISTEMA!#REF!) -> #REF! | P6: =IFERROR(SUM(BASE_CONCILI12[[#This Row],[SISTEMA]]*BASE_CONCILI12[[#This Row],[CUSTO MP (UN)]]),0) -> 0 | Q6: =IFERROR(VLOOKUP(BASE_CONCILI12[[#This Row],[CÓD. SAIB]],BASE_DIFERENÇA[],4,0),"0") -> 0 | R6: =BASE_CONCILI12[[#This Row],[30/jun]]-BASE_CONCILI12[[#This Row],[SISTEMA]] -> #REF! | S6: =IFERROR(BASE_CONCILI12[[#This Row],[DIFERENÇA ANTERIOR]]-BASE_CONCILI12[[#This Row],[DIFERENÇA ATUAL]],"-") -> - | T6: =VLOOKUP(BASE_CONCILI12[[#This Row],[CÓD. SAIB]],CUSTO!#REF!,3,0) -> #REF! | U6: =IFERROR(SUM(BASE_CONCILI12[[#This Row],[DIFERENÇA ATUAL]]*BASE_CONCILI12[[#This Row],[CUSTO MP (UN)]]),0) -> 0 | V6: =IFERROR(BASE_CONCILI12[[#This Row],[30/jun]]/BASE_CONCILI12[[#This Row],[SISTEMA]],"") | W6: =IFERROR(BASE_CONCILI12[[#This Row],[DIFERENÇA MÊS]]*BASE_CONCILI12[[#This Row],[CUSTO MP (UN)]],"-") -> - | X6: OK
A7: 31352 | C7: AA ENERGY FLAVOR | D7: AROMA | E7: =VLOOKUP(BASE_CONCILI12[[#This Row],[CÓD. SAIB]],CONT_ANTE!A:D,4,0) -> #N/A | F7: =SUMIF(#REF!,BASE_CONCILI12[[#This Row],[CÓD. SAIB]],#REF!) -> #REF! | G7: =SUMIF(#REF!,BASE_CONCILI12[[#This Row],[CÓD. SAIB]],#REF!) -> #REF! | H7: =BASE_CONCILI12[[#This Row],[CONSUMO REAL]]-BASE_CONCILI12[[#This Row],[CONSUMO TEORICO]] -> #REF! | I7: =SUMIF(#REF!,BASE_CONCILI12[[#This Row],[CÓD. SAIB]],#REF!) -> #REF! | J7: =SUMIF(#REF!,BASE_CONCILI12[[#This Row],[CÓD. SAIB]],#REF!) -> #REF! | K7: =BASE_CONCILI12[[#This Row],[30/mai]]+BASE_CONCILI12[[#This Row],[RECEBIMENTO]]-BASE_CONCILI12[[#This Row],[TRANSFERÊNCIA]]-BASE_CONCILI12[[#This Row],[CONSUMO REAL]] -> #N/A | L7: =IFERROR(VLOOKUP(BASE_CONCILI12[[#This Row],[CÓD. SAIB]],BASE_CONTAG[[LAVRE]:[CONTAGEM FINAL]],7,0),0) -> 0 | M7: =IFERROR(SUM(BASE_CONCILI12[[#This Row],[30/jun]]*BASE_CONCILI12[[#This Row],[CUSTO MP (UN)]]),0) -> 0 | N7: =IFERROR(VLOOKUP(BASE_CONCILI12[[#This Row],[CÓD. SAIB]],BASE_CONTAG[],5,0),"") -> 0 | O7: =SUMIF(SISTEMA!#REF!,BASE_CONCILI12[[#This Row],[CÓD. SAIB]],SISTEMA!#REF!) -> #REF! | P7: =IFERROR(SUM(BASE_CONCILI12[[#This Row],[SISTEMA]]*BASE_CONCILI12[[#This Row],[CUSTO MP (UN)]]),0) -> 0 | Q7: =IFERROR(VLOOKUP(BASE_CONCILI12[[#This Row],[CÓD. SAIB]],BASE_DIFERENÇA[],4,0),"0") -> 0 | R7: =BASE_CONCILI12[[#This Row],[30/jun]]-BASE_CONCILI12[[#This Row],[SISTEMA]] -> #REF! | S7: =IFERROR(BASE_CONCILI12[[#This Row],[DIFERENÇA ANTERIOR]]-BASE_CONCILI12[[#This Row],[DIFERENÇA ATUAL]],"-") -> - | T7: =VLOOKUP(BASE_CONCILI12[[#This Row],[CÓD. SAIB]],CUSTO!#REF!,3,0) -> #REF! | U7: =IFERROR(SUM(BASE_CONCILI12[[#This Row],[DIFERENÇA ATUAL]]*BASE_CONCILI12[[#This Row],[CUSTO MP (UN)]]),0) -> 0 | V7: =IFERROR(BASE_CONCILI12[[#This Row],[30/jun]]/BASE_CONCILI12[[#This Row],[SISTEMA]],"") | W7: =IFERROR(BASE_CONCILI12[[#This Row],[DIFERENÇA MÊS]]*BASE_CONCILI12[[#This Row],[CUSTO MP (UN)]],"-") -> - | X7: OK
A8: 2089 | C8: AROMA ART DE TUTTI FRUTTI RB 10766 | D8: AROMA | E8: =VLOOKUP(BASE_CONCILI12[[#This Row],[CÓD. SAIB]],CONT_ANTE!A:D,4,0) -> #N/A | F8: =SUMIF(#REF!,BASE_CONCILI12[[#This Row],[CÓD. SAIB]],#REF!) -> #REF! | G8: =SUMIF(#REF!,BASE_CONCILI12[[#This Row],[CÓD. SAIB]],#REF!) -> #REF! | H8: =BASE_CONCILI12[[#This Row],[CONSUMO REAL]]-BASE_CONCILI12[[#This Row],[CONSUMO TEORICO]] -> #REF! | I8: =SUMIF(#REF!,BASE_CONCILI12[[#This Row],[CÓD. SAIB]],#REF!) -> #REF! | J8: =SUMIF(#REF!,BASE_CONCILI12[[#This Row],[CÓD. SAIB]],#REF!) -> #REF! | K8: =BASE_CONCILI12[[#This Row],[30/mai]]+BASE_CONCILI12[[#This Row],[RECEBIMENTO]]-BASE_CONCILI12[[#This Row],[TRANSFERÊNCIA]]-BASE_CONCILI12[[#This Row],[CONSUMO REAL]] -> #N/A | L8: =IFERROR(VLOOKUP(BASE_CONCILI12[[#This Row],[CÓD. SAIB]],BASE_CONTAG[[LAVRE]:[CONTAGEM FINAL]],7,0),0) -> 0 | M8: =IFERROR(SUM(BASE_CONCILI12[[#This Row],[30/jun]]*BASE_CONCILI12[[#This Row],[CUSTO MP (UN)]]),0) -> 0 | N8: =IFERROR(VLOOKUP(BASE_CONCILI12[[#This Row],[CÓD. SAIB]],BASE_CONTAG[],5,0),"") | O8: =SUMIF(SISTEMA!#REF!,BASE_CONCILI12[[#This Row],[CÓD. SAIB]],SISTEMA!#REF!) -> #REF! | P8: =IFERROR(SUM(BASE_CONCILI12[[#This Row],[SISTEMA]]*BASE_CONCILI12[[#This Row],[CUSTO MP (UN)]]),0) -> 0 | Q8: =IFERROR(VLOOKUP(BASE_CONCILI12[[#This Row],[CÓD. SAIB]],BASE_DIFERENÇA[],4,0),"0") -> 0 | R8: =BASE_CONCILI12[[#This Row],[30/jun]]-BASE_CONCILI12[[#This Row],[SISTEMA]] -> #REF! | S8: =IFERROR(BASE_CONCILI12[[#This Row],[DIFERENÇA ANTERIOR]]-BASE_CONCILI12[[#This Row],[DIFERENÇA ATUAL]],"-") -> - | T8: =VLOOKUP(BASE_CONCILI12[[#This Row],[CÓD. SAIB]],CUSTO!#REF!,3,0) -> #REF! | U8: =IFERROR(SUM(BASE_CONCILI12[[#This Row],[DIFERENÇA ATUAL]]*BASE_CONCILI12[[#This Row],[CUSTO MP (UN)]]),0) -> 0 | V8: =IFERROR(BASE_CONCILI12[[#This Row],[30/jun]]/BASE_CONCILI12[[#This Row],[SISTEMA]],"") | W8: =IFERROR(BASE_CONCILI12[[#This Row],[DIFERENÇA MÊS]]*BASE_CONCILI12[[#This Row],[CUSTO MP (UN)]],"-") -> - | X8: OK
A9: 31351 | C9: AROMA ARTIFICIAL GUARANA | D9: AROMA | E9: =VLOOKUP(BASE_CONCILI12[[#This Row],[CÓD. SAIB]],CONT_ANTE!A:D,4,0) -> #N/A | F9: =SUMIF(#REF!,BASE_CONCILI12[[#This Row],[CÓD. SAIB]],#REF!) -> #REF! | G9: =SUMIF(#REF!,BASE_CONCILI12[[#This Row],[CÓD. SAIB]],#REF!) -> #REF! | H9: =BASE_CONCILI12[[#This Row],[CONSUMO REAL]]-BASE_CONCILI12[[#This Row],[CONSUMO TEORICO]] -> #REF! | I9: =SUMIF(#REF!,BASE_CONCILI12[[#This Row],[CÓD. SAIB]],#REF!) -> #REF! | J9: =SUMIF(#REF!,BASE_CONCILI12[[#This Row],[CÓD. SAIB]],#REF!) -> #REF! | K9: =BASE_CONCILI12[[#This Row],[30/mai]]+BASE_CONCILI12[[#This Row],[RECEBIMENTO]]-BASE_CONCILI12[[#This Row],[TRANSFERÊNCIA]]-BASE_CONCILI12[[#This Row],[CONSUMO REAL]] -> #N/A | L9: =IFERROR(VLOOKUP(BASE_CONCILI12[[#This Row],[CÓD. SAIB]],BASE_CONTAG[[LAVRE]:[CONTAGEM FINAL]],7,0),0) -> 0 | M9: =IFERROR(SUM(BASE_CONCILI12[[#This Row],[30/jun]]*BASE_CONCILI12[[#This Row],[CUSTO MP (UN)]]),0) -> 0 | N9: =IFERROR(VLOOKUP(BASE_CONCILI12[[#This Row],[CÓD. SAIB]],BASE_CONTAG[],5,0),"") -> 0 | O9: =SUMIF(SISTEMA!#REF!,BASE_CONCILI12[[#This Row],[CÓD. SAIB]],SISTEMA!#REF!) -> #REF! | P9: =IFERROR(SUM(BASE_CONCILI12[[#This Row],[SISTEMA]]*BASE_CONCILI12[[#This Row],[CUSTO MP (UN)]]),0) -> 0 | Q9: =IFERROR(VLOOKUP(BASE_CONCILI12[[#This Row],[CÓD. SAIB]],BASE_DIFERENÇA[],4,0),"0") -> 0 | R9: =BASE_CONCILI12[[#This Row],[30/jun]]-BASE_CONCILI12[[#This Row],[SISTEMA]] -> #REF! | S9: =IFERROR(BASE_CONCILI12[[#This Row],[DIFERENÇA ANTERIOR]]-BASE_CONCILI12[[#This Row],[DIFERENÇA ATUAL]],"-") -> - | T9: =VLOOKUP(BASE_CONCILI12[[#This Row],[CÓD. SAIB]],CUSTO!#REF!,3,0) -> #REF! | U9: =IFERROR(SUM(BASE_CONCILI12[[#This Row],[DIFERENÇA ATUAL]]*BASE_CONCILI12[[#This Row],[CUSTO MP (UN)]]),0) -> 0 | V9: =IFERROR(BASE_CONCILI12[[#This Row],[30/jun]]/BASE_CONCILI12[[#This Row],[SISTEMA]],"") | W9: =IFERROR(BASE_CONCILI12[[#This Row],[DIFERENÇA MÊS]]*BASE_CONCILI12[[#This Row],[CUSTO MP (UN)]],"-") -> - | X9: OK
A10: 31355 | C10: AROMA BAUNILHA | D10: AROMA | E10: =VLOOKUP(BASE_CONCILI12[[#This Row],[CÓD. SAIB]],CONT_ANTE!A:D,4,0) -> #N/A | F10: =SUMIF(#REF!,BASE_CONCILI12[[#This Row],[CÓD. SAIB]],#REF!) -> #REF! | G10: =SUMIF(#REF!,BASE_CONCILI12[[#This Row],[CÓD. SAIB]],#REF!) -> #REF! | H10: =BASE_CONCILI12[[#This Row],[CONSUMO REAL]]-BASE_CONCILI12[[#This Row],[CONSUMO TEORICO]] -> #REF! | I10: =SUMIF(#REF!,BASE_CONCILI12[[#This Row],[CÓD. SAIB]],#REF!) -> #REF! | J10: =SUMIF(#REF!,BASE_CONCILI12[[#This Row],[CÓD. SAIB]],#REF!) -> #REF! | K10: =BASE_CONCILI12[[#This Row],[30/mai]]+BASE_CONCILI12[[#This Row],[RECEBIMENTO]]-BASE_CONCILI12[[#This Row],[TRANSFERÊNCIA]]-BASE_CONCILI12[[#This Row],[CONSUMO REAL]] -> #N/A | L10: =IFERROR(VLOOKUP(BASE_CONCILI12[[#This Row],[CÓD. SAIB]],BASE_CONTAG[[LAVRE]:[CONTAGEM FINAL]],7,0),0) -> 11 | M10: =IFERROR(SUM(BASE_CONCILI12[[#This Row],[30/jun]]*BASE_CONCILI12[[#This Row],[CUSTO MP (UN)]]),0) -> 0 | N10: =IFERROR(VLOOKUP(BASE_CONCILI12[[#This Row],[CÓD. SAIB]],BASE_CONTAG[],5,0),"") -> 11 | O10: =SUMIF(SISTEMA!#REF!,BASE_CONCILI12[[#This Row],[CÓD. SAIB]],SISTEMA!#REF!) -> #REF! | P10: =IFERROR(SUM(BASE_CONCILI12[[#This Row],[SISTEMA]]*BASE_CONCILI12[[#This Row],[CUSTO MP (UN)]]),0) -> 0 | Q10: =IFERROR(VLOOKUP(BASE_CONCILI12[[#This Row],[CÓD. SAIB]],BASE_DIFERENÇA[],4,0),"0") -> 0 | R10: =BASE_CONCILI12[[#This Row],[30/jun]]-BASE_CONCILI12[[#This Row],[SISTEMA]] -> #REF! | S10: =IFERROR(BASE_CONCILI12[[#This Row],[DIFERENÇA ANTERIOR]]-BASE_CONCILI12[[#This Row],[DIFERENÇA ATUAL]],"-") -> - | T10: =VLOOKUP(BASE_CONCILI12[[#This Row],[CÓD. SAIB]],CUSTO!#REF!,3,0) -> #REF! | U10: =IFERROR(SUM(BASE_CONCILI12[[#This Row],[DIFERENÇA ATUAL]]*BASE_CONCILI12[[#This Row],[CUSTO MP (UN)]]),0) -> 0 | V10: =IFERROR(BASE_CONCILI12[[#This Row],[30/jun]]/BASE_CONCILI12[[#This Row],[SISTEMA]],"") | W10: =IFERROR(BASE_CONCILI12[[#This Row],[DIFERENÇA MÊS]]*BASE_CONCILI12[[#This Row],[CUSTO MP (UN)]],"-") -> - | X10: OK
A11: 31354 | C11: AROMA BLUEBERRY | D11: AROMA | E11: =VLOOKUP(BASE_CONCILI12[[#This Row],[CÓD. SAIB]],CONT_ANTE!A:D,4,0) -> #N/A | F11: =SUMIF(#REF!,BASE_CONCILI12[[#This Row],[CÓD. SAIB]],#REF!) -> #REF! | G11: =SUMIF(#REF!,BASE_CONCILI12[[#This Row],[CÓD. SAIB]],#REF!) -> #REF! | H11: =BASE_CONCILI12[[#This Row],[CONSUMO REAL]]-BASE_CONCILI12[[#This Row],[CONSUMO TEORICO]] -> #REF! | I11: =SUMIF(#REF!,BASE_CONCILI12[[#This Row],[CÓD. SAIB]],#REF!) -> #REF! | J11: =SUMIF(#REF!,BASE_CONCILI12[[#This Row],[CÓD. SAIB]],#REF!) -> #REF! | K11: =BASE_CONCILI12[[#This Row],[30/mai]]+BASE_CONCILI12[[#This Row],[RECEBIMENTO]]-BASE_CONCILI12[[#This Row],[TRANSFERÊNCIA]]-BASE_CONCILI12[[#This Row],[CONSUMO REAL]] -> #N/A | L11: =IFERROR(VLOOKUP(BASE_CONCILI12[[#This Row],[CÓD. SAIB]],BASE_CONTAG[[LAVRE]:[CONTAGEM FINAL]],7,0),0) -> 0 | M11: =IFERROR(SUM(BASE_CONCILI12[[#This Row],[30/jun]]*BASE_CONCILI12[[#This Row],[CUSTO MP (UN)]]),0) -> 0 | N11: =IFERROR(VLOOKUP(BASE_CONCILI12[[#This Row],[CÓD. SAIB]],BASE_CONTAG[],5,0),"") -> 0 | O11: =SUMIF(SISTEMA!#REF!,BASE_CONCILI12[[#This Row],[CÓD. SAIB]],SISTEMA!#REF!) -> #REF! | P11: =IFERROR(SUM(BASE_CONCILI12[[#This Row],[SISTEMA]]*BASE_CONCILI12[[#This Row],[CUSTO MP (UN)]]),0) -> 0 | Q11: =IFERROR(VLOOKUP(BASE_CONCILI12[[#This Row],[CÓD. SAIB]],BASE_DIFERENÇA[],4,0),"0") -> 0 | R11: =BASE_CONCILI12[[#This Row],[30/jun]]-BASE_CONCILI12[[#This Row],[SISTEMA]] -> #REF! | S11: =IFERROR(BASE_CONCILI12[[#This Row],[DIFERENÇA ANTERIOR]]-BASE_CONCILI12[[#This Row],[DIFERENÇA ATUAL]],"-") -> - | T11: =VLOOKUP(BASE_CONCILI12[[#This Row],[CÓD. SAIB]],CUSTO!#REF!,3,0) -> #REF! | U11: =IFERROR(SUM(BASE_CONCILI12[[#This Row],[DIFERENÇA ATUAL]]*BASE_CONCILI12[[#This Row],[CUSTO MP (UN)]]),0) -> 0 | V11: =IFERROR(BASE_CONCILI12[[#This Row],[30/jun]]/BASE_CONCILI12[[#This Row],[SISTEMA]],"") | W11: =IFERROR(BASE_CONCILI12[[#This Row],[DIFERENÇA MÊS]]*BASE_CONCILI12[[#This Row],[CUSTO MP (UN)]],"-") -> - | X11: OK
A12: 1820 | C12: AROMA DE LARANJA IDENTICO AO NATURAL | D12: AROMA | E12: =VLOOKUP(BASE_CONCILI12[[#This Row],[CÓD. SAIB]],CONT_ANTE!A:D,4,0) -> #N/A | F12: =SUMIF(#REF!,BASE_CONCILI12[[#This Row],[CÓD. SAIB]],#REF!) -> #REF! | G12: =SUMIF(#REF!,BASE_CONCILI12[[#This Row],[CÓD. SAIB]],#REF!) -> #REF! | H12: =BASE_CONCILI12[[#This Row],[CONSUMO REAL]]-BASE_CONCILI12[[#This Row],[CONSUMO TEORICO]] -> #REF! | I12: =SUMIF(#REF!,BASE_CONCILI12[[#This Row],[CÓD. SAIB]],#REF!) -> #REF! | J12: =SUMIF(#REF!,BASE_CONCILI12[[#This Row],[CÓD. SAIB]],#REF!) -> #REF! | K12: =BASE_CONCILI12[[#This Row],[30/mai]]+BASE_CONCILI12[[#This Row],[RECEBIMENTO]]-BASE_CONCILI12[[#This Row],[TRANSFERÊNCIA]]-BASE_CONCILI12[[#This Row],[CONSUMO REAL]] -> #N/A | L12: =IFERROR(VLOOKUP(BASE_CONCILI12[[#This Row],[CÓD. SAIB]],BASE_CONTAG[[LAVRE]:[CONTAGEM FINAL]],7,0),0) -> 12 | M12: =IFERROR(SUM(BASE_CONCILI12[[#This Row],[30/jun]]*BASE_CONCILI12[[#This Row],[CUSTO MP (UN)]]),0) -> 0 | N12: =IFERROR(VLOOKUP(BASE_CONCILI12[[#This Row],[CÓD. SAIB]],BASE_CONTAG[],5,0),"") -> 12 | O12: =SUMIF(SISTEMA!#REF!,BASE_CONCILI12[[#This Row],[CÓD. SAIB]],SISTEMA!#REF!) -> #REF! | P12: =IFERROR(SUM(BASE_CONCILI12[[#This Row],[SISTEMA]]*BASE_CONCILI12[[#This Row],[CUSTO MP (UN)]]),0) -> 0 | Q12: =IFERROR(VLOOKUP(BASE_CONCILI12[[#This Row],[CÓD. SAIB]],BASE_DIFERENÇA[],4,0),"0") -> 0 | R12: =BASE_CONCILI12[[#This Row],[30/jun]]-BASE_CONCILI12[[#This Row],[SISTEMA]] -> #REF! | S12: =IFERROR(BASE_CONCILI12[[#This Row],[DIFERENÇA ANTERIOR]]-BASE_CONCILI12[[#This Row],[DIFERENÇA ATUAL]],"-") -> - | T12: =VLOOKUP(BASE_CONCILI12[[#This Row],[CÓD. SAIB]],CUSTO!#REF!,3,0) -> #REF! | U12: =IFERROR(SUM(BASE_CONCILI12[[#This Row],[DIFERENÇA ATUAL]]*BASE_CONCILI12[[#This Row],[CUSTO MP (UN)]]),0) -> 0 | V12: =IFERROR(BASE_CONCILI12[[#This Row],[30/jun]]/BASE_CONCILI12[[#This Row],[SISTEMA]],"") | W12: =IFERROR(BASE_CONCILI12[[#This Row],[DIFERENÇA MÊS]]*BASE_CONCILI12[[#This Row],[CUSTO MP (UN)]],"-") -> - | X12: OK
A13: 31312 | C13: AROMA DE LIMAO VERDE | D13: AROMA | E13: =VLOOKUP(BASE_CONCILI12[[#This Row],[CÓD. SAIB]],CONT_ANTE!A:D,4,0) -> #N/A | F13: =SUMIF(#REF!,BASE_CONCILI12[[#This Row],[CÓD. SAIB]],#REF!) -> #REF! | G13: =SUMIF(#REF!,BASE_CONCILI12[[#This Row],[CÓD. SAIB]],#REF!) -> #REF! | H13: =BASE_CONCILI12[[#This Row],[CONSUMO REAL]]-BASE_CONCILI12[[#This Row],[CONSUMO TEORICO]] -> #REF! | I13: =SUMIF(#REF!,BASE_CONCILI12[[#This Row],[CÓD. SAIB]],#REF!) -> #REF! | J13: =SUMIF(#REF!,BASE_CONCILI12[[#This Row],[CÓD. SAIB]],#REF!) -> #REF! | K13: =BASE_CONCILI12[[#This Row],[30/mai]]+BASE_CONCILI12[[#This Row],[RECEBIMENTO]]-BASE_CONCILI12[[#This Row],[TRANSFERÊNCIA]]-BASE_CONCILI12[[#This Row],[CONSUMO REAL]] -> #N/A | L13: =IFERROR(VLOOKUP(BASE_CONCILI12[[#This Row],[CÓD. SAIB]],BASE_CONTAG[[LAVRE]:[CONTAGEM FINAL]],7,0),0) -> 0 | M13: =IFERROR(SUM(BASE_CONCILI12[[#This Row],[30/jun]]*BASE_CONCILI12[[#This Row],[CUSTO MP (UN)]]),0) -> 0 | N13: =IFERROR(VLOOKUP(BASE_CONCILI12[[#This Row],[CÓD. SAIB]],BASE_CONTAG[],5,0),"") -> 0 | O13: =SUMIF(SISTEMA!#REF!,BASE_CONCILI12[[#This Row],[CÓD. SAIB]],SISTEMA!#REF!) -> #REF! | P13: =IFERROR(SUM(BASE_CONCILI12[[#This Row],[SISTEMA]]*BASE_CONCILI12[[#This Row],[CUSTO MP (UN)]]),0) -> 0 | Q13: =IFERROR(VLOOKUP(BASE_CONCILI12[[#This Row],[CÓD. SAIB]],BASE_DIFERENÇA[],4,0),"0") -> 0 | R13: =BASE_CONCILI12[[#This Row],[30/jun]]-BASE_CONCILI12[[#This Row],[SISTEMA]] -> #REF! | S13: =IFERROR(BASE_CONCILI12[[#This Row],[DIFERENÇA ANTERIOR]]-BASE_CONCILI12[[#This Row],[DIFERENÇA ATUAL]],"-") -> - | T13: =VLOOKUP(BASE_CONCILI12[[#This Row],[CÓD. SAIB]],CUSTO!#REF!,3,0) -> #REF! | U13: =IFERROR(SUM(BASE_CONCILI12[[#This Row],[DIFERENÇA ATUAL]]*BASE_CONCILI12[[#This Row],[CUSTO MP (UN)]]),0) -> 0 | V13: =IFERROR(BASE_CONCILI12[[#This Row],[30/jun]]/BASE_CONCILI12[[#This Row],[SISTEMA]],"") | W13: =IFERROR(BASE_CONCILI12[[#This Row],[DIFERENÇA MÊS]]*BASE_CONCILI12[[#This Row],[CUSTO MP (UN)]],"-") -> - | X13: OK, AJUSTAR EM OP
A14: 31335 | C14: AROMA FRUTAS TROPICAIS | D14: AROMA | E14: =VLOOKUP(BASE_CONCILI12[[#This Row],[CÓD. SAIB]],CONT_ANTE!A:D,4,0) -> #N/A | F14: =SUMIF(#REF!,BASE_CONCILI12[[#This Row],[CÓD. SAIB]],#REF!) -> #REF! | G14: =SUMIF(#REF!,BASE_CONCILI12[[#This Row],[CÓD. SAIB]],#REF!) -> #REF! | H14: =BASE_CONCILI12[[#This Row],[CONSUMO REAL]]-BASE_CONCILI12[[#This Row],[CONSUMO TEORICO]] -> #REF! | I14: =SUMIF(#REF!,BASE_CONCILI12[[#This Row],[CÓD. SAIB]],#REF!) -> #REF! | J14: =SUMIF(#REF!,BASE_CONCILI12[[#This Row],[CÓD. SAIB]],#REF!) -> #REF! | K14: =BASE_CONCILI12[[#This Row],[30/mai]]+BASE_CONCILI12[[#This Row],[RECEBIMENTO]]-BASE_CONCILI12[[#This Row],[TRANSFERÊNCIA]]-BASE_CONCILI12[[#This Row],[CONSUMO REAL]] -> #N/A | L14: =IFERROR(VLOOKUP(BASE_CONCILI12[[#This Row],[CÓD. SAIB]],BASE_CONTAG[[LAVRE]:[CONTAGEM FINAL]],7,0),0) -> 0 | M14: =IFERROR(SUM(BASE_CONCILI12[[#This Row],[30/jun]]*BASE_CONCILI12[[#This Row],[CUSTO MP (UN)]]),0) -> 0 | N14: =IFERROR(VLOOKUP(BASE_CONCILI12[[#This Row],[CÓD. SAIB]],BASE_CONTAG[],5,0),"") -> 0 | O14: =SUMIF(SISTEMA!#REF!,BASE_CONCILI12[[#This Row],[CÓD. SAIB]],SISTEMA!#REF!) -> #REF! | P14: =IFERROR(SUM(BASE_CONCILI12[[#This Row],[SISTEMA]]*BASE_CONCILI12[[#This Row],[CUSTO MP (UN)]]),0) -> 0 | Q14: =IFERROR(VLOOKUP(BASE_CONCILI12[[#This Row],[CÓD. SAIB]],BASE_DIFERENÇA[],4,0),"0") -> 0 | R14: =BASE_CONCILI12[[#This Row],[30/jun]]-BASE_CONCILI12[[#This Row],[SISTEMA]] -> #REF! | S14: =IFERROR(BASE_CONCILI12[[#This Row],[DIFERENÇA ANTERIOR]]-BASE_CONCILI12[[#This Row],[DIFERENÇA ATUAL]],"-") -> - | T14: =VLOOKUP(BASE_CONCILI12[[#This Row],[CÓD. SAIB]],CUSTO!#REF!,3,0) -> #REF! | U14: =IFERROR(SUM(BASE_CONCILI12[[#This Row],[DIFERENÇA ATUAL]]*BASE_CONCILI12[[#This Row],[CUSTO MP (UN)]]),0) -> 0 | V14: =IFERROR(BASE_CONCILI12[[#This Row],[30/jun]]/BASE_CONCILI12[[#This Row],[SISTEMA]],"") | W14: =IFERROR(BASE_CONCILI12[[#This Row],[DIFERENÇA MÊS]]*BASE_CONCILI12[[#This Row],[CUSTO MP (UN)]],"-") -> - | X14: OK
A15: 31348 | C15: AROMA ID. AO NATURAL MARACUJA | D15: AROMA | E15: =VLOOKUP(BASE_CONCILI12[[#This Row],[CÓD. SAIB]],CONT_ANTE!A:D,4,0) -> #N/A | F15: =SUMIF(#REF!,BASE_CONCILI12[[#This Row],[CÓD. SAIB]],#REF!) -> #REF! | G15: =SUMIF(#REF!,BASE_CONCILI12[[#This Row],[CÓD. SAIB]],#REF!) -> #REF! | H15: =BASE_CONCILI12[[#This Row],[CONSUMO REAL]]-BASE_CONCILI12[[#This Row],[CONSUMO TEORICO]] -> #REF! | I15: =SUMIF(#REF!,BASE_CONCILI12[[#This Row],[CÓD. SAIB]],#REF!) -> #REF! | J15: =SUMIF(#REF!,BASE_CONCILI12[[#This Row],[CÓD. SAIB]],#REF!) -> #REF! | K15: =BASE_CONCILI12[[#This Row],[30/mai]]+BASE_CONCILI12[[#This Row],[RECEBIMENTO]]-BASE_CONCILI12[[#This Row],[TRANSFERÊNCIA]]-BASE_CONCILI12[[#This Row],[CONSUMO REAL]] -> #N/A | L15: =IFERROR(VLOOKUP(BASE_CONCILI12[[#This Row],[CÓD. SAIB]],BASE_CONTAG[[LAVRE]:[CONTAGEM FINAL]],7,0),0) -> 130 | M15: =IFERROR(SUM(BASE_CONCILI12[[#This Row],[30/jun]]*BASE_CONCILI12[[#This Row],[CUSTO MP (UN)]]),0) -> 0 | N15: =IFERROR(VLOOKUP(BASE_CONCILI12[[#This Row],[CÓD. SAIB]],BASE_CONTAG[],5,0),"") -> 130 | O15: =SUMIF(SISTEMA!#REF!,BASE_CONCILI12[[#This Row],[CÓD. SAIB]],SISTEMA!#REF!) -> #REF! | P15: =IFERROR(SUM(BASE_CONCILI12[[#This Row],[SISTEMA]]*BASE_CONCILI12[[#This Row],[CUSTO MP (UN)]]),0) -> 0 | Q15: =IFERROR(VLOOKUP(BASE_CONCILI12[[#This Row],[CÓD. SAIB]],BASE_DIFERENÇA[],4,0),"0") -> 0 | R15: =BASE_CONCILI12[[#This Row],[30/jun]]-BASE_CONCILI12[[#This Row],[SISTEMA]] -> #REF! | S15: =IFERROR(BASE_CONCILI12[[#This Row],[DIFERENÇA ANTERIOR]]-BASE_CONCILI12[[#This Row],[DIFERENÇA ATUAL]],"-") -> - | T15: =VLOOKUP(BASE_CONCILI12[[#This Row],[CÓD. SAIB]],CUSTO!#REF!,3,0) -> #REF! | U15: =IFERROR(SUM(BASE_CONCILI12[[#This Row],[DIFERENÇA ATUAL]]*BASE_CONCILI12[[#This Row],[CUSTO MP (UN)]]),0) -> 0 | V15: =IFERROR(BASE_CONCILI12[[#This Row],[30/jun]]/BASE_CONCILI12[[#This Row],[SISTEMA]],"") | W15: =IFERROR(BASE_CONCILI12[[#This Row],[DIFERENÇA MÊS]]*BASE_CONCILI12[[#This Row],[CUSTO MP (UN)]],"-") -> - | X15: OK
A16: 31349 | C16: AROMA ID. AO NATURAL MELANCIA | D16: AROMA | E16: =VLOOKUP(BASE_CONCILI12[[#This Row],[CÓD. SAIB]],CONT_ANTE!A:D,4,0) -> #N/A | F16: =SUMIF(#REF!,BASE_CONCILI12[[#This Row],[CÓD. SAIB]],#REF!) -> #REF! | G16: =SUMIF(#REF!,BASE_CONCILI12[[#This Row],[CÓD. SAIB]],#REF!) -> #REF! | H16: =BASE_CONCILI12[[#This Row],[CONSUMO REAL]]-BASE_CONCILI12[[#This Row],[CONSUMO TEORICO]] -> #REF! | I16: =SUMIF(#REF!,BASE_CONCILI12[[#This Row],[CÓD. SAIB]],#REF!) -> #REF! | J16: =SUMIF(#REF!,BASE_CONCILI12[[#This Row],[CÓD. SAIB]],#REF!) -> #REF! | K16: =BASE_CONCILI12[[#This Row],[30/mai]]+BASE_CONCILI12[[#This Row],[RECEBIMENTO]]-BASE_CONCILI12[[#This Row],[TRANSFERÊNCIA]]-BASE_CONCILI12[[#This Row],[CONSUMO REAL]] -> #N/A | L16: =IFERROR(VLOOKUP(BASE_CONCILI12[[#This Row],[CÓD. SAIB]],BASE_CONTAG[[LAVRE]:[CONTAGEM FINAL]],7,0),0) -> 142.5 | M16: =IFERROR(SUM(BASE_CONCILI12[[#This Row],[30/jun]]*BASE_CONCILI12[[#This Row],[CUSTO MP (UN)]]),0) -> 0 | N16: =IFERROR(VLOOKUP(BASE_CONCILI12[[#This Row],[CÓD. SAIB]],BASE_CONTAG[],5,0),"") -> 142.5 | O16: =SUMIF(SISTEMA!#REF!,BASE_CONCILI12[[#This Row],[CÓD. SAIB]],SISTEMA!#REF!) -> #REF! | P16: =IFERROR(SUM(BASE_CONCILI12[[#This Row],[SISTEMA]]*BASE_CONCILI12[[#This Row],[CUSTO MP (UN)]]),0) -> 0 | Q16: =IFERROR(VLOOKUP(BASE_CONCILI12[[#This Row],[CÓD. SAIB]],BASE_DIFERENÇA[],4,0),"0") -> 0 | R16: =BASE_CONCILI12[[#This Row],[30/jun]]-BASE_CONCILI12[[#This Row],[SISTEMA]] -> #REF! | S16: =IFERROR(BASE_CONCILI12[[#This Row],[DIFERENÇA ANTERIOR]]-BASE_CONCILI12[[#This Row],[DIFERENÇA ATUAL]],"-") -> - | T16: =VLOOKUP(BASE_CONCILI12[[#This Row],[CÓD. SAIB]],CUSTO!#REF!,3,0) -> #REF! | U16: =IFERROR(SUM(BASE_CONCILI12[[#This Row],[DIFERENÇA ATUAL]]*BASE_CONCILI12[[#This Row],[CUSTO MP (UN)]]),0) -> 0 | V16: =IFERROR(BASE_CONCILI12[[#This Row],[30/jun]]/BASE_CONCILI12[[#This Row],[SISTEMA]],"") | W16: =IFERROR(BASE_CONCILI12[[#This Row],[DIFERENÇA MÊS]]*BASE_CONCILI12[[#This Row],[CUSTO MP (UN)]],"-") -> - | X16: OK
... A28: 1124 | C28: CHAPA SEM IMPRESSAO | D28: CAIXA | E28: =VLOOKUP(BASE_CONCILI12[[#This Row],[CÓD. SAIB]],CONT_ANTE!A:D,4,0) -> #N/A | F28: =SUMIF(#REF!,BASE_CONCILI12[[#This Row],[CÓD. SAIB]],#REF!) -> #REF! | G28: =SUMIF(#REF!,BASE_CONCILI12[[#This Row],[CÓD. SAIB]],#REF!) -> #REF! | H28: =BASE_CONCILI12[[#This Row],[CONSUMO REAL]]-BASE_CONCILI12[[#This Row],[CONSUMO TEORICO]] -> #REF! | I28: =SUMIF(#REF!,BASE_CONCILI12[[#This Row],[CÓD. SAIB]],#REF!) -> #REF! | J28: =SUMIF(#REF!,BASE_CONCILI12[[#This Row],[CÓD. SAIB]],#REF!) -> #REF! | K28: =BASE_CONCILI12[[#This Row],[30/mai]]+BASE_CONCILI12[[#This Row],[RECEBIMENTO]]-BASE_CONCILI12[[#This Row],[TRANSFERÊNCIA]]-BASE_CONCILI12[[#This Row],[CONSUMO REAL]] -> #N/A | L28: =IFERROR(VLOOKUP(BASE_CONCILI12[[#This Row],[CÓD. SAIB]],BASE_CONTAG[[LAVRE]:[CONTAGEM FINAL]],7,0),0) -> 4960 | M28: =IFERROR(SUM(BASE_CONCILI12[[#This Row],[30/jun]]*BASE_CONCILI12[[#This Row],[CUSTO MP (UN)]]),0) -> 0 | N28: =IFERROR(VLOOKUP(BASE_CONCILI12[[#This Row],[CÓD. SAIB]],BASE_CONTAG[],5,0),"") -> 4960 | O28: =SUMIF(SISTEMA!#REF!,BASE_CONCILI12[[#This Row],[CÓD. SAIB]],SISTEMA!#REF!) -> #REF! | P28: =IFERROR(SUM(BASE_CONCILI12[[#This Row],[SISTEMA]]*BASE_CONCILI12[[#This Row],[CUSTO MP (UN)]]),0) -> 0 | Q28: =IFERROR(VLOOKUP(BASE_CONCILI12[[#This Row],[CÓD. SAIB]],BASE_DIFERENÇA[],4,0),"0") -> 0 | R28: =BASE_CONCILI12[[#This Row],[30/jun]]-BASE_CONCILI12[[#This Row],[SISTEMA]] -> #REF! | S28: =IFERROR(BASE_CONCILI12[[#This Row],[DIFERENÇA ANTERIOR]]-BASE_CONCILI12[[#This Row],[DIFERENÇA ATUAL]],"-") -> - | T28: =VLOOKUP(BASE_CONCILI12[[#This Row],[CÓD. SAIB]],CUSTO!#REF!,3,0) -> #REF! | U28: =IFERROR(SUM(BASE_CONCILI12[[#This Row],[DIFERENÇA ATUAL]]*BASE_CONCILI12[[#This Row],[CUSTO MP (UN)]]),0) -> 0 | V28: =IFERROR(BASE_CONCILI12[[#This Row],[30/jun]]/BASE_CONCILI12[[#This Row],[SISTEMA]],"") | W28: =IFERROR(BASE_CONCILI12[[#This Row],[DIFERENÇA MÊS]]*BASE_CONCILI12[[#This Row],[CUSTO MP (UN)]],"-") -> - | X28: CORREÇÃO DE APONTAMENTO - ACUMULO PERDA
A29: 32711 | C29: CX AUTO GIN JAMES COOK 6X1-IND | D29: CAIXA | E29: =VLOOKUP(BASE_CONCILI12[[#This Row],[CÓD. SAIB]],CONT_ANTE!A:D,4,0) -> #N/A | F29: =SUMIF(#REF!,BASE_CONCILI12[[#This Row],[CÓD. SAIB]],#REF!) -> #REF! | G29: =SUMIF(#REF!,BASE_CONCILI12[[#This Row],[CÓD. SAIB]],#REF!) -> #REF! | H29: =BASE_CONCILI12[[#This Row],[CONSUMO REAL]]-BASE_CONCILI12[[#This Row],[CONSUMO TEORICO]] -> #REF! | I29: =SUMIF(#REF!,BASE_CONCILI12[[#This Row],[CÓD. SAIB]],#REF!) -> #REF! | J29: =SUMIF(#REF!,BASE_CONCILI12[[#This Row],[CÓD. SAIB]],#REF!) -> #REF! | K29: =BASE_CONCILI12[[#This Row],[30/mai]]+BASE_CONCILI12[[#This Row],[RECEBIMENTO]]-BASE_CONCILI12[[#This Row],[TRANSFERÊNCIA]]-BASE_CONCILI12[[#This Row],[CONSUMO REAL]] -> #N/A | L29: =IFERROR(VLOOKUP(BASE_CONCILI12[[#This Row],[CÓD. SAIB]],BASE_CONTAG[[LAVRE]:[CONTAGEM FINAL]],7,0),0) -> 4400 | M29: =IFERROR(SUM(BASE_CONCILI12[[#This Row],[30/jun]]*BASE_CONCILI12[[#This Row],[CUSTO MP (UN)]]),0) -> 16365.479 | N29: =IFERROR(VLOOKUP(BASE_CONCILI12[[#This Row],[CÓD. SAIB]],BASE_CONTAG[],5,0),"") -> 4400 | O29: =SUMIF(SISTEMA!#REF!,BASE_CONCILI12[[#This Row],[CÓD. SAIB]],SISTEMA!#REF!) -> #REF! | P29: =IFERROR(SUM(BASE_CONCILI12[[#This Row],[SISTEMA]]*BASE_CONCILI12[[#This Row],[CUSTO MP (UN)]]),0) -> 0 | Q29: =IFERROR(VLOOKUP(BASE_CONCILI12[[#This Row],[CÓD. SAIB]],BASE_DIFERENÇA[],4,0),"0") -> 0 | R29: =BASE_CONCILI12[[#This Row],[30/jun]]-BASE_CONCILI12[[#This Row],[SISTEMA]] -> #REF! | S29: =IFERROR(BASE_CONCILI12[[#This Row],[DIFERENÇA ANTERIOR]]-BASE_CONCILI12[[#This Row],[DIFERENÇA ATUAL]],"-") -> - | T29: 3.719427 | U29: =IFERROR(SUM(BASE_CONCILI12[[#This Row],[DIFERENÇA ATUAL]]*BASE_CONCILI12[[#This Row],[CUSTO MP (UN)]]),0) -> 0 | V29: =IFERROR(BASE_CONCILI12[[#This Row],[30/jun]]/BASE_CONCILI12[[#This Row],[SISTEMA]],"") | W29: =IFERROR(BASE_CONCILI12[[#This Row],[DIFERENÇA MÊS]]*BASE_CONCILI12[[#This Row],[CUSTO MP (UN)]],"-") -> - | X29: OK
A30: 32714 | C30: CX FUNDO AUTO VODKA JAMES COOK 6X1-IND | D30: CAIXA | E30: =VLOOKUP(BASE_CONCILI12[[#This Row],[CÓD. SAIB]],CONT_ANTE!A:D,4,0) -> #N/A | F30: =SUMIF(#REF!,BASE_CONCILI12[[#This Row],[CÓD. SAIB]],#REF!) -> #REF! | G30: =SUMIF(#REF!,BASE_CONCILI12[[#This Row],[CÓD. SAIB]],#REF!) -> #REF! | H30: =BASE_CONCILI12[[#This Row],[CONSUMO REAL]]-BASE_CONCILI12[[#This Row],[CONSUMO TEORICO]] -> #REF! | I30: =SUMIF(#REF!,BASE_CONCILI12[[#This Row],[CÓD. SAIB]],#REF!) -> #REF! | J30: =SUMIF(#REF!,BASE_CONCILI12[[#This Row],[CÓD. SAIB]],#REF!) -> #REF! | K30: =BASE_CONCILI12[[#This Row],[30/mai]]+BASE_CONCILI12[[#This Row],[RECEBIMENTO]]-BASE_CONCILI12[[#This Row],[TRANSFERÊNCIA]]-BASE_CONCILI12[[#This Row],[CONSUMO REAL]] -> #N/A | L30: =IFERROR(VLOOKUP(BASE_CONCILI12[[#This Row],[CÓD. SAIB]],BASE_CONTAG[[LAVRE]:[CONTAGEM FINAL]],7,0),0) -> 16640 | M30: =IFERROR(SUM(BASE_CONCILI12[[#This Row],[30/jun]]*BASE_CONCILI12[[#This Row],[CUSTO MP (UN)]]),0) -> 61891.265 | N30: =IFERROR(VLOOKUP(BASE_CONCILI12[[#This Row],[CÓD. SAIB]],BASE_CONTAG[],5,0),"") -> 16640 | O30: =SUMIF(SISTEMA!#REF!,BASE_CONCILI12[[#This Row],[CÓD. SAIB]],SISTEMA!#REF!) -> #REF! | P30: =IFERROR(SUM(BASE_CONCILI12[[#This Row],[SISTEMA]]*BASE_CONCILI12[[#This Row],[CUSTO MP (UN)]]),0) -> 0 | Q30: =IFERROR(VLOOKUP(BASE_CONCILI12[[#This Row],[CÓD. SAIB]],BASE_DIFERENÇA[],4,0),"0") -> 0 | R30: =BASE_CONCILI12[[#This Row],[30/jun]]-BASE_CONCILI12[[#This Row],[SISTEMA]] -> #REF! | S30: =IFERROR(BASE_CONCILI12[[#This Row],[DIFERENÇA ANTERIOR]]-BASE_CONCILI12[[#This Row],[DIFERENÇA ATUAL]],"-") -> - | T30: 3.719427 | U30: =IFERROR(SUM(BASE_CONCILI12[[#This Row],[DIFERENÇA ATUAL]]*BASE_CONCILI12[[#This Row],[CUSTO MP (UN)]]),0) -> 0 | V30: =IFERROR(BASE_CONCILI12[[#This Row],[30/jun]]/BASE_CONCILI12[[#This Row],[SISTEMA]],"") | W30: =IFERROR(BASE_CONCILI12[[#This Row],[DIFERENÇA MÊS]]*BASE_CONCILI12[[#This Row],[CUSTO MP (UN)]],"-") -> - | X30: OK
A31: 30756 | C31: CX ONE WAY BAMBOA 12X300ML | D31: CAIXA | E31: =VLOOKUP(BASE_CONCILI12[[#This Row],[CÓD. SAIB]],CONT_ANTE!A:D,4,0) -> #N/A | F31: =SUMIF(#REF!,BASE_CONCILI12[[#This Row],[CÓD. SAIB]],#REF!) -> #REF! | G31: =SUMIF(#REF!,BASE_CONCILI12[[#This Row],[CÓD. SAIB]],#REF!) -> #REF! | H31: =BASE_CONCILI12[[#This Row],[CONSUMO REAL]]-BASE_CONCILI12[[#This Row],[CONSUMO TEORICO]] -> #REF! | I31: =SUMIF(#REF!,BASE_CONCILI12[[#This Row],[CÓD. SAIB]],#REF!) -> #REF! | J31: =SUMIF(#REF!,BASE_CONCILI12[[#This Row],[CÓD. SAIB]],#REF!) -> #REF! | K31: =BASE_CONCILI12[[#This Row],[30/mai]]+BASE_CONCILI12[[#This Row],[RECEBIMENTO]]-BASE_CONCILI12[[#This Row],[TRANSFERÊNCIA]]-BASE_CONCILI12[[#This Row],[CONSUMO REAL]] -> #N/A | L31: =IFERROR(VLOOKUP(BASE_CONCILI12[[#This Row],[CÓD. SAIB]],BASE_CONTAG[[LAVRE]:[CONTAGEM FINAL]],7,0),0) -> 177 | M31: =IFERROR(SUM(BASE_CONCILI12[[#This Row],[30/jun]]*BASE_CONCILI12[[#This Row],[CUSTO MP (UN)]]),0) -> 0 | N31: =IFERROR(VLOOKUP(BASE_CONCILI12[[#This Row],[CÓD. SAIB]],BASE_CONTAG[],5,0),"") -> 177 | O31: =SUMIF(SISTEMA!#REF!,BASE_CONCILI12[[#This Row],[CÓD. SAIB]],SISTEMA!#REF!) -> #REF! | P31: =IFERROR(SUM(BASE_CONCILI12[[#This Row],[SISTEMA]]*BASE_CONCILI12[[#This Row],[CUSTO MP (UN)]]),0) -> 0 | Q31: =IFERROR(VLOOKUP(BASE_CONCILI12[[#This Row],[CÓD. SAIB]],BASE_DIFERENÇA[],4,0),"0") -> 0 | R31: =BASE_CONCILI12[[#This Row],[30/jun]]-BASE_CONCILI12[[#This Row],[SISTEMA]] -> #REF! | S31: =IFERROR(BASE_CONCILI12[[#This Row],[DIFERENÇA ANTERIOR]]-BASE_CONCILI12[[#This Row],[DIFERENÇA ATUAL]],"-") -> - | T31: =VLOOKUP(BASE_CONCILI12[[#This Row],[CÓD. SAIB]],CUSTO!#REF!,3,0) -> #REF! | U31: =IFERROR(SUM(BASE_CONCILI12[[#This Row],[DIFERENÇA ATUAL]]*BASE_CONCILI12[[#This Row],[CUSTO MP (UN)]]),0) -> 0 | V31: =IFERROR(BASE_CONCILI12[[#This Row],[30/jun]]/BASE_CONCILI12[[#This Row],[SISTEMA]],"") | W31: =IFERROR(BASE_CONCILI12[[#This Row],[DIFERENÇA MÊS]]*BASE_CONCILI12[[#This Row],[CUSTO MP (UN)]],"-") -> - | X31: OK
A32: 30758 | C32: CX ONE WAY BAMBOA 12X330ML | D32: CAIXA | E32: =VLOOKUP(BASE_CONCILI12[[#This Row],[CÓD. SAIB]],CONT_ANTE!A:D,4,0) -> #N/A | F32: =SUMIF(#REF!,BASE_CONCILI12[[#This Row],[CÓD. SAIB]],#REF!) -> #REF! | G32: =SUMIF(#REF!,BASE_CONCILI12[[#This Row],[CÓD. SAIB]],#REF!) -> #REF! | H32: =BASE_CONCILI12[[#This Row],[CONSUMO REAL]]-BASE_CONCILI12[[#This Row],[CONSUMO TEORICO]] -> #REF! | I32: =SUMIF(#REF!,BASE_CONCILI12[[#This Row],[CÓD. SAIB]],#REF!) -> #REF! | J32: =SUMIF(#REF!,BASE_CONCILI12[[#This Row],[CÓD. SAIB]],#REF!) -> #REF! | K32: =BASE_CONCILI12[[#This Row],[30/mai]]+BASE_CONCILI12[[#This Row],[RECEBIMENTO]]-BASE_CONCILI12[[#This Row],[TRANSFERÊNCIA]]-BASE_CONCILI12[[#This Row],[CONSUMO REAL]] -> #N/A | L32: =IFERROR(VLOOKUP(BASE_CONCILI12[[#This Row],[CÓD. SAIB]],BASE_CONTAG[[LAVRE]:[CONTAGEM FINAL]],7,0),0) -> 14.5 | M32: =IFERROR(SUM(BASE_CONCILI12[[#This Row],[30/jun]]*BASE_CONCILI12[[#This Row],[CUSTO MP (UN)]]),0) -> 0 | N32: =IFERROR(VLOOKUP(BASE_CONCILI12[[#This Row],[CÓD. SAIB]],BASE_CONTAG[],5,0),"") -> 14.5 | O32: =SUMIF(SISTEMA!#REF!,BASE_CONCILI12[[#This Row],[CÓD. SAIB]],SISTEMA!#REF!) -> #REF! | P32: =IFERROR(SUM(BASE_CONCILI12[[#This Row],[SISTEMA]]*BASE_CONCILI12[[#This Row],[CUSTO MP (UN)]]),0) -> 0 | Q32: =IFERROR(VLOOKUP(BASE_CONCILI12[[#This Row],[CÓD. SAIB]],BASE_DIFERENÇA[],4,0),"0") -> 0 | R32: =BASE_CONCILI12[[#This Row],[30/jun]]-BASE_CONCILI12[[#This Row],[SISTEMA]] -> #REF! | S32: =IFERROR(BASE_CONCILI12[[#This Row],[DIFERENÇA ANTERIOR]]-BASE_CONCILI12[[#This Row],[DIFERENÇA ATUAL]],"-") -> - | T32: =VLOOKUP(BASE_CONCILI12[[#This Row],[CÓD. SAIB]],CUSTO!#REF!,3,0) -> #REF! | U32: =IFERROR(SUM(BASE_CONCILI12[[#This Row],[DIFERENÇA ATUAL]]*BASE_CONCILI12[[#This Row],[CUSTO MP (UN)]]),0) -> 0 | V32: =IFERROR(BASE_CONCILI12[[#This Row],[30/jun]]/BASE_CONCILI12[[#This Row],[SISTEMA]],"") | W32: =IFERROR(BASE_CONCILI12[[#This Row],[DIFERENÇA MÊS]]*BASE_CONCILI12[[#This Row],[CUSTO MP (UN)]],"-") -> - | X32: OK
A33: 1444 | C33: CX ONE WAY BAMBOA 6X600ML | D33: CAIXA | E33: =VLOOKUP(BASE_CONCILI12[[#This Row],[CÓD. SAIB]],CONT_ANTE!A:D,4,0) -> #N/A | F33: =SUMIF(#REF!,BASE_CONCILI12[[#This Row],[CÓD. SAIB]],#REF!) -> #REF! | G33: =SUMIF(#REF!,BASE_CONCILI12[[#This Row],[CÓD. SAIB]],#REF!) -> #REF! | H33: =BASE_CONCILI12[[#This Row],[CONSUMO REAL]]-BASE_CONCILI12[[#This Row],[CONSUMO TEORICO]] -> #REF! | I33: =SUMIF(#REF!,BASE_CONCILI12[[#This Row],[CÓD. SAIB]],#REF!) -> #REF! | J33: =SUMIF(#REF!,BASE_CONCILI12[[#This Row],[CÓD. SAIB]],#REF!) -> #REF! | K33: =BASE_CONCILI12[[#This Row],[30/mai]]+BASE_CONCILI12[[#This Row],[RECEBIMENTO]]-BASE_CONCILI12[[#This Row],[TRANSFERÊNCIA]]-BASE_CONCILI12[[#This Row],[CONSUMO REAL]] -> #N/A | L33: =IFERROR(VLOOKUP(BASE_CONCILI12[[#This Row],[CÓD. SAIB]],BASE_CONTAG[[LAVRE]:[CONTAGEM FINAL]],7,0),0) -> 0 | M33: =IFERROR(SUM(BASE_CONCILI12[[#This Row],[30/jun]]*BASE_CONCILI12[[#This Row],[CUSTO MP (UN)]]),0) -> 0 | N33: =IFERROR(VLOOKUP(BASE_CONCILI12[[#This Row],[CÓD. SAIB]],BASE_CONTAG[],5,0),"") -> 0 | O33: =SUMIF(SISTEMA!#REF!,BASE_CONCILI12[[#This Row],[CÓD. SAIB]],SISTEMA!#REF!) -> #REF! | P33: =IFERROR(SUM(BASE_CONCILI12[[#This Row],[SISTEMA]]*BASE_CONCILI12[[#This Row],[CUSTO MP (UN)]]),0) -> 0 | Q33: =IFERROR(VLOOKUP(BASE_CONCILI12[[#This Row],[CÓD. SAIB]],BASE_DIFERENÇA[],4,0),"0") -> 0 | R33: =BASE_CONCILI12[[#This Row],[30/jun]]-BASE_CONCILI12[[#This Row],[SISTEMA]] -> #REF! | S33: =IFERROR(BASE_CONCILI12[[#This Row],[DIFERENÇA ANTERIOR]]-BASE_CONCILI12[[#This Row],[DIFERENÇA ATUAL]],"-") -> - | T33: =VLOOKUP(BASE_CONCILI12[[#This Row],[CÓD. SAIB]],CUSTO!#REF!,3,0) -> #REF! | U33: =IFERROR(SUM(BASE_CONCILI12[[#This Row],[DIFERENÇA ATUAL]]*BASE_CONCILI12[[#This Row],[CUSTO MP (UN)]]),0) -> 0 | V33: =IFERROR(BASE_CONCILI12[[#This Row],[30/jun]]/BASE_CONCILI12[[#This Row],[SISTEMA]],"") | W33: =IFERROR(BASE_CONCILI12[[#This Row],[DIFERENÇA MÊS]]*BASE_CONCILI12[[#This Row],[CUSTO MP (UN)]],"-") -> - | X33: OK
A34: 30739 | C34: CX ONE WAY MOEMA 12X300ML | D34: CAIXA | E34: =VLOOKUP(BASE_CONCILI12[[#This Row],[CÓD. SAIB]],CONT_ANTE!A:D,4,0) -> #N/A | F34: =SUMIF(#REF!,BASE_CONCILI12[[#This Row],[CÓD. SAIB]],#REF!) -> #REF! | G34: =SUMIF(#REF!,BASE_CONCILI12[[#This Row],[CÓD. SAIB]],#REF!) -> #REF! | H34: =BASE_CONCILI12[[#This Row],[CONSUMO REAL]]-BASE_CONCILI12[[#This Row],[CONSUMO TEORICO]] -> #REF! | I34: =SUMIF(#REF!,BASE_CONCILI12[[#This Row],[CÓD. SAIB]],#REF!) -> #REF! | J34: =SUMIF(#REF!,BASE_CONCILI12[[#This Row],[CÓD. SAIB]],#REF!) -> #REF! | K34: =BASE_CONCILI12[[#This Row],[30/mai]]+BASE_CONCILI12[[#This Row],[RECEBIMENTO]]-BASE_CONCILI12[[#This Row],[TRANSFERÊNCIA]]-BASE_CONCILI12[[#This Row],[CONSUMO REAL]] -> #N/A | L34: =IFERROR(VLOOKUP(BASE_CONCILI12[[#This Row],[CÓD. SAIB]],BASE_CONTAG[[LAVRE]:[CONTAGEM FINAL]],7,0),0) -> 3324 | M34: =IFERROR(SUM(BASE_CONCILI12[[#This Row],[30/jun]]*BASE_CONCILI12[[#This Row],[CUSTO MP (UN)]]),0) -> 0 | N34: =IFERROR(VLOOKUP(BASE_CONCILI12[[#This Row],[CÓD. SAIB]],BASE_CONTAG[],5,0),"") -> 2360 | O34: =SUMIF(SISTEMA!#REF!,BASE_CONCILI12[[#This Row],[CÓD. SAIB]],SISTEMA!#REF!) -> #REF! | P34: =IFERROR(SUM(BASE_CONCILI12[[#This Row],[SISTEMA]]*BASE_CONCILI12[[#This Row],[CUSTO MP (UN)]]),0) -> 0 | Q34: =IFERROR(VLOOKUP(BASE_CONCILI12[[#This Row],[CÓD. SAIB]],BASE_DIFERENÇA[],4,0),"0") -> 0 | R34: =BASE_CONCILI12[[#This Row],[30/jun]]-BASE_CONCILI12[[#This Row],[SISTEMA]] -> #REF! | S34: =IFERROR(BASE_CONCILI12[[#This Row],[DIFERENÇA ANTERIOR]]-BASE_CONCILI12[[#This Row],[DIFERENÇA ATUAL]],"-") -> - | T34: =VLOOKUP(BASE_CONCILI12[[#This Row],[CÓD. SAIB]],CUSTO!#REF!,3,0) -> #REF! | U34: =IFERROR(SUM(BASE_CONCILI12[[#This Row],[DIFERENÇA ATUAL]]*BASE_CONCILI12[[#This Row],[CUSTO MP (UN)]]),0) -> 0 | V34: =IFERROR(BASE_CONCILI12[[#This Row],[30/jun]]/BASE_CONCILI12[[#This Row],[SISTEMA]],"") | W34: =IFERROR(BASE_CONCILI12[[#This Row],[DIFERENÇA MÊS]]*BASE_CONCILI12[[#This Row],[CUSTO MP (UN)]],"-") -> - | X34: OK
A35: 30738 | C35: CX ONE WAY MOEMA 6X600ML | D35: CAIXA | E35: =VLOOKUP(BASE_CONCILI12[[#This Row],[CÓD. SAIB]],CONT_ANTE!A:D,4,0) -> #N/A | F35: =SUMIF(#REF!,BASE_CONCILI12[[#This Row],[CÓD. SAIB]],#REF!) -> #REF! | G35: =SUMIF(#REF!,BASE_CONCILI12[[#This Row],[CÓD. SAIB]],#REF!) -> #REF! | H35: =BASE_CONCILI12[[#This Row],[CONSUMO REAL]]-BASE_CONCILI12[[#This Row],[CONSUMO TEORICO]] -> #REF! | I35: =SUMIF(#REF!,BASE_CONCILI12[[#This Row],[CÓD. SAIB]],#REF!) -> #REF! | J35: =SUMIF(#REF!,BASE_CONCILI12[[#This Row],[CÓD. SAIB]],#REF!) -> #REF! | K35: =BASE_CONCILI12[[#This Row],[30/mai]]+BASE_CONCILI12[[#This Row],[RECEBIMENTO]]-BASE_CONCILI12[[#This Row],[TRANSFERÊNCIA]]-BASE_CONCILI12[[#This Row],[CONSUMO REAL]] -> #N/A | L35: =IFERROR(VLOOKUP(BASE_CONCILI12[[#This Row],[CÓD. SAIB]],BASE_CONTAG[[LAVRE]:[CONTAGEM FINAL]],7,0),0) -> 4950 | M35: =IFERROR(SUM(BASE_CONCILI12[[#This Row],[30/jun]]*BASE_CONCILI12[[#This Row],[CUSTO MP (UN)]]),0) -> 0 | N35: =IFERROR(VLOOKUP(BASE_CONCILI12[[#This Row],[CÓD. SAIB]],BASE_CONTAG[],5,0),"") -> 4950 | O35: =SUMIF(SISTEMA!#REF!,BASE_CONCILI12[[#This Row],[CÓD. SAIB]],SISTEMA!#REF!) -> #REF! | P35: =IFERROR(SUM(BASE_CONCILI12[[#This Row],[SISTEMA]]*BASE_CONCILI12[[#This Row],[CUSTO MP (UN)]]),0) -> 0 | Q35: =IFERROR(VLOOKUP(BASE_CONCILI12[[#This Row],[CÓD. SAIB]],BASE_DIFERENÇA[],4,0),"0") -> 0 | R35: =BASE_CONCILI12[[#This Row],[30/jun]]-BASE_CONCILI12[[#This Row],[SISTEMA]] -> #REF! | S35: =IFERROR(BASE_CONCILI12[[#This Row],[DIFERENÇA ANTERIOR]]-BASE_CONCILI12[[#This Row],[DIFERENÇA ATUAL]],"-") -> - | T35: =VLOOKUP(BASE_CONCILI12[[#This Row],[CÓD. SAIB]],CUSTO!#REF!,3,0) -> #REF! | U35: =IFERROR(SUM(BASE_CONCILI12[[#This Row],[DIFERENÇA ATUAL]]*BASE_CONCILI12[[#This Row],[CUSTO MP (UN)]]),0) -> 0 | V35: =IFERROR(BASE_CONCILI12[[#This Row],[30/jun]]/BASE_CONCILI12[[#This Row],[SISTEMA]],"") | W35: =IFERROR(BASE_CONCILI12[[#This Row],[DIFERENÇA MÊS]]*BASE_CONCILI12[[#This Row],[CUSTO MP (UN)]],"-") -> - | X35: CORREÇÃO DE APONTAMENTO - ACUMULO PERDA
A36: 31584 | C36: CX PAPELAO TUBAINA 12X300ML | D36: CAIXA | E36: =VLOOKUP(BASE_CONCILI12[[#This Row],[CÓD. SAIB]],CONT_ANTE!A:D,4,0) -> #N/A | F36: =SUMIF(#REF!,BASE_CONCILI12[[#This Row],[CÓD. SAIB]],#REF!) -> #REF! | G36: =SUMIF(#REF!,BASE_CONCILI12[[#This Row],[CÓD. SAIB]],#REF!) -> #REF! | H36: =BASE_CONCILI12[[#This Row],[CONSUMO REAL]]-BASE_CONCILI12[[#This Row],[CONSUMO TEORICO]] -> #REF! | I36: =SUMIF(#REF!,BASE_CONCILI12[[#This Row],[CÓD. SAIB]],#REF!) -> #REF! | J36: =SUMIF(#REF!,BASE_CONCILI12[[#This Row],[CÓD. SAIB]],#REF!) -> #REF! | K36: =BASE_CONCILI12[[#This Row],[30/mai]]+BASE_CONCILI12[[#This Row],[RECEBIMENTO]]-BASE_CONCILI12[[#This Row],[TRANSFERÊNCIA]]-BASE_CONCILI12[[#This Row],[CONSUMO REAL]] -> #N/A | L36: =IFERROR(VLOOKUP(BASE_CONCILI12[[#This Row],[CÓD. SAIB]],BASE_CONTAG[[LAVRE]:[CONTAGEM FINAL]],7,0),0) -> 32578 | M36: =IFERROR(SUM(BASE_CONCILI12[[#This Row],[30/jun]]*BASE_CONCILI12[[#This Row],[CUSTO MP (UN)]]),0) -> 0 | N36: =IFERROR(VLOOKUP(BASE_CONCILI12[[#This Row],[CÓD. SAIB]],BASE_CONTAG[],5,0),"") -> 32578 | O36: =SUMIF(SISTEMA!#REF!,BASE_CONCILI12[[#This Row],[CÓD. SAIB]],SISTEMA!#REF!) -> #REF! | P36: =IFERROR(SUM(BASE_CONCILI12[[#This Row],[SISTEMA]]*BASE_CONCILI12[[#This Row],[CUSTO MP (UN)]]),0) -> 0 | Q36: =IFERROR(VLOOKUP(BASE_CONCILI12[[#This Row],[CÓD. SAIB]],BASE_DIFERENÇA[],4,0),"0") -> 0 | R36: =BASE_CONCILI12[[#This Row],[30/jun]]-BASE_CONCILI12[[#This Row],[SISTEMA]] -> #REF! | S36: =IFERROR(BASE_CONCILI12[[#This Row],[DIFERENÇA ANTERIOR]]-BASE_CONCILI12[[#This Row],[DIFERENÇA ATUAL]],"-") -> - | T36: =VLOOKUP(BASE_CONCILI12[[#This Row],[CÓD. SAIB]],CUSTO!#REF!,3,0) -> #REF! | U36: =IFERROR(SUM(BASE_CONCILI12[[#This Row],[DIFERENÇA ATUAL]]*BASE_CONCILI12[[#This Row],[CUSTO MP (UN)]]),0) -> 0 | V36: =IFERROR(BASE_CONCILI12[[#This Row],[30/jun]]/BASE_CONCILI12[[#This Row],[SISTEMA]],"") | W36: =IFERROR(BASE_CONCILI12[[#This Row],[DIFERENÇA MÊS]]*BASE_CONCILI12[[#This Row],[CUSTO MP (UN)]],"-") -> - | X36: OK
A37: 60 | C37: CARVAO ATIVADO | D37: CARVAO | E37: =VLOOKUP(BASE_CONCILI12[[#This Row],[CÓD. SAIB]],CONT_ANTE!A:D,4,0) -> #N/A | F37: =SUMIF(#REF!,BASE_CONCILI12[[#This Row],[CÓD. SAIB]],#REF!) -> #REF! | G37: =SUMIF(#REF!,BASE_CONCILI12[[#This Row],[CÓD. SAIB]],#REF!) -> #REF! | H37: =BASE_CONCILI12[[#This Row],[CONSUMO REAL]]-BASE_CONCILI12[[#This Row],[CONSUMO TEORICO]] -> #REF! | I37: =SUMIF(#REF!,BASE_CONCILI12[[#This Row],[CÓD. SAIB]],#REF!) -> #REF! | J37: =SUMIF(#REF!,BASE_CONCILI12[[#This Row],[CÓD. SAIB]],#REF!) -> #REF! | K37: =BASE_CONCILI12[[#This Row],[30/mai]]+BASE_CONCILI12[[#This Row],[RECEBIMENTO]]-BASE_CONCILI12[[#This Row],[TRANSFERÊNCIA]]-BASE_CONCILI12[[#This Row],[CONSUMO REAL]] -> #N/A | L37: =IFERROR(VLOOKUP(BASE_CONCILI12[[#This Row],[CÓD. SAIB]],BASE_CONTAG[[LAVRE]:[CONTAGEM FINAL]],7,0),0) -> 0 | M37: =IFERROR(SUM(BASE_CONCILI12[[#This Row],[30/jun]]*BASE_CONCILI12[[#This Row],[CUSTO MP (UN)]]),0) -> 0 | N37: =IFERROR(VLOOKUP(BASE_CONCILI12[[#This Row],[CÓD. SAIB]],BASE_CONTAG[],5,0),"") -> 0 | O37: =SUMIF(SISTEMA!#REF!,BASE_CONCILI12[[#This Row],[CÓD. SAIB]],SISTEMA!#REF!) -> #REF! | P37: =IFERROR(SUM(BASE_CONCILI12[[#This Row],[SISTEMA]]*BASE_CONCILI12[[#This Row],[CUSTO MP (UN)]]),0) -> 0 | Q37: =IFERROR(VLOOKUP(BASE_CONCILI12[[#This Row],[CÓD. SAIB]],BASE_DIFERENÇA[],4,0),"0") -> 0 | R37: =BASE_CONCILI12[[#This Row],[30/jun]]-BASE_CONCILI12[[#This Row],[SISTEMA]] -> #REF! | S37: =IFERROR(BASE_CONCILI12[[#This Row],[DIFERENÇA ANTERIOR]]-BASE_CONCILI12[[#This Row],[DIFERENÇA ATUAL]],"-") -> - | T37: =VLOOKUP(BASE_CONCILI12[[#This Row],[CÓD. SAIB]],CUSTO!#REF!,3,0) -> #REF! | U37: =IFERROR(SUM(BASE_CONCILI12[[#This Row],[DIFERENÇA ATUAL]]*BASE_CONCILI12[[#This Row],[CUSTO MP (UN)]]),0) -> 0 | V37: =IFERROR(BASE_CONCILI12[[#This Row],[30/jun]]/BASE_CONCILI12[[#This Row],[SISTEMA]],"") | W37: =IFERROR(BASE_CONCILI12[[#This Row],[DIFERENÇA MÊS]]*BASE_CONCILI12[[#This Row],[CUSTO MP (UN)]],"-") -> - | X37: OK
A38: 30257 | C38: ACIDO LACTICO | D38: CERVEJARIA | E38: =VLOOKUP(BASE_CONCILI12[[#This Row],[CÓD. SAIB]],CONT_ANTE!A:D,4,0) -> #N/A | F38: =SUMIF(#REF!,BASE_CONCILI12[[#This Row],[CÓD. SAIB]],#REF!) -> #REF! | G38: =SUMIF(#REF!,BASE_CONCILI12[[#This Row],[CÓD. SAIB]],#REF!) -> #REF! | H38: =BASE_CONCILI12[[#This Row],[CONSUMO REAL]]-BASE_CONCILI12[[#This Row],[CONSUMO TEORICO]] -> #REF! | I38: =SUMIF(#REF!,BASE_CONCILI12[[#This Row],[CÓD. SAIB]],#REF!) -> #REF! | J38: =SUMIF(#REF!,BASE_CONCILI12[[#This Row],[CÓD. SAIB]],#REF!) -> #REF! | K38: =BASE_CONCILI12[[#This Row],[30/mai]]+BASE_CONCILI12[[#This Row],[RECEBIMENTO]]-BASE_CONCILI12[[#This Row],[TRANSFERÊNCIA]]-BASE_CONCILI12[[#This Row],[CONSUMO REAL]] -> #N/A | L38: =IFERROR(VLOOKUP(BASE_CONCILI12[[#This Row],[CÓD. SAIB]],BASE_CONTAG[[LAVRE]:[CONTAGEM FINAL]],7,0),0) -> 120 | M38: =IFERROR(SUM(BASE_CONCILI12[[#This Row],[30/jun]]*BASE_CONCILI12[[#This Row],[CUSTO MP (UN)]]),0) -> 0 | N38: =IFERROR(VLOOKUP(BASE_CONCILI12[[#This Row],[CÓD. SAIB]],BASE_CONTAG[],5,0),"") -> 120 | O38: =SUMIF(SISTEMA!#REF!,BASE_CONCILI12[[#This Row],[CÓD. SAIB]],SISTEMA!#REF!) -> #REF! | P38: =IFERROR(SUM(BASE_CONCILI12[[#This Row],[SISTEMA]]*BASE_CONCILI12[[#This Row],[CUSTO MP (UN)]]),0) -> 0 | Q38: =IFERROR(VLOOKUP(BASE_CONCILI12[[#This Row],[CÓD. SAIB]],BASE_DIFERENÇA[],4,0),"0") -> 0 | R38: =BASE_CONCILI12[[#This Row],[30/jun]]-BASE_CONCILI12[[#This Row],[SISTEMA]] -> #REF! | S38: =IFERROR(BASE_CONCILI12[[#This Row],[DIFERENÇA ANTERIOR]]-BASE_CONCILI12[[#This Row],[DIFERENÇA ATUAL]],"-") -> - | T38: =VLOOKUP(BASE_CONCILI12[[#This Row],[CÓD. SAIB]],CUSTO!#REF!,3,0) -> #REF! | U38: =IFERROR(SUM(BASE_CONCILI12[[#This Row],[DIFERENÇA ATUAL]]*BASE_CONCILI12[[#This Row],[CUSTO MP (UN)]]),0) -> 0 | V38: =IFERROR(BASE_CONCILI12[[#This Row],[30/jun]]/BASE_CONCILI12[[#This Row],[SISTEMA]],"") | W38: =IFERROR(BASE_CONCILI12[[#This Row],[DIFERENÇA MÊS]]*BASE_CONCILI12[[#This Row],[CUSTO MP (UN)]],"-") -> - | X38: CORREÇÃO DE APONTAMENTO - MANTÉM SOBRA
A39: 30247 | C39: ALGINATO DE PROPILENO GLICOL | D39: CERVEJARIA | E39: =VLOOKUP(BASE_CONCILI12[[#This Row],[CÓD. SAIB]],CONT_ANTE!A:D,4,0) -> #N/A | F39: =SUMIF(#REF!,BASE_CONCILI12[[#This Row],[CÓD. SAIB]],#REF!) -> #REF! | G39: =SUMIF(#REF!,BASE_CONCILI12[[#This Row],[CÓD. SAIB]],#REF!) -> #REF! | H39: =BASE_CONCILI12[[#This Row],[CONSUMO REAL]]-BASE_CONCILI12[[#This Row],[CONSUMO TEORICO]] -> #REF! | I39: =SUMIF(#REF!,BASE_CONCILI12[[#This Row],[CÓD. SAIB]],#REF!) -> #REF! | J39: =SUMIF(#REF!,BASE_CONCILI12[[#This Row],[CÓD. SAIB]],#REF!) -> #REF! | K39: =BASE_CONCILI12[[#This Row],[30/mai]]+BASE_CONCILI12[[#This Row],[RECEBIMENTO]]-BASE_CONCILI12[[#This Row],[TRANSFERÊNCIA]]-BASE_CONCILI12[[#This Row],[CONSUMO REAL]] -> #N/A | L39: =IFERROR(VLOOKUP(BASE_CONCILI12[[#This Row],[CÓD. SAIB]],BASE_CONTAG[[LAVRE]:[CONTAGEM FINAL]],7,0),0) -> 28 | M39: =IFERROR(SUM(BASE_CONCILI12[[#This Row],[30/jun]]*BASE_CONCILI12[[#This Row],[CUSTO MP (UN)]]),0) -> 0 | N39: =IFERROR(VLOOKUP(BASE_CONCILI12[[#This Row],[CÓD. SAIB]],BASE_CONTAG[],5,0),"") -> 28 | O39: =SUMIF(SISTEMA!#REF!,BASE_CONCILI12[[#This Row],[CÓD. SAIB]],SISTEMA!#REF!) -> #REF! | P39: =IFERROR(SUM(BASE_CONCILI12[[#This Row],[SISTEMA]]*BASE_CONCILI12[[#This Row],[CUSTO MP (UN)]]),0) -> 0 | Q39: =IFERROR(VLOOKUP(BASE_CONCILI12[[#This Row],[CÓD. SAIB]],BASE_DIFERENÇA[],4,0),"0") -> 0 | R39: =BASE_CONCILI12[[#This Row],[30/jun]]-BASE_CONCILI12[[#This Row],[SISTEMA]] -> #REF! | S39: =IFERROR(BASE_CONCILI12[[#This Row],[DIFERENÇA ANTERIOR]]-BASE_CONCILI12[[#This Row],[DIFERENÇA ATUAL]],"-") -> - | T39: =VLOOKUP(BASE_CONCILI12[[#This Row],[CÓD. SAIB]],CUSTO!#REF!,3,0) -> #REF! | U39: =IFERROR(SUM(BASE_CONCILI12[[#This Row],[DIFERENÇA ATUAL]]*BASE_CONCILI12[[#This Row],[CUSTO MP (UN)]]),0) -> 0 | V39: =IFERROR(BASE_CONCILI12[[#This Row],[30/jun]]/BASE_CONCILI12[[#This Row],[SISTEMA]],"") | W39: =IFERROR(BASE_CONCILI12[[#This Row],[DIFERENÇA MÊS]]*BASE_CONCILI12[[#This Row],[CUSTO MP (UN)]],"-") -> - | X39: CORREÇÃO DE APONTAMENTO - MANTÉM SOBRA
A40: 31998 | C40: ANTIOXIDANTE IS CX 25KG | D40: CERVEJARIA | E40: =VLOOKUP(BASE_CONCILI12[[#This Row],[CÓD. SAIB]],CONT_ANTE!A:D,4,0) -> #N/A | F40: =SUMIF(#REF!,BASE_CONCILI12[[#This Row],[CÓD. SAIB]],#REF!) -> #REF! | G40: =SUMIF(#REF!,BASE_CONCILI12[[#This Row],[CÓD. SAIB]],#REF!) -> #REF! | H40: =BASE_CONCILI12[[#This Row],[CONSUMO REAL]]-BASE_CONCILI12[[#This Row],[CONSUMO TEORICO]] -> #REF! | I40: =SUMIF(#REF!,BASE_CONCILI12[[#This Row],[CÓD. SAIB]],#REF!) -> #REF! | J40: =SUMIF(#REF!,BASE_CONCILI12[[#This Row],[CÓD. SAIB]],#REF!) -> #REF! | K40: =BASE_CONCILI12[[#This Row],[30/mai]]+BASE_CONCILI12[[#This Row],[RECEBIMENTO]]-BASE_CONCILI12[[#This Row],[TRANSFERÊNCIA]]-BASE_CONCILI12[[#This Row],[CONSUMO REAL]] -> #N/A | L40: =IFERROR(VLOOKUP(BASE_CONCILI12[[#This Row],[CÓD. SAIB]],BASE_CONTAG[[LAVRE]:[CONTAGEM FINAL]],7,0),0) -> 0 | M40: =IFERROR(SUM(BASE_CONCILI12[[#This Row],[30/jun]]*BASE_CONCILI12[[#This Row],[CUSTO MP (UN)]]),0) -> 0 | N40: =IFERROR(VLOOKUP(BASE_CONCILI12[[#This Row],[CÓD. SAIB]],BASE_CONTAG[],5,0),"") -> 0 | O40: =SUMIF(SISTEMA!#REF!,BASE_CONCILI12[[#This Row],[CÓD. SAIB]],SISTEMA!#REF!) -> #REF! | P40: =IFERROR(SUM(BASE_CONCILI12[[#This Row],[SISTEMA]]*BASE_CONCILI12[[#This Row],[CUSTO MP (UN)]]),0) -> 0 | Q40: =IFERROR(VLOOKUP(BASE_CONCILI12[[#This Row],[CÓD. SAIB]],BASE_DIFERENÇA[],4,0),"0") -> 0 | R40: =BASE_CONCILI12[[#This Row],[30/jun]]-BASE_CONCILI12[[#This Row],[SISTEMA]] -> #REF! | S40: =IFERROR(BASE_CONCILI12[[#This Row],[DIFERENÇA ANTERIOR]]-BASE_CONCILI12[[#This Row],[DIFERENÇA ATUAL]],"-") -> - | T40: =VLOOKUP(BASE_CONCILI12[[#This Row],[CÓD. SAIB]],CUSTO!#REF!,3,0) -> #REF! | U40: =IFERROR(SUM(BASE_CONCILI12[[#This Row],[DIFERENÇA ATUAL]]*BASE_CONCILI12[[#This Row],[CUSTO MP (UN)]]),0) -> 0 | V40: =IFERROR(BASE_CONCILI12[[#This Row],[30/jun]]/BASE_CONCILI12[[#This Row],[SISTEMA]],"") | W40: =IFERROR(BASE_CONCILI12[[#This Row],[DIFERENÇA MÊS]]*BASE_CONCILI12[[#This Row],[CUSTO MP (UN)]],"-") -> - | X40: CORREÇÃO DE APONTAMENTO - MANTÉM FALTA
A41: 31952 | C41: BIOMAX L | D41: CERVEJARIA | E41: =VLOOKUP(BASE_CONCILI12[[#This Row],[CÓD. SAIB]],CONT_ANTE!A:D,4,0) -> #N/A | F41: =SUMIF(#REF!,BASE_CONCILI12[[#This Row],[CÓD. SAIB]],#REF!) -> #REF! | G41: =SUMIF(#REF!,BASE_CONCILI12[[#This Row],[CÓD. SAIB]],#REF!) -> #REF! | H41: =BASE_CONCILI12[[#This Row],[CONSUMO REAL]]-BASE_CONCILI12[[#This Row],[CONSUMO TEORICO]] -> #REF! | I41: =SUMIF(#REF!,BASE_CONCILI12[[#This Row],[CÓD. SAIB]],#REF!) -> #REF! | J41: =SUMIF(#REF!,BASE_CONCILI12[[#This Row],[CÓD. SAIB]],#REF!) -> #REF! | K41: =BASE_CONCILI12[[#This Row],[30/mai]]+BASE_CONCILI12[[#This Row],[RECEBIMENTO]]-BASE_CONCILI12[[#This Row],[TRANSFERÊNCIA]]-BASE_CONCILI12[[#This Row],[CONSUMO REAL]] -> #N/A | L41: =IFERROR(VLOOKUP(BASE_CONCILI12[[#This Row],[CÓD. SAIB]],BASE_CONTAG[[LAVRE]:[CONTAGEM FINAL]],7,0),0) -> 0 | M41: =IFERROR(SUM(BASE_CONCILI12[[#This Row],[30/jun]]*BASE_CONCILI12[[#This Row],[CUSTO MP (UN)]]),0) -> 0 | N41: =IFERROR(VLOOKUP(BASE_CONCILI12[[#This Row],[CÓD. SAIB]],BASE_CONTAG[],5,0),"") | O41: =SUMIF(SISTEMA!#REF!,BASE_CONCILI12[[#This Row],[CÓD. SAIB]],SISTEMA!#REF!) -> #REF! | P41: =IFERROR(SUM(BASE_CONCILI12[[#This Row],[SISTEMA]]*BASE_CONCILI12[[#This Row],[CUSTO MP (UN)]]),0) -> 0 | Q41: =IFERROR(VLOOKUP(BASE_CONCILI12[[#This Row],[CÓD. SAIB]],BASE_DIFERENÇA[],4,0),"0") -> 0 | R41: =BASE_CONCILI12[[#This Row],[30/jun]]-BASE_CONCILI12[[#This Row],[SISTEMA]] -> #REF! | S41: =IFERROR(BASE_CONCILI12[[#This Row],[DIFERENÇA ANTERIOR]]-BASE_CONCILI12[[#This Row],[DIFERENÇA ATUAL]],"-") -> - | T41: 0 | U41: =IFERROR(SUM(BASE_CONCILI12[[#This Row],[DIFERENÇA ATUAL]]*BASE_CONCILI12[[#This Row],[CUSTO MP (UN)]]),0) -> 0 | V41: =IFERROR(BASE_CONCILI12[[#This Row],[30/jun]]/BASE_CONCILI12[[#This Row],[SISTEMA]],"") | W41: =IFERROR(BASE_CONCILI12[[#This Row],[DIFERENÇA MÊS]]*BASE_CONCILI12[[#This Row],[CUSTO MP (UN)]],"-") -> - | X41: OK
A42: 30254 | C42: CLEAR MAX PVPP | D42: CERVEJARIA | E42: =VLOOKUP(BASE_CONCILI12[[#This Row],[CÓD. SAIB]],CONT_ANTE!A:D,4,0) -> #N/A | F42: =SUMIF(#REF!,BASE_CONCILI12[[#This Row],[CÓD. SAIB]],#REF!) -> #REF! | G42: =SUMIF(#REF!,BASE_CONCILI12[[#This Row],[CÓD. SAIB]],#REF!) -> #REF! | H42: =BASE_CONCILI12[[#This Row],[CONSUMO REAL]]-BASE_CONCILI12[[#This Row],[CONSUMO TEORICO]] -> #REF! | I42: =SUMIF(#REF!,BASE_CONCILI12[[#This Row],[CÓD. SAIB]],#REF!) -> #REF! | J42: =SUMIF(#REF!,BASE_CONCILI12[[#This Row],[CÓD. SAIB]],#REF!) -> #REF! | K42: =BASE_CONCILI12[[#This Row],[30/mai]]+BASE_CONCILI12[[#This Row],[RECEBIMENTO]]-BASE_CONCILI12[[#This Row],[TRANSFERÊNCIA]]-BASE_CONCILI12[[#This Row],[CONSUMO REAL]] -> #N/A | L42: =IFERROR(VLOOKUP(BASE_CONCILI12[[#This Row],[CÓD. SAIB]],BASE_CONTAG[[LAVRE]:[CONTAGEM FINAL]],7,0),0) -> 332 | M42: =IFERROR(SUM(BASE_CONCILI12[[#This Row],[30/jun]]*BASE_CONCILI12[[#This Row],[CUSTO MP (UN)]]),0) -> 0 | N42: =IFERROR(VLOOKUP(BASE_CONCILI12[[#This Row],[CÓD. SAIB]],BASE_CONTAG[],5,0),"") -> 332 | O42: =SUMIF(SISTEMA!#REF!,BASE_CONCILI12[[#This Row],[CÓD. SAIB]],SISTEMA!#REF!) -> #REF! | P42: =IFERROR(SUM(BASE_CONCILI12[[#This Row],[SISTEMA]]*BASE_CONCILI12[[#This Row],[CUSTO MP (UN)]]),0) -> 0 | Q42: =IFERROR(VLOOKUP(BASE_CONCILI12[[#This Row],[CÓD. SAIB]],BASE_DIFERENÇA[],4,0),"0") -> 0 | R42: =BASE_CONCILI12[[#This Row],[30/jun]]-BASE_CONCILI12[[#This Row],[SISTEMA]] -> #REF! | S42: =IFERROR(BASE_CONCILI12[[#This Row],[DIFERENÇA ANTERIOR]]-BASE_CONCILI12[[#This Row],[DIFERENÇA ATUAL]],"-") -> - | T42: =VLOOKUP(BASE_CONCILI12[[#This Row],[CÓD. SAIB]],CUSTO!#REF!,3,0) -> #REF! | U42: =IFERROR(SUM(BASE_CONCILI12[[#This Row],[DIFERENÇA ATUAL]]*BASE_CONCILI12[[#This Row],[CUSTO MP (UN)]]),0) -> 0 | V42: =IFERROR(BASE_CONCILI12[[#This Row],[30/jun]]/BASE_CONCILI12[[#This Row],[SISTEMA]],"") | W42: =IFERROR(BASE_CONCILI12[[#This Row],[DIFERENÇA MÊS]]*BASE_CONCILI12[[#This Row],[CUSTO MP (UN)]],"-") -> - | X42: CORREÇÃO DE APONTAMENTO - MANTÉM SOBRA
A43: 31198 | C43: CLEARMAX MF - ACIDO TANICO | D43: CERVEJARIA | E43: =VLOOKUP(BASE_CONCILI12[[#This Row],[CÓD. SAIB]],CONT_ANTE!A:D,4,0) -> #N/A | F43: =SUMIF(#REF!,BASE_CONCILI12[[#This Row],[CÓD. SAIB]],#REF!) -> #REF! | G43: =SUMIF(#REF!,BASE_CONCILI12[[#This Row],[CÓD. SAIB]],#REF!) -> #REF! | H43: =BASE_CONCILI12[[#This Row],[CONSUMO REAL]]-BASE_CONCILI12[[#This Row],[CONSUMO TEORICO]] -> #REF! | I43: =SUMIF(#REF!,BASE_CONCILI12[[#This Row],[CÓD. SAIB]],#REF!) -> #REF! | J43: =SUMIF(#REF!,BASE_CONCILI12[[#This Row],[CÓD. SAIB]],#REF!) -> #REF! | K43: =BASE_CONCILI12[[#This Row],[30/mai]]+BASE_CONCILI12[[#This Row],[RECEBIMENTO]]-BASE_CONCILI12[[#This Row],[TRANSFERÊNCIA]]-BASE_CONCILI12[[#This Row],[CONSUMO REAL]] -> #N/A | L43: =IFERROR(VLOOKUP(BASE_CONCILI12[[#This Row],[CÓD. SAIB]],BASE_CONTAG[[LAVRE]:[CONTAGEM FINAL]],7,0),0) -> 0 | M43: =IFERROR(SUM(BASE_CONCILI12[[#This Row],[30/jun]]*BASE_CONCILI12[[#This Row],[CUSTO MP (UN)]]),0) -> 0 | N43: =IFERROR(VLOOKUP(BASE_CONCILI12[[#This Row],[CÓD. SAIB]],BASE_CONTAG[],5,0),"") -> 0 | O43: =SUMIF(SISTEMA!#REF!,BASE_CONCILI12[[#This Row],[CÓD. SAIB]],SISTEMA!#REF!) -> #REF! | P43: =IFERROR(SUM(BASE_CONCILI12[[#This Row],[SISTEMA]]*BASE_CONCILI12[[#This Row],[CUSTO MP (UN)]]),0) -> 0 | Q43: =IFERROR(VLOOKUP(BASE_CONCILI12[[#This Row],[CÓD. SAIB]],BASE_DIFERENÇA[],4,0),"0") -> 0 | R43: =BASE_CONCILI12[[#This Row],[30/jun]]-BASE_CONCILI12[[#This Row],[SISTEMA]] -> #REF! | S43: =IFERROR(BASE_CONCILI12[[#This Row],[DIFERENÇA ANTERIOR]]-BASE_CONCILI12[[#This Row],[DIFERENÇA ATUAL]],"-") -> - | T43: =VLOOKUP(BASE_CONCILI12[[#This Row],[CÓD. SAIB]],CUSTO!#REF!,3,0) -> #REF! | U43: =IFERROR(SUM(BASE_CONCILI12[[#This Row],[DIFERENÇA ATUAL]]*BASE_CONCILI12[[#This Row],[CUSTO MP (UN)]]),0) -> 0 | V43: =IFERROR(BASE_CONCILI12[[#This Row],[30/jun]]/BASE_CONCILI12[[#This Row],[SISTEMA]],"") | W43: =IFERROR(BASE_CONCILI12[[#This Row],[DIFERENÇA MÊS]]*BASE_CONCILI12[[#This Row],[CUSTO MP (UN)]],"-") -> - | X43: OK
A44: 30256 | C44: CLORETO DE CALCIO | D44: CERVEJARIA | E44: =VLOOKUP(BASE_CONCILI12[[#This Row],[CÓD. SAIB]],CONT_ANTE!A:D,4,0) -> #N/A | F44: =SUMIF(#REF!,BASE_CONCILI12[[#This Row],[CÓD. SAIB]],#REF!) -> #REF! | G44: =SUMIF(#REF!,BASE_CONCILI12[[#This Row],[CÓD. SAIB]],#REF!) -> #REF! | H44: =BASE_CONCILI12[[#This Row],[CONSUMO REAL]]-BASE_CONCILI12[[#This Row],[CONSUMO TEORICO]] -> #REF! | I44: =SUMIF(#REF!,BASE_CONCILI12[[#This Row],[CÓD. SAIB]],#REF!) -> #REF! | J44: =SUMIF(#REF!,BASE_CONCILI12[[#This Row],[CÓD. SAIB]],#REF!) -> #REF! | K44: =BASE_CONCILI12[[#This Row],[30/mai]]+BASE_CONCILI12[[#This Row],[RECEBIMENTO]]-BASE_CONCILI12[[#This Row],[TRANSFERÊNCIA]]-BASE_CONCILI12[[#This Row],[CONSUMO REAL]] -> #N/A | L44: =IFERROR(VLOOKUP(BASE_CONCILI12[[#This Row],[CÓD. SAIB]],BASE_CONTAG[[LAVRE]:[CONTAGEM FINAL]],7,0),0) -> 11714.5 | M44: =IFERROR(SUM(BASE_CONCILI12[[#This Row],[30/jun]]*BASE_CONCILI12[[#This Row],[CUSTO MP (UN)]]),0) -> 0 | N44: =IFERROR(VLOOKUP(BASE_CONCILI12[[#This Row],[CÓD. SAIB]],BASE_CONTAG[],5,0),"") -> 11714.5 | O44: =SUMIF(SISTEMA!#REF!,BASE_CONCILI12[[#This Row],[CÓD. SAIB]],SISTEMA!#REF!) -> #REF! | P44: =IFERROR(SUM(BASE_CONCILI12[[#This Row],[SISTEMA]]*BASE_CONCILI12[[#This Row],[CUSTO MP (UN)]]),0) -> 0 | Q44: =IFERROR(VLOOKUP(BASE_CONCILI12[[#This Row],[CÓD. SAIB]],BASE_DIFERENÇA[],4,0),"0") -> 0 | R44: =BASE_CONCILI12[[#This Row],[30/jun]]-BASE_CONCILI12[[#This Row],[SISTEMA]] -> #REF! | S44: =IFERROR(BASE_CONCILI12[[#This Row],[DIFERENÇA ANTERIOR]]-BASE_CONCILI12[[#This Row],[DIFERENÇA ATUAL]],"-") -> - | T44: =VLOOKUP(BASE_CONCILI12[[#This Row],[CÓD. SAIB]],CUSTO!#REF!,3,0) -> #REF! | U44: =IFERROR(SUM(BASE_CONCILI12[[#This Row],[DIFERENÇA ATUAL]]*BASE_CONCILI12[[#This Row],[CUSTO MP (UN)]]),0) -> 0 | V44: =IFERROR(BASE_CONCILI12[[#This Row],[30/jun]]/BASE_CONCILI12[[#This Row],[SISTEMA]],"") | W44: =IFERROR(BASE_CONCILI12[[#This Row],[DIFERENÇA MÊS]]*BASE_CONCILI12[[#This Row],[CUSTO MP (UN)]],"-") -> - | X44: CORREÇÃO DE APONTAMENTO - MANTÉM SOBRA
A45: 30356 | C45: CORANTE CARAMELO CERVEJA | D45: CERVEJARIA | E45: =VLOOKUP(BASE_CONCILI12[[#This Row],[CÓD. SAIB]],CONT_ANTE!A:D,4,0) -> #N/A | F45: =SUMIF(#REF!,BASE_CONCILI12[[#This Row],[CÓD. SAIB]],#REF!) -> #REF! | G45: =SUMIF(#REF!,BASE_CONCILI12[[#This Row],[CÓD. SAIB]],#REF!) -> #REF! | H45: =BASE_CONCILI12[[#This Row],[CONSUMO REAL]]-BASE_CONCILI12[[#This Row],[CONSUMO TEORICO]] -> #REF! | I45: =SUMIF(#REF!,BASE_CONCILI12[[#This Row],[CÓD. SAIB]],#REF!) -> #REF! | J45: =SUMIF(#REF!,BASE_CONCILI12[[#This Row],[CÓD. SAIB]],#REF!) -> #REF! | K45: =BASE_CONCILI12[[#This Row],[30/mai]]+BASE_CONCILI12[[#This Row],[RECEBIMENTO]]-BASE_CONCILI12[[#This Row],[TRANSFERÊNCIA]]-BASE_CONCILI12[[#This Row],[CONSUMO REAL]] -> #N/A | L45: =IFERROR(VLOOKUP(BASE_CONCILI12[[#This Row],[CÓD. SAIB]],BASE_CONTAG[[LAVRE]:[CONTAGEM FINAL]],7,0),0) -> 320 | M45: =IFERROR(SUM(BASE_CONCILI12[[#This Row],[30/jun]]*BASE_CONCILI12[[#This Row],[CUSTO MP (UN)]]),0) -> 0 | N45: =IFERROR(VLOOKUP(BASE_CONCILI12[[#This Row],[CÓD. SAIB]],BASE_CONTAG[],5,0),"") -> 320 | O45: =SUMIF(SISTEMA!#REF!,BASE_CONCILI12[[#This Row],[CÓD. SAIB]],SISTEMA!#REF!) -> #REF! | P45: =IFERROR(SUM(BASE_CONCILI12[[#This Row],[SISTEMA]]*BASE_CONCILI12[[#This Row],[CUSTO MP (UN)]]),0) -> 0 | Q45: =IFERROR(VLOOKUP(BASE_CONCILI12[[#This Row],[CÓD. SAIB]],BASE_DIFERENÇA[],4,0),"0") -> 0 | R45: =BASE_CONCILI12[[#This Row],[30/jun]]-BASE_CONCILI12[[#This Row],[SISTEMA]] -> #REF! | S45: =IFERROR(BASE_CONCILI12[[#This Row],[DIFERENÇA ANTERIOR]]-BASE_CONCILI12[[#This Row],[DIFERENÇA ATUAL]],"-") -> - | T45: =VLOOKUP(BASE_CONCILI12[[#This Row],[CÓD. SAIB]],CUSTO!#REF!,3,0) -> #REF! | U45: =IFERROR(SUM(BASE_CONCILI12[[#This Row],[DIFERENÇA ATUAL]]*BASE_CONCILI12[[#This Row],[CUSTO MP (UN)]]),0) -> 0 | V45: =IFERROR(BASE_CONCILI12[[#This Row],[30/jun]]/BASE_CONCILI12[[#This Row],[SISTEMA]],"") | W45: =IFERROR(BASE_CONCILI12[[#This Row],[DIFERENÇA MÊS]]*BASE_CONCILI12[[#This Row],[CUSTO MP (UN)]],"-") -> - | X45: CORREÇÃO DE APONTAMENTO - MANTÉM FALTA
A46: 31828 | C46: ENZIMAS ULTRAFLO | D46: CERVEJARIA | E46: =VLOOKUP(BASE_CONCILI12[[#This Row],[CÓD. SAIB]],CONT_ANTE!A:D,4,0) -> #N/A | F46: =SUMIF(#REF!,BASE_CONCILI12[[#This Row],[CÓD. SAIB]],#REF!) -> #REF! | G46: =SUMIF(#REF!,BASE_CONCILI12[[#This Row],[CÓD. SAIB]],#REF!) -> #REF! | H46: =BASE_CONCILI12[[#This Row],[CONSUMO REAL]]-BASE_CONCILI12[[#This Row],[CONSUMO TEORICO]] -> #REF! | I46: =SUMIF(#REF!,BASE_CONCILI12[[#This Row],[CÓD. SAIB]],#REF!) -> #REF! | J46: =SUMIF(#REF!,BASE_CONCILI12[[#This Row],[CÓD. SAIB]],#REF!) -> #REF! | K46: =BASE_CONCILI12[[#This Row],[30/mai]]+BASE_CONCILI12[[#This Row],[RECEBIMENTO]]-BASE_CONCILI12[[#This Row],[TRANSFERÊNCIA]]-BASE_CONCILI12[[#This Row],[CONSUMO REAL]] -> #N/A | L46: =IFERROR(VLOOKUP(BASE_CONCILI12[[#This Row],[CÓD. SAIB]],BASE_CONTAG[[LAVRE]:[CONTAGEM FINAL]],7,0),0) -> 324 | M46: =IFERROR(SUM(BASE_CONCILI12[[#This Row],[30/jun]]*BASE_CONCILI12[[#This Row],[CUSTO MP (UN)]]),0) -> 0 | N46: =IFERROR(VLOOKUP(BASE_CONCILI12[[#This Row],[CÓD. SAIB]],BASE_CONTAG[],5,0),"") -> 324 | O46: =SUMIF(SISTEMA!#REF!,BASE_CONCILI12[[#This Row],[CÓD. SAIB]],SISTEMA!#REF!) -> #REF! | P46: =IFERROR(SUM(BASE_CONCILI12[[#This Row],[SISTEMA]]*BASE_CONCILI12[[#This Row],[CUSTO MP (UN)]]),0) -> 0 | Q46: =IFERROR(VLOOKUP(BASE_CONCILI12[[#This Row],[CÓD. SAIB]],BASE_DIFERENÇA[],4,0),"0") -> 0 | R46: =BASE_CONCILI12[[#This Row],[30/jun]]-BASE_CONCILI12[[#This Row],[SISTEMA]] -> #REF! | S46: =IFERROR(BASE_CONCILI12[[#This Row],[DIFERENÇA ANTERIOR]]-BASE_CONCILI12[[#This Row],[DIFERENÇA ATUAL]],"-") -> - | T46: =VLOOKUP(BASE_CONCILI12[[#This Row],[CÓD. SAIB]],CUSTO!#REF!,3,0) -> #REF! | U46: =IFERROR(SUM(BASE_CONCILI12[[#This Row],[DIFERENÇA ATUAL]]*BASE_CONCILI12[[#This Row],[CUSTO MP (UN)]]),0) -> 0 | V46: =IFERROR(BASE_CONCILI12[[#This Row],[30/jun]]/BASE_CONCILI12[[#This Row],[SISTEMA]],"") | W46: =IFERROR(BASE_CONCILI12[[#This Row],[DIFERENÇA MÊS]]*BASE_CONCILI12[[#This Row],[CUSTO MP (UN)]],"-") -> - | X46: CORREÇÃO DE APONTAMENTO - MANTÉM FALTA
A47: 2041 | C47: FERMENTO CERVEJEIRO FERMENTIS W-34/70 | D47: CERVEJARIA | E47: =VLOOKUP(BASE_CONCILI12[[#This Row],[CÓD. SAIB]],CONT_ANTE!A:D,4,0) -> #N/A | F47: =SUMIF(#REF!,BASE_CONCILI12[[#This Row],[CÓD. SAIB]],#REF!) -> #REF! | G47: =SUMIF(#REF!,BASE_CONCILI12[[#This Row],[CÓD. SAIB]],#REF!) -> #REF! | H47: =BASE_CONCILI12[[#This Row],[CONSUMO REAL]]-BASE_CONCILI12[[#This Row],[CONSUMO TEORICO]] -> #REF! | I47: =SUMIF(#REF!,BASE_CONCILI12[[#This Row],[CÓD. SAIB]],#REF!) -> #REF! | J47: =SUMIF(#REF!,BASE_CONCILI12[[#This Row],[CÓD. SAIB]],#REF!) -> #REF! | K47: =BASE_CONCILI12[[#This Row],[30/mai]]+BASE_CONCILI12[[#This Row],[RECEBIMENTO]]-BASE_CONCILI12[[#This Row],[TRANSFERÊNCIA]]-BASE_CONCILI12[[#This Row],[CONSUMO REAL]] -> #N/A | L47: =IFERROR(VLOOKUP(BASE_CONCILI12[[#This Row],[CÓD. SAIB]],BASE_CONTAG[[LAVRE]:[CONTAGEM FINAL]],7,0),0) -> 5 | M47: =IFERROR(SUM(BASE_CONCILI12[[#This Row],[30/jun]]*BASE_CONCILI12[[#This Row],[CUSTO MP (UN)]]),0) -> 0 | N47: =IFERROR(VLOOKUP(BASE_CONCILI12[[#This Row],[CÓD. SAIB]],BASE_CONTAG[],5,0),"") -> 5 | O47: =SUMIF(SISTEMA!#REF!,BASE_CONCILI12[[#This Row],[CÓD. SAIB]],SISTEMA!#REF!) -> #REF! | P47: =IFERROR(SUM(BASE_CONCILI12[[#This Row],[SISTEMA]]*BASE_CONCILI12[[#This Row],[CUSTO MP (UN)]]),0) -> 0 | Q47: =IFERROR(VLOOKUP(BASE_CONCILI12[[#This Row],[CÓD. SAIB]],BASE_DIFERENÇA[],4,0),"0") -> 0 | R47: =BASE_CONCILI12[[#This Row],[30/jun]]-BASE_CONCILI12[[#This Row],[SISTEMA]] -> #REF! | S47: =IFERROR(BASE_CONCILI12[[#This Row],[DIFERENÇA ANTERIOR]]-BASE_CONCILI12[[#This Row],[DIFERENÇA ATUAL]],"-") -> - | T47: =VLOOKUP(BASE_CONCILI12[[#This Row],[CÓD. SAIB]],CUSTO!#REF!,3,0) -> #REF! | U47: =IFERROR(SUM(BASE_CONCILI12[[#This Row],[DIFERENÇA ATUAL]]*BASE_CONCILI12[[#This Row],[CUSTO MP (UN)]]),0) -> 0 | V47: =IFERROR(BASE_CONCILI12[[#This Row],[30/jun]]/BASE_CONCILI12[[#This Row],[SISTEMA]],"") | W47: =IFERROR(BASE_CONCILI12[[#This Row],[DIFERENÇA MÊS]]*BASE_CONCILI12[[#This Row],[CUSTO MP (UN)]],"-") -> - | X47: NÃO CONSOME EM NENHUMA ESTRUTURA
A48: 30255 | C48: SILICA DARACLAR | D48: CERVEJARIA | E48: =VLOOKUP(BASE_CONCILI12[[#This Row],[CÓD. SAIB]],CONT_ANTE!A:D,4,0) -> #N/A | F48: =SUMIF(#REF!,BASE_CONCILI12[[#This Row],[CÓD. SAIB]],#REF!) -> #REF! | G48: =SUMIF(#REF!,BASE_CONCILI12[[#This Row],[CÓD. SAIB]],#REF!) -> #REF! | H48: =BASE_CONCILI12[[#This Row],[CONSUMO REAL]]-BASE_CONCILI12[[#This Row],[CONSUMO TEORICO]] -> #REF! | I48: =SUMIF(#REF!,BASE_CONCILI12[[#This Row],[CÓD. SAIB]],#REF!) -> #REF! | J48: =SUMIF(#REF!,BASE_CONCILI12[[#This Row],[CÓD. SAIB]],#REF!) -> #REF! | K48: =BASE_CONCILI12[[#This Row],[30/mai]]+BASE_CONCILI12[[#This Row],[RECEBIMENTO]]-BASE_CONCILI12[[#This Row],[TRANSFERÊNCIA]]-BASE_CONCILI12[[#This Row],[CONSUMO REAL]] -> #N/A | L48: =IFERROR(VLOOKUP(BASE_CONCILI12[[#This Row],[CÓD. SAIB]],BASE_CONTAG[[LAVRE]:[CONTAGEM FINAL]],7,0),0) -> 0 | M48: =IFERROR(SUM(BASE_CONCILI12[[#This Row],[30/jun]]*BASE_CONCILI12[[#This Row],[CUSTO MP (UN)]]),0) -> 0 | N48: =IFERROR(VLOOKUP(BASE_CONCILI12[[#This Row],[CÓD. SAIB]],BASE_CONTAG[],5,0),"") | O48: =SUMIF(SISTEMA!#REF!,BASE_CONCILI12[[#This Row],[CÓD. SAIB]],SISTEMA!#REF!) -> #REF! | P48: =IFERROR(SUM(BASE_CONCILI12[[#This Row],[SISTEMA]]*BASE_CONCILI12[[#This Row],[CUSTO MP (UN)]]),0) -> 0 | Q48: =IFERROR(VLOOKUP(BASE_CONCILI12[[#This Row],[CÓD. SAIB]],BASE_DIFERENÇA[],4,0),"0") -> 0 | R48: =BASE_CONCILI12[[#This Row],[30/jun]]-BASE_CONCILI12[[#This Row],[SISTEMA]] -> #REF! | S48: =IFERROR(BASE_CONCILI12[[#This Row],[DIFERENÇA ANTERIOR]]-BASE_CONCILI12[[#This Row],[DIFERENÇA ATUAL]],"-") -> - | T48: 0 | U48: =IFERROR(SUM(BASE_CONCILI12[[#This Row],[DIFERENÇA ATUAL]]*BASE_CONCILI12[[#This Row],[CUSTO MP (UN)]]),0) -> 0 | V48: =IFERROR(BASE_CONCILI12[[#This Row],[30/jun]]/BASE_CONCILI12[[#This Row],[SISTEMA]],"") | W48: =IFERROR(BASE_CONCILI12[[#This Row],[DIFERENÇA MÊS]]*BASE_CONCILI12[[#This Row],[CUSTO MP (UN)]],"-") -> - | X48: OK
A49: 30606 | C49: SILICA HP 9000 | D49: CERVEJARIA | E49: =VLOOKUP(BASE_CONCILI12[[#This Row],[CÓD. SAIB]],CONT_ANTE!A:D,4,0) -> #N/A | F49: =SUMIF(#REF!,BASE_CONCILI12[[#This Row],[CÓD. SAIB]],#REF!) -> #REF! | G49: =SUMIF(#REF!,BASE_CONCILI12[[#This Row],[CÓD. SAIB]],#REF!) -> #REF! | H49: =BASE_CONCILI12[[#This Row],[CONSUMO REAL]]-BASE_CONCILI12[[#This Row],[CONSUMO TEORICO]] -> #REF! | I49: =SUMIF(#REF!,BASE_CONCILI12[[#This Row],[CÓD. SAIB]],#REF!) -> #REF! | J49: =SUMIF(#REF!,BASE_CONCILI12[[#This Row],[CÓD. SAIB]],#REF!) -> #REF! | K49: =BASE_CONCILI12[[#This Row],[30/mai]]+BASE_CONCILI12[[#This Row],[RECEBIMENTO]]-BASE_CONCILI12[[#This Row],[TRANSFERÊNCIA]]-BASE_CONCILI12[[#This Row],[CONSUMO REAL]] -> #N/A | L49: =IFERROR(VLOOKUP(BASE_CONCILI12[[#This Row],[CÓD. SAIB]],BASE_CONTAG[[LAVRE]:[CONTAGEM FINAL]],7,0),0) -> 5 | M49: =IFERROR(SUM(BASE_CONCILI12[[#This Row],[30/jun]]*BASE_CONCILI12[[#This Row],[CUSTO MP (UN)]]),0) -> 0 | N49: =IFERROR(VLOOKUP(BASE_CONCILI12[[#This Row],[CÓD. SAIB]],BASE_CONTAG[],5,0),"") -> 5 | O49: =SUMIF(SISTEMA!#REF!,BASE_CONCILI12[[#This Row],[CÓD. SAIB]],SISTEMA!#REF!) -> #REF! | P49: =IFERROR(SUM(BASE_CONCILI12[[#This Row],[SISTEMA]]*BASE_CONCILI12[[#This Row],[CUSTO MP (UN)]]),0) -> 0 | Q49: =IFERROR(VLOOKUP(BASE_CONCILI12[[#This Row],[CÓD. SAIB]],BASE_DIFERENÇA[],4,0),"0") -> 0 | R49: =BASE_CONCILI12[[#This Row],[30/jun]]-BASE_CONCILI12[[#This Row],[SISTEMA]] -> #REF! | S49: =IFERROR(BASE_CONCILI12[[#This Row],[DIFERENÇA ANTERIOR]]-BASE_CONCILI12[[#This Row],[DIFERENÇA ATUAL]],"-") -> - | T49: =VLOOKUP(BASE_CONCILI12[[#This Row],[CÓD. SAIB]],CUSTO!#REF!,3,0) -> #REF! | U49: =IFERROR(SUM(BASE_CONCILI12[[#This Row],[DIFERENÇA ATUAL]]*BASE_CONCILI12[[#This Row],[CUSTO MP (UN)]]),0) -> 0 | V49: =IFERROR(BASE_CONCILI12[[#This Row],[30/jun]]/BASE_CONCILI12[[#This Row],[SISTEMA]],"") | W49: =IFERROR(BASE_CONCILI12[[#This Row],[DIFERENÇA MÊS]]*BASE_CONCILI12[[#This Row],[CUSTO MP (UN)]],"-") -> - | X49: CORREÇÃO DE APONTAMENTO - MANTÉM SOBRA
A50: 2032 | C50: XAROPE HIGH MALTOSE | D50: CERVEJARIA | E50: =VLOOKUP(BASE_CONCILI12[[#This Row],[CÓD. SAIB]],CONT_ANTE!A:D,4,0) -> #N/A | F50: =SUMIF(#REF!,BASE_CONCILI12[[#This Row],[CÓD. SAIB]],#REF!) -> #REF! | G50: =SUMIF(#REF!,BASE_CONCILI12[[#This Row],[CÓD. SAIB]],#REF!) -> #REF! | H50: =BASE_CONCILI12[[#This Row],[CONSUMO REAL]]-BASE_CONCILI12[[#This Row],[CONSUMO TEORICO]] -> #REF! | I50: =SUMIF(#REF!,BASE_CONCILI12[[#This Row],[CÓD. SAIB]],#REF!) -> #REF! | J50: =SUMIF(#REF!,BASE_CONCILI12[[#This Row],[CÓD. SAIB]],#REF!) -> #REF! | K50: =BASE_CONCILI12[[#This Row],[30/mai]]+BASE_CONCILI12[[#This Row],[RECEBIMENTO]]-BASE_CONCILI12[[#This Row],[TRANSFERÊNCIA]]-BASE_CONCILI12[[#This Row],[CONSUMO REAL]] -> #N/A | L50: =IFERROR(VLOOKUP(BASE_CONCILI12[[#This Row],[CÓD. SAIB]],BASE_CONTAG[[LAVRE]:[CONTAGEM FINAL]],7,0),0) -> 1049 | M50: =IFERROR(SUM(BASE_CONCILI12[[#This Row],[30/jun]]*BASE_CONCILI12[[#This Row],[CUSTO MP (UN)]]),0) -> 0 | N50: =IFERROR(VLOOKUP(BASE_CONCILI12[[#This Row],[CÓD. SAIB]],BASE_CONTAG[],5,0),"") -> 1049 | O50: =SUMIF(SISTEMA!#REF!,BASE_CONCILI12[[#This Row],[CÓD. SAIB]],SISTEMA!#REF!) -> #REF! | P50: =IFERROR(SUM(BASE_CONCILI12[[#This Row],[SISTEMA]]*BASE_CONCILI12[[#This Row],[CUSTO MP (UN)]]),0) -> 0 | Q50: =IFERROR(VLOOKUP(BASE_CONCILI12[[#This Row],[CÓD. SAIB]],BASE_DIFERENÇA[],4,0),"0") -> 0 | R50: =BASE_CONCILI12[[#This Row],[30/jun]]-BASE_CONCILI12[[#This Row],[SISTEMA]] -> #REF! | S50: =IFERROR(BASE_CONCILI12[[#This Row],[DIFERENÇA ANTERIOR]]-BASE_CONCILI12[[#This Row],[DIFERENÇA ATUAL]],"-") -> - | T50: =VLOOKUP(BASE_CONCILI12[[#This Row],[CÓD. SAIB]],CUSTO!#REF!,3,0) -> #REF! | U50: =IFERROR(SUM(BASE_CONCILI12[[#This Row],[DIFERENÇA ATUAL]]*BASE_CONCILI12[[#This Row],[CUSTO MP (UN)]]),0) -> 0 | V50: =IFERROR(BASE_CONCILI12[[#This Row],[30/jun]]/BASE_CONCILI12[[#This Row],[SISTEMA]],"") | W50: =IFERROR(BASE_CONCILI12[[#This Row],[DIFERENÇA MÊS]]*BASE_CONCILI12[[#This Row],[CUSTO MP (UN)]],"-") -> - | X50: OK
